Workbook

Sheet Index
B6: Blume Ventures Investment Profile
B7: Updated as of: | C7: December 2025
A9: A. | B9: Fund I
A10: B. | B10: Fund IA
A11: C. | B11: Fund II
A12: D. | B12: Fund III
A13: E. | B13: Fund IV
A14: F. | B14: Fund IIA
A15: G. | B15: Fund IIB
A16: H. | B16: Fund 1X
A17: I. | B17: Fund 1Y
A18: J. | B18: Fund V
B20: Notes:
B21: - All information in this file is updated as of the last reporting quarter i.e | E21: =C7 -> December 2025
B22: - INR Cashflows have been converted to USD using FX rates on each transaction date/quarter end date as applicable, and vice-versa
B23: USD / INR | C23: 83.4534 | D23: Rate as on quarter end | E23: 30th Jun'24
D24: FX Rate as on 28th June 2024

Sheet Fund I
B2: # | C2: Company | D2: Business / Brand | E2: Geography | F2: Sector | G2: Date | H2: Stage at Entry | I2: Current Stage | J2: Entry Valuation | K2: Last Round Valuation | L2: Valuation used for Mark to Market | M2: Discount to last round | N2: Effective Valuation for Mark-to-market | O2: Valuation Basis | P2: Total Invested Cost | Q2: Residual Cost | R2: Stake (At Entry) | S2: Stake (Current) | T2: Total Value | U2: Unrealised Value | V2: Realised Value | W2: Gross MOIC | X2: Gross IRR (₹) | Y2: If Exited, Mode of Exit | Z2: GP Exit MOIC | AA2: Value Creation by Fund | AB2: Co-investor(s) | AC2: Sourcing Route | AD2: Deal Source | AE2: Deal Lead | AF2: Status
G3: MM/YY | J3: ₹ Mn | K3: ₹ Mn | L3: ₹ Mn | N3: ₹ Mn | P3: ₹ Mn | Q3: ₹ Mn | R3: % | S3: % | T3: ₹ Mn | U3: ₹ Mn | V3: ₹ Mn | W3: x | X3: %
B4: 1 | C4: GreyOrange Robotics International Inc | D4: GreyOrange Robotics | E4: USA | F4: DeepTech | G4: 41177 | H4: Seed | I4: Series D | J4: 121.74923 | K4: 41634.55 | L4: =K4 -> 41634.55 | M4: 0.3 | N4: =L4*(1-M4) -> 29144.185 | O4: Valued at 30% discount to the last round (pre-money) | P4: 22.2 | Q4: 14.59634 | R4: 0.07749688 | S4: 0.014505105 | T4: =U4+V4 -> 1233.2587 | U4: 443.11442 | V4: 790.14431 | W4: =T4/P4 -> 55.552195 | X4: 0.5934786 | Y4: Partial exit - sale to Fund 1X | Z4: =V4/(P4-Q4) -> 103.91632 | AA4: Business Development connects, Investor connect, Finance & compliance support | AB4: Mithril Capital, Pavilion Capital, Binny Bansal, Antehelion Capital, H&M | AC4: Alumni network of GPs ( BITS alum connected through Sanjay) | AD4: Sanjay | AE4: Karthik | AF4: Partial Exit
B5: 2 | C5: Carbon Clean Solutions Pvt Ltd. | D5: Carbon Clean Solutions | E5: Mumbai | F5: CleanTech | G5: 40632 | H5: Seed | I5: Series C | J5: 149.0364 | K5: 48917.542 | L5: 37628.879 | M5: 0.15 | N5: =L5*(1-M5) -> 31984.547 | O5: Valued at a 50% discount to the secondary price of the last round | P5: 13.5 | Q5: 1.1124059 | R5: 0.090581898 | S5: 0.0017580433 | T5: =U5+V5 -> 935.57901 | U5: 40.342124 | V5: 895.23688 | W5: =T5/P5 -> 69.302149 | X5: 0.41588795 | Y5: Partial exit - Secondary sale to Chevron & CMA + Fund 1Y | Z5: =V5/(P5-Q5) -> 72.268826 | AA5: Business Development connects, structuring of the business as a UK domiciled entity , finance and compliance support, hiring | AB5: Chevron, Wave Equity Partners, Marubeni, Samsung Ventures, Saudi Aramco Energy Ventures, CEMEX | AC5: LP referral | AD5: Sanjay | AE5: Karthik | AF5: Partial Exit
B6: 3 | C6: Manash Lifestyle Private Ltd | D6: Purplle | E6: Mumbai | F6: E-Commerce | G6: 41472 | H6: Seed | I6: N.A | J6: 117.26804 | K6: N.A | L6: N.A | M6: 0 | N6: =M6 -> 0 | O6: Exit Value | P6: 12 | Q6: 0 | R6: 0.0731 | S6: N.A | T6: =U6+V6 -> 387.83128 | U6: 0 | V6: 387.83128 | W6: =T6/P6 -> 32.319273 | X6: 0.6296011 | Y6: Sale to Fund 1X | Z6: =V6/P6 -> 32.319273 | AA6: Business Development connects, Investor connect, finance and compliance support, hiring , strategic media arrangement | AB6: Goldman Sachs, Verlinvest, IvyCap, JSW Ventures | AC6: Angel Network | AD6: Karthik | AE6: Ashish | AF6: Exited
B7: 4 | C7: Dataweave Software Private Ltd | D7: Dataweave | E7: USA | F7: Analytics | G7: 41551 | H7: Seed | I7: Series A1 | J7: 382.8 | K7: 969.68 | L7: =K7 -> 969.68 | M7: 1 | N7: =L7*(1-M7) -> 0 | O7: Provisioned - 100% | P7: 6.961133 | Q7: 0 | R7: 0.075268817 | S7: 0.045927102 | T7: =U7+V7 -> 0 | U7: 0 | V7: 0 | W7: =T7/P7 -> 0 | X7: NA | AA7: Business Development connects, Investor connect, Structuring of business as a US domiciled entity, finance and compliance support, hiring of CFO | AB7: WaterBridge, WGG, Freakout, Recruit | AC7: Angel Network | AD7: Karthik | AE7: Sanjay | AF7: Provisioned
B8: 5 | C8: Serendipity Infolabs Private Ltd | D8: Taxiforsure | E8: Bengaluru | F8: Urban Mobility | G8: 41047 | H8: Seed | I8: N.A | J8: 127.04805 | K8: N.A | L8: N.A | M8: 0 | N8: =M8 -> 0 | O8: Exit Value | P8: 5.1623762 | Q8: 0 | R8: 0.0197 | S8: N.A | T8: =U8+V8 -> 47.4 | U8: 0 | V8: 47.4 | W8: =T8/P8 -> 9.1818182 | X8: 2.9664272 | Y8: Acquisition by Ola | Z8: =V8/P8 -> 9.1818182 | AA8: Structuring of follow-on rounds and exit transactions, Board participation | AB8: Accel, Helion, Bessemer | AC8: VC referral | AD8: Karthik | AE8: Karthik | AF8: Exited
C9: ANI Technologies Limited | D9: Ola Cabs | E9: Delhi | F9: Urban Mobility | G9: 42097 | H9: N.A | I9: N.A | J9: N.A | K9: N.A | L9: N.A | M9: 0 | N9: =M9 -> 0 | O9: Exit Value | P9: 12.437624 | Q9: 0 | R9: N.A | S9: N.A | T9: =U9+V9 -> 120.474 | U9: 0 | V9: 120.474 | W9: =T9/P9 -> 9.6862554 | X9: 0.52789122 | Y9: Secondary Sale to Temasek | Z9: =V9/P9 -> 9.6862554 | AB9: Softbank, Tiger Global, Falcon Edge, Seqouia, DST Global, Steadview Capital, Accel, Didi Chuxing, GIC, Matrix , RNT Capital | AC9: Swap for holding in TaxiFor Sure | AE9: Karthik | AF9: Exited
B10: 6 | C10: Instamojo Inc | D10: Instamojo | E10: USA | F10: FinTech | G10: 40636 | H10: Seed | I10: N.A | J10: 46.5 | K10: 969.68 | L10: =K10 -> 969.68 | M10: 1 | N10: =L10*(1-M10) -> 0 | O10: Provisioned - 100% | P10: 9.9 | Q10: 0 | R10: 0.075268817 | S10: 0.038717693 | T10: =U10+V10 -> 0 | U10: 0 | V10: 0 | W10: =T10/P10 -> 0 | X10: NA | AA10: Business Development connects , Hiring, Finance & compliance support | AB10: Kalaari Capital, Anypay, 500 Startups | AC10: Founder network ( connected through the founder's prior start-up) | AD10: Karthik | AE10: Karthik | AF10: Provisioned
B11: 7 | C11: E2E Networks Private Limited | D11: E2E Networks | E11: Delhi | F11: SaaS | G11: 41292 | H11: Seed | I11: N.A | J11: 137.50215 | K11: N.A | L11: N.A | M11: 0 | N11: =M11 -> 0 | O11: Exit Value | P11: 8.3 | Q11: 0 | R11: 0.1384 | S11: N.A | T11: =U11+V11 -> 234.30061 | U11: 0 | V11: 234.30061 | W11: =T11/P11 -> 28.228989 | X11: 0.45172761 | Y11: Exit via OFS in IPO and Public market | Z11: =V11/P11 -> 28.228989 | AA11: Venture debt, Support with IPO process, investor connects for IPO, business development connects , hiring | AC11: Referral by co-investor | AD11: Karthik | AE11: Ashish | AF11: Exited
B12: 8 | C12: Exotel Techcom Pvt. Ltd | D12: Exotel | E12: Bengaluru | F12: ='Fund 1X'!F6 -> SaaS | G12: 41096 | H12: Seed | I12: N.A | J12: 74.115367 | K12: N.A | L12: N.A | M12: 0 | N12: =M12 -> 0 | O12: Exit Value | P12: 10 | Q12: 0 | R12: 0.12 | S12: N.A | T12: =U12+V12 -> 199.34942 | U12: 0 | V12: 199.34942 | W12: =T12/P12 -> 19.934942 | X12: 0.43172993 | Y12: Sale to Fund 1X | Z12: =V12/P12 -> 19.934942 | AA12: Board participation, Business Development connects, Hiring | AB12: Mumbai Angels | AC12: Angel Network | AD12: Karthik | AE12: Karthik | AF12: Exited
B13: 9 | C13: Baldor Technologies Private Ltd | D13: Idfy | E13: Mumbai | F13: FinTech | G13: 41046 | H13: Seed | I13: N.A | J13: 57.767017 | K13: N.A | L13: N.A | M13: 0 | N13: =M13 -> 0 | O13: Exit Value | P13: 11.2 | Q13: 0 | R13: 0.098787497 | S13: N.A | T13: =U13+V13 -> 157.90365 | U13: 0 | V13: 157.90365 | W13: =T13/P13 -> 14.09854 | X13: 0.39209596 | Y13: Sale to Fund 1X | Z13: =V13/P13 -> 14.09854 | AA13: Business Development connects, Investor connect, hiring | AB13: MegaDelta, Dream Incubator | AC13: co-investor network - angel | AD13: Karthik | AE13: Karthik | AF13: Exited
B14: 10 | C14: Solvy Tech Solutions Pvt. Ltd | D14: Zopper | E14: Delhi | F14: FinTech | G14: 41367 | H14: Seed | I14: N.A | J14: 28.484574 | K14: N.A | L14: N.A | M14: 0 | N14: =M14 -> 0 | O14: Exit Value | P14: 18.5 | Q14: 0 | R14: 0.08116874 | S14: N.A | T14: =U14+V14 -> 387.62304 | U14: 0 | V14: 387.62304 | W14: =T14/P14 -> 20.952597 | X14: 0.37970463 | Y14: Sale to Fund 1Y | Z14: =V14/P14 -> 20.952597 | AA14: Sourcing of follow-on round investors, Finance and compliance support, assistance with M&A transactions , hiring | AB14: Tiger Global, Nirvana | AC14: Alumni network of GPs | AD14: Karthik | AE14: Karthik | AF14: Exited
B15: 11 | C15: Social Audience Private Ltd | D15: TookiTaki | E15: Bengaluru | F15: FinTech | G15: 41477 | H15: Seed | I15: N.A | J15: 122.28 | K15: 361.8393 | L15: =K15 -> 361.8393 | M15: 1 | N15: =L15*(1-M15) -> 0 | O15: Provisioned - 100% | P15: 4.8 | Q15: 0 | R15: 0.11835759 | S15: 0.0016 | T15: =U15+V15 -> 0 | U15: 0 | V15: 0 | W15: =T15/P15 -> 0 | X15: NA | AA15: Hiring, Finance & compliance support | AB15: Jungle Ventures, Rebright, Illuminate Financial | AC15: Referral by co-investor | AD15: Sanjay | AE15: Sanjay | AF15: Provisioned
B16: 12 | C16: Induslynk Training Services Pvt. Ltd. | D16: Mettl | E16: Delhi | F16: HRTech | G16: 40636 | H16: Seed | I16: N.A | J16: 112.27979 | K16: N.A | L16: N.A | M16: 0 | N16: =M16 -> 0 | O16: Exit Value | P16: 34 | Q16: 0 | R16: 0.089108358 | S16: N.A | T16: =U16+V16 -> 210.26103 | U16: 0 | V16: 210.26103 | W16: =T16/P16 -> 6.1841478 | X16: 0.34323018 | Y16: Acquisition by Mercer | Z16: =V16/P16 -> 6.1841478 | AA16: Follow-on investsor connect, finance and compliance support , business development connects, hiring | AB16: Kalaari | AC16: Founder network ( Inmobi founder ) | AD16: Sanjay | AE16: Karthik | AF16: Exited
B17: 13 | C17: ZipDial Mobile Solution Private Limited | D17: Zip Dial | E17: Bengaluru | F17: SaaS | G17: 40659 | H17: Seed | I17: N.A | J17: 122.28 | K17: N.A | L17: N.A | M17: 0 | N17: =M17 -> 0 | O17: Exit Value | P17: 15.5 | Q17: 0 | R17: 0.0245 | S17: N.A | T17: =U17+V17 -> 80.3 | U17: 0 | V17: 80.3 | W17: =T17/P17 -> 5.1806452 | X17: 0.61345489 | Y17: Acquisition by Twitter | Z17: =V17/P17 -> 5.1806452 | AA17: Introduction to follow-on round investors, Board participation | AB17: DSG, 500 Startups, Jungle Ventures, Times Internet, Unilazer | AC17: Angel Network | AD17: Karthik | AE17: Karthik | AF17: Exited
B18: 14 | C18: Webklipper Technologies Pvt. Ltd | D18: Webengage | E18: Mumbai | F18: SaaS | G18: 41257 | H18: Seed | I18: N.A | J18: 166.668 | K18: N.A | L18: N.A | M18: 0 | N18: =M18 -> 0 | O18: Exit Value | P18: 21.292777 | Q18: 0 | R18: 0.0605 | S18: N.A | T18: =U18+V18 -> 82.680533 | U18: 0 | V18: 82.680533 | W18: =T18/P18 -> 3.8830319 | X18: 0.20506152 | Y18: Sale to Fund 1X | Z18: =V18/P18 -> 3.8830319 | AA18: Board participation, Business Development connects, evaluating collaborations and acqui-hires from time to time, Hiring, Finance & compliance support | AB18: GTI Capital, IQ Capital, IAN | AC18: Referral by co-investor | AD18: Karthik | AE18: Karthik | AF18: Exited
B19: 15 | C19: Adepto Solutions Private Ltd | D19: Adepto | E19: Bengaluru | F19: AdTech | G19: 40746 | H19: Seed | I19: N.A | J19: 47.3 | K19: N.A | L19: N.A | M19: 0 | N19: =M19 -> 0 | O19: Written Off | P19: 11 | Q19: 0 | R19: 0.12675053 | S19: N.A | T19: =U19+V19 -> 0.00177 | U19: 0 | V19: 0.00177 | W19: =T19/P19 -> 0.00016090909 | X19: NA | AC19: Co-investor referral ( angel investor) | AD19: Karthik | AE19: Karthik | AF19: Written Off
C20: Kuliza Technologies Pvt. Ltd | D20: Kuliza | E20: Bengaluru | F20: FinTech | G20: 41485 | H20: Seed | I20: N.A | J20: N.A | K20: N.A | L20: N.A | M20: 0 | N20: =M20 -> 0 | O20: Provisioned - 100% | P20: 5 | Q20: 0 | R20: 0.070800706 | S20: N.A | T20: =U20+V20 -> 0 | U20: 0 | V20: 0 | W20: =T20/P20 -> 0 | X20: NA | AA20: Facilitating M&A, Finance and compliance support, business development connects | AB20: Emergent Ventures | AC20: Swap of shares of Adepto | AD20: Karthik | AE20: Ashish | AF20: Provisioned
B21: 16 | C21: Greytip Software Private Ltd | D21: Greytip | E21: Bengaluru | F21: HRTech | G21: 41607 | H21: Seed | I21: Series E | J21: 319.99753 | K21: N.A | L21: N.A | M21: 0 | N21: 0 | O21: Exit Value | P21: 21.000682 | Q21: 0 | R21: 0.049903462 | S21: 0.02628157 | T21: =U21+V21 -> 189.8619 | U21: 0 | V21: 189.8619 | W21: =T21/P21 -> 9.0407493 | X21: 0.24203198 | Y21: Secondary sale to Apax Partners | Z21: =V21/P21 -> 9.0407493 | AA21: support for venture debt, structuring of follow-on round, Business Development connects , Hiring, Finance & compliance support | AB21: MegaDelta, InfoEdge, GMO | AC21: Ecosystem referral | AD21: Karthik | AE21: Karthik | AF21: Exited
B22: 17 | C22: Promptec Renewable Energy Solutions Private Limited | D22: Prompt Renewables | E22: Bengaluru | F22: CleanTech | G22: 40627 | H22: Seed | I22: N.A | J22: 90 | K22: N.A | L22: N.A | M22: 0 | N22: =M22 -> 0 | O22: Exit Value | P22: 45 | Q22: 0 | R22: 0.055555576 | S22: N.A | T22: =U22+V22 -> 97.239294 | U22: 0 | V22: 97.239294 | W22: =T22/P22 -> 2.1608732 | X22: 0.28793276 | Y22: Acquisition by Havells | Z22: =V22/P22 -> 2.1608732 | AA22: Business Development connects, facilitating / helping in M&A, general counsel | AC22: Alumni network of GPs ( Karthik's alum introduced to the founder ) | AD22: Karthik | AE22: Karthik | AF22: Exited
B23: 18 | C23: Turtle Yogi Technologies Private Ltd | D23: 1Click (Turtleyogi) | E23: Bengaluru | F23: Digital media | G23: 41433 | H23: Seed | I23: N.A | J23: 30 | K23: N.A | L23: N.A | M23: 0 | N23: =M23 -> 0 | O23: Exit Value | P23: 4.8 | Q23: 0 | R23: 0.14250239 | S23: N.A | T23: =U23+V23 -> 7.9 | U23: 0 | V23: 7.9 | W23: =T23/P23 -> 1.6458333 | X23: 0.38133907 | Y23: Acquisition by Freshworks | Z23: =V23/P23 -> 1.6458333 | AA23: Finance and compliance, business development , connect with strategic collaborator , structuring of exit transaction | AC23: Angel Network | AD23: Karthik | AE23: Ashish | AF23: Exited
B24: 19 | C24: Threadsol Software Private Ltd | D24: Threadsol | E24: Delhi | F24: SaaS | G24: 41631 | H24: Seed | I24: N.A | J24: 52 | K24: N.A | L24: N.A | M24: 0 | N24: =M24 -> 0 | O24: Exit Value | P24: 13.891466 | Q24: 0 | R24: 0.1 | S24: N.A | T24: =U24+V24 -> 20.700262 | U24: 0 | V24: 20.700262 | W24: =T24/P24 -> 1.4901424 | X24: 0.10671253 | Y24: Acquisition by Coates Plc | Z24: =V24/P24 -> 1.4901424 | AA24: Business Development connects, Investor connect, Structuring of business as a SG domiciled entity, finance and compliance, Hiring , structuring of exit transaction | AB24: Catamaran Ventures | AC24: Angel Network | AD24: Karthik | AE24: Ashish | AF24: Exited
B25: 20 | C25: Newgen Internet Networks Pvt. Ltd | D25: Glamrs | E25: Mumbai | F25: Digital Media | G25: 41096 | H25: Seed | I25: N.A | J25: 89.96736 | K25: N.A | L25: N.A | M25: 0 | N25: =M25 -> 0 | O25: Exit Value | P25: 19 | Q25: 0 | R25: 0.11115142 | S25: N.A | T25: =U25+V25 -> 28.5 | U25: 0 | V25: 28.5 | W25: =T25/P25 -> 1.5 | X25: 0.046158484 | Y25: Acquisition by Purplle | Z25: =V25/P25 -> 1.5 | AA25: Business Development connects, Investor connect, finance and compliance, Hiring | AC25: Founder network | AD25: Karthik | AE25: Ashish | AF25: Exited
B26: 21 | C26: Spunk Media Private Ltd | D26: Qubecell | E26: Mumbai | F26: FinTech | G26: 41458 | H26: Seed | I26: N.A | J26: 63.25 | K26: N.A | L26: N.A | M26: 0 | N26: =M26 -> 0 | O26: Exit Value | P26: 3.5 | Q26: 0 | R26: 0.055335966 | S26: N.A | T26: =U26+V26 -> 5.1 | U26: 0 | V26: 5.1 | W26: =T26/P26 -> 1.4571429 | X26: 0.60094962 | Y26: Acquisition by Boku | Z26: =V26/P26 -> 1.4571429 | AB26: Kae Capital | AC26: Angel Network | AD26: Karthik | AE26: Adit* | AF26: Exited
B27: 22 | C27: Nowfloats Technologies Private Ltd | D27: Nowfloats | E27: Hyderabad | F27: SaaS | G27: 41439 | H27: Seed | I27: N.A | J27: 99.222222 | K27: N.A | L27: N.A | M27: 0 | N27: =M27 -> 0 | O27: Exit Value | P27: 13.48784 | Q27: 0 | R27: 0.0504 | S27: N.A | T27: =U27+V27 -> 17.265207 | U27: 0 | V27: 17.265207 | W27: =T27/P27 -> 1.2800572 | X27: 0.047209263 | Y27: Acquisition by Reliance Jio | Z27: =V27/P27 -> 1.2800572 | AA27: Business Development connects, Investor connect, finance and compliance, hiring | AB27: Omidyar, IIFL, Iron Pillar | AC27: Angel Network | AD27: Karthik | AE27: Ashish | AF27: Exited
B28: 23 | C28: Framebench Technologies Pvt. Ltd. | D28: Framebench | E28: Bengaluru | F28: Digital media | G28: 41082 | H28: Seed | I28: N.A | J28: 30.55 | K28: N.A | L28: N.A | M28: 0 | N28: =M28 -> 0 | O28: Exit Value | P28: 4.04 | Q28: 0 | R28: 0.1487 | S28: N.A | T28: =U28+V28 -> 4 | U28: 0 | V28: 4 | W28: =T28/P28 -> 0.99009901 | X28: -0.0026144622 | Y28: Acquisition by Freshworks | Z28: =V28/P28 -> 0.99009901 | AA28: Sourcing of follow-on round investors, Finance and compliance support, assistance with M&A transactions | AC28: Alumni network of GPs ( BITS alum connected throigh Sanjay) | AD28: Sanjay | AE28: Sanjay | AF28: Exited
B29: 24 | C29: Printo Document Services Private Ltd | D29: Printo | E29: Bengaluru | F29: E-Commerce | G29: 41162 | H29: Seed | I29: Series C1 | J29: 124.98675 | K29: 1063.8298 | L29: =K29 -> 1063.8298 | M29: 1 | N29: =L29*(1-M29) -> 0 | O29: Provisioned - 100% | P29: 15 | Q29: 0 | R29: 0.060006361 | S29: 0.0392 | T29: =U29+V29 -> 0 | U29: 0 | V29: 0 | W29: =T29/P29 -> 0 | X29: NA | AA29: Board participation, Business Development connects, evaluating collaborations and acqui-hires from time to time | AB29: Infoedge | AC29: Fund advisor's referral | AD29: Karthik | AE29: Karthik | AF29: Provisioned
B30: 25 | C30: HMS Infotech Private Ltd /Hotelogix Pte Limited | D30: Hotelogix | E30: Bengaluru | F30: Consumer Services | G30: 41004 | H30: Seed | I30: Series C | J30: 96.5 | K30: 1042.0633 | L30: =K30 -> 1042.0633 | M30: 1 | N30: =L30*(1-M30) -> 0 | O30: Provisioned - 100% | P30: 13.862911 | Q30: 0 | R30: 0.025890801 | S30: 0.015292786 | T30: =U30+V30 -> 0 | U30: 0 | V30: 0 | W30: =T30/P30 -> 0 | X30: NA | AA30: Board participation, cross-border structuring support , Finance & compliance support | AB30: Accel, Saama, Vertex | AC30: angel ecosystem | AD30: Karthik | AE30: Sanjay | AF30: Provisioned
B31: 26 | C31: Nivaata Systems Private Ltd | D31: Nivaata | E31: Bengaluru | F31: Urban Mobility | G31: 40919 | H31: Seed | I31: Pre Series C | J31: 109.12997 | K31: 8762 | L31: =K31 -> 8762 | M31: 1 | N31: =L31*(1-M31) -> 0 | O31: Provisioned - 100% | P31: 23.686624 | Q31: 0 | R31: 0.079264284 | S31: 0.077865743 | T31: =U31+V31 -> 0 | U31: 0 | V31: 0 | W31: =T31/P31 -> 0 | X31: NA | AA31: Strategy, Business Development connects, Hiring including sourcing of CXO | AB31: Bosch, Mayfield, GWB Group, VAMM Ventures | AC31: Eco-system referral | AD31: Karthik | AE31: Ashish | AF31: Provisioned
B32: 27 | C32: Chaitanya India Fin Credit Private Limited | D32: Chaitanya India | E32: Bengaluru | F32: FinTech | G32: 40578 | H32: Seed | I32: N.A | J32: 165.3 | K32: N.A | L32: N.A | M32: 0 | N32: =M32 -> 0 | O32: Exit Value | P32: 3.6 | Q32: 0 | R32: 0.021778584 | S32: N.A | T32: =U32+V32 -> 3.6 | U32: 0 | V32: 3.6 | W32: =T32/P32 -> 1 | X32: 4.8828125e-09 | Y32: Buyback | Z32: =V32/P32 -> 1 | AC32: Founder network | AD32: Karthik | AE32: Karthik | AF32: Exited
B33: 28 | C33: Valgen Infosystem Pvt Ltd. | D33: Valgen Infosystems | E33: Chennai | F33: RetailTech | G33: 40636 | H33: Seed | I33: N.A | J33: 69.9996 | K33: N.A | L33: N.A | M33: 0 | N33: =M33 -> 0 | O33: Exit Value | P33: 10.625 | Q33: 0 | R33: 0.10714347 | S33: N.A | T33: =U33+V33 -> 9.7394 | U33: 0 | V33: 9.7394 | W33: =T33/P33 -> 0.91664941 | X33: -0.009878268 | Y33: Acqusition by CloudCherry | Z33: =V33/P33 -> 0.91664941 | AC33: VC referral | AD33: Karthik | AE33: Karthik | AF33: Exited
B34: 29 | C34: WAH Holidays Private Ltd | D34: WeAreHolidays | E34: Delhi | F34: Consumer Services | G34: 41358 | H34: Seed | I34: N.A | J34: 55.2784 | K34: N.A | L34: N.A | M34: 0 | N34: =M34 -> 0 | O34: Written Off | P34: 7.5 | Q34: 0 | R34: 0.045269038 | S34: N.A | T34: =U34+V34 -> 2.7 | U34: 0 | V34: 2.7 | W34: =T34/P34 -> 0.36 | X34: NA | Z34: =V34/P34 -> 0.36 | AA34: Business Development connects, Finance and compliance support, Board participation, hiring, structuring of follow-on rounds | AB34: Matrix, Mumbai Angels | AC34: Angel Network | AD34: Sanjay | AE34: Karthik | AF34: Written Off
B35: 30 | C35: Karmic Labs Pvt.Ltd. | D35: Karmic | E35: Mumbai | F35: Life Sciences | G35: 40785 | H35: Seed | I35: N.A | J35: 51.047856 | K35: N.A | L35: N.A | M35: 0 | N35: =M35 -> 0 | O35: Written Off | P35: 10 | Q35: 0 | R35: 0.19594078 | S35: N.A | T35: =U35+V35 -> 2.8 | U35: 0 | V35: 2.8 | W35: =T35/P35 -> 0.28 | X35: NA | Z35: =V35/P35 -> 0.28 | AB35: Mumbai Angels, IAN | AC35: Angel Network | AD35: Karthik | AE35: Karthik | AF35: Written Off
B36: 31 | C36: Rolocule Games Pvt. Ltd | D36: Rolocule | E36: Pune | F36: Digital Media | G36: 41003 | H36: Seed | I36: N.A | J36: 62.6 | K36: N.A | L36: N.A | M36: 0 | N36: =M36 -> 0 | O36: Written Off | P36: 29.63569 | Q36: 0 | R36: 0.036817256 | S36: N.A | T36: =U36+V36 -> 7.486435 | U36: 0 | V36: 7.486435 | W36: =T36/P36 -> 0.25261551 | X36: NA | Z36: =V36/P36 -> 0.25261551 | AA36: Board participation, Finance and compliance support, facilitating co-founder split amicably | AB36: Mumbai Angels | AC36: Angel Network | AD36: Karthik | AE36: Karthik | AF36: Written Off
B37: 32 | C37: Shantani Proteome Analytics Pvt. Ltd | D37: Shantani | E37: Pune | F37: Life Sciences | G37: 41059 | H37: Seed | I37: N.A | J37: 44.76496 | K37: N.A | L37: N.A | M37: 0 | N37: =M37 -> 0 | O37: Written Off | P37: 8.8 | Q37: 0 | R37: 0.1116945 | S37: N.A | T37: =U37+V37 -> 1.74379 | U37: 0 | V37: 1.74379 | W37: =T37/P37 -> 0.19815795 | X37: NA | Z37: =V37/P37 -> 0.19815795 | AA37: Finance & compliance support | AB37: India Innovation Fund | AC37: Referral by co-investor | AD37: Karthik | AE37: Karthik | AF37: Written Off
B38: 33 | C38: RupeeStreet Financial Services Pvt Ltd. | D38: Moneysights | E38: Bengaluru | F38: FinTech | G38: 40850 | H38: Seed | I38: N.A | J38: 135 | K38: N.A | L38: N.A | M38: 0 | N38: =M38 -> 0 | O38: Written Off | P38: 11.999205 | Q38: 0 | R38: 0.074074074 | S38: N.A | T38: =U38+V38 -> 2.0098 | U38: 0 | V38: 2.0098 | W38: =T38/P38 -> 0.16749443 | X38: NA | Z38: =V38/P38 -> 0.16749443 | AA38: Introduction to follow-on round investors | AC38: Founder network ( connected through the founder’s prior start-up) | AD38: Sanjay | AE38: Sanjay | AF38: Written Off
B39: 34 | C39: Eki Communications Pvt Ltd | D39: Survelytics | E39: Mumbai | F39: MarketingTech | G39: 40654 | H39: Seed | I39: N.A | J39: 37.5 | K39: N.A | L39: N.A | M39: 0 | N39: =M39 -> 0 | O39: Written Off | P39: 5.5 | Q39: 0 | R39: 0.13333333 | S39: N.A | T39: =U39+V39 -> 0.002088 | U39: 0 | V39: 0.002088 | W39: =T39/P39 -> 0.00037963636 | X39: NA | Z39: =V39/P39 -> 0.00037963636 | AA39: Compliance support | AC39: Referral by co-investor | AD39: Sanjay | AE39: Sanjay | AF39: Written Off
B40: 35 | C40: Retail Quotient Research Pvt.Ltd | D40: RedQuanta | E40: Mumbai | F40: RetailTech | G40: 41142 | H40: Seed | I40: N.A | J40: 65.2 | K40: N.A | L40: N.A | M40: 0 | N40: =M40 -> 0 | O40: Written Off | P40: 5.484572 | Q40: 0 | R40: 0.053666542 | S40: N.A | T40: =U40+V40 -> 0.01276 | U40: 0 | V40: 0.01276 | W40: =T40/P40 -> 0.0023265261 | X40: NA | Z40: =V40/P40 -> 0.0023265261 | AC40: Accelerator network | AD40: Karthik | AE40: Sajid Fazalbhoy* | AF40: Written Off
B41: 36 | C41: 21Trends Private Ltd | D41: VoxPop | E41: Mumbai | F41: E-Commerce | G41: 41478 | H41: Seed | I41: N.A | J41: 30 | K41: N.A | L41: N.A | M41: 0 | N41: =M41 -> 0 | O41: Written Off | P41: 7.5 | Q41: 0 | R41: 0.25 | S41: N.A | T41: =U41+V41 -> 0.008286 | U41: 0 | V41: 0.008286 | W41: =T41/P41 -> 0.0011048 | X41: NA | Z41: =V41/P41 -> 0.0011048 | AA41: Facilitating collaboration with strategic investor, strategic media arrangement, Finance & compliance support | AC41: Founder network | AD41: Karthik | AE41: Ashish | AF41: Written Off
B42: 37 | C42: VoxApp Pvt.Ltd. | D42: Vox App | E42: Delhi | F42: RetailTech | G42: 41358 | H42: Seed | I42: N.A | J42: 97 | K42: N.A | L42: N.A | M42: 0 | N42: =M42 -> 0 | O42: Written Off | P42: 5 | Q42: 0 | R42: 0.051546392 | S42: N.A | T42: =U42+V42 -> 0.00385 | U42: 0 | V42: 0.00385 | W42: =T42/P42 -> 0.00077 | X42: NA | Z42: =V42/P42 -> 0.00077 | AA42: Business Development connects | AC42: Founder network ( connected through the founder’s prior start-up) | AD42: Karthik | AE42: Ashish | AF42: Written Off
B43: 38 | C43: Paletly Designs Private Limited | D43: Paletly | E43: Mumbai | F43: E-Commerce | G43: 41568 | H43: Seed | I43: N.A | J43: 48.5 | K43: N.A | L43: N.A | M43: 0 | N43: =M43 -> 0 | O43: Written Off | P43: 5.170561 | Q43: 0 | R43: 0.0676 | S43: N.A | T43: =U43+V43 -> 0.003316 | U43: 0 | V43: 0.003316 | W43: =T43/P43 -> 0.00064132306 | X43: NA | Z43: =V43/P43 -> 0.00064132306 | AA43: General counsel , Finance & compliance support | AB43: Kae Capital, Mumbai Angels | AC43: Co-investor referral | AD43: Karthik | AE43: Karthik | AF43: Written Off
B44: 39 | C44: Sporting Mindz | D44: Sporting Mindz | E44: Bengaluru | F44: E-Commerce | G44: 41509 | H44: Seed | I44: N.A | J44: 55.2 | K44: N.A | L44: N.A | M44: 0 | N44: =M44 -> 0 | O44: Written Off | P44: 2.5 | Q44: 0 | R44: 0.045289855 | S44: N.A | T44: =U44+V44 -> 0.001414 | U44: 0 | V44: 0.001414 | W44: =T44/P44 -> 0.0005656 | X44: NA | Z44: =V44/P44 -> 0.0005656 | AA44: Hiring, structuring M&A, connects to follow-on round investors, Board participation, finance and compliance | AC44: Founder network ( connected through the founder's prior start-up) | AD44: Karthik | AE44: Ashish | AF44: Written Off
C45: SportsNest Retail India Private Limited | D45: SportsNest | E45: Bengaluru | F45: E-Commerce | G45: 40837 | H45: Seed | I45: N.A | J45: N.A | K45: N.A | L45: N.A | M45: 0 | N45: =M45 -> 0 | O45: Written Off | P45: 19.1 | Q45: 0 | R45: 0.21052632 | S45: N.A | T45: =U45+V45 -> 0.0075788 | U45: 0 | V45: 0.0075788 | W45: =T45/P45 -> 0.00039679581 | X45: NA | Z45: =V45/P45 -> 0.00039679581 | AA45: Hiring, structuring M&A transaction, connects to follow-on round investors, Board participation, finance and compliance support | AD45: Karthik | AE45: Ashish | AF45: Written Off
C46: PlaygroundOnline | D46: PlaygroundOnline | E46: Bengaluru | F46: E-Commerce | G46: 41041 | H46: Seed | I46: N.A | J46: N.A | K46: N.A | L46: N.A | M46: 0 | N46: =M46 -> 0 | O46: Written Off | P46: 9.1 | Q46: 0 | R46: N.A | S46: N.A | T46: =U46+V46 -> 0.0091 | U46: 0 | V46: 0.0091 | W46: =T46/P46 -> 0.001 | X46: NA | Z46: =V46/P46 -> 0.001 | AA46: Hiring, structuring M&A, connects to follow-on round investors, Board participation, finance and compliance support | AC46: Founder network | AD46: Ashish | AE46: Ashish | AF46: Written Off
B47: 40 | C47: Fun Holidays & Vacations Pvt.Ltd. | D47: Polama | E47: Bengaluru | F47: Consumer Services | G47: 40780 | H47: Seed | I47: N.A | J47: 46.7 | K47: N.A | L47: N.A | M47: 0 | N47: =M47 -> 0 | O47: Written Off | P47: 3.5 | Q47: 0 | R47: 0.074946467 | S47: N.A | T47: =U47+V47 -> 0.001362 | U47: 0 | V47: 0.001362 | W47: =T47/P47 -> 0.00038914286 | X47: NA | Z47: =V47/P47 -> 0.00038914286 | AB47: Orios | AC47: VC referral | AD47: Karthik | AE47: Karthik | AF47: Written Off
B48: 41 | C48: Emotion Squard Technologies Private Ltd | D48: Emo2 | E48: Chennai | F48: SaaS | G48: 40975 | H48: Seed | I48: N.A | J48: 42.5 | K48: N.A | L48: N.A | M48: 0 | N48: =M48 -> 0 | O48: Written Off | P48: 9.4 | Q48: 0 | R48: 0.1 | S48: N.A | T48: =U48+V48 -> 0.003538 | U48: 0 | V48: 0.003538 | W48: =T48/P48 -> 0.00037638298 | X48: NA | Z48: =V48/P48 -> 0.00037638298 | AA48: Business development connects | AC48: Accelerator network | AD48: Karthik | AE48: Karthik | AF48: Written Off
B49: 42 | C49: Audio compass (India) Private Ltd | D49: AudioCompass | E49: Mumbai | F49: Consumer Services | G49: 41515 | H49: Seed | I49: N.A | J49: 90.8 | K49: N.A | L49: N.A | M49: 0 | N49: =M49 -> 0 | O49: Written Off | P49: 12.5 | Q49: 0 | R49: 0.12114537 | S49: N.A | T49: =U49+V49 -> 0.00428146 | U49: 0 | V49: 0.00428146 | W49: =T49/P49 -> 0.0003425168 | X49: NA | Z49: =V49/P49 -> 0.0003425168 | AA49: Introduction to follow-on round investors, Board participation, Finance & compliance support | AB49: Cox & Kings | AC49: Personal network of GPs | AD49: Karthik | AE49: Karthik | AF49: Written Off
B50: 43 | C50: Touchfone Technology (I) Pvt.Ltd. | D50: Touchfone | E50: Bengaluru | F50: Digital media | G50: 42625 | H50: Seed | I50: N.A | J50: 90 | K50: N.A | L50: N.A | M50: 0 | N50: =M50 -> 0 | O50: Written Off | P50: 3.170683 | Q50: 0 | R50: 0.10025 | S50: N.A | T50: =U50+V50 -> 5.851818 | U50: 0 | V50: 5.851818 | W50: =T50/P50 -> 1.8456017 | X50: NA | Z50: =V50/P50 -> 1.8456017 | AC50: VC referral | AD50: Karthik | AE50: Karthik | AF50: Written Off
C51: ScoopWhoop Media Private Ltd | D51: ScoopWhoop | E51: Delhi | F51: Digital media | G51: 42625 | H51: Seed | I51: N.A | J51: N.A | K51: N.A | L51: N.A | M51: 0 | N51: =M51 -> 0 | O51: Written Off | P51: 6.176919 | Q51: 0 | R51: N.A | S51: N.A | T51: =U51+V51 -> 6.794611 | U51: 0 | V51: 6.794611 | W51: =T51/P51 -> 1.1 | X51: NA | Z51: =V51/P51 -> 1.1 | AB51: Kalaari, Bharti Softbank | AC51: Swap for shares in Touchfone | AE51: Ashish | AF51: Written Off
B52: 44 | C52: Sparsha Learning Technologies Pvt.Ltd. | D52: Sparsha | E52: Bengaluru | F52: EdTech | G52: 40806 | H52: Seed | I52: N.A | J52: 49.994 | K52: N.A | L52: N.A | M52: 0 | N52: =M52 -> 0 | O52: Written Off | P52: 6.748 | Q52: 0 | R52: 0.134 | S52: N.A | T52: =U52+V52 -> 0.001928 | U52: 0 | V52: 0.001928 | W52: =T52/P52 -> 0.00028571429 | X52: NA | Z52: =V52/P52 -> 0.00028571429 | AC52: Co-investor referral ( angel investor) | AD52: Karthik | AE52: Karthik | AF52: Written Off
B53: 45 | C53: Style Kitchen Enterprises Pvt.Ltd. | D53: Missisippy | E53: Delhi | F53: E-Commerce | G53: 41142 | H53: Seed | I53: N.A | J53: 77.613654 | K53: N.A | L53: N.A | M53: 0 | N53: =M53 -> 0 | O53: Written Off | P53: 10 | Q53: 0 | R53: 0.12886598 | S53: N.A | T53: =U53+V53 -> 0.002382 | U53: 0 | V53: 0.002382 | W53: =T53/P53 -> 0.0002382 | X53: NA | Z53: =V53/P53 -> 0.0002382 | AA53: Business Development connects, Finance and compliance support , Board participation | AC53: Ecosystem referral | AD53: Karthik | AE53: Sajid Fazalbhoy* | AF53: Written Off
B54: 46 | C54: Insieve Private Limited | D54: Insieve | E54: Bengaluru | F54: Social Media | G54: 40994 | H54: Seed | I54: N.A | J54: 105.77778 | K54: N.A | L54: N.A | M54: 0 | N54: =M54 -> 0 | O54: Written Off | P54: 11.333985 | Q54: 0 | R54: 0.10712651 | S54: N.A | T54: =U54+V54 -> 0.002684 | U54: 0 | V54: 0.002684 | W54: =T54/P54 -> 0.00023680991 | X54: NA | Z54: =V54/P54 -> 0.00023680991 | AB54: Ojas | AC54: Angel Network | AD54: Karthik | AE54: Karthik | AF54: Written Off
B55: 47 | C55: IStage Entertainment Private Limited | D55: Indian Stage | E55: Bengaluru | F55: Business Services | G55: 41499 | H55: Seed | I55: N.A | J55: 80 | K55: N.A | L55: N.A | M55: 0 | N55: =M55 -> 0 | O55: Written Off | P55: 10.7 | Q55: 0 | R55: 0.12029569 | S55: N.A | T55: =U55+V55 -> 0.002074 | U55: 0 | V55: 0.002074 | W55: =T55/P55 -> 0.00019383178 | X55: NA | Z55: =V55/P55 -> 0.00019383178 | AA55: Board participation, Finance and compliance support, support for M&A | AC55: Co-investor referral | AD55: Karthik | AE55: Ashish | AF55: Written Off
B56: 48 | C56: Aurality Technologies Private Limited | D56: Giftery | E56: Mumbai | F56: E-Commerce | G56: 40994 | H56: Seed | I56: N.A | J56: 46.6 | K56: N.A | L56: N.A | M56: 0 | N56: =M56 -> 0 | O56: Written Off | P56: 3.675029 | Q56: 0 | R56: 0.078863283 | S56: N.A | T56: =U56+V56 -> 0 | U56: 0 | V56: 0 | W56: =T56/P56 -> 0 | X56: NA | Z56: =V56/P56 -> 0 | AA56: Help with M&A, Board participation | AC56: Co-investor referral ( angel investor) | AD56: Karthik | AE56: Karthik | AF56: Written Off
C57: GCI Network Pvt. Ltd | D57: GiftCardsIndia | E57: Mumbai | F57: E-Commerce | G57: 41985 | H57: Seed | I57: N.A | J57: N.A | K57: N.A | L57: N.A | M57: 0 | N57: =M57 -> 0 | O57: Written Off | P57: 2.499278 | Q57: 0 | R57: N.A | S57: N.A | T57: =U57+V57 -> 0.00272 | U57: 0 | V57: 0.00272 | W57: =T57/P57 -> 0.0010883143 | X57: NA | Z57: =V57/P57 -> 0.0010883143 | AC57: Acquired through swap of investment in Giftrey | AD57: Karthik | AE57: Karthik | AF57: Written Off
B58: 49 | C58: Madrat Games Private Ltd | D58: Madrat Games | E58: Bengaluru | F58: Gaming | G58: 40919 | H58: Seed | I58: N.A | J58: 45.529285 | K58: N.A | L58: N.A | M58: 0 | N58: =M58 -> 0 | O58: Written Off | P58: 23.8005 | Q58: 0 | R58: 0.21964984 | S58: N.A | T58: =U58+V58 -> 0.004156 | U58: 0 | V58: 0.004156 | W58: =T58/P58 -> 0.00017461818 | X58: NA | Z58: =V58/P58 -> 0.00017461818 | AB58: First Light Ventures | AC58: Outbound | AD58: Adit* | AE58: Adit* | AF58: Written Off
B59: 50 | C59: Spaces23 Software Labs Private Ltd. | D59: 23Spaces | E59: Mumbai | F59: AdTech | G59: 41156 | H59: Seed | I59: N.A | J59: 100 | K59: N.A | L59: N.A | M59: 0 | N59: =M59 -> 0 | O59: Written Off | P59: 19.26385 | Q59: 0 | R59: 0.125 | S59: N.A | T59: =U59+V59 -> 0.002144 | U59: 0 | V59: 0.002144 | W59: =T59/P59 -> 0.00011129655 | X59: NA | Z59: =V59/P59 -> 0.00011129655 | AA59: Board participation | AC59: Personal network of team member | AD59: Karthik | AE59: Adit* | AF59: Written Off
B60: 51 | C60: Careervita India Private Ltd | D60: Careervita | E60: Bengaluru | F60: HRTech | G60: 40917 | H60: Seed | I60: N.A | J60: 67.5 | K60: N.A | L60: N.A | M60: 0 | N60: =M60 -> 0 | O60: Written Off | P60: 23.499875 | Q60: 0 | R60: 0.17777778 | S60: N.A | T60: =U60+V60 -> 0.00237667 | U60: 0 | V60: 0.00237667 | W60: =T60/P60 -> 0.00010113543 | X60: NA | Z60: =V60/P60 -> 0.00010113543 | AA60: Strategic collaborator, hiring, business development connects, Finance & compliance support | AC60: Personal network of GPs | AD60: Karthik | AE60: Karthik | AF60: Written Off
B61: 52 | C61: Gharpay Money Transfer Services Pvt.Ltd. | D61: Clink | E61: Hyderabad | F61: FinTech | G61: 41239 | H61: Seed | I61: N.A | J61: 120 | K61: N.A | L61: N.A | M61: 0 | N61: =M61 -> 0 | O61: Written Off | P61: 10.0005 | Q61: 0 | R61: 0.0833375 | S61: N.A | T61: =U61+V61 -> 0.000667 | U61: 0 | V61: 0.000667 | W61: =T61/P61 -> 6.6696665e-05 | X61: NA | Z61: =V61/P61 -> 6.6696665e-05 | AB61: Sequoia | AC61: LP referral | AD61: Karthik | AE61: Karthik | AF61: Written Off
B62: 53 | C62: Remma Consulting Services Private Ltd. | D62: Remma | E62: Mumbai | F62: Real Estate | G62: 40667 | H62: Seed | I62: N.A | J62: 50 | K62: N.A | L62: N.A | M62: 0 | N62: =M62 -> 0 | O62: Written Off | P62: 6.5 | Q62: 0 | R62: 0.1625 | S62: N.A | T62: =U62+V62 -> 0.000275 | U62: 0 | V62: 0.000275 | W62: =T62/P62 -> 4.2307692e-05 | X62: NA | Z62: =V62/P62 -> 4.2307692e-05 | AC62: Co-investor referral ( angel investor) | AD62: Sanjay | AE62: Sajid Fazalbhoy* | AF62: Written Off
B63: 54 | C63: United Mobile Solutions Private Ltd | D63: UMA | E63: Bengaluru | F63: Social Media | G63: 41003 | H63: Seed | I63: N.A | J63: 111.33519 | K63: N.A | L63: N.A | M63: 0 | N63: =M63 -> 0 | O63: Written Off | P63: 6.054 | Q63: 0 | R63: 0.054393531 | S63: N.A | T63: =U63+V63 -> 0.000101 | U63: 0 | V63: 0.000101 | W63: =T63/P63 -> 1.6683185e-05 | X63: NA | Z63: =V63/P63 -> 1.6683185e-05 | AA63: Business Development connects | AB63: Mumbai Angels | AC63: Co-investor referral | AD63: Sanjay | AE63: Sanjay | AF63: Written Off
B64: 55 | C64: Cherish Maternity | D64: Cherish Maternity | E64: Bengaluru | F64: E-Commerce | G64: 41085 | H64: Seed | I64: N.A | J64: 33.3 | K64: N.A | L64: N.A | M64: 0 | N64: =M64 -> 0 | O64: Written Off | P64: 5 | Q64: 0 | R64: 0.075075075 | S64: N.A | T64: =U64+V64 -> 0.005237 | U64: 0 | V64: 0.005237 | W64: =T64/P64 -> 0.0010474 | X64: NA | Z64: =V64/P64 -> 0.0010474 | AB64: Orios, IAN | AC64: Co-investor referral | AD64: Karthik | AE64: Karthik | AF64: Written Off
B65: 56 | C65: Systemantics India Private Ltd | D65: Systemantics | E65: Bengaluru | F65: DeepTech | G65: 41585 | H65: Seed | I65: N.A | J65: 210 | K65: N.A | L65: N.A | M65: 0 | N65: =M65 -> 0 | O65: Written Off | P65: 10.5 | Q65: 0 | R65: 0.045 | S65: N.A | T65: =U65+V65 -> 0 | U65: 0 | V65: 0 | W65: =T65/P65 -> 0 | X65: NA | AB65: Nandan Nilekani, Accel | AC65: Referral by co-investor | AD65: Karthik | AE65: Karthik | AF65: Written Off
B66: 57 | C66: Hashcube Technologies Pvt. Ltd | D66: Hashcube | E66: Bengaluru | F66: Gaming | G66: 41096 | H66: Seed | I66: N.A | J66: 40 | K66: N.A | L66: N.A | M66: 0 | N66: =M66 -> 0 | O66: Written Off | P66: 4.15 | Q66: 0 | R66: 0.0625 | S66: N.A | T66: =U66+V66 -> 0.001174 | U66: 0 | V66: 0.001174 | W66: =T66/P66 -> 0.00028289157 | X66: NA | Z66: =V66/P66 -> 0.00028289157 | AB66: Nazara, IAN | AC66: co-investor network | AD66: Karthik | AE66: Karthik | AF66: Written Off
B67: 58 | C67: Snapbizz Cloudtech Pte Ltd | D67: Snapbizz | E67: Singapore | F67: RetailTech | G67: 41604 | H67: Seed | I67: Series B | J67: 1083.1349 | K67: 1272.25 | L67: =K67 -> 1272.25 | M67: 1 | N67: =L67*(1-M67) -> 0 | O67: Provisioned - 100% | P67: 10.7 | Q67: 0 | R67: 0.032851309 | S67: 0.019712355 | T67: =U67+V67 -> 0 | U67: 0 | V67: 0 | W67: =T67/P67 -> 0 | X67: NA | AB67: Jungle Ventures, Taurus Value Creation, Qualcomm | AC67: Founder network ( connected through the founder’s prior startup) | AD67: Karthik | AE67: Karthik | AF67: Provisioned
B68: 59 | C68: Shephertz Technologies Pvt.Ltd | D68: Shephertz | E68: Delhi | F68: Business Services | G68: 41298 | H68: Seed | I68: Series B1 | J68: 122.50433 | K68: 251.53551 | L68: =K68 -> 251.53551 | M68: 1 | N68: =L68*(1-M68) -> 0 | O68: Provisioned - 100% | P68: 13 | Q68: 0 | R68: 0.024478105 | S68: 0.057276884 | T68: =U68+V68 -> 0 | U68: 0 | V68: 0 | W68: =T68/P68 -> 0 | X68: NA | AA68: Board participation, Business Development connects, compliance support | AB68: Kae Capital, SRI Capital | AC68: Angel Network | AD68: Karthik | AE68: Sanjay | AF68: Provisioned
B69: 60 | C69: Ace Seafoods Bazar Private Ltd | D69: PescaFresh | E69: Mumbai | F69: E-Commerce | G69: 41502 | H69: Seed | I69: Pre Series A1 | J69: 187.5 | K69: 256.49967 | L69: =K69 -> 256.49967 | M69: 1 | N69: =L69*(1-M69) -> 0 | O69: Provisioned - 100% | P69: 13.9 | Q69: 0 | R69: 0.04276872 | S69: 0.0516 | T69: =U69+V69 -> 0 | U69: 0 | V69: 0 | W69: =T69/P69 -> 0 | X69: NA | AA69: Venture debt, general counsel , Hiring, Finance & compliance support | AB69: Orios, FAO Ventures | AC69: Angel Network | AD69: Karthik | AE69: Sajid Fazalbhoy* | AF69: Provisioned
B70: 61 | C70: Socialblood Inc | D70: Socialblood | E70: USA | F70: Social Media | G70: 41888 | H70: Seed | I70: Seed | J70: 17.886649 | K70: 17.886649 | L70: =K70 -> 17.886649 | M70: 1 | N70: =L70*(1-M70) -> 0 | O70: Provisioned - 100% | P70: 0.75 | Q70: 0 | R70: 0.037692638 | T70: =U70+V70 -> 0 | U70: 0 | V70: 0 | W70: =T70/P70 -> 0 | X70: NA | AC70: Referral by co-investor | AD70: Karthik | AE70: Karthik | AF70: Provisioned
B71: 62 | C71: Mobile Motion Technologies Pvt Ltd | D71: Mobstac | E71: Bengaluru | F71: RetailTech | G71: 40780 | H71: Seed | I71: N.A | J71: 77.330802 | K71: N.A | L71: N.A | M71: 0 | N71: =M71 -> 0 | O71: Exit Value | P71: 12.3 | Q71: 0 | R71: 0.025890801 | S71: N.A | T71: =U71+V71 -> 300.71141 | U71: 0 | V71: 300.71141 | W71: =T71/P71 -> 24.448082 | X71: 0.34608936 | Y71: Secondary sale to Telescope Partners | Z71: =V71/P71 -> 24.448082 | AA71: Hiring | AB71: Accel, Cisco | AC71: Angel Network | AD71: Karthik | AE71: Karthik | AF71: Exited
B72: 63 | C72: Infollion Research Services Private Ltd | D72: Infollion | E72: Delhi | F72: Business Services | G72: 41428 | H72: Seed | I72: N.A | J72: 80 | K72: N.A | L72: N.A | M72: 0 | N72: =M72 -> 0 | O72: Exit Value | P72: 8 | Q72: 0 | R72: 0.1 | S72: N.A | T72: =U72+V72 -> 101.35617 | U72: 0 | V72: 101.35617 | W72: =T72/P72 -> 12.669521 | X72: 0.29564655 | Y72: Exit via OFS in IPO and Public market | Z72: =V72/P72 -> 12.669521 | AA72: Board participation, Business Development connects | AC72: Founder referral ( E2E founder) | AD72: Karthik | AE72: Arpit | AF72: Exited
B73: 64 | C73: Signure Technologies Private Ltd | D73: Explara | E73: Bengaluru | F73: Business Services | G73: 41323 | H73: Seed | I73: Seed | J73: 32.25 | K73: 32.25 | L73: =K73 -> 32.25 | M73: 1 | N73: =L73*(1-M73) -> 0 | O73: Provisioned - 100% | P73: 11.8 | Q73: 0 | R73: 0.069767442 | T73: =U73+V73 -> 0 | U73: 0 | V73: 0 | W73: =T73/P73 -> 0 | X73: NA | AA73: Board participation, Business Development connects, structuring , finance and compliance support | AC73: Angel Network | AD73: Sajid Fazalbhoy* | AE73: Sajid Fazalbhoy* | AF73: Provisioned
B74: 65 | C74: OTH Online Pvt. Ltd. | D74: Accio | E74: Mumbai | F74: AdTech | G74: 41417 | H74: Seed | I74: N.A | J74: 276.38842 | K74: 619.75 | L74: =K74 -> 619.75 | M74: 1 | N74: =L74*(1-M74) -> 0 | O74: Provisioned - 100% | P74: 53.016539 | Q74: 0 | R74: 0.125 | S74: 0.14138401 | T74: =U74+V74 -> 1.476759 | U74: 0 | V74: 1.476759 | W74: =T74/P74 -> 0.027854685 | X74: NA | Z74: =V74/P74 -> 0.027854685 | AA74: Structuring of follow-on rounds, compliance support, Board participation , hiring , evluation of acqui-hires, strategic media arrangement | AC74: Alumni network of GPs | AD74: Karthik | AE74: Ashish | AF74: Provisioned
B75: 66 | C75: Level10 Enetrtainment Pvt. Ltd. | D75: Level10 | E75: Bengaluru | F75: Digital media | G75: 40780 | H75: Seed | I75: Seed | J75: 33 | K75: 33 | L75: =K75 -> 33 | M75: 1 | N75: =L75*(1-M75) -> 0 | O75: Provisioned - 100% | P75: 2.24 | Q75: 0 | R75: 0.066666667 | T75: =U75+V75 -> 0 | U75: 0 | V75: 0 | W75: =T75/P75 -> 0 | X75: NA | AB75: Seedfund | AC75: Angel Network | AD75: Karthik | AE75: Karthik | AF75: Provisioned
B76: 67 | C76: Covacsis Technologies Private Ltd | D76: Covacsis | E76: Mumbai | F76: SaaS | G76: 41142 | H76: Seed | I76: N.A | J76: 90 | K76: N.A | L76: N.A | M76: 0 | N76: =M76 -> 0 | O76: Written Off | P76: 19.9 | Q76: 0 | R76: 0.12222222 | S76: N.A | T76: =U76+V76 -> 0.025268 | U76: 0 | V76: 0.025268 | W76: =T76/P76 -> 0.0012697487 | X76: NA | Z76: =V76/P76 -> 0.0012697487 | AA76: Finance and compliance support, Business development , debt | AB76: Reliance GenNext, CISCO Ventures | AC76: Founder referral | AD76: Karthik | AE76: Karthik | AF76: Written Off
B77: 68 | C77: Appcity Commerce Pvt.Ltd. | D77: Unamia | E77: Bengaluru | F77: E-Commerce | G77: 41003 | H77: Seed | I77: N.A | J77: 223.7446 | K77: N.A | L77: N.A | M77: 0 | N77: =M77 -> 0 | O77: Written Off | P77: 5 | Q77: 0 | R77: 0.022346908 | S77: N.A | T77: =U77+V77 -> 0.0001 | U77: 0 | V77: 0.0001 | W77: =T77/P77 -> 2e-05 | X77: NA | Z77: =V77/P77 -> 2e-05 | AB77: Prime Ventures | AC77: Co-investor referral | AD77: Karthik | AE77: Karthik | AF77: Written Off
B78: 69 | C78: BatchCar | D78: BatchCar | E78: Mumbai | F78: Urban Mobility | G78: 41263 | H78: Seed | I78: N.A | J78: 77 | K78: N.A | L78: N.A | M78: 0 | N78: =M78 -> 0 | O78: Written Off | P78: 2 | Q78: 0 | R78: 0.025973974 | S78: N.A | T78: =U78+V78 -> 0 | U78: 0 | V78: 0 | W78: =T78/P78 -> 0 | X78: NA | AB78: Kae Capital | AC78: Angel Network | AD78: Sanjay | AE78: Sanjay | AF78: Written Off
B79: 70 | C79: Occasion Commerce Private Ltd | D79: Skoolshop | E79: Mumbai | F79: Business Services | G79: 41306 | H79: Seed | I79: N.A | J79: 56.246962 | K79: N.A | L79: N.A | M79: 0 | N79: =M79 -> 0 | O79: Written Off | P79: 11.7 | Q79: 0 | R79: 0.17245355 | S79: N.A | T79: =U79+V79 -> 0.001647 | U79: 0 | V79: 0.001647 | W79: =T79/P79 -> 0.00014076923 | X79: NA | Z79: =V79/P79 -> 0.00014076923 | AA79: Business Development connects, Finance and compliance support, introduction to follow-on round investors | AC79: VC referral | AD79: Karthik | AE79: Ashish | AF79: Written Off
B80: 71 | C80: Tripvillas Pte Ltd | D80: Tripvillas | E80: Singapore | F80: Consumer Services | G80: 41373 | H80: Seed | I80: N.A | J80: 219.23083 | K80: 526.0996 | L80: =K80 -> 526.0996 | M80: 1 | N80: =L80*(1-M80) -> 0 | O80: Provisioned - 100% | P80: 8.9 | Q80: 0 | R80: 0.0411 | S80: 0.037169383 | T80: =U80+V80 -> 0 | U80: 0 | V80: 0 | W80: =T80/P80 -> 0 | X80: NA | AA80: Structuring support, Finance and compliance support | AC80: Personal network of GPs | AD80: Sanjay | AE80: Sanjay | AF80: Provisioned
B81: 72 | C81: Homeveda Media Labs Private Ltd | D81: Homeveda | E81: Mumbai | F81: HealthTech | G81: 41403 | H81: Seed | I81: Seed | J81: 91.3563 | K81: 91.3563 | L81: =K81 -> 91.3563 | M81: 1 | N81: =L81*(1-M81) -> 0 | O81: Provisioned - 100% | P81: 13 | Q81: 0 | R81: 0.14229998 | S81: 0.14229998 | T81: =U81+V81 -> 0 | U81: 0 | V81: 0 | W81: =T81/P81 -> 0 | X81: NA | AA81: Board participation | AC81: Personal network of GPs | AD81: Karthik | AE81: Karthik | AF81: Provisioned
B82: 73 | C82: Snaplion Global Ltd | D82: SnapLion | E82: Gibraltar | F82: SaaS | G82: 41765 | H82: Seed | I82: N.A | J82: 142.41771 | K82: N.A | L82: N.A | M82: 0 | N82: =M82 -> 0 | O82: Written Off | P82: 7.1 | Q82: 0 | R82: 0.050050219 | S82: N.A | T82: =U82+V82 -> 0.0012 | U82: 0 | V82: 0.0012 | W82: =T82/P82 -> 0.00016901408 | X82: NA | Z82: =V82/P82 -> 0.00016901408 | AB82: Orios | AC82: Referral by co-investor | AD82: Sanjay | AE82: Arpit | AF82: Written Off
P83: =SUM(P4:P82) -> 922.31762 | Q83: =SUM(Q4:Q82) -> 15.708746 | T83: =SUM(T4:T82) -> 4893.9136 | U83: =SUM(U4:U82) -> 483.45654 | V83: =SUM(V4:V82) -> 4410.4571 | W83: =T83/P83 -> 5.3061044 | X83: 0.22810262
C86: * Indicates that the team member is no longer associated with the firm

Sheet Fund IA
B2: # | C2: Company | D2: Business / Brand | E2: Geography | F2: Sector | G2: Date | H2: Stage at Entry | I2: Current Stage | J2: Entry Valuation | K2: Last Round Valuation | L2: Valuation used for Mark to Market | M2: Discount to last round | N2: Effective Valuation for Mark-to-market | O2: Valuation Basis | P2: Total Invested Cost | Q2: Residual Cost | R2: Stake (At Entry) | S2: Stake (Current) | T2: Total Value | U2: Unrealised Value | V2: Realised Value | W2: Gross MOIC | X2: Gross IRR (₹) | Y2: If Exited, Mode of Exit | Z2: GP Exit MOIC | AA2: Value Creation by Fund | AB2: Co-investor(s) | AC2: Sourcing Route | AD2: Deal Source | AE2: Deal Lead | AF2: Status
G3: MM/YY | J3: ₹ Mn | K3: ₹ Mn | L3: ₹ Mn | N3: ₹ Mn | P3: ₹ Mn | Q3: ₹ Mn | R3: % | S3: % | T3: ₹ Mn | U3: ₹ Mn | V3: ₹ Mn | W3: x | X3: %
B4: 1 | C4: Fintech Solutions Private Limited | D4: Turtlemint | E4: Mumbai | F4: FinTech | G4: 42121 | H4: Seed | I4: N.A | J4: 114.5004 | K4: N.A | L4: N.A | M4: 0 | N4: 0 | O4: Exit Value | P4: 28.268405 | Q4: 0 | R4: 0.05240724 | S4: N.A | T4: =V4+U4 -> 540.55268 | U4: 0 | V4: 540.55268 | W4: =T4/P4 -> 19.12215 | X4: 0.70132714 | Y4: Sale to Fund 1X | Z4: =W4 -> 19.12215 | AA4: Investor connect, Finance and compliance support, hiring | AB4: Sequoia, Nexus, AMFAM, Mass Mutual, Jungle Ventures, GGV, SIG | AC4: Personal network of team member | AD4: Adit* | AE4: Ashish | AF4: Exited
B5: 2 | C5: GreyOrange Robotics International Inc | D5: GreyOrange Robotics | E5: USA | F5: DeepTech | G5: 42065 | H5: Series A - Secondary | I5: Series D | J5: 1423.7105 | K5: 41634.55 | L5: 41634.55 | M5: 0.3 | N5: =L5*(1-M5) -> 29144.185 | O5: Valued at 30% discount to the last round(pre-money) | P5: 9.4 | Q5: 6.5608785 | R5: 0.0064078532 | S5: 0.0014480418 | T5: =V5+U5 -> 110.63236 | U5: 45.116943 | V5: 65.515417 | W5: =T5/P5 -> 11.7694 | X5: 0.36874811 | Y5: Partial sale to Fund 1X | Z5: =V5/(P5-Q5) -> 23.075947 | AA5: Business Development connects, Investor connect, Finance & compliance support | AB5: Mithril Capital, Pavilion Capital, Binny Bansal, Antehelion Capital, H&M | AC5: Alumni network of GPs ( BITS alum connected through Sanjay) | AD5: Sanjay | AE5: Karthik | AF5: Partial Exit
B6: 3 | C6: Stelling Technologies Private Limited | D6: IntrCity | E6: Delhi | F6: Consumer Services | G6: 41892 | H6: Seed | I6: N.A | J6: 132.01616 | K6: N.A | L6: =K6 -> N.A | M6: 0 | N6: =M6 -> 0 | O6: Exit Value | P6: 15.4 | Q6: 0 | R6: 0.045575758 | S6: N.A | T6: =V6+U6 -> 183.83928 | U6: 0 | V6: 183.83928 | W6: =T6/P6 -> 11.937616 | X6: 0.30894382 | Y6: Sale to Fund 1Y | Z6: =W6 -> 11.937616 | AA6: Board participation, connects to follow-on round investors, support on M&A, structuring of rounds, general counsel, Hiring, Finance & compliance support | AB6: Mirablis Investment Trust, Helion, Omidyar, NRJN (Nandan Nilekeni) | AC6: LP referral | AD6: Karthik | AE6: Karthik | AF6: Exited
B7: 4 | C7: Manash Lifestyle Private Ltd | D7: Purplle | E7: Mumbai | F7: E-Commerce | G7: 42326 | H7: Series A2 | I7: N.A | J7: 1590.2467 | K7: N.A | L7: =K7 -> N.A | M7: 0 | N7: =M7 -> 0 | O7: Exit Value | P7: 6 | Q7: 0 | R7: 0.0037989409 | S7: N.A | T7: =V7+U7 -> 30.003084 | U7: 0 | V7: 30.003084 | W7: =T7/P7 -> 5.000514 | X7: 0.36411879 | Y7: Sale to Fund 1X | Z7: =W7 -> 5.000514 | AA7: Business Development connects, Investor connect, finance and compliance support, hiring , strategic media arrangement | AB7: Goldman Sachs, Verlinvest, IvyCap, JSW Ventures | AC7: Angel Network | AD7: Karthik | AE7: Ashish | AF7: Exited
B8: 5 | C8: E2E Networks Private Limited | D8: E2E Networks | E8: Delhi | F8: SaaS | G8: 41831 | H8: Seed | I8: N.A | J8: 137.50215 | K8: N.A | L8: =K8 -> N.A | M8: 0 | N8: =M8 -> 0 | O8: Exit Value | P8: 9 | Q8: 0 | R8: 0.065454545 | S8: N.A | T8: =V8+U8 -> 105.2576 | U8: 0 | V8: 105.2576 | W8: =T8/P8 -> 11.695289 | X8: 0.35847025 | Y8: Exit via OFS in IPO and Public market | Z8: =W8 -> 11.695289 | AA8: Venture debt, Support with IPO process, investor connects for IPO, business development connects , hiring | AC8: Referral by co-investor | AD8: Karthik | AE8: Ashish | AF8: Exited
B9: 6 | C9: Manak Waste Management Private Limited | D9: Cashify | E9: Delhi | F9: Re-commerce | G9: 42116 | H9: Seed | I9: N.A | J9: 174.00832 | K9: N.A | L9: =K9 -> N.A | M9: 0 | N9: =M9 -> 0 | O9: Exit Value | P9: 36.464294 | Q9: 0 | R9: 0.086236659 | S9: N.A | T9: =V9+U9 -> 496.19465 | U9: 0 | V9: 496.19465 | W9: =T9/P9 -> 13.607686 | X9: 0.52531864 | Y9: Sale to Fund 1Y | Z9: =W9 -> 13.607686 | AA9: Investor connect, Board participation, operations support , finance and complaince support | AB9: Shunwei, Bessemer, CDH, Morningside, AiHuiShou, Olympus Capital | AC9: Personal network of team member | AD9: Arpit | AE9: Arpit | AF9: Exited
B10: 7 | C10: Dataweave Software Private Ltd | D10: Dataweave | E10: USA | F10: Analytics | G10: 42065 | H10: Seed | I10: Series A1 | J10: 382.8 | K10: 53.108753 | L10: 0 | M10: 0 | N10: =M10 -> 0 | O10: Provisioned - 100% | P10: 9.358417 | Q10: =P10 -> 9.358417 | R10: 0.01566092 | S10: 0.013603848 | T10: =V10+U10 -> 0 | U10: 0 | V10: 0 | W10: =T10/P10 -> 0 | X10: NA | AA10: Business Development connects, Investor connect, Structuring of business as a US domiciled entity, finance and compliance support, hiring of CFO | AB10: WaterBridge, WGG, Freakout, Recruit | AC10: Angel Network | AD10: Karthik | AE10: Sanjay | AF10: Provisioned
B11: 8 | C11: ZipDial Mobile Solution Private Limited | D11: ZipDial | E11: Bengaluru | F11: SaaS | G11: 41901 | H11: Seed | I11: N.A | J11: 606.02836 | K11: N.A | L11: =K11 -> N.A | M11: 0 | N11: =M11 -> 0 | O11: Exit Value | P11: 5 | Q11: 0 | R11: 0.0082508251 | S11: N.A | T11: =V11+U11 -> 13.836736 | U11: 0 | V11: 13.836736 | W11: =T11/P11 -> 2.7673472 | X11: 2.0619896 | Y11: Acquisition by Twitter | Z11: =W11 -> 2.7673472 | AA11: Introduction to follow-on round investors, Board participation | AB11: DSG, 500 Startups, Jungle Ventures, Times Internet, Unilazer | AC11: Angel Network | AD11: Karthik | AE11: Karthik | AF11: Exited
B12: 9 | C12: Baldor Technologies Private Ltd | D12: Idfy | E12: Mumbai | F12: FinTech | G12: 42090 | H12: Seed | I12: N.A | J12: 449.67502 | K12: N.A | L12: =K12 -> N.A | M12: 0 | N12: =M12 -> 0 | O12: Exit Value | P12: 12 | Q12: 0 | R12: 0.026664496 | S12: N.A | T12: =V12+U12 -> 29.1906 | U12: 0 | V12: 29.1906 | W12: =T12/P12 -> 2.43255 | X12: 0.16906372 | Y12: Sale to Fund 1X | Z12: =W12 -> 2.43255 | AA12: Business Development connects, Investor connect, hiring | AB12: NEA, Transunion, MegaDelta | AC12: co-investor network - angel | AD12: Karthik | AE12: Karthik | AF12: Exited
B13: 10 | C13: Greytip Software Private Ltd | D13: Greytip | E13: Bengaluru | F13: HRTech | G13: 42206 | H13: Seed | I13: N.A | J13: 876.45223 | K13: N.A | L13: 0 | M13: 0 | N13: =M13 -> 0 | O13: Exit Value | P13: 11.749724 | Q13: 0 | R13: 0.017863523 | S13: N.A | T13: =V13+U13 -> 68.185371 | U13: 0 | V13: 68.185371 | W13: =T13/P13 -> 5.8031466 | X13: 0.21514648 | Y13: Secondary sale to Apax Partners | Z13: =W13 -> 5.8031466 | AA13: support for venture debt, structuring of follow-on round, Business Development connects , Hiring, Finance & compliance support | AB13: MegaDelta, InfoEdge, GMO | AC13: Ecosystem referral | AD13: Karthik | AE13: Karthik | AF13: Exited
B14: 11 | C14: Webklipper Technologies Pvt. Ltd | D14: Webengage | E14: Mumbai | F14: SaaS | G14: 42391 | H14: Seed | I14: N.A | J14: 1000 | K14: N.A | L14: =K14 -> N.A | M14: 0 | N14: =M14 -> 0 | O14: Exit Value | P14: 10 | Q14: 0 | R14: 0.0117 | S14: N.A | T14: =V14+U14 -> 13.440024 | U14: 0 | V14: 13.440024 | W14: =T14/P14 -> 1.3440024 | X14: 0.060844907 | Y14: Sale to Fund 1X | Z14: =W14 -> 1.3440024 | AA14: Board participation, Business Development connects, evaluating collaborations and acqui-hires from time to time, Hiring, Finance & compliance support | AB14: SWC, Singularity, IndiaQuotient | AC14: Referral by co-investor | AD14: Karthik | AE14: Karthik | AF14: Exited
B15: 12 | C15: Nowfloats Technologies Private Ltd | D15: Nowfloats | E15: Hyderabad | F15: SaaS | G15: 41439 | H15: Seed | I15: N.A | J15: 265.79542 | K15: N.A | L15: =K15 -> N.A | M15: 0 | N15: =M15 -> 0 | O15: Exit Value | P15: 16 | Q15: 0 | R15: 0.0148 | S15: N.A | T15: =V15+U15 -> 19.474287 | U15: 0 | V15: 19.474287 | W15: =T15/P15 -> 1.2171429 | X15: 0.046357573 | Y15: Acquisition by Reliance Jio | Z15: =W15 -> 1.2171429 | AA15: Business Development connects, Investor connect, finance and compliance, hiring | AB15: Omidyar, IIFL, Iron Pillar | AC15: Angel Network | AD15: Karthik | AE15: Ashish | AF15: Exited
B16: 13 | C16: Digissential Enterprises Private Limited | D16: Bill Bachao | E16: Bengaluru | F16: ConsumerTech | G16: 41971 | H16: Seed | I16: N.A | J16: 200 | K16: N.A | L16: =K16 -> N.A | M16: 0 | N16: =M16 -> 0 | O16: Exit Value | P16: 10 | Q16: 0 | R16: 0.05 | S16: N.A | T16: =V16+U16 -> 9.92581 | U16: 0 | V16: 9.92581 | W16: =T16/P16 -> 0.992581 | X16: -0.014679208 | Y16: Buyback | Z16: =W16 -> 0.992581 | AA16: Board participation, exit structuring | AC16: Founder was connected to the GPs through his earlier stint with Vodafone | AD16: Karthik | AE16: Karthik | AF16: Exited
B17: 14 | C17: Threadsol Software Private Ltd | D17: Threadsol | E17: Delhi | F17: SaaS | G17: 42478 | H17: Seed | I17: N.A | J17: 884.70634 | K17: N.A | L17: =K17 -> N.A | M17: 0 | N17: =M17 -> 0 | O17: Exit Value | P17: 7.335984 | Q17: 0 | R17: 0.0082 | S17: N.A | T17: =V17+U17 -> 7.335985 | U17: 0 | V17: 7.335985 | W17: =T17/P17 -> 1.0000001 | X17: 4.3945313e-08 | Y17: Acquisition by Coates Plc | Z17: =W17 -> 1.0000001 | AA17: Business Development connects, Investor connect, Structuring of business as a SG domiciled entity, finance and compliance, Hiring , structuring of exit transaction | AB17: Catamaran | AC17: Angel Network | AD17: Karthik | AE17: Ashish | AF17: Exited
B18: 15 | C18: Solvy Tech Solutions Pvt. Ltd | D18: Zopper | E18: Delhi | F18: FinTech | G18: 42178 | H18: Seed | I18: N.A | J18: 3374.914 | K18: N.A | L18: =K18 -> N.A | M18: 0 | N18: =M18 -> 0 | O18: Exit Value | P18: 3.9 | Q18: 0 | R18: 0.0012067925 | S18: N.A | T18: =V18+U18 -> 6.067284 | U18: 0 | V18: 6.067284 | W18: =T18/P18 -> 1.5557138 | X18: 0.061516743 | Y18: Sale to Fund 1Y | Z18: =W18 -> 1.5557138 | AA18: Sourcing of follow-on round investors, Finance and compliance support, assistance with M&A transactions , hiring | AB18: Nirvana, Tiger Global | AC18: Alumni network of GPs | AD18: Karthik | AE18: Karthik | AF18: Exited
B19: 16 | C19: WAH Holidays Private Ltd | D19: WeAreHolidays | E19: Delhi | F19: Consumer Services | G19: 42041 | H19: Seed | I19: N.A | J19: 270.17502 | K19: N.A | L19: =K19 -> N.A | M19: 0 | N19: =M19 -> 0 | O19: Written off - residual value received | P19: 5.4 | Q19: 0 | R19: 0.01367339 | S19: N.A | T19: =V19+U19 -> 0.625795 | U19: 0 | V19: 0.625795 | W19: =T19/P19 -> 0.11588796 | X19: NA | Y19: Write-off | Z19: =W19 -> 0.11588796 | AA19: Business Development connects, Finance and compliance support, Board participation, hiring, structuring of follow-on rounds | AB19: Matrix, Mumbai Angels | AC19: Angel Network | AD19: Sanjay | AE19: Karthik | AF19: Written Off
B20: 17 | C20: 21Trends Private Ltd | D20: Voxpop | E20: Mumbai | F20: E-Commerce | G20: 41710 | H20: Seed | I20: N.A | J20: 212.79873 | K20: N.A | L20: =K20 -> N.A | M20: 0 | N20: =M20 -> 0 | O20: Written off - residual value received | P20: 12.2 | Q20: 0 | R20: 0.061400895 | S20: N.A | T20: =V20+U20 -> 0.002696 | U20: 0 | V20: 0.002696 | W20: =T20/P20 -> 0.00022098361 | X20: NA | Y20: Write-off | Z20: =W20 -> 0.00022098361 | AA20: Facilitating collaboration with strategic investor, strategic media arrangement, Finance & compliance support | AC20: Founder network | AD20: Karthik | AE20: Ashish | AF20: Written Off
B21: 18 | C21: Shantani Proteome Analytics Pvt. Ltd | D21: Shantani | E21: Pune | F21: Life Sciences | G21: 41741 | H21: Seed | I21: N.A | J21: 157.54723 | K21: N.A | L21: =K21 -> N.A | M21: 0 | N21: =M21 -> 0 | O21: Written off - residual value received | P21: 3.8 | Q21: 0 | R21: 0.023804062 | S21: N.A | T21: =V21+U21 -> 0.363384 | U21: 0 | V21: 0.363384 | W21: =T21/P21 -> 0.095627368 | X21: NA | Y21: Write-off | Z21: =W21 -> 0.095627368 | AA21: Finance & compliance support | AB21: India Innovation Fund | AC21: Referral by co-investor | AD21: Karthik | AE21: Karthik | AF21: Written Off
B22: 19 | C22: Covacsis Technologies Private Ltd | D22: Covacsis | E22: Mumbai | F22: SaaS | G22: 42093 | H22: Seed | I22: N.A | J22: 389.97214 | K22: N.A | L22: =K22 -> N.A | M22: 0 | N22: =M22 -> 0 | O22: Written off - residual value received | P22: 2.5 | Q22: 0 | R22: 0.0084659668 | S22: N.A | T22: =V22+U22 -> 0 | U22: 0 | V22: 0 | W22: =T22/P22 -> 0 | X22: NA | Y22: Write-off | Z22: =W22 -> 0 | AA22: Finance and compliance support, Business development , debt | AB22: Reliance GenNext, CISCO Ventures | AC22: Founder referral | AD22: Karthik | AE22: Karthik | AF22: Written Off
B23: 20 | C23: Dataemo Technologies Pvt Ltd / Belong Pte Ltd | D23: Belong | E23: Singapore | F23: HRTech | G23: 41912 | H23: Seed | I23: N.A | J23: 177.6 | K23: N.A | L23: =K23 -> N.A | M23: 0 | N23: =M23 -> 0 | O23: Written off - residual value received | P23: 11.2 | Q23: 0 | R23: 0.033783784 | S23: N.A | T23: =V23+U23 -> 0 | U23: 0 | V23: 0 | W23: =T23/P23 -> 0 | X23: NA | Y23: Write-off | Z23: =W23 -> 0 | AA23: Business developement , Board participation, Hiring | AB23: Sequoia, Matrix | AC23: Founder was an ex-team member of a portfolio company | AD23: Karthik | AE23: Karthik | AF23: Written Off
P24: =SUM(P4:P23) -> 224.97682 | Q24: =SUM(Q4:Q23) -> 15.919295 | T24: =SUM(T4:T23) -> 1634.9276 | U24: =SUM(U4:U23) -> 45.116943 | V24: =SUM(V4:V23) -> 1589.8107 | W24: =T24/P24 -> 7.2670935 | X24: 0.34147082
C27: * Indicates that the team member is no longer associated with the firm

Sheet Fund II
B2: # | C2: Company | D2: Business / Brand | E2: Geography | F2: Sector | G2: Date | H2: Stage at Entry | I2: Current Stage | J2: Entry Valuation | K2: Last Round Valuation | L2: Valuation used for Mark to Market | M2: Discount to last round | N2: Effective Valuation for Mark-to-market | O2: Valuation Basis | P2: Total Invested Cost | Q2: Residual Cost | R2: Stake (At Entry) | S2: Stake (Current) | T2: Total Value | U2: Unrealised Value | V2: Realised Value | W2: Gross MOIC | X2: Gross IRR (₹) | Y2: If Exited, Mode of Exit | Z2: GP Exit MOIC | AA2: Value Creation by Fund | AB2: Co-investor(s) | AC2: Sourcing Route | AD2: Deal Source | AE2: Deal Lead | AF2: Status
G3: MM/YY | J3: ₹ Mn | K3: ₹ Mn | L3: ₹ Mn | N3: ₹ Mn | P3: ₹ Mn | Q3: ₹ Mn | R3: % | S3: % | T3: ₹ Mn | U3: ₹ Mn | V3: ₹ Mn | W3: x | X3: %
B4: 1 | C4: Sorting Hat Technology Private Limited | D4: Unacademy | E4: Bengaluru | F4: EdTech | G4: 42338 | H4: Seed | I4: Series H | J4: 325.80706 | K4: 251219.2 | L4: =K4 -> 251219.2 | M4: 0.91281097 | N4: =L4*(1-M4) -> 21903.557 | O4: Valued at $300 Mn basis the M&A offer received | P4: 134.37435 | Q4: =P4 -> 134.37435 | R4: 0.074183976 | S4: 0.0278 | T4: =U4+V4 -> 289.29428 | U4: 289.29428 | V4: 0 | W4: =T4/P4 -> 2.152898 | X4: 0.090212092 | AA4: Investor connect, Finance & compliance support , ESOP , operational finance support , hiring | AB4: General Atlantic, Facebook, Peak XV Partners, Nexus, Elevation Capital, Steadview Capital, Tiger Global, Dragoneer,SoftBank | AC4: Eco-system referral | AD4: Karthik | AE4: Karthik | AF4: Active
B5: 2 | C5: Value Drive Technologies Pvt Ltd | D5: Spinny | E5: Delhi | F5: Consumer Services | G5: 42447 | H5: Seed | I5: Series F | J5: 299.7532 | K5: 96707.808 | L5: =K5 -> 96707.808 | M5: 0.10587068 | N5: =L5*(1-M5) -> 86469.287 | O5: Held at secondary valuation of the last round (Series F - Mar 25) | P5: 91.965892 | Q5: 43.408817 | R5: 0.10006673 | S5: 0.024102379 | T5: =U5+V5 -> 3995.2659 | U5: 2107.7868 | V5: 1887.4791 | W5: =T5/P5 -> 43.442909 | X5: 0.70640911 | Y5: Partial exit - Secondary sale to Accel, Paramark | Z5: =V5/(P5-Q5) -> 38.871351 | AA5: Debt, Strategy, Investor connect, Finance & compliance support | AB5: ADQ, Tiger Global, Accel, Elevation Capital, Kaiser, Avenir, Think Investments, Fundamentum | AC5: Eco-system referral | AD5: Arpit | AE5: Arpit | AF5: Partial Exit
B6: 3 | C6: Dunzo Digital Private Limited | D6: Dunzo | E6: Bengaluru | F6: Consumer Tech | G6: 42223 | H6: Seed | I6: Series F | J6: 159.996 | K6: 60913.135 | L6: 772 | M6: 1 | N6: =L6*(1-M6) -> 0 | O6: Provisioned 100% | P6: 99.780115 | Q6: =P6 -> 99.780115 | R6: 0.14 | S6: 0.0245 | T6: =U6+V6 -> 0 | U6: 0 | V6: 0 | W6: =T6/P6 -> 0 | X6: NA | AA6: Investor connect, Finance & compliance support , Hiring | AB6: Aspada, Google Asia, LightBox, Reliance Retail, LGT Lightstone, LightRock | AC6: LP referral | AD6: Adit* | AE6: Karthik | AF6: Provisioned
B7: 4 | C7: Garagepreneurs Internet Private Limited | D7: Slice | E7: Bengaluru | F7: FinTech | G7: 42275 | H7: Series A1 | I7: CCD - Post Series B1 | J7: 133.3039 | K7: 19454.765 | L7: =K7 -> 19454.765 | M7: 0 | N7: =L7*(1-M7) -> 19454.765 | O7: Held at the CCD round (Post merger) | P7: 94.195658 | Q7: =P7 -> 94.195658 | R7: 0.15003751 | S7: 0.081093355 | T7: =U7+V7 -> 1577.6521 | U7: 1577.6521 | V7: 0 | W7: =T7/P7 -> 16.748672 | X7: 0.36665381 | AA7: Business development connects, Strategy, Investor connect, Compliance support , operational finnace support, business structuring | AB7: Tiger Global, Gunosy, Insight, Advent International | AC7: Events / Outbound | AD7: Adit* | AE7: Ashish | AF7: Active
B8: 5 | C8: Tricog Health Pte Ltd | D8: Tricog | E8: Singapore | F8: HealthTech | G8: 42543 | H8: Series A | I8: Series C | J8: 400.1069 | K8: 7029.5271 | L8: =K8 -> 7029.5271 | M8: 0 | N8: =L8*(1-M8) -> 7029.5271 | O8: Marked at Series C (Jan 23) | P8: 83.512193 | Q8: =P8 -> 83.512193 | R8: 0.125 | S8: 0.076019761 | T8: =U8+V8 -> 570.10782 | U8: 570.10782 | V8: 0 | W8: =T8/P8 -> 6.8266417 | X8: 0.24541058 | AA8: Strategy, Finance support , Investor connect , Structuring of business as a SG domiciled entity, operational finance support | AB8: Athera Venture Partners, UTEC, Sony Innovation Fund, Omron | AC8: Inbound / Events | AD8: Arpit | AE8: Sanjay | AF8: Active
B9: 6 | C9: Smallcase Technologies Private Limited | D9: SmallCase | E9: Bengaluru | F9: FinTech | G9: 42284 | H9: Seed | I9: Series D | J9: 100.006 | K9: 24870.194 | L9: =K9 -> 24870.194 | M9: 0.1793 | N9: =L9*(1-M9) -> 20410.968 | O9: Marked at the secondary valuation of the Series D (pre-money) round (Mar 25) | P9: 111.49582 | Q9: 43.367258 | R9: 0.14 | S9: 0.052254968 | T9: =U9+V9 -> 1744.3478 | U9: 1066.0917 | V9: 678.25615 | W9: =T9/P9 -> 15.644962 | X9: 0.41813425 | Y9: Partial exit - Secondary sale to GP managed vehicle | Z9: =V9/(P9-Q9) -> 9.9555328 | AA9: Fund raise connect, Finance & complaince support, strategy, hiring, operational finance support | AB9: State Street, Faering Capital, Amazon, Premji Invest, Sequoia, DSP Adiko, Beenext, Unitary Fund, Straddle Capital, HDFC | AC9: Founder network | AD9: Rohan* | AE9: Karthik | AF9: Partial Exit
B10: 7 | C10: Carthero Technologies Private Limited | D10: Runnr | E10: Bengaluru | F10: Consumer Services | G10: 42129 | H10: Series A | I10: NA | J10: 190.0063 | K10: NA | L10: 0 | M10: 0 | N10: NA | O10: Exit Value | P10: 132.47772 | R10: 0.08475 | S10: NA | T10: =U10+V10 -> 521.26577 | U10: 0 | V10: 521.26577 | W10: =T10/P10 -> 3.934743 | X10: 0.45268052 | Y10: Acquired by Zomato | Z10: =W10 -> 3.934743 | AA10: Business development connects, strategy, Investor connect, compliance support , ESOP structuring , exit sructuring and execution | AB10: Nexus, Sequoia, Matrix | AC10: Inbound / Events | AD10: Adit* | AE10: AF+KR | AF10: Exited
B11: 8 | C11: Service Lee Technologies Private Limited | D11: Servify | E11: Mumbai | F11: Consumer Tech | G11: 42373 | H11: Seed | I11: Series D3 | J11: 312.52435 | K11: 57770 | L11: 57770 | M11: 0.35 | N11: =L11*(1-M11) -> 37550.5 | O11: 35% discount to last round (Series D3 - August 23) | P11: 103.11818 | Q11: 53.42785 | R11: 0.08 | S11: 0.024620831 | T11: =U11+V11 -> 1990.6569 | U11: 931.79213 | V11: 1058.8648 | W11: =T11/P11 -> 19.304616 | X11: 0.39304954 | Y11: Partial exit - Secondary sale to Oister & GP managed vehicle | Z11: =V11/(P11-Q11) -> 21.309271 | AA11: Investor connect, round support, strategy, M&A, hiring, Finance & compliance support | AB11: Iron Pillar, Beenext, Singularity Investments, IFC | AC11: Founder network | AD11: Karthik | AE11: Karthik | AF11: Partial Exit
B12: 9 | C12: Bombinate Technologies Private Limited | D12: Vokal | E12: Bengaluru | F12: Social Media | G12: 42413 | H12: Seed | I12: NA | J12: 609.65616 | K12: NA | L12: 0 | M12: 0 | N12: =L12*(1-M12) -> 0 | O12: Written off - residual value received | P12: 180.69889 | R12: 0.0379 | S12: NA | T12: =U12+V12 -> 0.004455 | U12: 0 | V12: 0.004455 | W12: =T12/P12 -> 2.4654274e-05 | X12: NA | AA12: Investor connect, hiring | AB12: Tiger Global, Mirae, IIFL Accel, 3one4, Kalaari | AC12: ex-portfolio founder | AD12: Karthik | AE12: Karthik | AF12: Written Off
B13: 10 | C13: Mara Labs Inc. | D13: Locus | E13: USA | F13: Logistics | G13: 42452 | H13: Series A | I13: NA | J13: 866.41629 | K13: NA | L13: 0 | M13: 0 | N13: =L13*(1-M13) -> 0 | O13: Exit Value | P13: 122.59912 | Q13: 122.59912 | R13: 0.04 | S13: NA | T13: =U13+V13 -> 113.08637 | U13: 0 | V13: 113.08637 | W13: =T13/P13 -> 0.92240767 | X13: -0.010044631 | Y13: Acquired by Ingka Group | Z13: =W13 -> 0.92240767 | AA13: Hiring, Investor connect | AB13: Exfinity, Beenext, Falcon Edge, Tiger Global | AC13: Eco-system referral | AD13: Sanjay | AE13: Sanjay | AF13: Active
B14: 11 | C14: Hybrent Inc. | D14: Hybrent | E14: USA | F14: HealthTech | G14: 42608 | H14: Seed | I14: NA | J14: 415.00665 | K14: NA | L14: 0 | M14: 0 | N14: =L14*(1-M14) -> 0 | O14: Exit Value | P14: 92.037188 | R14: 0.1969 | S14: NA | T14: =U14+V14 -> 452.47797 | U14: 0 | V14: 452.47797 | W14: =T14/P14 -> 4.9162515 | X14: 0.41834691 | Y14: Acquired by Procurement Partners | Z14: =W14 -> 4.9162515 | AB14: Montane Ventures | AC14: Eco-system referral | AD14: scout | AE14: Karthik | AF14: Exited
B15: 12 | C15: mPAANI Solutions Private Limited | D15: LoveLocal | E15: Mumbai | F15: Retail-Tech | G15: 42251 | H15: Seed | I15: Pre-Series B | J15: 195.03 | K15: 5157.684 | L15: 0 | M15: 0 | N15: Cost | O15: Cost | P15: 84.89908 | Q15: =P15 -> 84.89908 | R15: 0.1385 | S15: 0.08 | T15: =U15+V15 -> 84.89908 | U15: 84.89908 | V15: 0 | W15: =T15/P15 -> 1 | X15: 2.9802322e-09 | AA15: Business development, Finance & compliance support , Hiring , ESOP, Investor connect | AB15: Vulcan, AVG, IDG,Chiratae, Technology Venture Fund,Saha Fund, Henkel, ACV, Candy Capital | AC15: Eco-system referral | AD15: Sajith | AE15: Karthik | AF15: Active
B16: 13 | C16: Squadrun Inc. | D16: Squad | E16: USA | F16: B2B Services | G16: 42772 | H16: Seed | I16: Series B | J16: 765.65925 | K16: 7545.1152 | L16: 0 | M16: 0 | N16: Cost | O16: Cost | P16: 67.564819 | Q16: =P16 -> 67.564819 | R16: 0.065 | S16: 0.0502 | T16: =U16+V16 -> 67.564819 | U16: 67.564819 | V16: 0 | W16: =T16/P16 -> 1 | X16: 0 | AA16: Business Development connect , hiring | AB16: Chiratae Ventures, Bertelsmann India Investments | AC16: LP referral | AD16: Sanjay | AE16: Karthik | AF16: Active
B17: 14 | C17: True Software Scandinavia AB | D17: Truecaller | E17: Mumbai | F17: FinTech | G17: 42334 | H17: Series A | I17: NA | J17: 1421.307 | K17: NA | L17: 0 | M17: 0 | N17: NA | O17: Exit Value (Includes proceeds from Chillr) | P17: 55.356995 | R17: 0.0422 | S17: NA | T17: =U17+V17 -> 247.01865 | U17: 0 | V17: 247.01865 | W17: =T17/P17 -> 4.4622843 | X17: 0.36432918 | Y17: Acquired by Truecaller in a stock swap deal | Z17: =W17 -> 4.4622843 | AB17: Sequioa,Uniqorn Ventures,MOBME Wireless | AD17: Karthik | AE17: Karthik | AF17: Exited
B18: 15 | C18: Yulu Bikes Pvt Ltd | D18: Yulu | E18: Bengaluru | F18: Urban Mobility | G18: 43214 | H18: CCD | I18: Series B2 | J18: 2127.2964 | K18: 18280 | L18: =K18 -> 18280 | M18: 0.57035125 | N18: =L18*(1-M18) -> 7853.9792 | O18: Estimated Exit Value | P18: 74.82264 | Q18: =P18 -> 74.82264 | R18: 0.0442 | S18: 0.0261 | T18: =U18+V18 -> 194.52041 | U18: 194.52041 | V18: 0 | W18: =T18/P18 -> 2.5997533 | X18: 0.14310011 | AA18: Investor connects for follow-on rounds, Finance & complaince support, Hiring | AB18: Magna International, Bajaj Auto, Akatsuki, 3one4 | AC18: Founder network ( connected through the founder's prior startup) | AD18: Sanjay | AE18: Sanjay | AF18: Active
B19: 16 | C19: Minjar Inc | D19: Minjar | E19: USA | F19: SaaS | G19: 42884 | H19: Seed | I19: NA | J19: 613.29754 | K19: NA | L19: 0 | M19: 0 | N19: NA | O19: Exit Value | P19: 61.531786 | R19: 0.1 | S19: NA | T19: =U19+V19 -> 177.44447 | U19: 0 | V19: 177.44447 | W19: =T19/P19 -> 2.8837855 | X19: 4.8712531 | Y19: Acquired by Nutanix Inc | Z19: =W19 -> 2.8837855 | AA19: Business development connects, strategy, Investor connect, compliance support , exit sructuring and execution | AC19: ex-portfolio founder | AD19: Sanjay | AE19: Sanjay | AF19: Exited
B20: 17 | C20: Healthifyme Pte Ltd | D20: Healthifyme | E20: Singapore | F20: HealthTech | G20: 42454 | H20: Series B | I20: Convert Note | J20: 1397.5615 | K20: 15601.189 | L20: =K20 -> 15601.189 | M20: 1 | N20: =L20*(1-M20) -> 0 | O20: Provisioned 100% | P20: 136.97367 | Q20: =P20 -> 136.97367 | R20: 0.0573 | S20: 0.018472895 | T20: =U20+V20 -> 0 | U20: 0 | V20: 0 | W20: =T20/P20 -> 0 | X20: NA | AA20: Strategy, Finance support , Investor connect , hiring | AB20: Chiratae Ventures, Khosla Ventures, Sistema Asia Fund, HealthQuad, LeapFrog Investments, Athera Venture Partners | AC20: Eco-system referral | AD20: Sanjay | AE20: Karthik | AF20: Provisioned
B21: 18 | C21: Sekhmet Technologies Private Limited | D21: THB | E21: Delhi | F21: HealthTech | G21: 43119 | H21: Seed | I21: Series C | J21: 500.18116 | K21: 6483.9432 | L21: 2105.5397 | M21: 0 | N21: =L21*(1-M21) -> 2105.5397 | O21: Held at Series B round (March 21 - two rounds prior to the last round) | P21: 73.83494 | Q21: =P21 -> 73.83494 | R21: 0.13 | S21: 0.0604 | T21: =U21+V21 -> 169.51512 | U21: 169.51512 | V21: 0 | W21: =T21/P21 -> 2.2958659 | X21: 0.1153734 | AA21: Finance & Compliance support , general counsel, hiring | AB21: Healthquad Fund, Dream Incubator, Filter Capital, Edelweiss Capital, Cornerstone Ventures | AC21: LP referral | AD21: Arpit | AE21: Arpit | AF21: Active
B22: 19 | C22: Health Arx Technologies Private Limited | D22: BeatO | E22: Delhi | F22: HealthTech | G22: 43111 | H22: Pre Series A | I22: Series B | J22: 321.00382 | K22: 7332.7707 | L22: =K22 -> 7332.7707 | M22: 0.5 | N22: =L22*(1-M22) -> 3666.3854 | O22: Marked at 50% discount to the last round (Series B - Nov'22) | P22: 91.663456 | Q22: =P22 -> 91.663456 | R22: 0.125 | S22: 0.071436447 | T22: =U22+V22 -> 261.91354 | U22: 261.91354 | V22: 0 | W22: =T22/P22 -> 2.8573388 | X22: 0.15724209 | AA22: Hiring, strategy and goal setting, market research, business development , Investor connect | AB22: Lightrock India, HealthQuad, Flipkart, W Health Ventures, Orios Venture Partners , Parkview, Leo Capital | AC22: Eco-system referral | AD22: Arpit | AE22: Arpit | AF22: Active
B23: 20 | C23: Mycelium Software Inc. | D23: Rocketium | E23: Bengaluru | F23: SaaS | G23: 43097 | H23: Seed | I23: Series A1 | J23: 111.98781 | K23: 2511.9971 | L23: =K23 -> 2511.9971 | M23: 0.5 | N23: =L23*(1-M23) -> 1255.9986 | O23: Marked at 50% discount to the last round (Series A1 - July 24) | P23: 22.308697 | Q23: =P23 -> 22.308697 | R23: 0.077890134 | S23: 0.048 | T23: =U23+V23 -> 60.415931 | U23: 60.415931 | V23: 0 | W23: =T23/P23 -> 2.7081784 | X23: 0.14584426 | AA23: Business Development connect , general counsel , hiring, Finance & compliance | AB23: Tenacity Ventures, Emergent, Industry Ventures | AC23: through portfolio founder | AD23: Ashish | AE23: Sajith | AF23: Active
B24: 21 | C24: Wynaut Webventures Private Limited | D24: Futwork | E24: Mumbai | F24: B2B Services | G24: 42447 | H24: Seed | I24: Series A | J24: 71.444492 | K24: 709.19243 | L24: 0 | M24: 1 | N24: =L24*(1-M24) -> 0 | O24: Provisioned 100% | P24: 42.754521 | Q24: =P24 -> 42.754521 | R24: 0.07 | S24: 0.1296 | T24: =U24+V24 -> 0 | U24: 0 | V24: 0 | W24: =T24/P24 -> 0 | X24: NA | AA24: Business development connects, Strategy, Finance & Compliance support | AB24: Michael & Susan Dell Foundation, Simile, Artha | AC24: Founder network | AD24: Rohan* | AE24: Sajith | AF24: Provisioned
B25: 22 | C25: Kaleidofin Private Limited | D25: Kaleidofin | E25: Chennai | F25: FinTech | G25: 43181 | H25: Seed | I25: Series B2 | J25: 733.29971 | K25: 7310.2892 | L25: =K25 -> 7310.2892 | M25: 0 | N25: =L25*(1-M25) -> 7310.2892 | O25: Marked up to the last round (Series B2 - August 24) | P25: 95.768592 | Q25: =P25 -> 95.768592 | R25: 0.0698 | S25: 0.04 | T25: =U25+V25 -> 262.00137 | U25: 262.00137 | V25: 0 | W25: =T25/P25 -> 2.7357756 | X25: 0.16188213 | AA25: Business Development connect , general counsel , investor connect, Finance & complaince support, Hiring | AB25: Oikocredit, Omidyar, Michael & Susan Dell Foundation, Bill & Melinda Gates Foundation, Rabo Partnership | AC25: Eco-system referral | AD25: Karthik | AE25: Ashish | AF25: Active
B26: 23 | C26: Stellapps Technologies Private Limited | D26: Stellapps | E26: Bengaluru | F26: AgriTech | G26: 42864 | H26: Series A1 | I26: Series C | J26: 1128.419 | K26: 6245.8286 | L26: =K26 -> 6245.8286 | M26: 0 | N26: =L26*(1-M26) -> 6245.8286 | O26: Marked up to the last round (Series C - September 24) | P26: 104.13215 | Q26: =P26 -> 104.13215 | R26: 0.0487 | S26: 0.0218 | T26: =U26+V26 -> 112.13311 | U26: 112.13311 | V26: 0 | W26: =T26/P26 -> 1.0768347 | X26: 0.0099796325 | AA26: Fund raise connect, hiring , secondary acquistion structuring , Business Development connect | AB26: Bill and Melinda Gates Foundation, IDH Farmfit, Stride Ventures, Blue Ashva Sampada, Omnivore Partners | AC26: VC referral | AD26: Karthik | AE26: Ashish | AF26: Active
B27: 24 | C27: Chatpay Commerce Private Limited | D27: PitStop >>Autoverse | E27: Bengaluru | F27: Consumer Services | G27: 43004 | H27: Bridge | I27: NA | J27: 265.03592 | K27: N.A | L27: 0 | M27: 0 | N27: 0 | O27: Written off - residual value received | P27: 89.185459 | R27: 0.0981 | S27: NA | T27: =U27+V27 -> 0.00052166 | U27: 0 | V27: 0.00052166 | W27: =T27/P27 -> 5.8491598e-06 | X27: NA | Z27: =W27 -> 5.8491598e-06 | AA27: Investor connect, operational finance support , hiring | AB27: Exfinity, Ventureast, Singularity | AC27: ex-portfolio founder | AD27: Sajid Fazalbhoy* | AE27: Arpit | AF27: Written Off
B28: 25 | C28: Iluminar Media Private Limited | D28: LBB | E28: Delhi | F28: Commerce & Consumer Brands | G28: 42993 | H28: Seed | I28: NA | J28: 499.98096 | K28: N.A | L28: N.A | M28: 0 | N28: NA | O28: Written off - residual value received | P28: 124.12731 | R28: 0.0942 | S28: NA | T28: =U28+V28 -> 44.025596 | U28: 0 | V28: 44.025596 | W28: =T28/P28 -> 0.35468097 | X28: -0.64531903 | Z28: =W28 -> 0.35468097 | AA28: Helped recruit CTO (even before deal closure), actively led brainstorming strategy and product roadmap sessions, as LBB sharpened focus from just content discovery to real commerce, investor connects for follow on rounds | AB28: Indian Angel Network,Chirate, Inventus | AC28: VC referral | AD28: Arpit | AE28: Sanjay | AF28: Written Off
B29: 26 | C29: Qyuki Digital Media Private Limited | D29: Qyuki | E29: Bengaluru | F29: Media & Entertainment | G29: 43066 | H29: Seed | I29: Series A1 | J29: 316.66662 | K29: 3359.1587 | L29: =K29 -> 3359.1587 | M29: 1 | N29: =L29*(1-M29) -> 0 | O29: Provisioned 100% | P29: 106.03974 | Q29: =P29 -> 106.03974 | R29: 0.1629 | S29: 0.092 | T29: =U29+V29 -> 0 | U29: 0 | V29: 0 | W29: =T29/P29 -> 0 | X29: NA | AA29: Strategy, Finance support , Investor connect , hiring | AB29: Infoedge, CISCO Ventures,BD Mauritius, LuckLegend, DI | AC29: Eco-system referral | AD29: Karthik | AE29: Ashish | AF29: Provisioned
B30: 27 | C30: Servicemart Technologies Private Limited | D30: iservice | E30: Bengaluru | F30: Consumer Tech | G30: 42613 | H30: Seed | I30: NA | J30: 199.91745 | K30: N.A | L30: NA | M30: 0 | N30: NA | O30: Exit Value | P30: 24.99561 | R30: 0.125 | S30: NA | T30: =U30+V30 -> 0 | U30: 0 | V30: 0 | W30: =T30/P30 -> 0 | X30: 0 | Y30: Acquired by Servify in a stock-swap deal | Z30: =W30 -> 0 | AA30: Strategy, Finance support , Investor connect , M&A, hiring | AC30: Founder network | AD30: Karthik | AE30: Karthik | AF30: Written Off
B31: 28 | C31: Aaidea Solutions Private Limited | D31: Milkbasket | E31: Delhi | F31: Consumer Tech | G31: 42873 | H31: Seed | I31: NA | J31: 273.525 | K31: N.A | L31: NA | M31: 0 | N31: NA | O31: Exit Value | P31: 161.94913 | R31: 0.1005 | S31: NA | T31: =U31+V31 -> 161.84378 | U31: 0 | V31: 161.84378 | W31: =T31/P31 -> 0.99934946 | X31: -0.00065054272 | Y31: Acquired by Reliance | Z31: =W31 -> 0.99934946 | AA31: Investor connect, hiring | AB31: Unilever,Ultimate Lenovo, Mayfield | AC31: Inbound / Events | AD31: Arpit | AE31: Arpit | AF31: Exited
B32: 29 | C32: Zenatix Solutions Private Limited | D32: Zenatix | E32: Delhi | F32: DeepTech | G32: 42273 | H32: Bridge | I32: NA | J32: 202.27448 | K32: N.A | L32: NA | M32: 0 | N32: NA | O32: Exit Value | P32: 52.382275 | R32: 0.10998589 | S32: NA | T32: =U32+V32 -> 52.111469 | U32: 0 | V32: 52.111469 | W32: =T32/P32 -> 0.9948302 | X32: -0.0032642648 | Y32: Acquired by Hero Electronics | Z32: =W32 -> 0.9948302 | AA32: Business development, Investor connect , hiring | AB32: Pi Ventures | AC32: Eco-system referral | AD32: Arpit | AE32: Arpit | AF32: Exited
B33: 30 | C33: Mockbank Learning Private Limited | D33: Mockbank | E33: Mumbai | F33: EdTech | G33: 42212 | H33: Seed | I33: NA | J33: 125.0025 | K33: N.A | L33: NA | M33: 0 | N33: NA | O33: Written off - residual value received | P33: 12.50375 | R33: 0.1 | S33: NA | T33: =U33+V33 -> 7.548178 | U33: 0 | V33: 7.548178 | W33: =T33/P33 -> 0.60367314 | X33: -0.39632686 | Z33: =W33 -> 0.60367314 | AA33: NA | AD33: Arpit | AE33: Arpit | AF33: Written Off
B34: 31 | C34: Codelink Technologies Private Limited | D34: Blaez | E34: Delhi | F34: Customer Services | G34: 42299 | H34: Seed | I34: NA | J34: 118.207 | K34: N.A | L34: NA | M34: 0 | N34: NA | O34: Written off - residual value received | P34: 9.306275 | R34: 0.037069213 | S34: NA | T34: =U34+V34 -> 1.16835 | U34: 0 | V34: 1.16835 | W34: =T34/P34 -> 0.12554432 | X34: -0.87445568 | Z34: =W34 -> 0.12554432 | AA34: NA | AD34: Rohan* | AE34: Rohan* | AF34: Written Off
B35: 32 | C35: Mech Mocha Game Studios Private Limited | D35: MechMocha | E35: Bengaluru | F35: Media & Entertainment | G35: 42291 | H35: Seed | I35: NA | J35: 179.99447 | K35: N.A | L35: NA | M35: 0 | N35: NA | O35: Exit value | P35: 113.77836 | R35: 0.1375 | S35: NA | T35: =U35+V35 -> 0.404234 | U35: 0 | V35: 0.404234 | W35: =T35/P35 -> 0.0035528198 | X35: -0.99644718 | Y35: Acquired by Flipkart | Z35: =W35 -> 0.0035528198 | AA35: Business development connects, strategy, Investor connect, Hiring | AB35: Accel,Shunwei, Akatsuki | AC35: Inbound / Events | AD35: Arpit | AE35: Arpit | AF35: Written Off
B36: 33 | C36: Sitara Digital Ventures Private Limited | D36: The Wedding Brigade | E36: Mumbai | F36: Consumer Services | G36: 42443 | H36: Seed | I36: NA | J36: 156.26829 | K36: N.A | L36: NA | M36: 0 | N36: NA | O36: Written off - residual value received | P36: 78.397951 | R36: 0.16 | S36: NA | T36: =U36+V36 -> 0.03546 | U36: 0 | V36: 0.03546 | W36: =T36/P36 -> 0.00045230774 | X36: NA | Z36: =W36 -> 0.00045230774 | AA36: Business development connects, Strategy, Investor connect, Finance & Compliance support , hiring | AB36: Mountain Pine Capital, LetsVenture Investors | AC36: Inbound / Events | AD36: Sajid Fazalbhoy* | AE36: Sajid Fazalbhoy* | AF36: Written Off
B37: 34 | C37: Rizort Inc | D37: Rizort | E37: USA | F37: HR Tech | G37: 43061 | H37: Seed | I37: NA | J37: 664.51577 | K37: 1428.442 | L37: NA | M37: 0 | N37: NA | O37: Provisioned 100% | P37: 77.354773 | Q37: =P37 -> 77.354773 | R37: 0.0961 | S37: NA | T37: =U37+V37 -> 0 | U37: 0 | V37: 0 | W37: =T37/P37 -> 0 | X37: NA | AA37: Business Development connect , general counsel , hiring | AC37: ex-CXO of a start-up where a GPs had invested in personal capacity before founding Blume | AD37: Karthik | AE37: Karthik | AF37: Provisioned
B38: 35 | C38: Sourceeasy Inc | D38: Sourceeasy | E38: USA / Bengaluru | F38: Manufacturing SaaS | G38: 42332 | H38: Seed | I38: NA | J38: NA | K38: N.A | L38: NA | M38: 0 | N38: NA | O38: Provisioned 100% | P38: 57.333412 | Q38: =P38 -> 57.333412 | R38: 0.054565116 | S38: NA | T38: =U38+V38 -> 0 | U38: 0 | V38: 0 | W38: =T38/P38 -> 0 | X38: NA | AA38: NA | AC38: Eco-system referral | AD38: Karthik | AE38: Karthik | AF38: Provisioned
C39: Manufactured.net | D39: Manufactured.net | E39: USA | F39: SaaS | G39: 43089 | H39: Seed | I39: NA | J39: 66.454987 | K39: N.A | L39: NA | M39: 0 | N39: NA | O39: Provisioned 100% | P39: 11.634956 | Q39: =P39 -> 11.634956 | R39: NA | S39: NA | T39: =U39+V39 -> 0 | U39: 0 | V39: 0 | W39: =T39/P39 -> 0 | X39: NA | AA39: General counsel, Business Development connect | AC39: Holding pursuant to restructuring of Sourceeasy Inc | AD39: Sanjay | AE39: Karthik | AF39: Provisioned
B40: 36 | C40: Tusker Workspace Private Limited | D40: Bhive | E40: Bengaluru | F40: Real Estate | G40: 42299 | H40: Seed | I40: Pre Series A | J40: 154.49637 | K40: 166.59893 | L40: =K40 -> 166.59893 | M40: 1 | N40: =L40*(1-M40) -> 0 | O40: Provisioned 100% | P40: 60.994072 | Q40: =P40 -> 60.994072 | R40: 0.1081 | S40: 0.137 | T40: =U40+V40 -> 0.008907 | U40: 0 | V40: 0.008907 | W40: =T40/P40 -> 0.00014603058 | X40: NA | AA40: Business development connects, Strategy, Investor connect, venture debt | AC40: Eco-system referral | AD40: scout | AE40: Ashish | AF40: Provisioned
B41: 37 | C41: Hachi Labs Incorporation | D41: LeadCandy | E41: USA | F41: HR Tech | G41: 42219 | H41: Seed | I41: NA | J41: 267.1756 | K41: N.A | L41: NA | M41: 0 | N41: NA | O41: Written off - residual value received | P41: 22.273203 | Q41: =P41 -> 22.273203 | R41: NA | S41: NA | T41: =U41+V41 -> 0 | U41: 0 | V41: 0 | W41: =T41/P41 -> 0 | X41: NA | Z41: =W41 -> 0 | AA41: General counsel, Business Development connects | AC41: VC referral | AD41: Karthik | AE41: Karthik | AF41: Provisioned
B42: 38 | C42: SminQ India Solutions Private Limited | D42: GetMarkk | E42: Pune | F42: Retail-Tech | G42: 42458 | H42: Seed | I42: NA | J42: 326.3629 | K42: N.A | L42: NA | M42: 0 | N42: NA | O42: Written off - residual value received | P42: 75.959076 | R42: 0.1021 | S42: NA | T42: =U42+V42 -> 0.870224 | U42: 0 | V42: 0.870224 | W42: =T42/P42 -> 0.011456485 | X42: NA | Z42: =W42 -> 0.011456485 | AA42: Strategy around the pivot to cross-border model, cross-border connects in US to facilitate market entry, business development, general counsel | AB42: Saama Capita,Beenext | AC42: Founder network ( connected through the founder's prior startup) | AD42: Sanjay | AE42: Sanjay | AF42: Written Off
B43: 39 | C43: Sourcecode Media Private Limited | D43: FactorDaily | E43: Bengaluru | F43: Media & Entertainment | G43: 42633 | H43: Series A | I43: NA | J43: 263.79672 | K43: N.A | L43: NA | M43: 0 | N43: NA | O43: Written off - residual value received | P43: 45.054723 | R43: 0.0985 | S43: NA | T43: =U43+V43 -> 0.056426 | U43: 0 | V43: 0.056426 | W43: =T43/P43 -> 0.0012523881 | X43: NA | Z43: =W43 -> 0.0012523881 | AA43: Business Development connect , strategy | AB43: Accel | AC43: Eco-system referral | AD43: Karthik | AE43: Karthik | AF43: Written Off
B44: 40 | C44: Opentalk Inc | D44: Open Talk | E44: Singapore | F44: Social Media | G44: 43021 | H44: Seed | I44: NA | J44: 419.3017 | K44: N.A | L44: NA | M44: 0 | N44: NA | O44: Written off - residual value received | P44: 24.044821 | R44: 0.0567 | S44: NA | T44: =U44+V44 -> 0.021052 | U44: 0 | V44: 0.021052 | W44: =T44/P44 -> 0.00087553158 | X44: NA | Z44: =W44 -> 0.00087553158 | AA44: Finance & Compliance support | AC44: ex-startup founder, referred by a portfolio founder | AD44: Karthik | AE44: Karthik | AF44: Written Off
B45: 41 | C45: V H Education Services Private Limited | D45: Skillenza | E45: Bengaluru | F45: HR Tech | G45: 42445 | H45: Seed | I45: NA | J45: 198.40507 | K45: N.A | L45: NA | M45: 0 | N45: NA | O45: Provisioned 100% | P45: 33.003203 | R45: 0.125 | S45: NA | T45: =U45+V45 -> 0.01772 | U45: 0 | V45: 0.01772 | W45: =T45/P45 -> 0.00053691758 | X45: NA | AA45: Strategy, Investor connect, Finance & Compliance support , support in investmemnt round | AC45: Eco-system referral | AD45: scout | AE45: Ashish | AF45: Written Off
B46: 42 | C46: Patchus Communications Private Limited | D46: Patch | E46: Delhi | F46: B2B Services | G46: 42830 | H46: Seed | I46: NA | J46: 50.0045 | K46: N.A | L46: NA | M46: 0 | N46: NA | O46: Written off - residual value received | P46: 12.83049 | R46: 0.1 | S46: NA | T46: =U46+V46 -> 1.675865 | U46: 0 | V46: 1.675865 | W46: =T46/P46 -> 0.13061582 | X46: -0.86938418 | Z46: =W46 -> 0.13061582 | AA46: Strategy, Finance & Compliance support , investor connect | AC46: Founder network | AD46: Ashish | AE46: Ashish | AF46: Written Off
B47: 43 | C47: Volare Technologies Private Limited | D47: Intouchapp | E47: Pune | F47: Social Media | G47: 42369 | H47: Seed | I47: NA | J47: 201.28961 | K47: 194.11536 | L47: =K47 -> 194.11536 | M47: 1 | N47: =L47*(1-M47) -> 0 | O47: Provisioned 100% | P47: 61.290409 | Q47: =P47 -> 61.290409 | R47: 0.3 | S47: NA | T47: =U47+V47 -> 0 | U47: 0 | V47: 0 | W47: =T47/P47 -> 0 | X47: NA | AA47: Strategy, Business Development , Finance & compliance support, hiring | AC47: Eco-system referral | AD47: Karthik | AE47: Karthik | AF47: Provisioned
B48: 44 | C48: Oku Tech Private Limited | D48: Fastfox | E48: Delhi | F48: Real Estate | G48: 42446 | H48: Series A | I48: NA | J48: 1061.579 | K48: N.A | L48: NA | M48: 0 | N48: NA | O48: Written off - residual value received | P48: 82.994671 | R48: 0.050963205 | S48: NA | T48: =U48+V48 -> 3.4151353 | U48: 0 | V48: 3.4151353 | W48: =T48/P48 -> 0.04114885 | X48: -0.42953258 | Y48: FastFox was acquired by Elara which in turn has been acquired by News Corp | Z48: =W48 -> 0.04114885 | AA48: General counsel, hiring | AC48: VC referral | AD48: Sajid Fazalbhoy* | AE48: Sajid Fazalbhoy* | AF48: Written Off
B49: 45 | C49: Inzane Labs Private Limited | D49: Oheyo/ Pagalguy | E49: Mumbai | F49: EdTech | G49: 42459 | H49: Seed | I49: NA | J49: 487.30005 | K49: 466.6641 | L49: =K49 -> 466.6641 | M49: 1 | N49: =L49*(1-M49) -> 0 | O49: Provisioned 100% | P49: 37.584027 | Q49: =P49 -> 37.584027 | R49: 0.077 | S49: NA | T49: =U49+V49 -> 0 | U49: 0 | V49: 0 | W49: =T49/P49 -> 0 | X49: NA | AA49: NA | AC49: LP referral | AD49: Karthik | AE49: Karthik | AF49: Provisioned
B50: 46 | C50: Unocoin Technologies Pte Ltd | D50: Unocoin | E50: Singapore | F50: FinTech | G50: 42579 | H50: Seed | I50: Series A | J50: 605.18158 | K50: 964.80303 | L50: =K50 -> 964.80303 | M50: 1 | N50: =L50*(1-M50) -> 0 | O50: Provisioned 100% | P50: 29.409712 | Q50: =P50 -> 29.409712 | R50: 0.05 | S50: 0.049 | T50: =U50+V50 -> 0 | U50: 0 | V50: 0 | W50: =T50/P50 -> 0 | X50: NA | AA50: General counsel | AB50: Dream Incubator, Boost VC, Tim Draper | AC50: Inbound / Events | AD50: Arpit | AE50: Arpit | AF50: Provisioned
B51: 47 | C51: Monkeybox Food Technology Private Limited | D51: MonkeyBox | E51: Bengaluru | F51: Consumer Brands | G51: 42334 | H51: Seed | I51: NA | J51: 104.23561 | K51: N.A | L51: =K51 -> N.A | M51: 0 | N51: NA | O51: Written off - residual value received | P51: 62.990897 | R51: 0.1064 | S51: NA | T51: =U51+V51 -> 0 | U51: 0 | V51: 0 | W51: =T51/P51 -> 0 | X51: NA | AA51: Business development connects, Strategy, Investor connect, Compliance support , hiring, venture debt | AC51: ex-portfolio founder | AD51: Ashish | AE51: Ashish | AF51: Written Off
B52: 48 | C52: Zillion Technologies Private Limited | D52: Zillion | E52: Delhi | F52: Consumer Internet | G52: 42292 | H52: Seed | I52: NA | J52: NA | K52: 160.89908 | L52: =K52 -> 160.89908 | M52: 1 | N52: =L52*(1-M52) -> 0 | O52: Provisioned 100% | P52: 2.5 | Q52: =P52 -> 2.5 | R52: NA | S52: NA | T52: =U52+V52 -> 0 | U52: 0 | V52: 0 | W52: =T52/P52 -> 0 | X52: NA | AA52: NA | AD52: Sajid Fazalbhoy* | AE52: Sajid Fazalbhoy* | AF52: Provisioned
B53: 49 | C53: Gyankosh Solutions Private Limited | D53: Flipclass | E53: Bengaluru | F53: EdTech | G53: 42202 | H53: Seed | I53: NA | J53: 162.59924 | K53: N.A | L53: NA | M53: 0 | N53: NA | O53: Written off - residual value received | P53: 27.198066 | Q53: =P53 -> 27.198066 | R53: 0.13316431 | S53: NA | T53: =U53+V53 -> 0 | U53: 0 | V53: 0 | W53: =T53/P53 -> 0 | X53: NA | Z53: =W53 -> 0 | AA53: NA | AD53: Karthik | AE53: Karthik | AF53: Provisioned
C54: Total | P54: =SUM(P4:P53) -> 3654.9829 | Q54: =SUM(Q4:Q53) -> 1963.0003 | T54: =U54+V54 -> 13164.789 | U54: =SUM(U4:U53) -> 7755.6882 | V54: =SUM(V4:V53) -> 5409.1007 | W54: =T54/P54 -> 3.6018743 | X54: 0.20607448
C56: * Indicates that the team member is no longer associated with the firm

Sheet Fund III
B2: # | C2: Company | D2: Business / Brand | E2: Geography | F2: Sector | G2: Date | H2: Stage at Entry | I2: Current Stage | J2: Entry Valuation | K2: Last Round Valuation | L2: Valuation used for Mark to Market | M2: Discount to last round | N2: Effective Valuation for Mark-to-market | O2: Valuation Basis | P2: Total Invested Cost | Q2: Residual Cost | R2: Stake (At Entry) | S2: Stake (Current) | T2: Total Value | U2: Unrealised Value | V2: Realised Value | W2: Gross MOIC | X2: Gross IRR (₹) | Y2: If Exited, Mode of Exit | Z2: GP Exit MOIC | AA2: Value Creation by Fund | AB2: Co-investor(s) | AC2: Sourcing Route | AD2: Deal Source | AE2: Deal Lead | AF2: Status
G3: MM/YY | J3: ₹ Mn | K3: ₹ Mn | L3: ₹ Mn | N3: ₹ Mn | P3: ₹ Mn | Q3: ₹ Mn | R3: % | S3: % | T3: ₹ Mn | U3: ₹ Mn | V3: ₹ Mn | W3: x | X3: %
B4: =B3+1 -> 1 | C4: Procol Tech Private Limited | D4: Procol | E4: NCR | F4: B2B Marketplace | G4: 43626 | H4: Seed | I4: Series A | J4: 280.54037 | K4: 5853.928 | L4: =K4 -> 5853.928 | M4: 0 | N4: =L4*(1-M4) -> 5853.928 | O4: Marked to the latest round (Pre-Series A - July 22) | P4: 187.73201 | Q4: =P4 -> 187.73201 | R4: 0.20141412 | S4: 0.1972 | T4: =U4+V4 -> 1154.2839 | U4: 1154.2839 | V4: 0 | W4: =T4/P4 -> 6.1485727 | X4: 0.40763498 | AA4: Go-to-Market and business model - led by KR, SP, AF Fund -raise SP - articulation of strategy, Helping founders reset balance better between product and distribution / sales. Intros to potential employees, consultants Business Development - Jitesh | AB4: GMO Venture Partners, Anchorage Capital, Surge(Peak XV Partners), Beenext, Rainmatter | AC4: Connected by Mahesh Kabra ( advisor) | AD4: Karthik | AE4: Karthik | AF4: Active
B5: 2 | C5: Bunch Microtechnologies Private Limited | D5: Classplus | E5: NCR | F5: EdTech | G5: 43745 | H5: Seed | I5: Series E | J5: 850.04053 | K5: 51752.013 | L5: =K5 -> 51752.013 | M5: 0.5 | N5: =L5*(1-M5) -> 25876.006 | O5: 50% discount to the last round (Series E - Feb'22) | P5: 704.71358 | Q5: =P5 -> 704.71358 | R5: 0.10001981 | S5: 0.1013 | T5: =U5+V5 -> 2379.3364 | U5: 2379.3364 | V5: 0 | W5: =T5/P5 -> 3.3763169 | X5: 0.2667653 | AA5: Mentoring, coaching marketplace team to reengineer themselves + rework strategy to grow faster, recruitment + interviews of senior business + marketing CXOs - SP, Fund raise - Karthik Finance hiring - AF Hiring support - Passion Connect Finance Control - Constellation | AB5: Tiger Global, Alpha Wave Incubation, Surge (Peak XV Partners), RTP Global, Strive | AC5: Outbound | AD5: Karthik | AE5: Sajith | AF5: Active
B6: 3 | C6: Ono Labs Private Limited | D6: Mastree | E6: Bengaluru | F6: SaaS | G6: 43804 | H6: Seed | I6: NA | J6: 240.02 | K6: NA | L6: 0 | M6: 0 | N6: =L6*(1-M6) -> 0 | O6: Exit Value | P6: 40.02 | Q6: 0 | R6: 0.16673611 | S6: NA | T6: =U6+V6 -> 90 | U6: 0 | V6: 90 | W6: =T6/P6 -> 2.2488756 | X6: 7.5339242 | Y6: Acquired by Unacademy | Z6: =W6 -> 2.2488756 | AA6: Product + business strategy coaching, connecting to brand consultant, intros to partners for distribution - SP Connect with Unacademy - KR Hiring - Passion Connect | AB6: NA. | AC6: Blume Alumni ( ex-analyst) | AD6: Sajith | AE6: Sajith | AF6: Exited
B7: 4 | C7: Greenizon Agritech Consultancy Private Limited | D7: Jai Kisan | E7: Mumbai | F7: AgriTech | G7: 43536 | H7: Seed | I7: Series B6 | J7: 115.02136 | K7: 15109.619 | L7: 5628.9897 | M7: 0.5 | N7: =L7*(1-M7) -> 2814.4949 | O7: Marked at 50% discount to the Series A round (June 21) | P7: 525.50479 | Q7: =P7 -> 525.50479 | R7: 0.12856288 | S7: 0.17640433 | T7: =U7+V7 -> 568.28986 | U7: 568.28986 | V7: 0 | W7: =T7/P7 -> 1.0814171 | X7: 0.017709848 | AA7: Mentoring & guidance - KR Fund raise - AF Hiring - AF, Passion Connect Business structuring, Finance Control - Constellation | AB7: GMO Venture Partners, Yara Growth Ventures, DG Daiwa Ventures, NabVentures, Arkam | AC7: Eco-system referral | AD7: Sajid Fazalbhoy* | AE7: Ashish | AF7: Active
B8: 5 | C8: Lambdatest Inc | D8: TestMu | E8: NCR / USA | F8: SaaS | G8: 43826 | H8: Seed | I8: Series D3 | J8: 8617.7894 | K8: 32536.816 | L8: =K8 -> 32536.816 | M8: 0.2 | N8: =L8*(1-M8) -> 26029.453 | O8: Valued at 20% discount to the Series D3 round (Dec'24) | P8: 372.27805 | Q8: =P8 -> 372.27805 | R8: 0.17227235 | S8: 0.1169 | T8: =U8+V8 -> 2901.0013 | U8: 2901.0013 | V8: 0 | W8: =T8/P8 -> 7.7925661 | X8: 0.54107289 | AA8: Go-to-Market - SN + AC Fund raise - SN + KR | AB8: Premji Invest, GIC, Peak XV Partners, Leo Capital, Telstra, Avaatar, Qualcomm | AC8: Eco-system referral ( Ramakant Sharma - Founder - Livspace) | AD8: Sanjay | AE8: Sanjay | AF8: Active
B9: 6 | C9: PM Labs, Inc. | D9: Agara | E9: Bengaluru / USA | F9: SaaS | G9: 43497 | H9: Pre-Series A | I9: NA | J9: 602.16781 | K9: NA | L9: 0 | M9: 0 | N9: =L9*(1-M9) -> 0 | O9: Exit Value | P9: 161.16059 | Q9: 0 | R9: 0.17431732 | S9: NA | T9: =U9+V9 -> 644.42632 | U9: 0 | V9: 644.42632 | W9: =T9/P9 -> 3.9986594 | X9: 0.91397628 | Y9: Acquired by Coinbase | Z9: =W9 -> 3.9986594 | AA9: Business Development - Jitesh Fund raise - SN Corporate matters - AF | AB9: UTEC, RTP Global | AC9: Eco-system referral ( Pankaj Gupta, Google) | AD9: Sanjay | AE9: Sanjay | AF9: Exited
B10: =IF(C10="","",B9+1) -> 7 | C10: Euler Motors Private Limited | D10: Euler | E10: NCR | F10: Mobility-Tech | G10: 43523 | H10: Seed | I10: Series D | J10: 485.53368 | K10: 14380 | L10: =K10 -> 14380 | M10: 0 | N10: =L10*(1-M10) -> 14380 | O10: Marked up to the Series D round (Mar 25) | P10: 455.09862 | Q10: =P10 -> 455.09862 | R10: 0.1977228 | S10: 0.039622092 | T10: =U10+V10 -> 592.55572 | U10: 592.55572 | V10: 0 | W10: =T10/P10 -> 1.3020381 | X10: 0.058552715 | AA10: Finance hiring - AF Hiring support - Passion Connect Finance Control - Constellation Fund raise (all aspects) - AF Business strategy, monitoring and tactical advisory, mentoring and team building- Arpit Business Development - Jitesh | AB10: Hero MotoCorp, GIC, Asian Development Bank, British International Investment, Piramal Alternatives, Athera Venture Partners | AC10: Outbound reach-out from Blume intern | AD10: Arpit | AE10: Arpit | AF10: Active
B11: =IF(C11="","",B10+1) -> 8 | C11: Uolo EdTech Private Limited | D11: Uolo | E11: NCR | F11: EdTech | G11: 44105 | H11: Seed | I11: Pre Series B | J11: 700.35524 | K11: 3140.2157 | L11: 0 | M11: 0 | N11: =L11*(1-M11) -> 0 | O11: Cost | P11: 294.79389 | Q11: =P11 -> 294.79389 | R11: 0.14285915 | S11: 0.133 | T11: =U11+V11 -> 294.79389 | U11: 294.79389 | V11: 0 | W11: =T11/P11 -> 1 | X11: -7.4505806e-10 | AA11: Connecting them to potential content partners, market intelligence, and helping founder think through product roadmap - SP Advisory - KR | AB11: Winter Capital, Omidyar, Tencent, Morphosis Capital | AC11: Ex-portfolio founder | AD11: Karthik | AE11: Sajith | AF11: Active
B12: =IF(C12="","",B11+1) -> 9 | C12: Sprinto Technology Private Limited | D12: Sprinto | E12: Bengaluru | F12: SaaS | G12: 43859 | H12: Seed | I12: Series B | J12: 724.10524 | K12: 8724.105 | L12: =K12 -> 8724.105 | M12: 0 | N12: =L12*(1-M12) -> 8724.105 | O12: Marked to the latest round (Series B - April 24) | P12: 183.65168 | Q12: =P12 -> 183.65168 | R12: 0.18818052 | S12: 0.1298 | T12: =U12+V12 -> 1132.2258 | U12: 1132.2258 | V12: 0 | W12: =T12/P12 -> 6.1650715 | X12: 0.46126249 | AA12: Mentoring, Fund raise and Advisory - KR + SN | AB12: Elevation, Accel | AC12: Founder network ( connected through the founder's prior startup) | AD12: Karthik | AE12: Sanjay | AF12: Active
B13: =IF(C13="","",B12+1) -> 10 | C13: Weblength Infonet Private Limited | D13: SuperSet | E13: NCR | F13: EdTech | G13: 44238 | H13: Seed | I13: NA | J13: 399.99999 | K13: NA | L13: 0 | M13: 0 | N13: =L13*(1-M13) -> 0 | O13: Exit Value | P13: 79.999992 | Q13: 0 | R13: 0.2 | S13: NA | T13: =U13+V13 -> 319.39997 | U13: 0 | V13: 319.39997 | W13: =T13/P13 -> 3.9925 | X13: 3.0385747 | Y13: Acquired by Great Learning | Z13: =W13 -> 3.9925 | AA13: SP - founder mentoring, helping the founders think through fundraising narratives, intros to customers, helping the founder think through sales org structuring. hiring reference checks | AC13: Inbound | AD13: Sajith | AE13: Sajith | AF13: Exited
B14: =IF(C14="","",B13+1) -> 11 | C14: Bureau Inc. | D14: Bureau | E14: Bengaluru / USA | F14: FinTech | G14: 44138 | H14: Seed | I14: Series A1 | J14: 1706.3096 | K14: 9196.8859 | L14: =K14 -> 9196.8859 | M14: 0 | N14: =L14*(1-M14) -> 9196.8859 | O14: Marked to the latest round (Series B - Nov'24) | P14: 228.12928 | Q14: =P14 -> 228.12928 | R14: 0.11906917 | S14: 0.115 | T14: =U14+V14 -> 714.64229 | U14: 714.64229 | V14: 0 | W14: =T14/P14 -> 3.1326197 | X14: 0.30973451 | AA14: Advisory - KR | AB14: Commerce Ventures, GMO Venture Partners, Quona Capital, Village Global, Okta, Sorenson, PayPal | AC14: Ex-portfolio founder | AD14: Karthik | AE14: Karthik | AF14: Active
B15: =IF(C15="","",B14+1) -> 12 | C15: Medfin India Private Limited | D15: Medfin | E15: Bengaluru | F15: HealthTech | G15: 44147 | H15: Seed | I15: Pre Series B | J15: 964.69526 | K15: 2297.3331 | L15: 0 | M15: 1 | N15: =L15*(1-M15) -> 0 | O15: Provision -100% | P15: 275.24591 | Q15: =P15 -> 275.24591 | R15: 0.15008639 | S15: 0.14522264 | T15: =U15+V15 -> 0 | U15: 0 | V15: 0 | W15: =T15/P15 -> 0 | X15: NA | AA15: Business development relationships - Jitesh Fund raise (all aspects) - Capital Markets Team Finance Management - Ashish Mentoring and team building - Arpit Business strategy, monitoring and tactical advisory - Arpit | AB15: Axilor, HealthX Capital, Dream Incubator | AC15: via banker | AD15: Arpit | AE15: Arpit | AF15: Provisioned
B16: 13 | C16: Vasudhaiva Kutumbakam Group Private Limited | D16: Leverage | E16: NCR | F16: EdTech | G16: 43455 | H16: Seed | I16: Series C1 | J16: 225.55533 | K16: 11477.963 | L16: =K16 -> 11477.963 | M16: 0 | N16: =L16*(1-M16) -> 11477.963 | O16: Marked to the latest round (Series C1 - June 24) | P16: 400.12165 | Q16: =P16 -> 400.12165 | R16: 0.15 | S16: 0.17042941 | T16: =U16+V16 -> 1955.4953 | U16: 1955.4953 | V16: 0 | W16: =T16/P16 -> 4.8872519 | X16: 0.40223075 | AA16: Helping the founder to rethink of the business from a broader lens, reworking how they measure and track business goals via cohort approach, helping the founder devise and craft a compelling fundraising narrative - SP Finance Control - Constellation Fund raise ( all aspects) - KR Debt raise- AF | AB16: Educational Testing Service (ETS), DSG Consumer Partners, Kaizenvest, Tomorrow Capital, DSP Invest, Artha India Ventures, NB Ventures | AC16: Founder was connected from a previous angel invetsment | AD16: Karthik | AE16: Sajith | AF16: Active
B17: 14 | C17: Octopolis Technologies Private Limited | D17: ApnaKlub | E17: NCR | F17: B2B Marketplace | G17: 44320 | H17: Seed | I17: Pre Series B5 | J17: 450.04787 | K17: 7212.7156 | L17: 2659.8746 | M17: 0 | N17: =L17*(1-M17) -> 2659.8746 | O17: Marked up at Series A round (April 22) - Subsequent rounds marked at cost | P17: 214.5246 | Q17: =P17 -> 214.5246 | R17: 0.20000939 | S17: 0.1366 | T17: =U17+V17 -> 435.03145 | U17: 435.03145 | V17: 0 | W17: =T17/P17 -> 2.027886 | X17: 0.19688113 | AB17: Tiger Global, Surge (Peak XV Partners), Whiteboard Capital, Truescale, Flourish Ventures | AC17: Blume network | AD17: Karthik | AE17: Ashish | AF17: Active
B18: 15 | C18: Pilani Experts Technology Labs Private Limited | D18: Tapchief | E18: Bengaluru | F18: HR Tech | G18: 43642 | H18: Seed | I18: NA | J18: 490.69829 | K18: NA | L18: 0 | M18: 0 | N18: =L18*(1-M18) -> 0 | O18: Exit Value | P18: 140.085 | Q18: 0 | R18: 0.1288 | S18: NA | T18: =U18+V18 -> 163.08753 | U18: 0 | V18: 163.08753 | W18: =T18/P18 -> 1.1642041 | X18: 0.13068216 | Y18: Acquired by Unacademy | Z18: =W18 -> 1.1642041 | AA18: Mentoring, fund raise, exit - SN + AF Business Development - Jitesh Advisory - KR | AB18: One97 | AC18: Founder network | AD18: Sanjay | AE18: Sanjay | AF18: Exited
B19: =IF(C19="","",B18+1) -> 16 | C19: Ultrahuman Healthcare Private Limited | D19: Ultrahuman | E19: Bengaluru | F19: HealthTech | G19: 43928 | H19: Series A | I19: Series B3 | J19: 2130 | K19: 10382.792 | L19: =K19 -> 10382.792 | M19: 0 | N19: =L19*(1-M19) -> 10382.792 | O19: Marked up to the last round (Series B3 - March 24) | P19: 370.47103 | Q19: =P19 -> 370.47103 | R19: 0.060360554 | S19: 0.0719 | T19: =U19+V19 -> 746.14974 | U19: 746.14974 | V19: 0 | W19: =T19/P19 -> 2.0140569 | X19: 0.15949777 | AA19: Advisory - KR | AB19: Nexus, AlphaWave Incubation, Steadview | AC19: Ex-portfolio founder | AD19: Karthik | AE19: Karthik | AF19: Active
B20: =IF(C20="","",B19+1) -> 17 | C20: Tartan Aerial Sense Tech Private Limited | D20: Niqo Robotics | E20: Bengaluru | F20: AgriTech | G20: 43502 | H20: Series A | I20: Series B | J20: 486.81314 | K20: 3320 | L20: 0 | M20: 0 | N20: =L20*(1-M20) -> 0 | O20: Cost | P20: 140.73637 | Q20: =P20 -> 140.73637 | R20: 0.067179846 | S20: 0.0929 | T20: =U20+V20 -> 140.73637 | U20: 140.73637 | V20: 0 | W20: =T20/P20 -> 1 | X20: 2.9802322e-09 | AA20: Mentoring and Advisory - KR Cross-border structuring - AF | AB20: Omnivore, Beenext, FMC Ventures, Brida Innovation Ventures | AC20: Founder network ( connected by Stellapps founder) | AD20: Karthik | AE20: Karthik | AF20: Active
B21: =IF(C21="","",B20+1) -> 18 | C21: Pixxel Inc | D21: Pixxel | E21: Bengaluru / USA | F21: SpaceTech | G21: 44057 | H21: Seed | I21: Series B | J21: 2041.1191 | K21: 16824.596 | L21: =K21 -> 16824.596 | M21: 0 | N21: =L21*(1-M21) -> 16824.596 | O21: Marked up to the last round (Series B - April 23) | P21: 385.25399 | Q21: =P21 -> 385.25399 | R21: 0.099992799 | S21: 0.0787 | T21: =U21+V21 -> 1199.6155 | U21: 1199.6155 | V21: 0 | W21: =T21/P21 -> 3.1138303 | X21: 0.32381964 | AA21: Go-to-Market - SN + AC Finance control, Finance hiring - Constellation | AB21: Google, Radical Ventures, Lightspeed, GrowX, Sparta, Athera Venture Partners, Accenture, Omnivore, Glade Brook | AC21: Alumni network of GPs ( BITS alum connected through Sanjay) | AD21: Sanjay | AE21: Sanjay | AF21: Active
B22: =IF(C22="","",B21+1) -> 19 | C22: HealthAssure Private Limited | D22: HealthAssure | E22: Mumbai | F22: HealthTech | G22: 43636 | H22: Seed | I22: Pre Series B | J22: 1235.0006 | K22: 2214.723 | L22: =K22 -> 2214.723 | M22: 0 | N22: =L22*(1-M22) -> 2214.723 | O22: Marked up to the last round (Series A2 - September 22) | P22: 199.69086 | Q22: =P22 -> 199.69086 | R22: 0.12831284 | S22: 0.1193 | T22: =U22+V22 -> 264.23734 | U22: 264.23734 | V22: 0 | W22: =T22/P22 -> 1.323232 | X22: 0.050566921 | AB22: Blue Ashva Capital, Leo Capital | AC22: Sanjay's personal network | AD22: Sajid Fazalbhoy* | AE22: Arpit | AF22: Active
B23: =IF(C23="","",B22+1) -> 20 | C23: Arka Venture Labs Fund Partners LLC | D23: Arka | E23: USA | F23: Accelerator | G23: 43627 | H23: Seed | I23: NA | J23: NA | K23: NA | L23: 0 | M23: 0 | N23: =L23*(1-M23) -> 0 | O23: Cost | P23: 105.99944 | Q23: =P23 -> 105.99944 | R23: 0.25 | S23: 0.25 | T23: =U23+V23 -> 105.99944 | U23: 105.99944 | V23: 0 | W23: =T23/P23 -> 1 | X23: 0 | AA23: Sacaling up, Go-to-Market - Radhesh Fund raise - Radhesh, SN Portfolio construction and structuring - KR + AF | AB23: Emergent Ventures , Benhamou Global Ventures | AC23: NA - concept was framed by Blume - underlying investments sourced through networks of Blume, Radhesh, Emergent and BGV | AD23: Sanjay | AE23: Sanjay | AF23: Active
B24: =IF(C24="","",B23+1) -> 21 | C24: Ethereal Machines Private Limited | D24: Ethereal | E24: Bengaluru | F24: DeepTech | G24: 43459 | H24: Seed | I24: Pre Series B | J24: 329.78544 | K24: 4835.0696 | L24: =K24 -> 4835.0696 | M24: 0 | N24: =L24*(1-M24) -> 4835.0696 | O24: Marked up to last round (Pre-Series B - June 24) | P24: 163.99336 | Q24: =P24 -> 163.99336 | R24: 0.2146 | S24: 0.13336341 | T24: =U24+V24 -> 485.44104 | U24: 485.44104 | V24: 0 | W24: =T24/P24 -> 2.9601262 | X24: 0.24391882 | AA24: Mentoring - Arpit Finance control, compliances support - Constellation | AB24: Peak XV Partners (Surge), Steadview | AC24: Events /Outbound | AD24: Arpit | AE24: Arpit | AF24: Active
B25: 22 | C25: Qikwork Services Private Limited | D25: Smartstaff | E25: Bengaluru | F25: HR-Tech | G25: 44181 | H25: Seed | I25: Series A4 | J25: 769.59158 | K25: 2810 | L25: =K25 -> 2810 | M25: 1 | N25: =L25*(1-M25) -> 0 | O25: Provision -100% | P25: 258.99865 | Q25: =P25 -> 258.99865 | R25: 0.12018877 | S25: 0.14712806 | T25: =U25+V25 -> 0 | U25: 0 | V25: 0 | W25: =T25/P25 -> 0 | X25: NA | AA25: SP - product and business strategy KR - Mentoring | AB25: Nexus Ventures, Arkam Ventures, Alteria Capital | AC25: Ex-portfolio founder | AD25: Karthik | AE25: Sajith | AF25: Provisioned
B26: =IF(C26="","",B25+1) -> 23 | C26: ATI Motors Inc | D26: ATI Motors | E26: Bengaluru / USA | F26: DeepTech | G26: 44320 | H26: Pre- Series A | I26: Series B | J26: 848.98212 | K26: 6075.893 | L26: =K26 -> 6075.893 | M26: 0 | N26: =L26*(1-M26) -> 6075.893 | O26: Marked up to last round (Series B - Dec'24) | P26: 195.84462 | Q26: =P26 -> 195.84462 | R26: 0.10021776 | S26: 0.14587908 | T26: =U26+V26 -> 490.72975 | U26: 490.72975 | V26: 0 | W26: =T26/P26 -> 2.5057096 | X26: 0.27555651 | AA26: - | AB26: True Ventures, Athera Venture Partners, Exfinity Ventures, MFV Partners | AC26: Blume Founders Fund | AD26: Arpit | AE26: Arpit | AF26: Active
B27: =IF(C27="","",B26+1) -> 24 | C27: Blume Founders Fund | D27: BFF | E27: NA | F27: NA | H27: NA | I27: NA | J27: NA | K27: NA | L27: 0 | M27: 0 | N27: =L27*(1-M27) -> 0 | O27: NA | P27: 110.23543 | Q27: =P27 -> 110.23543 | R27: NA | S27: NA | T27: =U27+V27 -> 235.69829 | U27: 235.69829 | V27: 0 | W27: =T27/P27 -> 2.1381356 | X27: 0.18022133 | AA27: - | AB27: - | AC27: - | AF27: Active
B28: =IF(C28="","",B27+1) -> 25 | C28: Zolve Innovations Inc | D28: Zolve | E28: USA | F28: FinTech | G28: 44495 | H28: Seed | I28: Series B | J28: 3793.999 | K28: 15150.214 | L28: =K28 -> 15150.214 | M28: 0 | N28: =L28*(1-M28) -> 15150.214 | O28: Marked up to last round (Series B - Jan'25) | P28: 34.533613 | Q28: =P28 -> 34.533613 | R28: 0.0091021671 | S28: 0.0050674195 | T28: =U28+V28 -> 76.772489 | U28: 76.772489 | V28: 0 | W28: =T28/P28 -> 2.2231236 | X28: 0.23499966 | AA28: - | AB28: Accel, Tiger Global, Lightspeed, DST Global, Craegis, HSBC, GMO | AC28: Ex-portfolio founder | AD28: Karthik | AE28: Karthik | AF28: Active
B29: =IF(C29="","",B28+1) -> 26 | C29: Technicolour Dream Pants Private Limited | D29: Stage3 | E29: NCR | F29: E-commerce | G29: 43724 | H29: Seed | I29: Pre Series A | J29: 264.12134 | K29: 447.6152 | L29: 0 | M29: 0 | N29: =L29*(1-M29) -> 0 | O29: Exit Value | P29: 93.580799 | Q29: =P29 -> 93.580799 | R29: 0.22212129 | S29: NA | T29: =U29+V29 -> 0.006861 | U29: 0.006861 | V29: 0 | W29: =T29/P29 -> 7.3316322e-05 | X29: 2.9802322e-09 | AA29: Mentoring, Fund raise - KR Product roadmap feedback - SP | AB29: - | AC29: - | AD29: Karthik | AE29: Karthik | AF29: Written Off
B30: =IF(C30="","",B29+1) -> 27 | C30: Taaraka Technologies Private Limited | D30: Taaraka | E30: Mumbai | F30: ConsumerTech | G30: 43407 | H30: Seed | I30: Seed | J30: 263.56403 | K30: 273.11174 | L30: 0 | M30: 0 | N30: =L30*(1-M30) -> 0 | O30: Provision -100% | P30: 86.02439 | Q30: =P30 -> 86.02439 | R30: 0.22763864 | S30: 0.2664713 | T30: =U30+V30 -> 0 | U30: 0 | V30: 0 | W30: =T30/P30 -> 0 | X30: NA | AA30: Mentoring, Fund raise - AF Product roadmap feedback - KS, Radhika | AB30: - | AC30: Founder was connected through his earlier stint from previous stint with TVF | AD30: Karthik | AE30: Ashish | AF30: Provisioned
B31: 28 | C31: Tinkerix Techonologies Private Limited | D31: Cellfish | E31: Hyderabad | F31: Mobile Telephony | G31: 43675 | H31: Seed | I31: Seed | J31: 242.82245 | K31: =J31 -> 242.82245 | L31: 0 | M31: 0 | N31: =L31*(1-M31) -> 0 | O31: Provision -100% | P31: 60.003228 | Q31: =P31 -> 60.003228 | R31: 0.24216008 | S31: 0.24216008 | T31: =U31+V31 -> 0 | U31: 0 | V31: 0 | W31: =T31/P31 -> 0 | X31: NA | AA31: Mentoring and Advisory - KR | AB31: - | AC31: Via Angel invetsor on cap table | AD31: Karthik | AE31: Karthik | AF31: Provisioned
B32: 29 | C32: RayIoT Solutions Private Limited | D32: RayIOT | E32: Bengaluru | F32: IoT | G32: 43878 | H32: Seed | I32: NA | J32: 121.6 | K32: NA | L32: NA | M32: 0 | N32: NA | O32: Exit Value | P32: 21.6 | Q32: 0 | R32: 0.17763158 | S32: NA | T32: =U32+V32 -> 0.0216 | U32: 0 | V32: 0.0216 | W32: =T32/P32 -> 0.001 | X32: -0.87307075 | Z32: =W32 -> 0.001 | AA32: Hiring support - Passion Connect Business strategy, monitoring and tactical advisory - Arpit | AB32: - | AC32: Inbound from the founder | AD32: Arpit | AE32: Arpit | AF32: Written Off
P33: =SUM(P4:P32) -> 6490.0254 | Q33: =SUM(Q4:Q32) -> 6047.1598 | T33: =SUM(T4:T32) -> 17089.978 | U33: =SUM(U4:U32) -> 15873.043 | V33: =SUM(V4:V32) -> 1216.9354 | W33: =T33/P33 -> 2.6332683 | X33: 0.25267154
C36: * Indicates that the team member is no longer associated with the firm

Sheet Fund IV
B2: # | C2: Company | D2: Business / Brand | E2: Geography | F2: Sector | G2: Date | H2: Stage at Entry | I2: Current Stage | J2: Entry Valuation | K2: Last Round Valuation | L2: Valuation used for Mark to Market | M2: Discount to last round | N2: Effective Valuation for Mark-to-market | O2: Valuation Basis | P2: Total Invested Cost | Q2: Residual Cost | R2: Stake (At Entry) | S2: Stake (Current) | T2: Total Value | U2: Unrealised Value | V2: Realised Value | W2: Gross MOIC | X2: Gross IRR (₹) | Y2: If Exited, Mode of Exit | Z2: GP Exit MOIC | AA2: Value Creation by Fund | AB2: Co-investor(s) | AC2: Sourcing Route | AD2: Deal Source | AE2: Deal Lead | AF2: Status
G3: MM/YY | J3: ₹ Mn | K3: ₹ Mn | L3: ₹ Mn | N3: ₹ Mn | P3: ₹ Mn | Q3: ₹ Mn | R3: % | S3: % | T3: ₹ Mn | U3: ₹ Mn | V3: ₹ Mn | W3: x | X3: %
B4: 1 | C4: Wattapp Technologies Private Limited | D4: ElectricPe | E4: Bengaluru | F4: CleanTech | G4: 44550 | H4: Seed | I4: Pre Series A | J4: 749.99925 | K4: 4365.6896 | L4: =K4 -> 4365.6896 | M4: 0 | N4: =L4*(1-M4) -> 4365.6896 | O4: Cost | P4: 209.98194 | Q4: =P4 -> 209.98194 | R4: 0.14998515 | S4: 0.1562 | T4: =U4+V4 -> 209.98194 | U4: 209.98194 | V4: 0 | W4: =T4/P4 -> 1 | X4: NA | Y4: - | Z4: - | AA4: Marketing strategy, Business Developement connect | AB4: Green Frontier Capital, Micelio Fund, NB Ventures, Anchorage Capital Partners, Supermorpheus, Climate Angels | AD4: Arpit | AE4: Arpit | AF4: Active
B5: =B4+1 -> 2 | C5: Upgrid Solutions Private Limited | D5: BatterySmart | E5: NCR | F5: CleanTech | G5: 44560 | H5: Seed | I5: Series B | J5: 1069.9968 | K5: 40400.462 | L5: 28947.652 | M5: 0.16164585 | N5: =L5*(1-M5) -> 24268.384 | O5: Valued at secondary price of the last round (Series B - May 24) | P5: 1295.2487 | Q5: =P5 -> 1295.2487 | R5: 0.1518 | S5: 0.1443 | T5: =U5+V5 -> 3322.681 | U5: 3322.681 | V5: 0 | W5: =T5/P5 -> 2.5652842 | X5: 0.42037324 | Y5: - | Z5: - | AA5: Investor connect, Connect for Google Catalyst program, GitHub credits / discounts | AB5: British International Investment (BII), Ecosystem Integrity Fund(EIF), Tiger Global, LeapFrog Investments, Panasonic, MUFG, Orios Ventures | AD5: Arpit | AE5: Arpit | AF5: Active
B6: =B5+1 -> 3 | C6: Oritur Technologies Private Limited | D6: Wizcommerce | E6: NCR | F6: SaaS | G6: 44497 | H6: Seed | I6: Series A | J6: 733.77816 | K6: 3327.7922 | L6: =K6 -> 3327.7922 | M6: 0 | N6: =L6*(1-M6) -> 3327.7922 | O6: Marked up to the last round (Series A - Sept'25) | P6: 189.60359 | Q6: =P6 -> 189.60359 | R6: 0.14 | S6: 0.12980714 | T6: =U6+V6 -> 431.97118 | U6: 431.97118 | V6: 0 | W6: =T6/P6 -> 2.2782859 | X6: 0.2868059 | Y6: - | Z6: - | AA6: Sparring on strategy and help on getting them to PMF, hiring intros, follow on investor intros, helping with google credits etc. | AB6: Peak XV, Alpha Wave, Z47, Neon | AC6: Inbound | AD6: Sajith | AE6: Sajith | AF6: Active
B7: =B6+1 -> 4 | C7: Zipy Inc. | D7: Zipy | E7: USA | F7: SaaS | G7: 44554 | H7: Seed | I7: Seed | J7: 787.62998 | K7: 787.62998 | L7: =K7 -> 787.62998 | M7: 1 | N7: =L7*(1-M7) -> 0 | O7: Provision -100% | P7: 119.47624 | Q7: =P7 -> 119.47624 | R7: 0.15169082 | S7: 0.15169082 | T7: =U7+V7 -> 0 | U7: 0 | V7: 0 | W7: =T7/P7 -> 0 | X7: NA | Y7: - | Z7: - | AB7: Together Fund, Better Capital, ldCap, FirstCheque | AD7: Sanjay | AE7: Sanjay | AF7: Provisioned
B8: =B7+1 -> 5 | C8: Zapscale Inc | D8: Zapscale | E8: USA | F8: SaaS | G8: 44559 | H8: Seed | I8: Seed | J8: 652.28997 | K8: 1291.7449 | L8: =K8 -> 1291.7449 | M8: 1 | N8: =L8*(1-M8) -> 0 | O8: Provision -100% | P8: 162.81443 | Q8: =P8 -> 162.81443 | R8: 0.15058822 | S8: 0.15058822 | T8: =U8+V8 -> 0 | U8: 0 | V8: 0 | W8: =T8/P8 -> 0 | X8: -0.95148134 | Y8: - | Z8: - | AB8: Arka Venture Labs, 100x Entrepreneurs | AC8: Repeat Blume Founder | AD8: Arpit | AE8: Arpit | AF8: Provisioned
B9: =B8+1 -> 6 | C9: Nabosh Technologies Private Limited | D9: Alippo | E9: Bengaluru | F9: EdTech | G9: 44591 | H9: Seed | I9: Seed | J9: 840.00007 | K9: 840.00007 | L9: =K9 -> 840.00007 | M9: 0.5 | N9: =L9*(1-M9) -> 420.00003 | O9: Provision - 50% | P9: 104.97996 | Q9: =P9 -> 104.97996 | R9: 0.125 | S9: 0.125 | T9: =U9+V9 -> 52.489982 | U9: 52.489982 | V9: 0 | W9: =T9/P9 -> 0.5 | X9: -0.16277557 | Y9: - | Z9: - | AA9: Mentoring, Marketing strategy | AB9: 100Unicorns, Inventus | AD9: Karthik | AE9: Karthik | AF9: Active
B10: =B9+1 -> 7 | C10: Scribble Data Private Limited | D10: Scribble Data | E10: Bengaluru | F10: SaaS | G10: 44629 | H10: Seed | I10: Seed | J10: 842.25397 | K10: 842.25397 | L10: =K10 -> 842.25397 | M10: 0.5 | N10: =L10*(1-M10) -> 421.12699 | O10: Provision - 50% | P10: 132.19229 | Q10: =P10 -> 132.19229 | R10: 0.1569 | S10: 0.1569 | T10: =U10+V10 -> 66.096147 | U10: 66.096147 | V10: 0 | W10: =T10/P10 -> 0.5 | X10: -0.16608306 | Y10: - | Z10: - | AB10: Sprout Investments, LogX Venture Partners | AD10: Anirvan | AE10: Sanjay | AF10: Active
B11: =B10+1 -> 8 | C11: Aerem Finance Private Limited | D11: Aerem | E11: Mumbai | F11: FinTech | G11: 44649 | H11: Seed | I11: Pre Series B | J11: 675.0004 | K11: 9050.265 | L11: =K11 -> 9050.265 | M11: 0 | N11: =L11*(1-M11) -> 9050.265 | O11: Marked up to the last round (Pre-Series B - Dec'25) | P11: 591.81014 | Q11: =P11 -> 591.81014 | R11: 0.16666729 | S11: 0.1845197 | T11: =U11+V11 -> 1669.9674 | U11: 1669.9674 | V11: 0 | W11: =T11/P11 -> 2.8217959 | X11: 0.63824181 | Y11: - | Z11: - | AA11: Investor connect | AB11: Avaana Capital, UTEC, BII, SE Ventures, SMBC, Riverwalk | AC11: Kabir - B Capital | AD11: Ashish | AE11: Ashish | AF11: Active
B12: =B11+1 -> 9 | C12: Multipl FinTech Solutions Private Limited | D12: Multipl | E12: Bengaluru | F12: FinTech | G12: 44705 | H12: Seed | I12: Pre Series A1 | J12: 750.05719 | K12: 750.05719 | L12: =K12 -> 750.05719 | M12: 1 | N12: =L12*(1-M12) -> 0 | O12: Provision -100% | P12: 174.75008 | Q12: =P12 -> 174.75008 | R12: 0.15 | S12: 0.1998 | T12: =U12+V12 -> 0 | U12: 0 | V12: 0 | W12: =T12/P12 -> 0 | X12: NA | Y12: - | Z12: - | AA12: Investor connect, troubleshooting with Meta | AB12: GrowX Ventures, IIFL, Kotak Securities, MIXI Global | AC12: Candidate who we interviewed for a role in Fintech team | AD12: Ashish | AE12: Ashish | AF12: Provisioned
B13: =B12+1 -> 10 | C13: Asset10 Software Private Limited | D13: BlueCopa | E13: Hyderabad | F13: SaaS | G13: 44739 | H13: Seed | I13: Series A | J13: 727.30322 | K13: 3063.5157 | L13: =K13 -> 3063.5157 | M13: 0 | N13: =L13*(1-M13) -> 3063.5157 | O13: Marked up to the last round (Series A - Oct'25) | P13: 284.62816 | Q13: =P13 -> 284.62816 | R13: 0.15788784 | S13: 0.1773 | T13: =U13+V13 -> 543.14032 | U13: 543.14032 | V13: 0 | W13: =T13/P13 -> 1.9082452 | X13: 0.36011514 | Y13: - | Z13: - | AA13: Business Developement connect, Investor connect | AB13: Analog, Lets Venture, Titan Capital, Good Capital, Dallas | AD13: Anirvan | AE13: Sanjay | AF13: Active
B14: =B13+1 -> 11 | C14: Stage Technologies Private Limited | D14: Stage | E14: NCR | F14: Media and Content | G14: 44580 | H14: Pre Series A | I14: Series A | J14: 995.36004 | K14: 6720 | L14: =K14 -> 6720 | M14: 0 | N14: =L14*(1-M14) -> 6720 | O14: Marked up to the last round (Series B - Nov'24) | P14: 565.63612 | Q14: =P14 -> 565.63612 | R14: 0.060279064 | S14: 0.1444 | T14: =U14+V14 -> 970.28344 | U14: 970.28344 | V14: 0 | W14: =T14/P14 -> 1.7153845 | X14: 0.28625953 | Y14: - | Z14: - | AA14: Investor connect, Troubleshooting with Meta, Google Playstore, Zoho Credits | AB14: Inflection Point Ventures, NB Ventures, Dholakia Ventures, TSM Ventures, Venture Catalysts, Sprout Investments WeFounderCircle, Goodwater | AD14: Karthik | AE14: Karthik | AF14: Active
B15: =B14+1 -> 12 | C15: Vecmocon Technologies Private Limited | D15: Vecmocon | E15: NCR | F15: CleanTech | G15: 44827 | H15: Pre Series A | I15: Pre Series A | J15: 1653.5954 | K15: 5506.7029 | L15: =K15 -> 5506.7029 | M15: 0 | N15: =L15*(1-M15) -> 5506.7029 | O15: Marked up to the last round (Series A - Oct'24) | P15: 397.60947 | Q15: =P15 -> 397.60947 | R15: 0.16797908 | S15: 0.10483767 | T15: =U15+V15 -> 707.13359 | U15: 707.13359 | V15: 0 | W15: =T15/P15 -> 1.7784627 | X15: 0.28288394 | Y15: - | Z15: - | AA15: Investor connect, Connect for debt financing, Business Developement connect | AB15: British International Investment (BII), Ecosystem Integrity Fund (EIF), Tiger Global, ADB, Aavishkar Capital | AD15: Arpit | AE15: Arpit | AF15: Active
B16: =B15+1 -> 13 | C16: ResellMe Tech Private Limited | D16: Resellme | E16: NCR | F16: Commerce and Consumer Brands | G16: 44834 | H16: Seed | I16: Seed | J16: 378.65818 | K16: 378.65818 | L16: =K16 -> 378.65818 | M16: 1 | N16: =L16*(1-M16) -> 0 | O16: Provision -100% | P16: 50.000111 | Q16: =P16 -> 50.000111 | R16: 0.1160259 | S16: 0.132 | T16: =U16+V16 -> 0 | U16: 0 | V16: 0 | W16: =T16/P16 -> 0 | X16: NA | Y16: - | Z16: - | AA16: Sparring on strategy and help on getting them to PMF, hiring intros, follow on investor intros. | AB16: Angels | AC16: Inbound | AD16: Sajith | AE16: Sajith | AF16: Provisioned
B17: =B16+1 -> 14 | C17: Virohan Private Limited | D17: Virohan | E17: NCR | F17: EdTech | G17: 44928 | H17: Pre Series B1 | I17: Series B | J17: 2283.963 | K17: 5756.5408 | L17: =K17 -> 5756.5408 | M17: 0.37531234 | N17: =L17*(1-M17) -> 3596.04 | O17: Marked at the secondary price of the last round (Series B - Dec'25) | P17: 594.40773 | Q17: =P17 -> 594.40773 | R17: 0.089758786 | S17: 0.1616 | T17: =U17+V17 -> 684.44093 | U17: 684.44093 | V17: 0 | W17: =T17/P17 -> 1.1514671 | X17: 0.084320423 | Y17: - | Z17: - | AA17: Sparring on strategy and driving efficiencies on GTM, hiring intros, follow on investor intros. | AB17: Rebright Partners , Bharat Inclusion Seed Fund, Mitsui Sumitomo Insurance | AD17: Sajith | AE17: Sajith | AF17: Active
B18: =B17+1 -> 15 | C18: Chefkart Hospitality Private Limited | D18: Chefkart | E18: NCR | F18: FoodTech | G18: 44617 | H18: Seed | I18: Pre Series A1 | J18: 797.50003 | K18: 101 | L18: =K18 -> 101 | M18: 1 | N18: =L18*(1-M18) -> 0 | O18: Provision -100% | P18: 171.19223 | Q18: =P18 -> 171.19223 | R18: 0.060421901 | S18: 0.22025991 | T18: =U18+V18 -> 0 | U18: 0 | V18: 0 | W18: =T18/P18 -> 0 | X18: NA | Y18: - | Z18: - | AA18: Sparring on strategy and help on trying to get them to PMF, hiring intros, follow on investor intros. | AB18: Pravega, LetsVenture | AC18: Eco-system referral | AD18: Sajith | AE18: Sajith | AF18: Provisioned
B19: =B18+1 -> 16 | C19: Since99 Apparel Private Limited | D19: Freakins | E19: Mumbai | F19: Commerce and Consumer Brands | G19: 45036 | H19: Seed | I19: Series A1 | J19: 1020.0251 | K19: 2295.3228 | L19: 0 | M19: 1 | N19: =L19*(1-M19) -> 0 | O19: Provision -100% | P19: 265.0005 | Q19: =P19 -> 265.0005 | R19: 0.1373 | S19: 0.1734 | T19: =U19+V19 -> 0 | U19: 0 | V19: 0 | W19: =T19/P19 -> 0 | X19: NA | Y19: - | Z19: - | AA19: Sparring on strategy and driving efficiencies on GTM, hiring intros, follow on investor intros. | AB19: Z47, Dexter Capital Advisors | AC19: Eco-system referral | AD19: Sajith | AE19: Sajith | AF19: Active
B20: =B19+1 -> 17 | C20: Zivy Applications India Private Limited | D20: Zivy | E20: Bengaluru | F20: SaaS | G20: 45092 | H20: CCD | I20: CCD | J20: NA | K20: NA | L20: NA | M20: 0 | N20: NA | O20: Cost | P20: 41 | Q20: =P20 -> 41 | R20: NA | S20: NA | T20: =U20+V20 -> 41 | U20: 41 | V20: 0 | W20: =T20/P20 -> 1 | X20: NA | Y20: - | Z20: - | AA20: Sparring on product ideation. | AB20: Everywhere, India Silicon Capital, Mars Shot VC, Pradigm | AC20: Co-investor referral | AD20: Sajith | AE20: Sajith | AF20: Active
B21: =B20+1 -> 18 | C21: Pico Xpress Private Limited | D21: Pico | E21: Bengaluru | F21: Logistics | G21: 45041 | H21: Seed | I21: Seed 2 | J21: 494.47248 | K21: 1286.0246 | L21: 0 | M21: 0 | N21: =L21*(1-M21) -> 0 | O21: Cost | P21: 209.34651 | Q21: =P21 -> 209.34651 | R21: 0.04999874 | S21: 0.19249407 | T21: =U21+V21 -> 209.34651 | U21: 209.34651 | V21: 0 | W21: =T21/P21 -> 1 | X21: NA | Y21: - | Z21: - | AA21: Investor connect | AB21: Inuka Capital, Veltis Capital | AD21: Arpit | AE21: Arpit | AF21: Active
B22: =B21+1 -> 19 | C22: Atomicwork Inc | D22: Atomicwork | E22: USA | F22: SaaS | G22: 44915 | H22: Seed | I22: Series A | J22: 3699.9236 | K22: 9983.4504 | L22: =K22 -> 9983.4504 | M22: 0 | N22: =L22*(1-M22) -> 9983.4504 | O22: Marked up to the last round (Series A - Jan'25) | P22: 828.68823 | Q22: =P22 -> 828.68823 | R22: 0.11 | S22: 0.1025 | T22: =U22+V22 -> 1242.7673 | U22: 1242.7673 | V22: 0 | W22: =T22/P22 -> 1.4996802 | X22: 0.22911982 | Y22: - | Z22: - | AA22: Business Developement connect, Investor connect | AB22: Z47, Storm Ventures, Neon Fund, Peak XV, Khosla | AC22: Repeat Blume Founder | AD22: Sanjay | AE22: Sanjay | AF22: Active
B23: =B22+1 -> 20 | C23: Mysa Innovation Private Limited | D23: Mysa | E23: Bengaluru | F23: FinTech | G23: 45173 | H23: Seed | I23: Pre Series A | J23: 879.89971 | K23: 1511.333 | L23: =K23 -> 1511.333 | M23: 0 | N23: =L23*(1-M23) -> 1511.333 | O23: Cost | P23: 231.64292 | Q23: =P23 -> 231.64292 | R23: 0.16670333 | S23: 0.1891 | T23: =U23+V23 -> 231.64292 | U23: 231.64292 | V23: 0 | W23: =T23/P23 -> 1 | X23: NA | Y23: - | Z23: - | AA23: Business Developement connects | AB23: Antler, Neon Venture, Peer Capital, 100x, Piper Serica, Ikemori Venture, Raise Fintech | AC23: Repeat Blume Founder | AD23: Ashish | AE23: Ashish | AF23: Active
B24: =B23+1 -> 21 | C24: Flashmonk Private Limited | D24: Flash | E24: Bengaluru | F24: Commerce and Consumer Brands | G24: 45182 | H24: Pre Series A | I24: Pre Series A | J24: 3422.3749 | K24: 3422.3749 | L24: =K24 -> 3422.3749 | M24: 0 | N24: =L24*(1-M24) -> 3422.3749 | O24: Cost | P24: 342.17216 | Q24: =P24 -> 342.17216 | R24: 0.099980911 | S24: 0.099980911 | T24: =U24+V24 -> 342.17216 | U24: 342.17216 | V24: 0 | W24: =T24/P24 -> 1 | X24: NA | Y24: - | Z24: - | AA24: Business Developement connect | AB24: PeerCapital, White Venture Capital | AD24: Karthik | AE24: Karthik | AF24: Active
B25: =B24+1 -> 22 | C25: DPDZERO Technologies Private Limited | D25: DPD Zero | E25: Bengaluru | F25: FinTech | G25: 45175 | H25: Seed | I25: Series A | J25: 1146.713 | K25: 2081.036 | L25: =K25 -> 2081.036 | M25: 0 | N25: =L25*(1-M25) -> 2081.036 | O25: Marked at the last priced round (Series A - Jul'25) | P25: 353.99074 | Q25: =P25 -> 353.99074 | R25: 0.15696875 | S25: 0.18700933 | T25: =U25+V25 -> 514.81132 | U25: 514.81132 | V25: 0 | W25: =T25/P25 -> 1.4543073 | X25: 0.27177106 | Y25: - | Z25: - | AA25: Sparring on strategy and help on trying to get them to PMF, hiring intros, follow on investor intros, business development intros. | AB25: GMO, India Quotient, Better Ventures | AC25: Blume Network Programs | AD25: Sajith | AE25: Sajith | AF25: Active
B26: =B25+1 -> 23 | C26: Localbuy Technologies Private Limited | D26: SuperK | E26: Bengaluru | F26: Commerce and Consumer Brands | G26: 45282 | H26: Series A | I26: Series B | J26: 1979.9984 | K26: 4750 | L26: =K26 -> 4750 | M26: 0 | N26: =L26*(1-M26) -> 4750 | O26: Marked at the last priced round (Series B - June 25) | P26: 399.95731 | Q26: =P26 -> 399.95731 | R26: 0.101 | S26: 0.12156713 | T26: =U26+V26 -> 577.43634 | U26: 577.43634 | V26: 0 | W26: =T26/P26 -> 1.4437449 | X26: 0.34977037 | Y26: - | Z26: - | AA26: Business Developement connect, Investor Connect, Connect for debt financing | AB26: O21 Capital, Silver Needle | AD26: Karthik | AE26: Karthik | AF26: Active
B27: =B26+1 -> 24 | C27: Upward and Onward Inc. | D27: Interview Kickstart | E27: USA | F27: EdTech | G27: 45324 | H27: Series A | I27: Series A | J27: 12880.979 | K27: 17198.501 | L27: =K27 -> 17198.501 | M27: 0 | N27: =L27*(1-M27) -> 17198.501 | O27: Cost | P27: 860.83999 | Q27: =P27 -> 860.83999 | R27: 0.0636 | S27: 0.0636 | T27: =U27+V27 -> 899.19799 | U27: 899.19799 | V27: 0 | W27: =T27/P27 -> 1.0445588 | X27: NA | Y27: - | Z27: - | AA27: Business strategy, Troubleshooting with Meta, Freshworks credits | AD27: Karthik | AE27: Karthik | AF27: Active
B28: =B27+1 -> 25 | C28: Opticap Holding India Private Limited | D28: Optimo | E28: Bengaluru | F28: FinTech | G28: 45355 | H28: Seed | I28: Seed | J28: 2172.1032 | K28: 4999.9918 | L28: =K28 -> 4999.9918 | M28: 0 | N28: =L28*(1-M28) -> 4999.9918 | O28: Cost | P28: 807.99222 | Q28: =P28 -> 807.99222 | R28: 0.1418 | S28: 0.1418 | T28: =U28+V28 -> 807.99222 | U28: 807.99222 | V28: 0 | W28: =T28/P28 -> 1 | X28: NA | Y28: - | Z28: - | AA28: Investor connect | AB28: Omnivore | AC28: Repeat Seasoned Founder | AD28: Ashish | AE28: Ashish | AF28: Active
B29: =B28+1 -> 26 | C29: Speedup Inc | D29: SpeedUp/SiftHub | E29: USA | F29: SaaS | G29: 45358 | H29: Seed | I29: Seed | J29: 2068.725 | K29: 2068.725 | L29: =K29 -> 2068.725 | M29: 0 | N29: =L29*(1-M29) -> 2068.725 | O29: Cost | P29: 206.8748 | Q29: =P29 -> 206.8748 | R29: 0.1 | S29: 0.1 | T29: =U29+V29 -> 224.79928 | U29: 224.79928 | V29: 0 | W29: =T29/P29 -> 1.0866441 | X29: 0.046735999 | Y29: - | Z29: - | AA29: GTM connects | AB29: Z47, Neon | AD29: Sanjay | AE29: Sanjay | AF29: Active
B30: =B29+1 -> 27 | C30: Tower22 Inc. | D30: Clientell | E30: Bengaluru | F30: SaaS | G30: 45363 | H30: Pre Series A | I30: Pre Series A | J30: 651.7814 | K30: 651.7814 | L30: =K30 -> 651.7814 | M30: 0 | N30: =L30*(1-M30) -> 651.7814 | O30: Cost | P30: 123.31672 | Q30: =P30 -> 123.31672 | R30: 0.1824 | S30: 0.1824 | T30: =U30+V30 -> 129.03492 | U30: 129.03492 | V30: 0 | W30: =T30/P30 -> 1.04637 | X30: NA | Y30: - | Z30: - | AA30: GTM connect, Hiring support (Metamorph), Business Developement connect | AB30: Chiratae, Artha, Z5 Capital | AD30: Sanjay | AE30: Sanjay | AF30: Active
B31: =B30+1 -> 28 | C31: Bambrew Plant Fiber Technology Private Limited | D31: Bambrew | E31: Bengaluru | F31: CleanTech | G31: 45379 | H31: Series A | I31: Series A | J31: 1185.6592 | K31: 1185.6592 | L31: =K31 -> 1185.6592 | M31: 0 | N31: =L31*(1-M31) -> 1185.6592 | O31: Realised Value | P31: 149.9982 | Q31: 0 | R31: 0.125 | S31: 0.125 | T31: =U31+V31 -> 108.20287 | U31: 0 | V31: 108.20287 | W31: =T31/P31 -> 0.72136109 | X31: -0.26395526 | Y31: - | Z31: - | AA31: Business Developement connects, hiring , Investor connect | AB31: Blue Ashva Capital, Indus Capital | AD31: Arpit | AE31: Arpit | AF31: Active
B32: =B31+1 -> 29 | C32: Leaguex Gaming Private Limited | D32: LightFury Games | E32: Bengaluru | F32: Gaming | G32: 45394 | H32: Seed | I32: Seed | J32: 3319.9512 | K32: 3319.9512 | L32: =K32 -> 3319.9512 | M32: 0 | N32: =L32*(1-M32) -> 3319.9512 | O32: Cost | P32: 475.19039 | Q32: =P32 -> 475.19039 | R32: 0.12500079 | S32: 0.12500079 | T32: =U32+V32 -> 475.19039 | U32: 475.19039 | V32: 0 | W32: =T32/P32 -> 1 | X32: NA | Y32: - | Z32: - | AA32: Investor connect | AB32: MIXI Global Investments, Gemba Capital, Times Internet , Venture Catalyst, Angels | AD32: Karthik | AE32: Karthik | AF32: Active
B33: =B32+1 -> 30 | C33: Fitstok Trading Services Private Limited | D33: Vutto | E33: NCR | F33: Mobility Tech | G33: 45398 | H33: Seed | I33: Series A | J33: 622.4491 | K33: 2395.3788 | L33: =K33 -> 2395.3788 | M33: 0 | N33: =L33*(1-M33) -> 2395.3788 | O33: Marked at the last priced round (Series A - Aug'25) | P33: 275.12473 | Q33: =P33 -> 275.12473 | R33: 0.1 | S33: 0.16387379 | T33: =U33+V33 -> 392.53979 | U33: 392.53979 | V33: 0 | W33: =T33/P33 -> 1.4267702 | X33: 0.63717529 | Y33: - | Z33: - | AA33: Sparring on product ideation, and strategy | AB33: RTP Global, Angels | AC33: Inbound | AD33: Sajith | AE33: Sajith | AF33: Active
B34: =B33+1 -> 31 | C34: Complement Theory Inc. | D34: Complement 1 | E34: Goa | F34: Healthcare | G34: 45454 | H34: Seed | I34: Seed | J34: 5152.392 | K34: 5152.392 | L34: =K34 -> 5152.392 | M34: 0.5 | N34: =L34*(1-M34) -> 2576.196 | O34: Provision - 50% | P34: 516.78 | Q34: =P34 -> 516.78 | R34: 0.1667 | S34: 0.1667 | T34: =U34+V34 -> 258.39 | U34: 258.39 | V34: 0 | W34: =T34/P34 -> 0.5 | X34: -0.36301233 | Y34: - | Z34: - | AA34: Sparring on product ideation, and strategy | AB34: Owl Ventures | AC34: Inbound | AD34: Karthik + Sajith | AE34: Karthik + Sajith | AF34: Active
B35: =B34+1 -> 32 | C35: Fashor Lifestyle Private Limited | D35: Fashor | E35: Chennai | F35: Commerce and Consumer Brands | G35: 45467 | H35: Series A | I35: Series A | J35: 2195.5253 | K35: 2195.5253 | L35: =K35 -> 2195.5253 | M35: 0 | N35: =L35*(1-M35) -> 2195.5253 | O35: Cost | P35: 307.50282 | Q35: =P35 -> 307.50282 | R35: 0.1246 | S35: 0.1246 | T35: =U35+V35 -> 307.50282 | U35: 307.50282 | V35: 0 | W35: =T35/P35 -> 1 | X35: 0.00065186918 | Y35: - | Z35: - | AA35: Sparring on strategy and driving efficiencies on GTM, connecting to experts and advisors. | AB35: Sprout Venture Partners, Inflection Point Ventures, Venture Catalysts | AC35: Eco-system referral | AD35: Sajith | AE35: Sajith | AF35: Active
B36: =B35+1 -> 33 | C36: Moving Tech Innovations Private Limited | D36: Namma Yatri | E36: Bengaluru | F36: Mobility Tech | G36: 45485 | H36: Pre Series A | I36: Pre Series A | J36: 4593.2521 | K36: 4593.2521 | L36: =K36 -> 4593.2521 | M36: 0 | N36: =L36*(1-M36) -> 4593.2521 | O36: Cost | P36: 459.32516 | Q36: =P36 -> 459.32516 | R36: 0.1 | S36: 0.1 | T36: =U36+V36 -> 459.32516 | U36: 459.32516 | V36: 0 | W36: =T36/P36 -> 1 | X36: NA | Y36: - | Z36: - | AA36: Sparring on product ideation, and strategy | AB36: Antler Global Fund Master,Google International LLC ,Better Industries Pte Ltd, Vimal | AC36: Eco-system referral | AD36: Karthik | AE36: Karthik | AF36: Active
B37: =B36+1 -> 34 | C37: Billion Hearts Software Technologies Private Limited | D37: PicSee | E37: Bengaluru | F37: Media & Content | G37: 45609 | H37: Seed | I37: Seed | J37: 1199.9538 | K37: 1199.9538 | L37: =K37 -> 1199.9538 | M37: 0 | N37: =L37*(1-M37) -> 1199.9538 | O37: Cost | P37: 149.99827 | Q37: =P37 -> 149.99827 | R37: 0.12500337 | S37: 0.12500337 | T37: =U37+V37 -> 149.99827 | U37: 149.99827 | V37: 0 | W37: =T37/P37 -> 1 | X37: NA | Y37: - | Z37: - | AA37: - | AB37: General Catalyst, Athera | AC37: Repeat Blume Founder | AD37: Karthik | AE37: Karthik | AF37: Active
B38: =B37+1 -> 35 | C38: Savdo Technologies Private Limited | D38: Zoplar | E38: NCR | F38: HealthTech | G38: 45646 | H38: Series A | I38: Series A | J38: 1377.2162 | K38: 1377.2162 | L38: =K38 -> 1377.2162 | M38: 0 | N38: =L38*(1-M38) -> 1377.2162 | O38: Realisable Value | P38: 206.57733 | Q38: =P38 -> 206.57733 | R38: 0.1499963 | S38: 0.1499963 | T38: =U38+V38 -> 103.28867 | U38: 103.28867 | V38: 0 | W38: =T38/P38 -> 0.5 | X38: NA | Y38: - | Z38: - | AA38: - | AB38: Beenext | AC38: Outbound | AD38: Anurag | AE38: Sajith | AF38: Active
B39: =B38+1 -> 36 | C39: Optimized Electotech Private Limited | D39: Optimized | E39: Bengaluru | F39: DeepTech | G39: 45698 | H39: Seed E | I39: Seed E | J39: 1893.0004 | K39: 1893.0004 | L39: =K39 -> 1893.0004 | M39: 0 | N39: =L39*(1-M39) -> 1893.0004 | O39: Cost | P39: 190.00008 | Q39: =P39 -> 190.00008 | R39: 0.10036911 | S39: 0.10036911 | T39: =U39+V39 -> 190.00008 | U39: 190.00008 | V39: 0 | W39: =T39/P39 -> 1 | X39: NA | Y39: - | Z39: - | AA39: - | AB39: Mela Ventures, Helios Capital, 100 Unicorns | AD39: Arpit | AE39: Arpit | AF39: Active
B40: =B39+1 -> 37 | C40: Grey Orange International Inc | D40: GreyOrange | E40: USA | F40: DeepTech | G40: 45701 | H40: Series D | I40: Series D | J40: ='Fund I'!K4 -> 41634.55 | K40: ='Fund I'!L4 -> 41634.55 | L40: =K40 -> 41634.55 | M40: 0 | N40: =L40*(1-M40) -> 41634.55 | O40: Cost | P40: 260.72987 | Q40: =P40 -> 260.72987 | R40: 0.0060606032 | S40: 0.0060606032 | T40: =U40+V40 -> 260.72987 | U40: 260.72987 | V40: 0 | W40: =T40/P40 -> 1 | X40: NA | Y40: - | Z40: - | AA40: ='Fund 1X'!AA9 -> Business Development connects, Investor connect, Finance & compliance support | AB40: Cowen, Mithril, Three State Capital | AC40: Crossover Strategy | AD40: Karthik | AE40: Karthik | AF40: Active
B41: =B40+1 -> 38 | C41: GoStops Hospitality Private Limited | D41: goStops | E41: NCR | F41: Commerce and Consumer Brands | G41: 45726 | H41: Series A | I41: Series A | J41: 1650.056 | K41: 1650.056 | L41: =K41 -> 1650.056 | M41: 0 | N41: =L41*(1-M41) -> 1650.056 | O41: Cost | P41: 270.65177 | Q41: =P41 -> 270.65177 | R41: 0.1515 | S41: 0.1515 | T41: =U41+V41 -> 270.65177 | U41: 270.65177 | V41: 0 | W41: =T41/P41 -> 1 | X41: NA | Y41: - | Z41: - | AB41: Angels | AD41: Ashish | AE41: Ashish | AF41: Active
B42: =B41+1 -> 39 | C42: Umrit Health Tech Private Limited | D42: FOXO | E42: Bengaluru | F42: HealthTech | G42: 45734 | H42: Pre Seed | I42: Pre Seed | J42: 400.06053 | K42: 400.06053 | L42: =K42 -> 400.06053 | M42: 0 | N42: =L42*(1-M42) -> 400.06053 | O42: Cost | P42: 40.00143 | Q42: =P42 -> 40.00143 | R42: 0.099988445 | S42: 0.099988445 | T42: =U42+V42 -> 40.00143 | U42: 40.00143 | V42: 0 | W42: =T42/P42 -> 1 | X42: NA | Y42: - | Z42: - | AA42: Business Development connects | AB42: Angels | AC42: Repeat Blume Founder | AD42: Arpit | AE42: Arpit | AF42: Active
B43: =B42+1 -> 40 | C43: Volt14 Solutions India Private Limited | D43: Volt14 | E43: Singapore | F43: Mobility Tech | G43: 45740 | H43: Pre Series A | I43: Pre Series A | J43: 1377.2162 | K43: 1377.2162 | L43: =K43 -> 1377.2162 | M43: 0 | N43: =L43*(1-M43) -> 1377.2162 | O43: Cost | P43: 87.002175 | Q43: =P43 -> 87.002175 | R43: 0.19048005 | S43: 0.19048005 | T43: =U43+V43 -> 87.002175 | U43: 87.002175 | V43: 0 | W43: =T43/P43 -> 1 | X43: NA | Y43: - | Z43: - | AA43: - | AB43: Beyond Ventures | AD43: Arpit | AE43: Arpit | AF43: Active
B44: =B43+1 -> 41 | C44: Network Program Investments | D44: - | E44: - | F44: - | G44: NA | H44: - | I44: =G44 -> NA | J44: =I44 -> NA | K44: =J44 -> NA | L44: =K44 -> NA | M44: 0 | N44: NA | O44: Cost | P44: 1092.725 | Q44: 1029.682 | R44: NA | S44: NA | T44: =U44+V44 -> 920.20955 | U44: 916.83807 | V44: 3.3714796 | W44: =T44/P44 -> 0.84212367 | X44: NA | Y44: - | Z44: - | AA44: - | AB44: - | AD44: - | AE44: - | AF44: Active
B45: =B44+1 -> 42 | C45: Blume Founders Fund | D45: BFF 2.0 | E45: - | F45: - | G45: NA | H45: - | I45: =G45 -> NA | J45: =I45 -> NA | K45: =J45 -> NA | L45: =K45 -> NA | M45: 0 | N45: NA | O45: Cost | P45: 246.87372 | Q45: =P45 -> 246.87372 | R45: NA | S45: NA | T45: =U45+V45 -> 242.88487 | U45: 242.88487 | V45: 0 | W45: =T45/P45 -> 0.98384255 | X45: -0.0073759511 | Y45: - | Z45: - | AA45: - | AB45: - | AD45: - | AE45: - | AF45: Active
B46: =B45+1 -> 43 | C46: Blume Super Scout | D46: BSS | E46: - | F46: - | G46: NA | H46: - | I46: =G46 -> NA | J46: =I46 -> NA | K46: =I46 -> NA | L46: =J46 -> NA | M46: 0 | N46: NA | O46: Cost | P46: 239.30984 | Q46: =P46 -> 239.30984 | R46: NA | S46: NA | T46: =U46+V46 -> 257.05038 | U46: 257.05038 | V46: 0 | W46: NA | X46: NA | Y46: - | Z46: - | AA46: - | AB46: - | AD46: - | AE46: - | AF46: Active
P47: =SUM(P4:P46) -> 14682.944 | Q47: =SUM(Q4:Q46) -> 14469.903 | T47: =SUM(T4:T46) -> 18401.355 | U47: =SUM(U4:U46) -> 18289.781 | V47: =SUM(V4:V46) -> 111.57435 | W47: =T47/P47 -> 1.253247 | X47: 0.129043

Sheet Fund V
B2: # | C2: Company | D2: Business / Brand | E2: Geography | F2: Sector | G2: Date | H2: Stage at Entry | I2: Current Stage | J2: Entry Valuation | K2: Last Round Valuation | L2: Valuation used for Mark-to-market | M2: Discount to last round | N2: Effective Valuation for Mark-to-market | O2: Valuation Basis | P2: Total Invested Cost | Q2: Residual Cost | R2: Stake (At Entry) | S2: Stake (Current) | T2: Total Value | U2: Unrealised Value | V2: Realised Value | W2: Gross MOIC | X2: Gross IRR (₹) | Y2: If Exited, Mode of Exit | Z2: GP Exit MOIC | AA2: Value Creation by Fund | AB2: Co-investor(s) | AC2: Sourcing Route | AD2: Deal Source | AE2: Deal Lead | AF2: Status | AG2: Comments
G3: MM/YY | J3: ₹ Mn | K3: ₹ Mn | L3: ₹ Mn | N3: ₹ Mn | P3: ₹ Mn | Q3: ₹ Mn | R3: % | S3: % | T3: ₹ Mn | U3: ₹ Mn | V3: ₹ Mn | W3: x | X3: %
B4: 1 | C4: Mave Health Private Limited | D4: MaveHealth | E4: Bengaluru | F4: HealthTech | G4: 45904 | H4: Seed | I4: Seed | J4: 722.52834 | K4: 722.52834 | L4: =K4 -> 722.52834 | M4: 0 | N4: =L4*(1-M4) -> 722.52834 | O4: Cost | P4: 116.79916 | Q4: =P4 -> 116.79916 | R4: 0.16165355 | S4: 0.16165355 | T4: =U4+V4 -> 116.79916 | U4: 116.79916 | V4: 0 | W4: =T4/P4 -> 1 | X4: 0 | Y4: 0 | Z4: 0 | AB4: Inuka Capital LP AL trust, Aureolis Ventures LLP, Stargazer Fund – I, Eagle10 Ventures LLP, Angels | AE4: Arpit | AF4: Active
B5: =B4+1 -> 2 | C5: Confido Health Inc. | D5: Confido Health | E5: USA | F5: HealthTech | G5: 45854 | H5: Series A | I5: Series A | J5: 2952.2217 | K5: 2952.2217 | L5: =K5 -> 2952.2217 | M5: 0 | N5: 33.500312 | O5: Cost | P5: 441.77807 | Q5: =P5 -> 441.77807 | R5: 0.14925236 | S5: 0.14925236 | T5: =U5+V5 -> 441.77807 | U5: 441.77807 | V5: 0 | W5: =T5/P5 -> 1 | X5: 0 | Y5: 0 | Z5: 0 | AB5: Together Fund, DeVC, MedMountain Ventures | AE5: Sanjay | AF5: Active
B6: =B5+1 -> 3 | C6: MeantToBe Inc. | D6: Meant To Be | E6: USA | F6: Consumer Tech | G6: 45910 | H6: Series A | I6: Series A | J6: 1840.5194 | K6: 2894.4339 | L6: =K6 -> 2894.4339 | M6: 0 | N6: 33.330043 | O6: Cost | P6: 324.11622 | Q6: =P6 -> 324.11622 | R6: 0.069931094 | S6: 0.1248489 | T6: =U6+V6 -> 324.11622 | U6: 324.11622 | V6: 0 | W6: =T6/P6 -> 1 | X6: 0 | Y6: 0 | Z6: 0 | AB6: Peak XV Partners Investments VIII-1, Shine Capital | AE6: Karthik | AF6: Active
B7: =B6+1 -> 4 | C7: Divinecarat Lifestyles Private Limited | D7: Lucira | E7: Mumbai | F7: ConsumerTech | G7: 45916 | H7: Seed | I7: Seed | J7: 1189.5515 | K7: 1189.5515 | L7: =K7 -> 1189.5515 | M7: 0 | N7: =L7*(1-M7) -> 1189.5515 | O7: Cost | P7: 250.02305 | Q7: =P7 -> 250.02305 | R7: 0.21018307 | S7: 0.21018307 | T7: =U7+V7 -> 250.02305 | U7: 250.02305 | V7: 0 | W7: =T7/P7 -> 1 | X7: 0 | Y7: 0 | Z7: 0 | AB7: Spring Marketing Capital, Symphsis LSV LLP, SiriusOne Capital Fund | AE7: Karthik | AF7: Active
B8: =B7+1 -> 5 | C8: IDO Devices Private Limited | D8: iDO | E8: NCR | F8: DeepTech | G8: 45916 | H8: Seed A | I8: Seed A | J8: 950 | K8: 950 | L8: =K8 -> 950 | M8: 0 | N8: =L8*(1-M8) -> 950 | O8: Cost | P8: 80.750083 | Q8: =P8 -> 80.750083 | R8: 0.16999974 | S8: 0.16999974 | T8: =U8+V8 -> 80.750083 | U8: 80.750083 | V8: 0 | W8: =T8/P8 -> 1 | X8: 0 | Y8: 0 | Z8: 0 | AB8: Merak Ventures VCC, Merak Ventures Fund I, Angels | AE8: Arpit | AF8: Active
B9: =B8+1 -> 6 | C9: Radmeen Solutions Private Limited | D9: Epithera | E9: Bengaluru | F9: ConsumerTech | G9: 45874 | H9: Seed | I9: Seed | J9: 400 | K9: 400 | L9: =K9 -> 400 | M9: 0 | N9: =L9*(1-M9) -> 400 | O9: Cost | P9: 72.1 | Q9: =P9 -> 72.1 | R9: 0.18025 | S9: 0.18025 | T9: =U9+V9 -> 72.1 | U9: 72.1 | V9: 0 | W9: =T9/P9 -> 1 | X9: 0 | Y9: 0 | Z9: 0 | AB9: SiriusOne Capital Fund, Consumer Collective (a scheme of IA Growth Opportunities Fund I acting through its trustees Axis Trustee Services Limited), Veltis Capital Fund II, AL Trust, Angels. | AE9: Sajith | AF9: Active
B10: =B9+1 -> 7 | C10: Ozi Technologies Private Limited | D10: Ozi | E10: NCR | F10: ConsumerTech | G10: 45888 | H10: Seed 1 | I10: Seed 2 | J10: 1024.5158 | K10: 1135.1978 | L10: =K10 -> 1135.1978 | M10: 0 | N10: =L10*(1-M10) -> 1135.1978 | O10: Cost | P10: 221.42834 | Q10: =P10 -> 221.42834 | R10: 0.1080857 | S10: 0.19499953 | T10: =U10+V10 -> 221.42834 | U10: 221.42834 | V10: 0 | W10: =T10/P10 -> 1 | X10: 0 | Y10: 0 | Z10: 0 | AB10: Art Ventures Fund, Joule One Advisors LLP, Zeropearl Fund I, Symphysis LSV LLP, Panthera peak LLP, Huddle, Angels | AE10: Sajith | AF10: Active
B11: =B10+1 -> 8 | C11: PowerUp Technologies Private Limited | D11: PowerUp | E11: Mumbai | F11: FinTech | G11: 45867 | H11: Seed A | I11: Seed B | J11: 615.17994 | K11: 4497.145 | L11: =K11 -> 4497.145 | M11: 0 | N11: =L11*(1-M11) -> 4497.145 | O11: Cost | P11: 311.80041 | Q11: =P11 -> 311.80041 | R11: 0.057855772 | S11: 0.1538616 | T11: =U11+V11 -> 311.80041 | U11: 311.80041 | V11: 0 | W11: =T11/P11 -> 1 | X11: 0 | Y11: 0 | Z11: 0 | AB11: Kae, Accel, Peak XV, 8i, DeVC, Eight Innovate | AE11: Ashish | AF11: Active
B12: =B11+1 -> 9 | C12: OKA Housing Technologies Private Limited | D12: Nivasa | E12: Mumbai | F12: FinTech | G12: 45937 | H12: Seed 1 | I12: Seed 1 | J12: 1215.6993 | K12: 1215.6993 | L12: =K12 -> 1215.6993 | M12: 0 | N12: =L12*(1-M12) -> 1215.6993 | O12: Cost | P12: 50.000413 | Q12: =P12 -> 50.000413 | R12: 0.040837027 | S12: 0.040837027 | T12: =U12+V12 -> 50.000413 | U12: 50.000413 | V12: 0 | W12: =T12/P12 -> 1 | X12: 0 | Y12: 0 | Z12: 0 | AB12: Four SB Ltd, Whiteboard, Other Investors | AE12: Ashish | AF12: Active
B13: =B12+1 -> 10 | C13: Hexo Inc. | D13: Hexo | E13: USA | F13: Artificial Intelligence | G13: 46006 | H13: SAFE | I13: SAFE | J13: NA | K13: NA | L13: NA | M13: 0 | N13: NA | O13: Cost | P13: 22.6807 | Q13: =P13 -> 22.6807 | R13: NA | S13: NA | T13: =U13+V13 -> 22.6807 | U13: 22.6807 | V13: 0 | W13: =T13/P13 -> 1 | X13: 0 | Y13: 0 | Z13: 0 | AF13: Active
P14: =SUM(P3:P13) -> 1891.4765 | Q14: =SUM(Q3:Q13) -> 1891.4765 | T14: =SUM(T3:T13) -> 1891.4765 | U14: =SUM(U3:U13) -> 1891.4765 | V14: 0 | W14: =T14/P14 -> 1

Sheet Fund IIA
B2: # | C2: Company | D2: Business / Brand | E2: Geography | F2: Sector | G2: Date | H2: Stage at Entry | I2: Current Stage | J2: Entry Valuation | K2: Last Round Valuation | L2: Valuation used for Mark to Market | M2: Discount to last round | N2: Effective Valuation for Mark-to-market | O2: Valuation Basis | P2: Total Invested Cost | Q2: Residual Cost | R2: Stake (At Entry) | S2: Stake (Current) | T2: Total Value | U2: Unrealised Value | V2: Realised Value | W2: Gross MOIC | X2: Gross IRR (₹) | Y2: If Exited, Mode of Exit | Z2: GP Exit MOIC | AA2: Value Creation by Fund | AB2: Co-investor(s) | AC2: Sourcing Route | AD2: Deal Source | AE2: Deal Lead | AF2: Status
G3: MM/YY | J3: ₹ Mn | K3: ₹ Mn | L3: ₹ Mn | N3: ₹ Mn | P3: ₹ Mn | Q3: ₹ Mn | R3: % | S3: % | T3: ₹ Mn | U3: ₹ Mn | V3: ₹ Mn | W3: x | X3: %
B4: 1 | C4: GreyOrange Robotics International Inc | D4: GreyOrange | E4: USA | F4: DeepTech | G4: 43329 | H4: Series C | I4: Series D | J4: 29734.07 | K4: ='Fund IA'!K5 -> 41634.55 | L4: =K4 -> 41634.55 | M4: 0.3 | N4: =L4*(1-M4) -> 29144.185 | O4: 30% discount to the last round | P4: 366.8005 | Q4: 366.8005 | R4: 0.012379046 | S4: 0.0087604625 | T4: =U4+V4 -> 341.45012 | U4: 341.45012 | V4: 0 | W4: =T4/P4 -> 0.93088781 | X4: -0.0099159824 | AA4: Business Development connects, Investor connect, Finance & compliance support | AB4: Mithril Capital, Pavilion Capital, Binny Bansal, Antehelion Capital, H&M | AC4: Alumni network of GPs ( BITS alum connected through Sanjay) | AD4: Sanjay | AE4: Karthik | AF4: Active
B5: 2 | C5: Manash Lifestyle Private Ltd | D5: Purplle | E5: Mumbai | F5: E-Commerce | G5: 43340 | H5: Series B | I5: Series F | J5: 3065.66 | K5: 106410.98 | L5: 106410.98 | M5: 0.11516728 | N5: =L5*(1-M5) -> 94155.913 | O5: Valued at secondary price to the last round (Series F - May 24) | P5: 113.01638 | Q5: 57.002211 | R5: 0.0081580077 | S5: 0.005691197 | T5: =U5+V5 -> 1156.9835 | U5: 569.22975 | V5: 587.7537 | W5: =T5/P5 -> 10.237307 | X5: 0.42247983 | Y5: Partial exit via secondary sale to Chiratae | Z5: =V5/(P5-Q5) -> 10.492946 | AA5: Business Development connects, Investor connect, finance and compliance support, hiring , strategic media arrangement | AB5: Goldman Sachs, Verlinvest, IvyCap, JSW Ventures,Sequoia, Kedaara Capital, Premji Invest, Paramark Ventures, ADIA, Tenacity | AC5: Angel Network | AD5: Karthik | AE5: Ashish | AF5: Partial Exit
B6: 3 | C6: Stelling Technologies Limited | D6: IntrCity | E6: NCR | F6: Consumer Services | G6: 43455 | H6: Series B | I6: Series D | J6: 2467.875 | K6: 11500 | L6: =K6 -> 11500 | M6: 0 | N6: =L6*(1-M6) -> 11500 | O6: Marked up to the last round (Series D - Oct'25) | P6: 209.00494 | Q6: 2.9536418 | R6: 0.026338658 | S6: 0.031957385 | T6: =U6+V6 -> 390.80014 | U6: 390.80014 | V6: 0 | W6: =T6/P6 -> 1.8698129 | X6: 0.10321616 | AA6: Board participation, connects to follow-on round investors, support on M&A, structuring of rounds, general counsel, Hiring, Finance & compliance support | AB6: A91, Mirablis, Helion, Omidyar, NRJN (Nandan Nilekeni) | AC6: LP referral | AD6: Karthik | AE6: Karthik | AF6: Active
B7: 4 | C7: Fintech Solutions Private Limited | D7: Turtlemint | E7: Mumbai | F7: FinTech | G7: 43362 | H7: Series C | I7: Series E | J7: 3693.25 | K7: 65190.93 | L7: =K7 -> 65190.93 | M7: 0.2 | N7: =L7*(1-M7) -> 52152.744 | O7: 20% discount to the last round (Series E - May 22) | P7: 179.41715 | Q7: 179.41715 | R7: 0.01818184 | S7: 0.0175 | T7: =U7+V7 -> 910.16635 | U7: 910.16635 | V7: 0 | W7: =T7/P7 -> 5.072906 | X7: 0.29024033 | AA7: Investor connect, Finance and compliance support, hiring | AB7: Sequoia, Nexus, AMFAM, Mass Mutual, Jungle Ventures, GGV, SIG, Amansa Capital, Vitruvian, Marshall Wace, Jungle Ventures | AC7: Personal network of team member | AD7: Adit* | AE7: Ashish | AF7: Active
B8: 5 | C8: Sorting Hat Technology Private Limited | D8: Unacademy | E8: Bangalore | F8: EdTech | G8: 43281 | H8: Series D | I8: Series H | J8: 15751.649 | K8: 251219.2 | L8: =K8 -> 251219.2 | M8: 0.91281097 | N8: =L8*(1-M8) -> 21903.557 | O8: ='Fund II'!O4 -> Valued at $300 Mn basis the M&A offer received | P8: 540.09574 | Q8: 540.09574 | R8: 0.02223036 | S8: 0.0172 | T8: =U8+V8 -> 294.57842 | U8: 294.57842 | V8: 0 | W8: =T8/P8 -> 0.5454189 | X8: 4.8828125e-09 | AA8: Investor connect, Finance & compliance support , ESOP , operational finance support , hiring | AB8: General Atlantic, Facebook, Peak XV Partners, Nexus, Elevation Capital, Steadview Capital, Tiger Global, Dragoneer,SoftBank | AC8: Eco-system referral | AD8: Karthik | AE8: Karthik | AF8: Active
B9: 6 | C9: Dunzo Digital Private Limited | D9: Dunzo | E9: Bangalore | F9: Consumer Tech | G9: 43410 | H9: Series C | I9: Series F | J9: 3747.586 | K9: ='Fund II'!K6 -> 60913.135 | L9: =K9 -> 60913.135 | M9: 1 | N9: =L9*(1-M9) -> 0 | O9: Provisioned | P9: 287.65933 | Q9: 287.65933 | R9: 0.019137503 | S9: =5435/299736 -> 0.018132623 | T9: =U9+V9 -> 0 | U9: 0 | V9: 0 | W9: =T9/P9 -> 0 | X9: NA | AA9: Investor connect, Finance & compliance support , Hiring | AB9: Aspada, Google Asia, LightBox, Reliance Retail, LGT Lightstone, LightRock | AC9: LP referral | AD9: Adit* | AE9: Karthik | AF9: Provisioned
B10: 7 | C10: Service Lee Technologies Private Limited | D10: Servify | E10: Mumbai | F10: Consumer Tech | G10: 43334 | H10: Series B | I10: Series D3 | J10: 3046.8995 | K10: ='Fund II'!K11 -> 57770 | L10: =K10 -> 57770 | M10: 0.35 | N10: =L10*(1-M10) -> 37550.5 | O10: ='Fund II'!O11 -> 35% discount to last round (Series D3 - August 23) | P10: 225.34968 | Q10: 112.71827 | R10: 0.04174926 | S10: 0.017887401 | T10: =U10+V10 -> 1393.1497 | U10: 676.85874 | V10: 716.29095 | W10: =T10/P10 -> 6.1821685 | X10: 0.30116328 | Y10: Partial exit via secondary sale to Oister & GP managed vehicle | Z10: =V10/(P10-Q10) -> 6.3596024 | AA10: Investor connect, round support, strategy, M&A, hiring, Finance & compliance support | AB10: Iron Pillar, Beenext, Singularity Investments | AC10: Founder network | AD10: Karthik | AE10: Karthik | AF10: Partial Exit
B11: 8 | C11: Aaidea Solutions Private Limited | D11: Milkbasket | E11: Bangalore | F11: Consumer Tech | G11: 43606 | H11: Series B | I11: - | J11: 5576.6794 | K11: 0 | L11: 0 | M11: 0 | N11: 0 | O11: Exited | P11: 174.57852 | Q11: 0 | R11: 0.024810156 | S11: 0 | T11: =U11+V11 -> 174.57852 | U11: 0 | V11: =P11 -> 174.57852 | W11: =T11/P11 -> 1 | X11: NA | Y11: Acquired by Reliance Retail | Z11: =V11/P11 -> 1 | AA11: Investor connect, hiring | AB11: Unilever,Ultimate Lenovo, Mayfield | AC11: Inbound / Events | AD11: Arpit | AE11: Karthik | AF11: Exited
B12: 9 | C12: Manak Waste Management Private Limited | D12: Cashify | E12: NCR | F12: Re-commerce | G12: 43745 | H12: Series C2 | I12: Series E | J12: 3656.12 | K12: 19884.01 | L12: =K12 -> 19884.01 | M12: 0.139253 | N12: =L12*(1-M12) -> 17115.102 | O12: Valued at secondary price to the last round (Series E - Feb'23) | P12: 70.913257 | Q12: =P12 -> 70.913257 | R12: 0.019422474 | S12: =970/84770 -> 0.011442727 | T12: =U12+V12 -> 200.1284 | U12: 200.1284 | V12: 0 | W12: =T12/P12 -> 2.8221578 | X12: 0.18093928 | AA12: Investor connect, Board participation, operations support , finance and complaince support | AB12: NewQuest Capital Partners, Prosus Ventures, Paramark Ventures, Shunwei, Bessemer, CDH, Morningside, AiHuiShou, Olympus Capital | AC12: Personal network of team member | AD12: Arpit | AE12: Arpit | AF12: Active
B13: 10 | C13: Tricog Health Pte Ltd | D13: Tricog | E13: Bangalore | F13: HealthTech | G13: 43748 | H13: Series B | I13: Series C | J13: 3758.3749 | K13: 7029.5271 | L13: =K13 -> 7029.5271 | M13: 0 | N13: =L13*(1-M13) -> 7029.5271 | O13: Marked at Series C (Jan 23) | P13: 85.53539 | Q13: =P13 -> 85.53539 | R13: 0.022 | S13: 0.018849319 | T13: =U13+V13 -> 154.84794 | U13: 154.84794 | V13: 0 | W13: =T13/P13 -> 1.8103377 | X13: 0.0999502 | AA13: Strategy, Finance support , Investor connect , Structuring of business as a SG domiciled entity, operational finance support | AB13: Athera Venture Partners, UTEC, Sony Innovation Fund, Omron | AC13: Inbound / Events | AD13: Arpit | AE13: Sanjay | AF13: Active
B14: 11 | C14: Smallcase Technologies Private Limited | D14: Smallcase | E14: Bangalore | F14: FinTech | G14: 44099 | H14: Series B | I14: ='Fund II'!I9 -> Series D | J14: 3819.4847 | K14: ='Fund II'!K9 -> 24870.194 | L14: ='Fund II'!L9 -> 24870.194 | M14: ='Fund II'!M9 -> 0.1793 | N14: =L14*(1-M14) -> 20410.968 | O14: ='Fund II'!O9 -> Marked at the secondary valuation of the Series D (pre-money) round (Mar 25) | P14: 109.98031 | Q14: 67.22089 | R14: 0.028794029 | S14: 0.012477008 | T14: =U14+V14 -> 416.6587 | U14: 254.6653 | V14: 161.9934 | W14: =T14/P14 -> 3.7884845 | X14: 0.30051701 | Y14: Partial exit via secondary sale to GP managed vehicle | Z14: =V14/(P14-Q14) -> 3.7884845 | AA14: Fund raise connect, Finance & complaince support, strategy, hiring, operational finance support | AB14: State Street, Faering Capital, Amazon, Premji Invest, Sequoia, DSP Adiko, Beenext, Unitary Fund, Straddle Capital, HDFC | AC14: Founder network | AD14: Rohan* | AE14: Karthik | AF14: Partial Exit
B15: 12 | C15: Sekhment Technologies Private Limited | D15: THB | E15: Delhi | F15: HealthTech | G15: 44256 | H15: Series B | I15: Series C | J15: 2105.5397 | K15: ='Fund II'!K21 -> 6483.9432 | L15: 0 | M15: 0 | N15: =L15*(1-M15) -> 0 | O15: Cost | P15: 65.760421 | Q15: =P15 -> 65.760421 | R15: 0.0284 | S15: 0.0236 | T15: =U15+V15 -> 65.760421 | U15: 65.760421 | V15: 0 | W15: =T15/P15 -> 1 | X15: -1.2207031e-09 | AA15: Finance & Compliance support , general counsel, hiring | AB15: Healthquad Fund, Dream Incubator, Filter Capital, Edelweiss Capital, Cornerstone Ventures | AC15: LP referral | AD15: Arpit | AE15: Arpit | AF15: Active
P16: =SUM(P4:P15) -> 2428.1116 | Q16: =SUM(Q4:Q15) -> 1836.0768 | T16: =SUM(T4:T15) -> 5499.1021 | U16: =SUM(U4:U15) -> 3858.4856 | V16: =SUM(V4:V15) -> 1640.6166 | W16: =T16/P16 -> 2.264765 | X16: 0.14117331
C19: * Indicates that the team member is no longer associated with the firm

Sheet Fund IIB
B2: # | C2: Company | D2: Business / Brand | E2: Geography | F2: Sector | G2: Date | H2: Stage at Entry | I2: Current Stage | J2: Entry Valuation | K2: Last Round Valuation | L2: Valuation used for Mark to Market | M2: Discount to last round | N2: Effective Valuation for Mark-to-market | O2: Valuation Basis | P2: Total Invested Cost | Q2: Residual Cost | R2: Stake (At Entry) | S2: Stake (Current) | T2: Total Value | U2: Unrealised Value | V2: Realised Value | W2: Gross MOIC | X2: Gross IRR (₹) | Y2: If Exited, Mode of Exit | Z2: GP Exit MOIC | AA2: Value Creation by Fund | AB2: Co-investor(s) | AC2: Sourcing Route | AD2: Deal Source | AE2: Deal Lead | AF2: Status
G3: MM/YY | J3: ₹ Mn | K3: ₹ Mn | L3: ₹ Mn | N3: ₹ Mn | P3: ₹ Mn | Q3: ₹ Mn | R3: % | S3: % | T3: ₹ Mn | U3: ₹ Mn | V3: ₹ Mn | W3: x | X3: %
B4: 1 | C4: Garagepreneurs Internet Private Limited | D4: Slice | E4: Bangalore | F4: FinTech | G4: 44589 | H4: Secondary - Prior to Series B | I4: CCD - Post Series B1 | J4: 70669.041 | K4: ='Fund II'!K7 -> 19454.765 | L4: =K4 -> 19454.765 | M4: 0 | N4: =L4*(1-M4) -> 19454.765 | O4: Held at the CCD round (Post merger) | P4: 357.10712 | Q4: 357.10712 | R4: 0.0044 | S4: 0.0062133248 | T4: =U4+V4 -> 120.87877 | U4: 120.87877 | V4: 0 | W4: =T4/P4 -> 0.33849443 | X4: -0.28837541 | Y4: - | Z4: - | AA4: Business development connects, Strategy, Investor connect, Compliance support , operational finnace support, business structuring | AB4: Tiger Global, Gunosy, Insight, Advent International | AC4: Events / Outbound | AD4: Adit* | AE4: Ashish | AF4: Active
B5: 2 | C5: Service Lee Technologies Private Limited | D5: Servify | E5: Bangalore | F5: Consumer Tech | G5: 44617 | H5: Series D1 | I5: Series D3 | J5: ='Fund IIA'!K10 -> 57770 | K5: ='Fund IIA'!L10 -> 57770 | L5: =K5 -> 57770 | M5: 0.35 | N5: =L5*(1-M5) -> 37550.5 | O5: ='Fund II'!O11 -> 35% discount to last round (Series D3 - August 23) | P5: 349.99988 | Q5: 349.99988 | R5: 0.0083248252 | S5: 0.0075731701 | T5: =U5+V5 -> 286.16184 | U5: 286.16184 | V5: 0 | W5: =T5/P5 -> 0.81760554 | X5: -0.050969723 | Y5: - | Z5: - | AA5: Investor connect, Finance & compliance support , Hiring | AB5: Iron Pillar, Beenext, Singularity Investments | AC5: LP referral | AD5: Karthik | AE5: Karthik | AF5: Active
B6: 3 | C6: Manash Lifestyle Private Ltd | D6: Purplle | E6: USA | F6: E-Commerce | G6: 44589 | H6: Series D1 | I6: Series F | J6: 53694.026 | K6: ='Fund IIA'!K5 -> 106410.98 | L6: =K6 -> 106410.98 | M6: ='Fund IIA'!M5 -> 0.11516728 | N6: =L6*(1-M6) -> 94155.913 | O6: ='Fund IIA'!O5 -> Valued at secondary price to the last round (Series F - May 24) | P6: 267.82078 | Q6: 234.93051 | R6: 0.0033170899 | S6: 0.0034153881 | T6: =U6+V6 -> 386.75314 | U6: 341.53785 | V6: 45.215289 | W6: =T6/P6 -> 1.4440744 | X6: 0.10848469 | Y6: Secondary exit | Z6: =V6/(P6-Q6) -> 1.3747314 | AA6: Business Development connects, Investor connect, Finance & compliance support | AB6: Mithril Capital, Pavilion Capital, Binny Bansal, Antehelion Capital, H&M | AC6: Alumni network of GPs ( BITS alum connected through Sanjay) | AD6: Karthik | AE6: Ashish | AF6: Partial Exit
B7: 4 | C7: Fintech Solutions Private Limited | D7: Turtlemint | E7: NCR | F7: FinTech | G7: 44683 | H7: Series E | I7: Series E | J7: ='Fund IIA'!K7 -> 65190.93 | K7: =J7 -> 65190.93 | L7: =K7 -> 65190.93 | M7: 0.2 | N7: =L7*(1-M7) -> 52152.744 | O7: ='Fund IIA'!O7 -> 20% discount to the last round (Series E - May 22) | P7: 227.99392 | Q7: 227.99392 | R7: 0.0034973258 | S7: 0.0034973258 | T7: =U7+V7 -> 182.39514 | U7: 182.39514 | V7: 0 | W7: =T7/P7 -> 0.8 | X7: -0.05909963 | Y7: - | Z7: - | AA7: Board participation, connects to follow-on round investors, support on M&A, structuring of rounds, general counsel, Hiring, Finance & compliance support | AB7: Mirablis, Helion, Omidyar, NRJN (Nandan Nilekeni) | AC7: LP referral | AD7: Adit* | AE7: Ashish | AF7: Active
B8: 5 | C8: Webklipper Technologies Pvt. Ltd | D8: Webengage | E8: Mumbai | F8: SaaS | G8: 44774 | H8: Series B | I8: Seires B1 | J8: 6847.5 | K8: 6847.5 | L8: 0 | M8: 0 | N8: =L8*(1-M8) -> 0 | O8: Cost | P8: 80.001558 | Q8: 80.001558 | R8: 0.01133 | S8: 0.01133 | T8: =U8+V8 -> 80.001558 | U8: 80.001558 | V8: 0 | W8: =T8/P8 -> 1 | X8: 2.9802322e-09 | Y8: - | Z8: - | AA8: Business Development connects, Investor connect, hiring | AB8: NEA, Transunion, MegaDelta, Analog, Elev8, KB Investment, Tenacity | AC8: co-investor network - angel | AD8: Karthik | AE8: Karthik | AF8: Active
B9: 6 | C9: Squadrun Inc. | D9: Squad | E9: NCR | F9: B2B Services | G9: 44933 | H9: Series B | I9: Series B | J9: ='Fund II'!K16 -> 7545.1152 | K9: =J9 -> 7545.1152 | L9: 0 | M9: 0 | N9: =L9*(1-M9) -> 0 | O9: Cost | P9: 122.33999 | Q9: 122.33999 | R9: 0.015945572 | S9: 0.015945572 | T9: =U9+V9 -> 134.87969 | U9: 134.87969 | V9: 0 | W9: =T9/P9 -> 1.1024988 | X9: 0.033878753 | Y9: - | Z9: - | AA9: Business Development connect , hiring | AB9: Chiratae Ventures, Bertelsmann India Investments | AC9: LP referral | AD9: Sanjay | AE9: Karthik | AF9: Active
B10: 7 | C10: Healthifyme Pte Ltd | D10: HealthifyMe | E10: Singapore/Bangalore | F10: HealthTech | G10: 44973 | H10: Convert Note | I10: Series C2 | J10: Convert Note | K10: ='Fund II'!K20 -> 15601.189 | L10: 0 | M10: 0 | N10: =L10*(1-M10) -> 0 | O10: Cost | P10: 82.835 | Q10: 82.835 | R10: 0.0066214221 | S10: 0.0066214221 | T10: =U10+V10 -> 83.54348 | U10: 83.54348 | V10: 0 | W10: =T10/P10 -> 1.0085529 | X10: 0.0029677302 | Y10: - | Z10: - | AA10: Strategy, Finance support , Investor connect , hiring | AB10: Chiratae Ventures, Khosla Ventures, Sistema Asia Fund, HealthQuad, LeapFrog Investments, Athera Venture Partners | AC10: Eco-system referral | AD10: Sanjay | AE10: Karthik | AF10: Active
P11: =SUM(P4:P10) -> 1488.0983 | Q11: =SUM(Q4:Q10) -> 1455.208 | T11: =SUM(T4:T10) -> 1274.6136 | U11: =SUM(U4:U10) -> 1229.3983 | V11: =SUM(V4:V10) -> 45.215289 | W11: =T11/P11 -> 0.85653861 | X11: -0.043473284
C13: * Indicates that the team member is no longer associated with the firm

Sheet Fund 1X
B2: # | C2: Company | D2: Business / Brand | E2: Geography | F2: Sector | G2: Date | H2: Stage at Entry | I2: Current Stage | J2: Entry Valuation | K2: Last Round Valuation | L2: Valuation used for MTM | M2: Discount to last round | N2: Effective Valuation for Mark-to-market | O2: Valuation Basis | P2: Total Invested Cost | Q2: Residual Cost | R2: Stake (At Entry) | S2: Stake (Current) | T2: Total Value | U2: Unrealised Value | V2: Realised Value | W2: Gross MOIC | X2: Gross IRR (₹) | Y2: If Exited, Mode of Exit | Z2: GP Exit MOIC | AA2: Value Creation by Fund | AB2: Co-investor(s) | AC2: Sourcing Route | AD2: Deal Source | AE2: Deal Lead | AF2: Status
G3: MM/YY | J3: ₹ Mn | K3: ₹ Mn | L3: ₹ Mn | N3: ₹ Mn | P3: ₹ Mn | Q3: ₹ Mn | R3: % | S3: % | T3: ₹ Mn | U3: ₹ Mn | V3: ₹ Mn | W3: x | X3: %
B4: 1 | C4: Manash Lifestyle Private Ltd | D4: Purplle | E4: Mumbai | F4: E-Commerce | G4: 44197 | H4: Series D | I4: Series F | J4: 15395.263 | K4: ='Fund IIB'!K6 -> 106410.98 | L4: =K4 -> 106410.98 | M4: ='Fund IIB'!M6 -> 0.11516728 | N4: =L4*(1-M4) -> 94155.913 | O4: ='Fund IIB'!O6 -> Valued at secondary price to the last round (Series F - May 24) | P4: 843.43854 | Q4: 504.83968 | R4: 0.041978025 | S4: 0.017104228 | T4: =U4+V4 -> 2838.4875 | U4: 1708.5581 | V4: 1129.9294 | W4: =T4/P4 -> 3.3653756 | X4: 0.31594874 | Y4: Partial exit via Secondary sale to Neo Wealth, Chiratae & Oister | Z4: =V4/(P4-Q4) -> 3.3370738 | AA4: Business Development connects, Investor connect, finance and compliance support, hiring , strategic media arrangement | AB4: Goldman Sachs, Verlinvest, IvyCap, JSW Ventures,Sequoia, Kedaara Capital, Premji Invest, Paramark Ventures, ADIA, Tenacity | AC4: Angel Network | AD4: Karthik | AE4: Ashish | AF4: Partial Exit
B5: 2 | C5: Fintech Solutions Private Limited | D5: Turtlemint | E5: Mumbai | F5: FinTech | G5: 44228 | H5: Series D2 | I5: Series E | J5: 17113.085 | K5: ='Fund IIB'!K7 -> 65190.93 | L5: =K5 -> 65190.93 | M5: 0.2 | N5: =L5*(1-M5) -> 52152.744 | O5: ='Fund IIB'!O7 -> 20% discount to the last round (Series E - May 22) | P5: 692.58764 | Q5: =P5 -> 692.58764 | R5: 0.0287 | S5: 0.0287 | T5: =U5+V5 -> 1497.1152 | U5: 1497.1152 | V5: 0 | W5: =T5/P5 -> 2.1616256 | X5: 0.18199329 | Y5: 0 | Z5: 0 | AA5: Investor connect, Finance and compliance support, hiring | AB5: Sequoia, Nexus, AMFAM, Mass Mutual, Jungle Ventures, GGV, SIG, Amansa Capital, Vitruvian, Marshall Wace, Jungle Ventures | AC5: Personal network of team member | AD5: Adit* | AE5: Ashish | AF5: Active
B6: 3 | C6: Exotel Techcom Pvt. Ltd | D6: Exotel | E6: Bengalore | F6: SaaS | G6: 44197 | H6: Series B1 | I6: Series D | J6: 1845.0281 | K6: 27665.001 | L6: =K6 -> 27665.001 | M6: 0.31320978 | N6: =L6*(1-M6) -> 19000.052 | O6: 31% discount to the last round (Series D - Jan'22) | P6: 571.5107 | Q6: =P6 -> 571.5107 | R6: 0.10971701 | S6: 0.0878 | T6: =U6+V6 -> 1667.9078 | U6: 1667.9078 | V6: 0 | W6: =T6/P6 -> 2.9184192 | X6: 0.26451676 | Y6: 0 | Z6: 0 | AA6: Board participation, Business Development connects, Hiring | AB6: A91 Partners, IIFL, Sistema, CX Partners, Steadview | AC6: Angel Network | AD6: Karthik | AE6: Karthik | AF6: Active
B7: 4 | C7: Baldor Technologies Private Ltd | D7: Idfy | E7: Mumbai | F7: FinTech | G7: 44197 | H7: Series D2 | I7: Series E | J7: 1483.9115 | K7: 10552.21 | L7: =K7*(1+13.7193310246606%) -> 11999.903 | M7: 0 | N7: =L7*(1-M7) -> 11999.903 | O7: Valued at the latest exit valuation | P7: 312.24298 | Q7: 232.10136 | R7: 0.1216915 | S7: 0.082737881 | T7: =U7+V7 -> 1335.8245 | U7: 992.96604 | V7: 342.85842 | W7: =T7/P7 -> 4.2781568 | X7: 0.36922751 | Y7: Partial exit via Secondary sale to GP managed vehicle | Z7: =V7/(P7-Q7) -> 4.2781568 | AA7: Business Development connects, Investor connect, hiring | AB7: NEA, Transunion, MegaDelta, Analog, Elev8, KB Investment, Tenacity | AC7: co-investor network - angel | AD7: Karthik | AE7: Karthik | AF7: Partial Exit
B8: 5 | C8: Webklipper Technologies Pvt. Ltd | D8: Webengage | E8: Mumbai | F8: SaaS | G8: 44197 | H8: Pre Series B | I8: Series B1 | J8: 1470.2809 | K8: ='Fund IIB'!K8 -> 6847.5 | L8: =K8 -> 6847.5 | M8: 0 | N8: =L8*(1-M8) -> 6847.5 | O8: Marked up to the last round (Series B - July 22) | P8: 202.54614 | Q8: =P8 -> 202.54614 | R8: 0.090178937 | S8: 0.07657 | T8: =U8+V8 -> 540.51208 | U8: 540.51208 | V8: 0 | W8: =T8/P8 -> 2.6685874 | X8: 0.23675007 | Y8: 0 | Z8: 0 | AA8: Board participation, Business Development connects, evaluating collaborations and acqui-hires from time to time, Hiring, Finance & compliance support | AB8: SWC, Singularity, IndiaQuotient | AC8: Referral by co-investor | AD8: Karthik | AE8: Karthik | AF8: Active
B9: 6 | C9: GreyOrange International Inc | D9: GreyOrange Robotics | E9: USA | F9: DeepTech | G9: 44525 | H9: Series C | I9: Series D | J9: 16600.651 | K9: ='Fund IIA'!K4 -> 41634.55 | L9: =K9 -> 41634.55 | M9: 0.3 | N9: =L9*(1-M9) -> 29144.185 | O9: ='Fund IIA'!O4 -> 30% discount to the last round | P9: 855.65973 | Q9: =P9 -> 855.65973 | R9: 0.015964564 | S9: 0.0081827509 | T9: =U9+V9 -> 254.95169 | U9: 254.95169 | V9: 0 | W9: =T9/P9 -> 0.2979592 | X9: -0.2556308 | Y9: 0 | Z9: 0 | AA9: Business Development connects, Investor connect, Finance & compliance support | AB9: Mithril Capital, Pavilion Capital, Binny Bansal, Antehelion Capital, H&M | AC9: Alumni network of GPs ( BITS alum connected through Sanjay) | AD9: Sanjay | AE9: Karthik | AF9: Active
P10: =SUM(P4:P9) -> 3477.9857 | Q10: =SUM(Q4:Q9) -> 3059.2453 | T10: =SUM(T4:T9) -> 8134.7987 | U10: =SUM(U4:U9) -> 6662.0109 | V10: =SUM(V4:V9) -> 1472.7878 | W10: =T10/P10 -> 2.3389396 | X10: 0.21340939
C12: * Indicates that the team member is no longer associated with the firm

Sheet Fund 1Y
B2: # | C2: Company | D2: Business / Brand | E2: Geography | F2: Sector | G2: Date | H2: Stage at Entry | I2: Current Stage | J2: Entry Valuation | K2: Last Round Valuation | L2: Valuation used for Mark-to-market | M2: Discount to last round | N2: Effective Valuation for Mark-to-market | O2: Valuation Basis | P2: Total Invested Cost | Q2: Residual Cost | R2: Stake (At Entry) | S2: Stake (Current) | T2: Total Value | U2: Unrealised Value | V2: Realised Value | W2: Gross MOIC | X2: Gross IRR (₹) | Y2: If Exited, Mode of Exit | Z2: GP Exit MOIC | AA2: Value Creation by Fund | AB2: Co-investor(s) | AC2: Sourcing Route | AD2: Deal Source | AE2: Deal Lead | AF2: Status | AG2: Comments
G3: MM/YY | J3: ₹ Mn | K3: ₹ Mn | L3: ₹ Mn | N3: ₹ Mn | P3: ₹ Mn | Q3: ₹ Mn | R3: % | S3: % | T3: ₹ Mn | U3: ₹ Mn | V3: ₹ Mn | W3: x | X3: %
B4: 1 | C4: Manash Lifestyle Private Limited | D4: Purplle | E4: Mumbai | F4: E-Commerce | G4: 44921 | H4: Series E | I4: Series F | J4: 86757.374 | K4: ='Fund 1X'!K4 -> 106410.98 | L4: =K4 -> 106410.98 | M4: ='Fund 1X'!M4 -> 0.11516728 | N4: =L4*(1-M4) -> 94155.913 | O4: ='Fund 1X'!O4 -> Valued at secondary price to the last round (Series F - May 24) | P4: 453.77958 | Q4: =P4 -> 453.77958 | R4: 0.0053688721 | S4: 0.0046601457 | T4: =U4+V4 -> 492.57348 | U4: 492.57348 | V4: 0 | W4: =T4/P4 -> 1.0854906 | X4: 0.027590761 | Y4: 0 | Z4: 0 | AA4: Business Development connects, Investor connect, finance and compliance support, hiring , strategic media arrangement | AB4: Goldman Sachs, Verlinvest, IvyCap, JSW Ventures,Sequoia, Kedaara Capital, Premji Invest, Paramark Ventures, ADIA, Tenacity | AC4: Angel Network | AD4: Karthik | AE4: Ashish | AF4: Active | AG4: At entry, the Fund invested a mix of primary and secondary capital. The secodary component was done at a 20% discount
B5: =B4+1 -> 2 | C5: Solvy Tech Solutions Private Limited | D5: Zopper | E5: NCR | F5: FinTech | G5: 44869 | H5: Series E | I5: Series F | J5: 7867.9017 | K5: 16712.583 | L5: 14053.271 | M5: 0.25 | N5: =L5*(1-M5) -> 10539.954 | O5: Valued at a 25% discount to the secondary price of the last round (Series F - Oct'24) | P5: 804.04449 | Q5: =P5 -> 804.04449 | R5: 0.0861 | S5: 0.0878851 | T5: =U5+V5 -> 853.52062 | U5: 853.52062 | V5: 0 | W5: =T5/P5 -> 1.0615341 | X5: 0.021147159 | Y5: 0 | Z5: 0 | AA5: Sourcing of follow-on round investors, Finance and compliance support, assistance with M&A transactions , hiring | AB5: ICICI Ventures, Bessemer Venture Partners, Creaegis, Elevation, Dharana | AC5: Alumni network of GPs | AD5: Karthik | AE5: Karthik | AF5: Active | AG5: A part of the investment in Zopper is via secondary acquisition of shares, as a discount of 8.26% to the entry valuation.
B6: =B5+1 -> 3 | C6: Manak Waste Management Private Limited | D6: Cashify | E6: NCR | F6: Re-commerce | G6: 44981 | H6: Series E | I6: Series E | J6: ='Fund IIA'!K12 -> 19884.01 | K6: 257.8 | L6: 257.8 | M6: 0 | N6: =L6*(1-M6) -> 257.8 | O6: Cost | P6: 656.40802 | Q6: =P6 -> 656.40802 | R6: 0.0361 | S6: 0.0361 | T6: =U6+V6 -> 656.40802 | U6: 656.40802 | V6: 0 | W6: =T6/P6 -> 1 | X6: NA | Y6: 0 | Z6: 0 | AA6: Investor connect, Board participation, operations support , finance and complaince support | AB6: NewQuest Capital Partners, Prosus Ventures, Paramark Ventures, Shunwei, Bessemer, CDH, Morningside, AiHuiShou, Olympus Capital | AC6: Personal network of team member | AD6: Arpit | AE6: Arpit | AF6: Active | AG6: A part of the investment in Cashify is via secondary acquisition of shares, as a discount of 12.85% to the entry valuation.
B7: =B6+1 -> 4 | C7: Carbon Clean Solutions Limited | D7: Carbon Clean Solutions | E7: U.K | F7: CleanTech | G7: 45280 | H7: Series C | I7: Series C | J7: ='Fund I'!K5 -> 48917.542 | K7: =J7 -> 48917.542 | L7: =K7 -> 48917.542 | M7: 0 | N7: =L7*(1-M7) -> 48917.542 | O7: Cost | P7: 129.97752 | Q7: =P7 -> 129.97752 | R7: 0.00283 | S7: 0.00283 | T7: =U7+V7 -> 140.55598 | U7: 140.55598 | V7: 0 | W7: =T7/P7 -> 1.0813868 | X7: 0.039239761 | Y7: 0 | Z7: 0 | AA7: Business Development connects, structuring of the business as a UK domiciled entity , finance and compliance support, hiring | AB7: Chevron, Wave Equity Partners, Marubeni, Samsung Ventures, Saudi Aramco Energy Ventures, CEMEX | AC7: LP referral | AD7: Sanjay | AE7: Karthik | AF7: Active | AG7: The entire investment in Carbon Clean is via secondary acquisition of shares, as a discount of 15% to the entry valuation.
B8: =B7+1 -> 5 | C8: Ultrahuman Healthcare Private Limited | D8: Ultrahuman | E8: Bengaluru | F8: HealthTech | G8: 45364 | H8: Series B3 | I8: Series B3 | J8: ='Fund III'!K19 -> 10382.792 | K8: =J8 -> 10382.792 | L8: =K8 -> 10382.792 | M8: 0 | N8: =L8*(1-M8) -> 10382.792 | O8: Cost | P8: 298.5199 | Q8: =P8 -> 298.5199 | R8: 0.0288 | S8: 0.0288 | T8: =U8+V8 -> 298.5199 | U8: 298.5199 | V8: 0 | W8: =T8/P8 -> 1 | X8: NA | Y8: 0 | Z8: 0 | AA8: Advisory | AB8: Nexus, AlphaWave Incubation, Steadview | AC8: Ex-portfolio founder | AD8: Karthik | AE8: Karthik | AF8: Active
B9: =B8+1 -> 6 | C9: Sprinto Technology Private Limited | D9: Sprinto | E9: Bengaluru | F9: SaaS | G9: 45398 | H9: Series B | I9: Series B | J9: ='Fund III'!K12 -> 8724.105 | K9: =J9 -> 8724.105 | L9: =K9 -> 8724.105 | M9: 0 | N9: =L9*(1-M9) -> 8724.105 | O9: Cost | P9: 166.24476 | Q9: =P9 -> 166.24476 | R9: 0.0143 | S9: 0.0143 | T9: =U9+V9 -> 166.24476 | U9: 166.24476 | V9: 0 | W9: =T9/P9 -> 1 | X9: NA | Y9: 0 | Z9: 0 | AA9: Mentoring, Fund raise and Advisory | AB9: Elevation, Accel | AC9: Founder network ( connected through the founder's prior startup) | AD9: Karthik | AE9: Sanjay | AF9: Active
B10: =B9+1 -> 7 | C10: Euler Motors Private Limited | D10: Euler | E10: NCR | F10: Mobility-Tech | G10: 45430 | H10: Series C3 | I10: ='Fund III'!I10 -> Series D | J10: 7323.6954 | K10: ='Fund III'!K10 -> 14380 | L10: =K10 -> 14380 | M10: 0 | N10: =L10*(1-M10) -> 14380 | O10: ='Fund III'!O10 -> Marked up to the Series D round (Mar 25) | P10: 319.99777 | Q10: =P10 -> 319.99777 | R10: 0.0438 | S10: 0.021936255 | T10: =U10+V10 -> 328.08092 | U10: 328.08092 | V10: 0 | W10: =T10/P10 -> 1.02526 | X10: 0.015499613 | Y10: 0 | Z10: 0 | AA10: Finance hiring - AF Hiring support - Passion Connect Finance Control - Constellation Fund raise (all aspects) - AF Business strategy, monitoring and tactical advisory, mentoring and team building- Arpit Business Development - Jitesh | AB10: GIC, Asian Development Bank, British International Investment, Piramal Alternatives, Athera Venture Partners | AC10: Outbound reach-out from Blume intern | AD10: Arpit | AE10: Arpit | AF10: Active
B11: =B10+1 -> 8 | C11: Stelling Technologies Private Limited | D11: IntrCity | E11: NCR | F11: Consumer Services | G11: 45440 | H11: Series C3 | I11: Series D | J11: 7572.5084 | K11: ='Fund IIA'!K6 -> 11500 | L11: =K11 -> 11500 | M11: 0 | N11: =L11*(1-M11) -> 11500 | O11: ='Fund IIA'!O6 -> Marked up to the last round (Series D - Oct'25) | P11: 183.83928 | Q11: =P11 -> 183.83928 | R11: 0.0243 | S11: 0.019615605 | T11: =U11+V11 -> 239.8751 | U11: 239.8751 | V11: 0 | W11: =T11/P11 -> 1.3048088 | X11: 0.18158496 | Y11: 0 | Z11: 0 | AA11: Board participation, connects to follow-on round investors, support on M&A, structuring of rounds, general counsel, Hiring, Finance & compliance support | AB11: A91, Mirablis, Helion, Omidyar, NRJN (Nandan Nilekeni) | AC11: LP referral | AD11: Karthik | AE11: Karthik | AF11: Active
B12: =B11+1 -> 9 | C12: Stellapps Technologies Private Limited | D12: Stellapps | E12: Bengaluru | F12: AgriTech | G12: 45495 | H12: Series B1B | I12: Series C | J12: ='Fund II'!K26 -> 6245.8286 | K12: =J12 -> 6245.8286 | L12: =K12 -> 6245.8286 | M12: 0 | N12: =L12*(1-M12) -> 6245.8286 | O12: Cost | P12: 249.98934 | Q12: =P12 -> 249.98934 | R12: 0.0102 | S12: 0.0462 | T12: =U12+V12 -> 249.98934 | U12: 249.98934 | V12: 0 | W12: =T12/P12 -> 1 | X12: NA | Y12: 0 | Z12: 0 | AA12: Fund raise connect, hiring , secondary acquistion structuring , Business Development connect | AB12: Bill and Melinda Gates Foundation, IDH Farmfit, Stride Ventures, Blue Ashva Sampada, Omnivore Partners | AC12: VC referral | AD12: Karthik | AE12: Ashish | AF12: Active
B13: =B12+1 -> 10 | C13: Garagepreneurs Internet Private Limited | D13: Slice | E13: Bengaluru | F13: FinTech | G13: 45554 | H13: CCD | I13: CCD - Post Series B1 | J13: ='Fund IIB'!K4 -> 19454.765 | K13: =J13 -> 19454.765 | L13: =K13 -> 19454.765 | M13: 0 | N13: =L13*(1-M13) -> 19454.765 | O13: Cost | P13: 170 | Q13: =P13 -> 170 | R13: 0.0089 | S13: 0.0087382192 | T13: =U13+V13 -> 170 | U13: 170 | V13: 0 | W13: =T13/P13 -> 1 | X13: NA | Y13: 0 | Z13: 0 | AA13: Business development connects, Strategy, Investor connect, Compliance support , operational finnace support, business structuring | AC13: Events / Outbound | AD13: Adit | AE13: Ashish | AF13: Active
B14: =B13+1 -> 11 | C14: LendingOps Labs Private Limited | D14: Lending Labs | E14: Bengaluru | F14: FinTech | G14: 45786 | H14: Seed | I14: Seed | J14: Face value | K14: Face value | L14: Face value | M14: 0 | N14: 0 | O14: Cost | P14: 0.009259 | Q14: =P14 -> 0.009259 | R14: 0.0083331008 | S14: 0.0083331008 | T14: =U14+V14 -> 0.009259 | U14: 0.009259 | V14: 0 | W14: =T14/P14 -> 1 | X14: NA | Y14: 0 | Z14: 0 | AA14: - | AB14: - | AC14: - | AD14: Karthik | AE14: Ashish | AF14: Active | AG14: Blume Fund I had originally invested in Kuliza Technologies Private Limited. Following the restructuring of the business and holdings in Kuliza, and given the long-standing relationship with the founder, these shares were offered to Fund 1Y, a natural extension to Fund 1, at face value as a gesture of continuity and as scope of value capture in the new business.
P15: =SUM(P4:P14) -> 3432.8099 | Q15: =SUM(Q4:Q14) -> 3432.8099 | T15: =SUM(T4:T14) -> 3595.7774 | U15: =SUM(U4:U14) -> 3595.7774 | V15: 0 | W15: =T15/P15 -> 1.0474735 | X15: 0.021256754
