Workbook
Name CIQWBGuid: "9b8b128a-ea69-4f95-8ab7-4b521b087d2d"
Name IQ_CH: 110000
Name IQ_CQ: 5000
Name IQ_CY: 10000
Name IQ_DAILY: 500000
Name IQ_DNTM: 700000
Name IQ_FH: 100000
Name IQ_FQ: 500
Name IQ_FWD_CY: 10001
Name IQ_FWD_CY1: 10002
Name IQ_FWD_CY2: 10003
Name IQ_FWD_FY: 1001
Name IQ_FWD_FY1: 1002
Name IQ_FWD_FY2: 1003
Name IQ_FWD_Q: 501
Name IQ_FWD_Q1: 502
Name IQ_FWD_Q2: 503
Name IQ_FY: 1000
Name IQ_LATESTK: 1000
Name IQ_LATESTQ: 500
Name IQ_LTM: 2000
Name IQ_LTMMONTH: 120000
Name IQ_MONTH: 15000
Name IQ_MTD: 800000
Name IQ_NAMES_REVISION_DATE_: "04/25/2019 07:38:24"
Name IQ_NTM: 6000
Name IQ_QTD: 750000
Name IQ_TODAY: 0
Name IQ_WEEK: 50000
Name IQ_YTD: 3000
Name IQ_YTDMONTH: 130000

Sheet B2B - Non Repair Inputs
A1: Non- Repair (INR) - Inputs | B1: 43208 | C1: 43238 | D1: 43269 | E1: 43282 | F1: 43313 | G1: 43344 | H1: 43374 | I1: 43405 | J1: 43435 | K1: 43466 | L1: 43497 | M1: 43525 | N1: 43556 | O1: 43586 | P1: 43617 | Q1: 43647 | R1: =Q1+31 -> 43678 | S1: =R1+31 -> 43709 | T1: =S1+31 -> 43740 | U1: =T1+31 -> 43771 | V1: =U1+31 -> 43802 | W1: =V1+31 -> 43833 | X1: =W1+31 -> 43864 | Y1: =X1+31 -> 43895 | ... BS1: =BR1+31 -> 45321 | BT1: =BS1+30 -> 45351 | BU1: =BT1+30 -> 45381 | BV1: =BU1+30 -> 45411 | BW1: =BV1+30 -> 45441 | BX1: =BW1+30 -> 45471 | BY1: =BX1+30 -> 45501 | BZ1: =BY1+30 -> 45531 | CA1: =BZ1+30 -> 45561 | ... EC1: =EB1+30 -> 47181 | ED1: x
A2: Gross Revenue (inc. tax) | B2: 127373162 | C2: 119526214 | D2: 1.3361892e+08 | E2: 1.5572126e+08 | F2: 1.8292117e+08 | G2: 190468885 | H2: 203496304 | I2: 191306750 | J2: 241759536 | K2: 234336044 | L2: 2.3858167e+08 | M2: 208964937 | N2: 2.6952158e+08 | O2: 2.6688728e+08 | P2: 2.8626461e+08 | Q2: 292672912 | R2: 2.4150233e+08 | S2: 214319223 | T2: 181364156 | U2: 220788768 | V2: 2.6449597e+08 | W2: 267334479 | X2: 2.9379328e+08 | Y2: 182610351 | Z2: 0 | AA2: 140900548 | AB2: 146263086 | AC2: 119828870 | AD2: 200268733 | AE2: 206503898 | AF2: 186804306 | AG2: 2.2063889e+08 | AH2: 3.5443276e+08 | AI2: 3.059086e+08 | AJ2: 3.8260216e+08 | AK2: 3.2157717e+08 | AL2: 2.2184714e+08 | AM2: 1.0392815e+08 | AN2: 2.2950755e+08 | AO2: 322690111 | AP2: 3.1847108e+08 | AQ2: 3.0977751e+08 | AR2: 2.7614005e+08 | AS2: 3.141244e+08 | AT2: 4.2050482e+08 | AU2: 3.877668e+08 | AV2: 406585986 | AW2: 367317139 | AX2: 364497378 | AY2: 418830243 | AZ2: =AZ3+AZ4 -> 3.2287098e+08 | BA2: =BA3+BA4 -> 3.5962884e+08 | BB2: =BB3+BB4 -> 3.7669515e+08 | BC2: =BC3+BC4 -> 3.7649862e+08 | BD2: =BD3+BD4 -> 4.2638107e+08 | BE2: =BE3+BE4 -> 4.6466709e+08 | BF2: =BF3+BF4 -> 5.8646851e+08 | BG2: =BG3+BG4 -> 5.2943297e+08 | ... DQ2: =DQ3+DQ4 -> 0 | EC2: =EC3+EC4 -> 0 | ED2: x
A3: Offline | AZ3: 57900213 | BA3: 62484773 | BB3: 63293292 | BC3: 1.1271932e+08 | BD3: 1.0161536e+08 | BE3: 1.2246949e+08 | BF3: 1.4776989e+08 | BG3: 1.1208485e+08 | BH3: 59806800 | BI3: 64466321 | BJ3: 39228577 | BK3: 32647113 | BL3: 33153913 | BM3: 15345796 | BN3: 12681235 | BO3: 18397365 | BP3: 28562914 | BQ3: 51819029 | BR3: 42511549 | BS3: 26524843 | BT3: 18495206 | BU3: 31427878 | BV3: 27850812 | BW3: 22729297 | BX3: 10946710 | BY3: 21263730 | BZ3: 29270284 | CA3: 35801443 | CB3: 25116076 | CC3: 15694579 | CD3: 35993006 | CE3: 54975279 | CF3: 35182058 | CG3: 70684511 | CH3: 57976140 | CI3: 56362233 | CJ3: 25843707 | CK3: 29562162 | CL3: 19353126 | CM3: 16747344 | CN3: 22624143 | CO3: 41629922 | CP3: 72883676 | CQ3: 54851941 | CR3: 38432467 | ED3: x
A4: Online | AZ4: 2.6497076e+08 | BA4: 2.9714407e+08 | BB4: 3.1340186e+08 | BC4: 2.637793e+08 | BD4: 3.247657e+08 | BE4: 3.421976e+08 | BF4: 4.3869863e+08 | BG4: 4.1734813e+08 | BH4: 3.7824561e+08 | BI4: 4.1863154e+08 | BJ4: 4.2592753e+08 | BK4: 4.3511469e+08 | BL4: 3.2300388e+08 | BM4: 3.2850307e+08 | BN4: 3.4456507e+08 | BO4: 3.2209393e+08 | BP4: 2.884787e+08 | BQ4: 3.1590853e+08 | BR4: 2.9801067e+08 | BS4: 2.8335834e+08 | BT4: 3.0843154e+08 | BU4: 2.9969907e+08 | BV4: 3.1798799e+08 | BW4: 3.3608515e+08 | BX4: 3.2954318e+08 | BY4: 3.0327311e+08 | BZ4: 2.8538817e+08 | CA4: 2.4773517e+08 | CB4: 3.0363596e+08 | CC4: 3.1660862e+08 | CD4: 3.3832818e+08 | CE4: 3.6436917e+08 | CF4: 4.4184371e+08 | CG4: 5.2195693e+08 | CH4: 4.5438369e+08 | CI4: 4.5251806e+08 | CJ4: 4.9366874e+08 | CK4: 4.7876586e+08 | CL4: 4.1957962e+08 | CM4: 3.5971942e+08 | CN4: 4.5657266e+08 | CO4: 5.2491022e+08 | CP4: 6.1854909e+08 | CQ4: 6.8487692e+08 | CR4: 6.4630524e+08 | ED4: x
ED5: x
A6: Devices | B6: 32077 | C6: 28685 | D6: 34758 | E6: 39298 | F6: 47222 | G6: 49152 | H6: 52716 | I6: 52798 | J6: 67323 | K6: 62990 | L6: 67278 | M6: 53088 | N6: 72396 | O6: 75630 | P6: 76377 | Q6: 71644 | R6: 63244 | S6: 56263 | T6: 46046 | U6: 53509 | V6: 66574 | W6: 66672 | X6: 82936 | Y6: 53988 | Z6: 0 | AA6: 39616 | AB6: 42186 | AC6: 23110 | AD6: 42469 | AE6: 37673 | AF6: 38371 | AG6: 52692 | AH6: 66087 | AI6: 50483 | AJ6: 69399 | AK6: 58903 | AL6: 39902 | AM6: 20877 | AN6: 46075 | AO6: 67308 | AP6: 70639 | AQ6: 66964 | AR6: 60018 | AS6: 75086 | AT6: 92309 | AU6: 84249 | AV6: 78598 | AW6: 72738 | AX6: 67201 | AY6: 75950 | AZ6: =SUM(AZ7:AZ8) -> 55593 | BA6: =SUM(BA7:BA8) -> 62571 | BB6: =SUM(BB7:BB8) -> 65439 | BC6: =SUM(BC7:BC8) -> 69439 | BD6: =SUM(BD7:BD8) -> 64427 | BE6: =SUM(BE7:BE8) -> 69556 | BF6: =SUM(BF7:BF8) -> 86447 | BG6: =SUM(BG7:BG8) -> 76462 | ... DQ6: =SUM(DQ7:DQ8) -> 0 | EC6: =SUM(EC7:EC8) -> 0 | ED6: x
A7: Offline | AZ7: 9439 | BA7: 10854 | BB7: 10760 | BC7: 21806 | BD7: 13898 | BE7: 17371 | BF7: 20911 | BG7: 15473 | BH7: 10466 | BI7: 13386 | BJ7: 5026 | BK7: 4403 | BL7: 5764 | BM7: 3408 | BN7: 2073 | BO7: 3244 | BP7: 5103 | BQ7: 13036 | BR7: 4139 | BS7: 3210 | BT7: 2867 | BU7: 4926 | BV7: 4229 | BW7: 3319 | BX7: 2009 | BY7: 4449 | BZ7: 4259 | CA7: 4375 | CB7: 2935 | CC7: 2537 | CD7: 7861 | CE7: 12311 | CF7: 5940 | CG7: 10233 | CH7: 8955 | CI7: 9131 | CJ7: 3136 | CK7: 4004 | CL7: 2650 | CM7: 3295 | CN7: 2653 | CO7: 6330 | CP7: 7285 | CQ7: 4480 | CR7: 3629.5641 | ED7: x
A8: Online | AZ8: 46154 | BA8: 51717 | BB8: 54679 | BC8: 47633 | BD8: 50529 | BE8: 52185 | BF8: 65536 | BG8: 60989 | BH8: 51027 | BI8: 57821 | BJ8: 56260 | BK8: 54644 | BL8: 37687 | BM8: 40718 | BN8: 45738 | BO8: 43900 | BP8: 34529 | BQ8: 33684 | BR8: 30780 | BS8: 29203 | BT8: 30576 | BU8: 28090 | BV8: 30573 | BW8: 35826 | BX8: 35853 | BY8: 35328 | BZ8: 31014 | CA8: 27470 | CB8: 30565 | CC8: 33360 | CD8: 37963 | CE8: 38551 | CF8: 40985 | CG8: 48977 | CH8: 43458 | CI8: 45214 | CJ8: 48592 | CK8: 47661 | CL8: 45521 | CM8: 38590 | CN8: 46497 | CO8: 54158 | CP8: 60087 | CQ8: 58857 | CR8: 58229 | ED8: x
ED9: x
A10: Returns (inc. tax) | B10: 0 | C10: 0 | D10: 0 | E10: 0 | F10: 0 | G10: 0 | H10: 0 | I10: 0 | J10: 0 | K10: 0 | L10: 0 | M10: 0 | N10: 73665.555 | O10: 18545.06 | P10: 35350.414 | Q10: 313486.29 | R10: 1159355.2 | S10: 1898626.9 | T10: 1537513.1 | U10: 1643268.5 | V10: 3134468.3 | W10: 3493815.9 | X10: 2214326.7 | Y10: 681691.8 | Z10: 58689 | AA10: 78042.06 | AB10: 302378.05 | AC10: 90474.93 | AD10: 203264.43 | AE10: 1361023.8 | AF10: 2293737.3 | AG10: 2673237.4 | AH10: 2807817 | AI10: 3084430.9 | AJ10: 3797965.8 | AK10: 4332916.3 | AL10: 3505842.3 | AM10: 4420191.5 | AN10: 8957793.6 | AO10: 13662088 | AP10: 16041871 | AQ10: 26276687 | AR10: 33122634 | AS10: 23397431 | AT10: 30706134 | AU10: 32673536 | AV10: 43288241 | AW10: 50451902 | AX10: 49613456 | AY10: 64881764 | AZ10: =AZ11+AZ12 -> 69152023 | BA10: =BA11+BA12 -> 64276477 | BB10: =BB11+BB12 -> 61835594 | BC10: =BC11+BC12 -> 53480848 | BD10: =BD11+BD12 -> 46389583 | BE10: =BE11+BE12 -> 53539111 | BF10: =BF11+BF12 -> 62969264 | BG10: =BG11+BG12 -> 57422683 | ... DQ10: =DQ11+DQ12 -> 0 | EC10: =EC11+EC12 -> 0 | ED10: x
A11: Offline | AZ11: 584761.33 | BA11: 130274.59 | BB11: 163329.98 | BC11: 380127.04 | BD11: 1177382.5 | BE11: 2269684.6 | BF11: 308900.99 | BG11: 249670.93 | BH11: 568887.69 | BI11: 1351326 | BJ11: 489349 | BK11: 596455.25 | BL11: 152981.59 | BM11: 200262.42 | BN11: 27457.577 | BO11: 201581.7 | BP11: 2088827.9 | BQ11: 270666.24 | BR11: 88826.571 | BS11: 720660.15 | BT11: 1462117.2 | BU11: 1052057 | BV11: 645068.35 | BW11: 639875.17 | BX11: 851158.77 | BY11: 95498.433 | BZ11: 100441.8 | CA11: 86477.185 | CB11: 313479.17 | CC11: 280926.05 | CD11: 185949.37 | CE11: 12510.888 | CF11: 62892.962 | CG11: 90180.167 | CH11: 147495.14 | CI11: 1251985.5 | CJ11: 55430.529 | CK11: 246236.78 | CL11: 54944.39 | CM11: 93690.25 | CN11: 29481.83 | CO11: 111605.68 | CP11: 311799.45 | CQ11: 120490.87 | CR11: 29857.06 | ED11: x
A12: Online | AZ12: 68567261 | BA12: 64146203 | BB12: 61672264 | BC12: 53100721 | BD12: 45212201 | BE12: 51269427 | BF12: 62660363 | BG12: 57173013 | BH12: 57521228 | BI12: 61272930 | BJ12: 76047181 | BK12: 72098825 | BL12: 55542143 | BM12: 59960809 | BN12: 56538940 | BO12: 50706878 | BP12: 42722467 | BQ12: 33017650 | BR12: 39291726 | BS12: 37875847 | BT12: 40077373 | BU12: 34575290 | BV12: 38382767 | BW12: 40540331 | BX12: 36969260 | BY12: 38326106 | BZ12: 38440252 | CA12: 41192892 | CB12: 38187234 | CC12: 35123003 | CD12: 38377281 | CE12: 34152064 | CF12: 31020347 | CG12: 38758008 | CH12: 42143225 | CI12: 41219534 | CJ12: 59098386 | CK12: 46927371 | CL12: 50189998 | CM12: 40320148 | CN12: 43616763 | CO12: 43585970 | CP12: 57750700 | CQ12: 58166177 | CR12: 62582269 | ED12: x
ED13: x
A14: Devices | B14: 0 | C14: 0 | D14: 0 | E14: 0 | F14: 0 | G14: 0 | H14: 0 | I14: 0 | J14: 0 | K14: 0 | L14: 0 | M14: 0 | N14: 9 | O14: 1 | P14: 4 | Q14: 31 | R14: 137 | S14: 193 | T14: 159 | U14: 148 | V14: 326 | W14: 451 | X14: 337 | Y14: 109 | Z14: 9 | AA14: 1 | AB14: 42 | AC14: 9 | AD14: 41 | AE14: 163 | AF14: 338 | AG14: 440 | AH14: 464 | AI14: 386 | AJ14: 487 | AK14: 544 | AL14: 529 | AM14: 751 | AN14: 1454 | AO14: 2406 | AP14: 3126 | AQ14: 4565 | AR14: 5997 | AS14: 4301 | AT14: 5405 | AU14: 5899 | AV14: 7326 | AW14: 8324 | AX14: 8454 | AY14: 11659 | AZ14: =SUM(AZ15:AZ16) -> 12670 | BA14: =SUM(BA15:BA16) -> 9847 | BB14: =SUM(BB15:BB16) -> 9688 | BC14: =SUM(BC15:BC16) -> 8687 | BD14: =SUM(BD15:BD16) -> 8023 | BE14: =SUM(BE15:BE16) -> 8041 | BF14: =SUM(BF15:BF16) -> 8690 | BG14: =SUM(BG15:BG16) -> 7618 | ... DQ14: =SUM(DQ15:DQ16) -> 0 | EC14: =SUM(EC15:EC16) -> 0 | ED14: x
A15: Offline | AZ15: 98 | BA15: 18 | BB15: 19 | BC15: 90 | BD15: 235 | BE15: 236 | BF15: 39 | BG15: 18 | BH15: 44 | BI15: 301 | BJ15: 33 | BK15: 36 | BL15: 13 | BM15: 11 | BN15: 3 | BO15: 16 | BP15: 101 | BQ15: 15 | BR15: 6 | BS15: 37 | BT15: 65 | BU15: 53 | BV15: 32 | BW15: 26 | BX15: 47 | BY15: 7 | BZ15: 5 | CA15: 4 | CB15: 20 | CC15: 19 | CD15: 12 | CE15: 1 | CF15: 4 | CG15: 5 | CH15: 7 | CI15: 38 | CJ15: 5 | CK15: 11 | CL15: 3 | CM15: 7 | CN15: 2 | CO15: 15 | CP15: 20 | CQ15: 5 | CR15: 2 | ED15: x
A16: Online | AZ16: 12572 | BA16: 9829 | BB16: 9669 | BC16: 8597 | BD16: 7788 | BE16: 7805 | BF16: 8651 | BG16: 7600 | BH16: 7097 | BI16: 7443 | BJ16: 9147 | BK16: 8142 | BL16: 6160 | BM16: 6267 | BN16: 6524 | BO16: 5654 | BP16: 4701 | BQ16: 3420 | BR16: 3691 | BS16: 3335 | BT16: 3361 | BU16: 3021 | BV16: 3318 | BW16: 3853 | BX16: 3974 | BY16: 4020 | BZ16: 3975 | CA16: 4193 | CB16: 3866 | CC16: 3564 | CD16: 3940 | CE16: 3084 | CF16: 2578 | CG16: 3041 | CH16: 3414 | CI16: 3184 | CJ16: 4800.6316 | CK16: 3809 | CL16: 3994 | CM16: 3306 | CN16: 3861 | CO16: 3927 | CP16: 4814 | CQ16: 4246 | CR16: 4440 | ED16: x
A18: Return% | B18: =B14/B6 -> 0 | C18: =C14/C6 -> 0 | D18: =D14/D6 -> 0 | E18: =E14/E6 -> 0 | F18: =F14/F6 -> 0 | G18: =G14/G6 -> 0 | H18: =H14/H6 -> 0 | I18: =I14/I6 -> 0 | ... DQ18: =DQ14/DQ6 -> #DIV/0! | EC18: =EC14/EC6 -> #DIV/0! | ED18: x
ED19: x
A20: #RTO | ED20: x
A21: #Quality return | ED21: x
ED22: x
A23: Revenue Pre Tax (after returns) | B23: =B2-B10 -> 127373162 | C23: =C2-C10 -> 119526214 | D23: =D2-D10 -> 1.3361892e+08 | E23: =E2-E10 -> 1.5572126e+08 | F23: =F2-F10 -> 1.8292117e+08 | G23: =G2-G10 -> 190468885 | H23: =H2-H10 -> 203496304 | I23: =I2-I10 -> 191306750 | ... DQ23: =DQ2-DQ10 -> 0 | ED23: x
A24: Offline | AZ24: =AZ3-AZ11 -> 57315452 | BA24: =BA3-BA11 -> 62354498 | BB24: =BB3-BB11 -> 63129962 | BC24: =BC3-BC11 -> 1.123392e+08 | BD24: =BD3-BD11 -> 1.0043798e+08 | BE24: =BE3-BE11 -> 1.2019981e+08 | BF24: =BF3-BF11 -> 1.4746099e+08 | BG24: =BG3-BG11 -> 1.1183517e+08 | ... DQ24: =DQ3-DQ11 -> 0 | ED24: x
A25: Online | AZ25: =AZ4-AZ12 -> 1.964035e+08 | BA25: =BA4-BA12 -> 2.3299787e+08 | BB25: =BB4-BB12 -> 2.5172959e+08 | BC25: =BC4-BC12 -> 2.1067857e+08 | BD25: =BD4-BD12 -> 2.795535e+08 | BE25: =BE4-BE12 -> 2.9092817e+08 | BF25: =BF4-BF12 -> 3.7603826e+08 | BG25: =BG4-BG12 -> 3.6017512e+08 | ... DQ25: =DQ4-DQ12 -> 0 | ED25: x
ED26: x
A27: Tax | B27: 1571885 | C27: 1933226.9 | D27: 2144810.8 | E27: 2670744.5 | F27: 3520739.2 | G27: 3375803 | H27: 2640496 | I27: 3233060 | J27: 3701309 | K27: 2919247 | L27: 2007686 | M27: 2008229 | N27: 2074638.9 | O27: 2149447 | P27: 2794451.4 | Q27: 3291671.1 | R27: 3107953 | S27: 2375814.6 | T27: 2358981.6 | U27: 2789918.8 | V27: 2858485.1 | W27: 2908758.5 | X27: 3984937.7 | Y27: 2321371.6 | Z27: -1030.5643 | AA27: 3900614 | AB27: 3270039.7 | AC27: 2663850.8 | AD27: 4690032.1 | AE27: 4140394.6 | AF27: 3479215.8 | AG27: 4885138.6 | AH27: 5677808.9 | AI27: 4311081.9 | AJ27: 5245946.8 | AK27: 3879587.6 | AL27: 2963722 | AM27: 2026289 | AN27: 4833429.7 | AO27: 6484924.1 | AP27: 6968696.5 | AQ27: 6104232 | AR27: 5760470 | AS27: 4515277 | AT27: 5958902.2 | AU27: 5855167 | AV27: 5581986 | AW27: 5571264.4 | AX27: 4708314 | AY27: 6279353 | AZ27: =SUM(AZ28:AZ29) -> 4093538 | BA27: =SUM(BA28:BA29) -> 5519187.2 | BB27: =SUM(BB28:BB29) -> 5516764.6 | BC27: =SUM(BC28:BC29) -> 4791504.7 | BD27: =SUM(BD28:BD29) -> 6953816.6 | BE27: =SUM(BE28:BE29) -> 7179089.4 | BF27: =SUM(BF28:BF29) -> 10406552 | BG27: =SUM(BG28:BG29) -> 9057356 | ... DQ27: =SUM(DQ28:DQ29) -> 0 | ED27: x
A28: Offline | AZ28: 960772.07 | BA28: 1180105.8 | BB28: 1161482.7 | BC28: 1878845 | BD28: 1629749.6 | BE28: 2117305.1 | BF28: 1382356.2 | BG28: 779964.99 | BH28: 596616.3 | BI28: 653500.05 | BJ28: 475368.76 | BK28: 198593.3 | BL28: 139299.02 | BM28: 137603.5 | BN28: 146922.95 | BO28: 179555.22 | BP28: 263183.63 | BQ28: 210872.93 | BR28: 198148.78 | BS28: 102098.82 | BT28: 126079.52 | BU28: 193607.99 | BV28: 266230.94 | BW28: 104389.34 | BX28: 83506.939 | BY28: 171907.84 | BZ28: 119979.73 | CA28: 117804.4 | CB28: 73628.41 | CC28: 115456.84 | CD28: 108032.84 | CE28: 267402.99 | CF28: 403646.39 | CG28: 411033.32 | CH28: 222232.41 | CI28: 339234.07 | CJ28: 218144.36 | CK28: 418634.84 | CL28: 236448.76 | CM28: 197511.29 | CN28: 279793.06 | CO28: 444109.4 | CP28: 618311.15 | CQ28: 522041.17 | CR28: 550125.01 | ED28: x
A29: Online | AZ29: 3132765.9 | BA29: 4339081.4 | BB29: 4355281.9 | BC29: 2912659.7 | BD29: 5324067 | BE29: 5061784.3 | BF29: 9024195.8 | BG29: 8277391.1 | BH29: 6656547.8 | BI29: 7729670.7 | BJ29: 8363230.5 | BK29: 7156313.9 | BL29: 7022111.1 | BM29: 7815907.2 | BN29: 8136675.3 | BO29: 6020908 | BP29: 6350776.3 | BQ29: 7198305.9 | BR29: 5551900.4 | BS29: 5584592.1 | BT29: 7544686.7 | BU29: 7830571.5 | BV29: 8261600.7 | BW29: 8732766.7 | BX29: 8098787.9 | BY29: 7351110.3 | BZ29: 6390671.9 | CA29: 5169085 | CB29: 7376989.1 | CC29: 8396610 | CD29: 7479113.1 | CE29: 8702327.1 | CF29: 11041332 | CG29: 11266326 | CH29: 10768936 | CI29: 13780580 | CJ29: 16283897 | CK29: 12669575 | CL29: 11624734 | CM29: 11375144 | CN29: 13815388 | CO29: 15375280 | CP29: 17711509 | CQ29: 20663540 | CR29: 20888366 | ED29: x
A30: Tax% | ED30: x
ED31: x
A32: Revenue Post Tax (after returns) | B32: =B23-B27 -> 125801277 | C32: =C23-C27 -> 1.1759299e+08 | D32: =D23-D27 -> 1.3147411e+08 | E32: =E23-E27 -> 1.5305052e+08 | F32: =F23-F27 -> 1.7940043e+08 | G32: =G23-G27 -> 187093082 | H32: =H23-H27 -> 200855808 | I32: =I23-I27 -> 188073690 | ... DQ32: =DQ23-DQ27 -> 0 | ED32: x
A33: Offline | AZ33: =AZ24-AZ28 -> 56354680 | BA33: =BA24-BA28 -> 61174392 | BB33: =BB24-BB28 -> 61968479 | BC33: =BC24-BC28 -> 1.1046035e+08 | BD33: =BD24-BD28 -> 98808232 | BE33: =BE24-BE28 -> 1.1808251e+08 | BF33: =BF24-BF28 -> 1.4607863e+08 | BG33: =BG24-BG28 -> 1.1105521e+08 | ... DQ33: =DQ24-DQ28 -> 0 | ED33: x
A34: Online | AZ34: =AZ25-AZ29 -> 1.9327073e+08 | BA34: =BA25-BA29 -> 2.2865879e+08 | BB34: =BB25-BB29 -> 2.4737431e+08 | BC34: =BC25-BC29 -> 2.0776591e+08 | BD34: =BD25-BD29 -> 2.7422944e+08 | BE34: =BE25-BE29 -> 2.8586639e+08 | BF34: =BF25-BF29 -> 3.6701407e+08 | BG34: =BG25-BG29 -> 3.5189773e+08 | ... DQ34: =DQ25-DQ29 -> 0 | ED34: x
ED35: x
A36: Devices | B36: =B6-B14 -> 32077 | C36: =C6-C14 -> 28685 | D36: =D6-D14 -> 34758 | E36: =E6-E14 -> 39298 | F36: =F6-F14 -> 47222 | G36: =G6-G14 -> 49152 | H36: =H6-H14 -> 52716 | I36: =I6-I14 -> 52798 | ... DQ36: =DQ6-DQ14 -> 0 | ED36: x
A37: Offline | AZ37: =AZ7-AZ15 -> 9341 | BA37: =BA7-BA15 -> 10836 | BB37: =BB7-BB15 -> 10741 | BC37: =BC7-BC15 -> 21716 | BD37: =BD7-BD15 -> 13663 | BE37: =BE7-BE15 -> 17135 | BF37: =BF7-BF15 -> 20872 | BG37: =BG7-BG15 -> 15455 | ... DQ37: =DQ7-DQ15 -> 0 | ED37: x
A38: Online | AZ38: =AZ8-AZ16 -> 33582 | BA38: =BA8-BA16 -> 41888 | BB38: =BB8-BB16 -> 45010 | BC38: =BC8-BC16 -> 39036 | BD38: =BD8-BD16 -> 42741 | BE38: =BE8-BE16 -> 44380 | BF38: =BF8-BF16 -> 56885 | BG38: =BG8-BG16 -> 53389 | ... DQ38: =DQ8-DQ16 -> 0 | ED38: x
A39: ASP | ED39: x
ED40: x
ED41: x
A42: Growth% | ED42: x
A43: Revenue% | ED43: x
A44: Devices% | ED44: x
ED45: x
A46: COGS | ED46: x
A47: Buying Cost | ED47: x
A48: Spares & Consumables | ED48: x
A49: Warranty Cost t/f to D2C | ED49: x
A50: Inventory Writeoff | ED50: x
A51: Provision for inventory ageing | ED51: x
A52: Pick up Logistics Cost | ED52: x
A53: Engineers Cost | ED53: x
A54: Refurbishing Center Cost | ED54: x
ED55: x
A56: Offline | ED56: x
A57: Online | ED57: x
A58: CoGS% | ED58: x
ED59: x
A60: Gross Margin 1 | ED60: x
A61: Offline | ED61: x
A62: Online | ED62: x
ED63: x
A64: Gross Margin 1% | ED64: x
ED65: x
A66: Gross Margin 2 | ED66: x
A67: Offline | ED67: x
A68: Online | ED68: x
ED69: x
A70: Gross Margin 2% | ED70: x
A71: Offline | ED71: x
A72: Online | ED72: x
ED73: x
A74: Operational Cost | ED74: x
A75: Sales Logistics | ED75: x
A76: Warehousing | ED76: x
A77: Collection Cost | ED77: x
A78: Packaging | ED78: x
A79: Operational Cost% | ED79: x
ED80: x
A81: Contribution Margin 1 | ED81: x
A82: CM1% | ED82: x
ED83: x
A84: Direct Channel Cost | ED84: x
A85: Payroll (i + ii + iii) | ED85: x
A86: (i) Sales team | ED86: x
A87: #No. of Sales person | ED87: x
A88: KAA | ED88: x
A89: #No. of Managers | ED89: x
A90: (ii) Support | ED90: x
A91: #No. of people | ED91: x
A92: (iii) Dealer Onboarding cost | ED92: x
A93: #No. of Sales person | ED93: x
A94: Selling Center Cost | ED94: x
A95: Customer Support Cost | ED95: x
... A98: Direct Channel Cost% | ED98: x
ED99: x
A100: Contribution Margin 2 | ED100: x
A101: CM2% | ED101: x
ED102: x
A103: BTL Marketing | ED103: x
...

Sheet Summary Dashboard
C4: FY25 | D4: FY26 | E4: FY27 | F4: FY28
B5: Revenue
B6: B2B - Non Repair | C6: ='B2B- Non Repair'!FG32 -> 3.9389294e+09 | D6: ='B2B- Non Repair'!FH32 -> 5.8927142e+09 | E6: ='B2B- Non Repair'!FI32 -> 7.5558035e+09 | F6: ='B2B- Non Repair'!FJ32 -> 9.4447544e+09
B16: Gross Margin %
B17: B2B - Non Repair | C17: ='B2B- Non Repair'!FG70 -> 0.06359302 | D17: ='B2B- Non Repair'!FH70 -> 0.06863504 | E17: ='B2B- Non Repair'!FI70 -> 0.066490362 | F17: ='B2B- Non Repair'!FJ70 -> 0.075282652

Sheet P&L - Inputs
A1: Inputs Sheet | B1: 43208 | C1: 43238 | D1: 43269 | E1: 43282 | F1: 43313 | G1: 43344 | H1: 43374 | I1: 43405 | J1: 43435 | K1: 43466 | L1: 43497 | M1: 43525 | N1: 43556 | O1: 43586 | P1: 43617 | Q1: 43647 | R1: =Q1+31 -> 43678 | S1: =R1+31 -> 43709 | T1: =S1+31 -> 43740 | U1: =T1+31 -> 43771 | V1: =U1+31 -> 43802 | W1: =V1+31 -> 43833 | X1: =W1+31 -> 43864 | Y1: =X1+31 -> 43895 | ... BS1: =BR1+31 -> 45321 | BT1: =BS1+30 -> 45351 | BU1: =BT1+30 -> 45381 | BV1: =BU1+30 -> 45411 | BW1: =BV1+30 -> 45441 | BX1: =BW1+30 -> 45471 | BY1: =BX1+30 -> 45501 | BZ1: =BY1+30 -> 45531 | CA1: =BZ1+30 -> 45561 | ... EC1: =EB1+30 -> 47181 | ED1: x
ED2: x
A3: B2B - Non Repair | ED3: x
A4: Transaction growth % | N4: =N12/B12-1 -> 1.2569442 | O4: =O12/C12-1 -> 1.6365696 | P4: =P12/D12-1 -> 1.1973934 | Q4: =Q12/E12-1 -> 0.82309532 | R4: =R12/F12-1 -> 0.33929101 | S4: =S12/G12-1 -> 0.14467367 | T4: =T12/H12-1 -> -0.12652705 | U4: =U12/I12-1 -> 0.013466419 | ... CS4: =CS12/CG12-1 -> 0.006795688 | CT4: 0.33 | CU4: =CT4 -> 0.33 | CV4: =CU4 -> 0.33 | CW4: =CV4 -> 0.33 | CX4: =CW4 -> 0.33 | CY4: =CX4 -> 0.33 | CZ4: =CY4 -> 0.33 | DA4: =CZ4 -> 0.33 | DB4: =DA4 -> 0.33 | ... DE4: =DD4 -> 0.33 | DF4: 0.25 | DG4: =DF4 -> 0.25 | DH4: =DG4 -> 0.25 | DI4: =DH4 -> 0.25 | DJ4: =DI4 -> 0.25 | DK4: =DJ4 -> 0.25 | DL4: =DK4 -> 0.25 | DM4: =DL4 -> 0.25 | DN4: =DM4 -> 0.25 | ... DQ4: =DP4 -> 0.25 | DR4: 0.2 | DS4: =DR4 -> 0.2 | DT4: =DS4 -> 0.2 | DU4: =DT4 -> 0.2 | DV4: =DU4 -> 0.2 | DW4: =DV4 -> 0.2 | DX4: =DW4 -> 0.2 | DY4: =DX4 -> 0.2 | DZ4: =DY4 -> 0.2 | ... EC4: =EB4 -> 0.2 | ED4: x
ED5: x
A6: GMV | ED6: x
A7: Gross GMV | B7: 127373162 | C7: 119525214 | D7: 1.3361892e+08 | E7: 1.5572126e+08 | F7: 1.8292117e+08 | G7: 190468885 | H7: 203496304 | I7: 191306750 | J7: 241759536 | K7: 234336044 | L7: 2.3858167e+08 | M7: 208964937 | N7: 2.6952158e+08 | O7: 2.6688728e+08 | P7: 2.8626461e+08 | Q7: 292672912 | R7: 2.4150233e+08 | S7: 214319223 | T7: 181364156 | U7: 220788768 | V7: 2.5449597e+08 | W7: 257334479 | X7: 2.9379328e+08 | Y7: 182610351 | Z7: 0 | AA7: 140900548 | AB7: 146263086 | AC7: 119828870 | AD7: 200258733 | AE7: 206503898 | AF7: 186804306 | AG7: 2.2063889e+08 | AH7: 3.5443276e+08 | AI7: 3.059086e+08 | AJ7: 3.8260216e+08 | AK7: 3.2157717e+08 | AL7: 2.2184714e+08 | AM7: 1.0392815e+08 | AN7: 2.2950755e+08 | AO7: 322690111 | AP7: 3.1847108e+08 | AQ7: 3.0977751e+08 | AR7: 2.7614005e+08 | AS7: 3.141244e+08 | AT7: 4.2050482e+08 | AU7: 3.877668e+08 | AV7: 406585986 | AW7: 367317139 | AX7: 364497378 | AY7: 418830243 | AZ7: =AZ8+AZ9 -> 3.2287098e+08 | BA7: =BA8+BA9 -> 3.5962884e+08 | BB7: =BB8+BB9 -> 3.7669515e+08 | BC7: =BC8+BC9 -> 3.7649862e+08 | BD7: =BD8+BD9 -> 4.2638107e+08 | BE7: =BE8+BE9 -> 4.6466709e+08 | BF7: =BF8+BF9 -> 5.8646851e+08 | BG7: =BG8+BG9 -> 5.2943297e+08 | ... CS7: =CS8+CS9 -> 6.7110911e+08 | CT7: =CT12*CT18 -> 6.910943e+08 | CU7: =CU12*CU18 -> 7.1656878e+08 | CV7: =CV12*CV18 -> 6.8206219e+08 | CW7: =CW12*CW18 -> 6.812315e+08 | CX7: =CX12*CX18 -> 6.3516119e+08 | CY7: =CY12*CY18 -> 5.5227681e+08 | CZ7: =CZ12*CZ18 -> 6.4806984e+08 | DA7: =DA12*DA18 -> 7.9756762e+08 | ... EC7: =EC12*EC18 -> 1.179033e+09 | ED7: x
A8: Offline | AZ8: 57900213 | BA8: 62484773 | BB8: 63293292 | BC8: 1.1271932e+08 | BD8: 1.0161536e+08 | BE8: 1.2246949e+08 | BF8: 1.4776989e+08 | BG8: 1.1208485e+08 | BH8: 59806800 | BI8: 64466321 | BJ8: 39228577 | BK8: 32647113 | BL8: 33153913 | BM8: 15345796 | BN8: 12681235 | BO8: 18397365 | BP8: 28562914 | BQ8: 51819029 | BR8: 42511549 | BS8: 26524843 | BT8: 18495206 | BU8: 31427878 | BV8: 27850812 | BW8: 22729297 | BX8: 10946710 | BY8: 21263730 | BZ8: 29270284 | CA8: 35801443 | CB8: 25116076 | CC8: 15694579 | CD8: 35993006 | CE8: 54975279 | CF8: 35182058 | CG8: 70684511 | CH8: 57976140 | CI8: 56362233 | CJ8: 25843707 | CK8: 29562162 | CL8: 19353126 | CM8: 16747344 | CN8: 22624143 | CO8: 41629922 | CP8: 72883676 | CQ8: 54851941 | CR8: 38432467 | CS8: 26174248 | CT8: =CS8/CS$7*CT$7 -> 26953699 | CU8: =CT8/CT$7*CU$7 -> 27947242 | CV8: =CU8/CU$7*CV$7 -> 26601434 | CW8: =CV8/CV$7*CW$7 -> 26569036 | CX8: =CW8/CW$7*CX$7 -> 24772225 | CY8: =CX8/CX$7*CY$7 -> 21539612 | CZ8: =CY8/CY$7*CZ$7 -> 25275682 | DA8: =CZ8/CZ$7*DA$7 -> 31106316 | ... EC8: =EB8/EB$7*EC$7 -> 45984030 | ED8: x
A9: Online | AZ9: 2.6497076e+08 | BA9: 2.9714407e+08 | BB9: 3.1340186e+08 | BC9: 2.637793e+08 | BD9: 3.247657e+08 | BE9: 3.421976e+08 | BF9: 4.3869863e+08 | BG9: 4.1734813e+08 | BH9: 3.7824561e+08 | BI9: 4.1863154e+08 | BJ9: 4.2592753e+08 | BK9: 4.3511469e+08 | BL9: 3.2300388e+08 | BM9: 3.2850307e+08 | BN9: 3.4456507e+08 | BO9: 3.2209393e+08 | BP9: 2.884787e+08 | BQ9: 3.1590853e+08 | BR9: 2.9801067e+08 | BS9: 2.8335834e+08 | BT9: 3.0843154e+08 | BU9: 2.9969907e+08 | BV9: 3.1798799e+08 | BW9: 3.3608515e+08 | BX9: 3.2954318e+08 | BY9: 3.0327311e+08 | BZ9: 2.8538817e+08 | CA9: 2.4773517e+08 | CB9: 3.0363596e+08 | CC9: 3.1660862e+08 | CD9: 3.3832818e+08 | CE9: 3.6436917e+08 | CF9: 4.4184371e+08 | CG9: 5.2195693e+08 | CH9: 4.5438369e+08 | CI9: 4.5251806e+08 | CJ9: 4.9366874e+08 | CK9: 4.7876586e+08 | CL9: 4.1957962e+08 | CM9: 3.5971942e+08 | CN9: 4.5657266e+08 | CO9: 5.2491022e+08 | CP9: 6.1854909e+08 | CQ9: 6.8487692e+08 | CR9: 6.4630524e+08 | CS9: 6.4493486e+08 | CT9: =CS9/CS$7*CT$7 -> 6.641406e+08 | CU9: =CT9/CT$7*CU$7 -> 6.8862154e+08 | CV9: =CU9/CU$7*CV$7 -> 6.5546076e+08 | CW9: =CV9/CV$7*CW$7 -> 6.5466247e+08 | CX9: =CW9/CW$7*CX$7 -> 6.1038896e+08 | CY9: =CX9/CX$7*CY$7 -> 5.307372e+08 | CZ9: =CY9/CY$7*CZ$7 -> 6.2279416e+08 | DA9: =CZ9/CZ$7*DA$7 -> 7.664613e+08 | ... EC9: =EB9/EB$7*EC$7 -> 1.133049e+09 | ED9: x
ED10: x
A11: Devices | ED11: x
A12: Devices sold | B12: 32077 | C12: 28685 | D12: 34758 | E12: 39298 | F12: 47222 | G12: 49152 | H12: 52716 | I12: 52798 | J12: 67323 | K12: 62990 | L12: 67278 | M12: 53088 | N12: 72396 | O12: 75630 | P12: 76377 | Q12: 71644 | R12: 63244 | S12: 56263 | T12: 46046 | U12: 53509 | V12: 66574 | W12: 66672 | X12: 82936 | Y12: 53988 | Z12: 0 | AA12: 39616 | AB12: 42186 | AC12: 23110 | AD12: 42469 | AE12: 37673 | AF12: 38371 | AG12: 52592 | AH12: 66087 | AI12: 50483 | AJ12: 69399 | AK12: 58903 | AL12: 39902 | AM12: 20877 | AN12: 46075 | AO12: 67308 | AP12: 70639 | AQ12: 66964 | AR12: 60018 | AS12: 75086 | AT12: 92309 | AU12: 84249 | AV12: 78598 | AW12: 72738 | AX12: 67201 | AY12: 75950 | AZ12: =AZ13+AZ14 -> 55593 | BA12: =BA13+BA14 -> 62571 | BB12: =BB13+BB14 -> 65439 | BC12: =BC13+BC14 -> 69439 | BD12: =BD13+BD14 -> 64427 | BE12: =BE13+BE14 -> 69556 | BF12: =BF13+BF14 -> 86447 | BG12: =BG13+BG14 -> 76462 | ... EC12: =EC13+EC14 -> 118926.68 | ED12: x
A13: # Offline sales | AZ13: 9439 | BA13: 10854 | BB13: 10760 | BC13: 21806 | BD13: 13898 | BE13: 17371 | BF13: 20911 | BG13: 15473 | BH13: 10466 | BI13: 13386 | BJ13: 5025 | BK13: 4403 | BL13: 5764 | BM13: 3408 | BN13: 2073 | BO13: 3244 | BP13: 5103 | BQ13: 13036 | BR13: 4139 | BS13: 3210 | BT13: 2867 | BU13: 4925 | BV13: 4229 | BW13: 3319 | BX13: 2009 | BY13: 4449 | BZ13: 4259 | CA13: 4375 | CB13: 2935 | CC13: 2537 | CD13: 7861 | CE13: 12311 | CF13: 5940 | CG13: 10233 | CH13: 8955 | CI13: 9131 | CJ13: 3136 | CK13: 4004 | CL13: 2650 | CM13: 3295 | CN13: 2653 | CO13: 6330 | CP13: 7285 | CQ13: 4480 | CR13: 3629.5641 | CS13: 2417.3727 | CT13: =CH13*(1+CT4) -> 11910.15 | CU13: =CI13*(1+CU4) -> 12144.23 | CV13: =CJ13*(1+CV4) -> 4170.88 | CW13: =CK13*(1+CW4) -> 5325.32 | CX13: =CL13*(1+CX4) -> 3524.5 | CY13: =CM13*(1+CY4) -> 4382.35 | CZ13: =CN13*(1+CZ4) -> 3528.49 | DA13: =CO13*(1+DA4) -> 8418.9 | ... EC13: =DQ13*(1+EC4) -> 4822.6585 | ED13: x
A14: # Online sales | AZ14: 46154 | BA14: 51717 | BB14: 54679 | BC14: 47633 | BD14: 50529 | BE14: 52185 | BF14: 65536 | BG14: 60989 | BH14: 51027 | BI14: 57821 | BJ14: 56250 | BK14: 54644 | BL14: 37687 | BM14: 40718 | BN14: 45738 | BO14: 43900 | BP14: 34529 | BQ14: 33684 | BR14: 30780 | BS14: 29203 | BT14: 30576 | BU14: 28090 | BV14: 30573 | BW14: 35825 | BX14: 35853 | BY14: 35328 | BZ14: 31014 | CA14: 27470 | CB14: 30565 | CC14: 33360 | CD14: 37963 | CE14: 38551 | CF14: 40985 | CG14: 48977 | CH14: 43458 | CI14: 45214 | CJ14: 48592 | CK14: 47661 | CL14: 45521 | CM14: 38590 | CN14: 46497 | CO14: 54158 | CP14: 60087 | CQ14: 58857 | CR14: 58229 | CS14: 57195 | CT14: =CH14*(1+CT4) -> 57799.14 | CU14: =CI14*(1+CU4) -> 60134.62 | CV14: =CJ14*(1+CV4) -> 64627.36 | CW14: =CK14*(1+CW4) -> 63389.13 | CX14: =CL14*(1+CX4) -> 60542.93 | CY14: =CM14*(1+CY4) -> 51324.7 | CZ14: =CN14*(1+CZ4) -> 61841.01 | DA14: =CO14*(1+DA4) -> 72030.14 | ... EC14: =DQ14*(1+EC4) -> 114104.02 | ED14: x
A15: Offline % | AZ15: =AZ13/AZ$12 -> 0.16978756 | BA15: =BA13/BA$12 -> 0.17346694 | BB15: =BB13/BB$12 -> 0.16442794 | BC15: =BC13/BC$12 -> 0.31403102 | BD15: =BD13/BD$12 -> 0.21571701 | BE15: =BE13/BE$12 -> 0.24974122 | BF15: =BF13/BF$12 -> 0.24189388 | BG15: =BG13/BG$12 -> 0.20236196 | ... CS15: =CS13/CS$12 -> 0.040551526 | CT15: =CT13/CT12 -> 0.17085456 | CU15: =CU13/CU12 -> 0.16801914 | CV15: =CV13/CV12 -> 0.060624807 | CW15: =CW13/CW12 -> 0.077499274 | CX15: =CX13/CX12 -> 0.055012352 | CY15: =CY13/CY12 -> 0.078667781 | CZ15: =CZ13/CZ12 -> 0.05397762 | DA15: =DA13/DA12 -> 0.10464886 | ... EC15: =EC13/EC12 -> 0.040551526 | ED15: x
A16: Online % | AZ16: =AZ14/AZ$12 -> 0.83021244 | BA16: =BA14/BA$12 -> 0.82653306 | BB16: =BB14/BB$12 -> 0.83557206 | BC16: =BC14/BC$12 -> 0.68596898 | BD16: =BD14/BD$12 -> 0.78428299 | BE16: =BE14/BE$12 -> 0.75025878 | BF16: =BF14/BF$12 -> 0.75810612 | BG16: =BG14/BG$12 -> 0.79763804 | ... CS16: =CS14/CS$12 -> 0.95944847 | CT16: =CT14/CT12 -> 0.82914544 | CU16: =CU14/CU12 -> 0.83198086 | CV16: =CV14/CV12 -> 0.93937519 | CW16: =CW14/CW12 -> 0.92250073 | CX16: =CX14/CX12 -> 0.94498765 | CY16: =CY14/CY12 -> 0.92133222 | CZ16: =CZ14/CZ12 -> 0.94602238 | DA16: =DA14/DA12 -> 0.89535114 | ... EC16: =EC14/EC12 -> 0.95944847 | ED16: x
ED17: x
A18: Average Selling Price | B18: =B7/B12 -> 3970.8564 | C18: =C7/C12 -> 4166.8194 | D18: =D7/D12 -> 3844.2636 | E18: =E7/E12 -> 3962.5747 | F18: =F7/F12 -> 3873.6431 | G18: =G7/G12 -> 3875.0994 | H18: =H7/H12 -> 3860.238 | I18: =I7/I12 -> 3623.3712 | ... CS18: =CS7/CS12 -> 11257.883 | CT18: =SUM(CH7:CS7)/SUM(CH12:CS12)*(1+CT19) -> 9913.9483 | CU18: =CT18*(1+CU19) -> 9913.9483 | CV18: =CU18*(1+CV19) -> 9913.9483 | CW18: =CV18*(1+CW19) -> 9913.9483 | CX18: =CW18*(1+CX19) -> 9913.9483 | CY18: =CX18*(1+CY19) -> 9913.9483 | CZ18: =CY18*(1+CZ19) -> 9913.9483 | DA18: =CZ18*(1+DA19) -> 9913.9483 | DB18: =DA18*(1+DB19) -> 9913.9483 | ... EC18: =EB18*(1+EC19) -> 9913.9483 | ED18: x
A19: ASP Growth % | BJ19: =BJ18/BI18-1 -> 0.11893015 | BK19: =BK18/BJ18-1 -> 0.043545781 | BL19: =BL18/BK18-1 -> 0.034703137 | BM19: =BM18/BL18-1 -> -0.049328764 | BN19: =BN18/BM18-1 -> -0.041114214 | BO19: =BO18/BN18-1 -> -0.033415845 | BP19: =BP18/BO18-1 -> 0.10761976 | BQ19: =BQ18/BP18-1 -> -0.016095231 | ... CS19: =CS18/CR18-1 -> 0.017026615 | CT19: -0.02 | DE19: 0 | DQ19: 0 | ED19: x
ED20: x
A21: Returns | ED21: x
A22: Return Amount | B22: 0 | C22: 0 | D22: 0 | E22: 0 | F22: 0 | G22: 0 | H22: 0 | I22: 0 | J22: 0 | K22: 0 | L22: 0 | M22: 0 | N22: 73665.555 | O22: 18545.06 | P22: 35350.414 | Q22: 313486.29 | R22: 1159355.2 | S22: 1898625.9 | T22: 1537513.1 | U22: 1643258.5 | V22: 3134468.3 | W22: 3493815.9 | X22: 2214325.7 | Y22: 681691.8 | Z22: 58689 | AA22: 78042.06 | AB22: 302378.05 | AC22: 90474.93 | AD22: 203264.43 | AE22: 1361023.8 | AF22: 2293737.3 | AG22: 2573237.4 | AH22: 2807817 | AI22: 3084430.9 | AJ22: 3797965.8 | AK22: 4332916.3 | AL22: 3505842.3 | AM22: 4420191.5 | AN22: 8957793.6 | AO22: 13662088 | AP22: 16041871 | AQ22: 25276687 | AR22: 33122634 | AS22: 23397431 | AT22: 30706134 | AU22: 32573536 | AV22: 43288241 | AW22: 50451902 | AX22: 49613456 | AY22: 64881764 | AZ22: =AZ23+AZ24 -> 69152023 | BA22: =BA23+BA24 -> 64276477 | BB22: =BB23+BB24 -> 61835594 | BC22: =BC23+BC24 -> 53480848 | BD22: =BD23+BD24 -> 46389583 | BE22: =BE23+BE24 -> 53529111 | BF22: =BF23+BF24 -> 62969264 | BG22: =BG23+BG24 -> 57422683 | ... EC22: =EC23+EC24 -> 1.2733613e+08 | ED22: x
A23: Offline | AZ23: 584761.33 | BA23: 130274.59 | BB23: 163329.98 | BC23: 380127.04 | BD23: 1177382.5 | BE23: 2259684.6 | BF23: 308900.99 | BG23: 249670.93 | BH23: 568887.69 | BI23: 1351325 | BJ23: 489349 | BK23: 596455.25 | BL23: 152981.59 | BM23: 200262.42 | BN23: 27457.577 | BO23: 201581.7 | BP23: 2088827.9 | BQ23: 270666.24 | BR23: 88826.571 | BS23: 720660.15 | BT23: 1462117.2 | BU23: 1052057 | BV23: 645068.35 | BW23: 639875.17 | BX23: 851158.77 | BY23: 95498.433 | BZ23: 100441.8 | CA23: 86477.185 | CB23: 313479.17 | CC23: 280926.05 | CD23: 185949.37 | CE23: 12510.888 | CF23: 62892.962 | CG23: 90180.167 | CH23: 147495.14 | CI23: 1251985.5 | CJ23: 55430.529 | CK23: 246236.78 | CL23: 54944.39 | CM23: 93690.25 | CN23: 29481.83 | CO23: 111605.68 | CP23: 311799.45 | CQ23: 120490.87 | CR23: 29857.06 | CS23: 112658.46 | CT23: =CS23/CS27*CT27 -> 270750.95 | CU23: =CT23/CT27*CU27 -> 276072.24 | CV23: =CU23/CU27*CV27 -> 94815.742 | CW23: =CV23/CV27*CW27 -> 121059.38 | CX23: =CW23/CW27*CX27 -> 80121.721 | CY23: =CX23/CX27*CY27 -> 99623.045 | CZ23: =CY23/CY27*CZ27 -> 80212.425 | DA23: =CZ23/CZ27*DA27 -> 191385.09 | ... EC23: =EB23/EB27*EC27 -> 109632.49 | ED23: x
A24: Online | AZ24: 68567261 | BA24: 64146203 | BB24: 61672264 | BC24: 53100721 | BD24: 45212201 | BE24: 51269427 | BF24: 62660363 | BG24: 57173013 | BH24: 57521228 | BI24: 61272930 | BJ24: 76047181 | BK24: 72098825 | BL24: 55542143 | BM24: 59960809 | BN24: 56538940 | BO24: 50706878 | BP24: 42722467 | BQ24: 33017650 | BR24: 39291725 | BS24: 37875847 | BT24: 40077373 | BU24: 34575290 | BV24: 38382767 | BW24: 40540331 | BX24: 36969260 | BY24: 38326106 | BZ24: 38440252 | CA24: 41192892 | CB24: 38187234 | CC24: 35123003 | CD24: 38377281 | CE24: 34152064 | CF24: 31020347 | CG24: 38758008 | CH24: 42143225 | CI24: 41219534 | CJ24: 59098386 | CK24: 46927371 | CL24: 50189998 | CM24: 40320148 | CN24: 43616763 | CO24: 43585970 | CP24: 57750700 | CQ24: 58166177 | CR24: 62582269 | CS24: 66033595 | CT24: =CS24/CS28*CT28 -> 64446297 | CU24: =CT24/CT28*CU28 -> 67050368 | CV24: =CU24/CU28*CV28 -> 72059793 | CW24: =CV24/CV28*CW28 -> 70679161 | CX24: =CW24/CW28*CX28 -> 67505635 | CY24: =CX24/CX28*CY28 -> 57227268 | CZ24: =CY24/CY28*CZ28 -> 68953000 | DA24: =CZ24/CZ28*DA28 -> 80313925 | ... EC24: =EB24/EB28*EC28 -> 1.2722649e+08 | ED24: x
ED25: x
A26: Devices | B26: 0 | C26: 0 | D26: 0 | E26: 0 | F26: 0 | G26: 0 | H26: 0 | I26: 0 | J26: 0 | K26: 0 | L26: 0 | M26: 0 | N26: 9 | O26: 1 | P26: 4 | Q26: 31 | R26: 137 | S26: 193 | T26: 159 | U26: 148 | V26: 325 | W26: 451 | X26: 337 | Y26: 109 | Z26: 9 | AA26: 1 | AB26: 42 | AC26: 9 | AD26: 41 | AE26: 163 | AF26: 338 | AG26: 440 | AH26: 464 | AI26: 386 | AJ26: 487 | AK26: 544 | AL26: 529 | AM26: 751 | AN26: 1454 | AO26: 2406 | AP26: 3125 | AQ26: 4565 | AR26: 5997 | AS26: 4301 | AT26: 5405 | AU26: 5899 | AV26: 7326 | AW26: 8324 | AX26: 8454 | AY26: 11659 | AZ26: =AZ27+AZ28 -> 12670 | BA26: =BA27+BA28 -> 9847 | BB26: =BB27+BB28 -> 9688 | BC26: =BC27+BC28 -> 8687 | BD26: =BD27+BD28 -> 8023 | BE26: =BE27+BE28 -> 8041 | BF26: =BF27+BF28 -> 8690 | BG26: =BG27+BG28 -> 7618 | ... EC26: =EC27+EC28 -> 9221.2526 | ED26: x
A27: Offline | AZ27: 98 | BA27: 18 | BB27: 19 | BC27: 90 | BD27: 235 | BE27: 236 | BF27: 39 | BG27: 18 | BH27: 44 | BI27: 301 | BJ27: 33 | BK27: 36 | BL27: 13 | BM27: 11 | BN27: 3 | BO27: 16 | BP27: 101 | BQ27: 15 | BR27: 6 | BS27: 37 | BT27: 65 | BU27: 53 | BV27: 32 | BW27: 25 | BX27: 47 | BY27: 7 | BZ27: 5 | CA27: 4 | CB27: 20 | CC27: 19 | CD27: 12 | CE27: 1 | CF27: 4 | CG27: 5 | CH27: 7 | CI27: 38 | CJ27: 5 | CK27: 11 | CL27: 3 | CM27: 7 | CN27: 2 | CO27: 15 | CP27: 20 | CQ27: 5 | CR27: 2 | CS27: 10 | CT27: =CT13*CT30 -> 24.0329 | CU27: =CU13*CU30 -> 24.505238 | CV27: =CV13*CV30 -> 8.4162114 | CW27: =CW13*CW30 -> 10.745699 | CX27: =CX13*CX30 -> 7.1119134 | CY27: =CY13*CY30 -> 8.8429262 | CZ27: =CZ13*CZ30 -> 7.1199646 | DA27: =DA13*DA30 -> 16.98808 | ... EC27: =EC13*EC30 -> 9.7314029 | ED27: x
A28: Online | AZ28: 12572 | BA28: 9829 | BB28: 9669 | BC28: 8597 | BD28: 7788 | BE28: 7805 | BF28: 8651 | BG28: 7600 | BH28: 7097 | BI28: 7443 | BJ28: 9147 | BK28: 8142 | BL28: 6160 | BM28: 6257 | BN28: 6524 | BO28: 5654 | BP28: 4701 | BQ28: 3420 | BR28: 3691 | BS28: 3335 | BT28: 3361 | BU28: 3021 | BV28: 3318 | BW28: 3853 | BX28: 3974 | BY28: 4020 | BZ28: 3975 | CA28: 4193 | CB28: 3866 | CC28: 3564 | CD28: 3940 | CE28: 3084 | CF28: 2578 | CG28: 3041 | CH28: 3414 | CI28: 3184 | CJ28: 4800.6316 | CK28: 3809 | CL28: 3994 | CM28: 3306 | CN28: 3861 | CO28: 3927 | CP28: 4814 | CQ28: 4246 | CR28: 4440 | CS28: 4781 | CT28: =CT14*CT31 -> 4666.0756 | CU28: =CU14*CU31 -> 4854.6169 | CV28: =CV14*CV31 -> 5217.312 | CW28: =CW14*CW31 -> 5117.3507 | CX28: =CX14*CX31 -> 4887.5794 | CY28: =CY14*CY31 -> 4143.3995 | CZ28: =CZ14*CZ31 -> 4992.3723 | DA28: =DA14*DA31 -> 5814.9321 | ... EC28: =EC14*EC31 -> 9211.5212 | ED28: x
ED29: x
A30: Offline Returns % | AZ30: =AZ27/AZ13 -> 0.010382456 | BA30: =BA27/BA13 -> 0.0016583748 | BB30: =BB27/BB13 -> 0.0017657993 | BC30: =BC27/BC13 -> 0.0041273044 | BD30: =BD27/BD13 -> 0.016908908 | BE30: =BE27/BE13 -> 0.013585861 | BF30: =BF27/BF13 -> 0.0018650471 | BG30: =BG27/BG13 -> 0.0011633167 | ... CS30: =CS27/CS13 -> 0.0041367225 | CT30: =AVERAGE(CH30:CS30) -> 0.0020178503 | CU30: =CT30 -> 0.0020178503 | CV30: =CU30 -> 0.0020178503 | CW30: =CV30 -> 0.0020178503 | CX30: =CW30 -> 0.0020178503 | CY30: =CX30 -> 0.0020178503 | CZ30: =CY30 -> 0.0020178503 | DA30: =CZ30 -> 0.0020178503 | DB30: =DA30 -> 0.0020178503 | ... EC30: =EB30 -> 0.0020178503 | ED30: x
A31: Online Returns % | AZ31: =AZ28/AZ14 -> 0.27239243 | BA31: =BA28/BA14 -> 0.19005356 | BB31: =BB28/BB14 -> 0.17683206 | BC31: =BC28/BC14 -> 0.18048412 | BD31: =BD28/BD14 -> 0.15412931 | BE31: =BE28/BE14 -> 0.14956405 | BF31: =BF28/BF14 -> 0.13200378 | BG31: =BG28/BG14 -> 0.12461264 | ... CS31: =CS28/CS14 -> 0.083591223 | CT31: =AVERAGE(CH31:CS31) -> 0.080729152 | CU31: =CT31 -> 0.080729152 | CV31: =CU31 -> 0.080729152 | CW31: =CV31 -> 0.080729152 | CX31: =CW31 -> 0.080729152 | CY31: =CX31 -> 0.080729152 | CZ31: =CY31 -> 0.080729152 | DA31: =CZ31 -> 0.080729152 | DB31: =DA31 -> 0.080729152 | ... EC31: =EB31 -> 0.080729152 | ED31: x
A32: Overall Returns % | B32: =B26/B12 -> 0 | C32: =C26/C12 -> 0 | D32: =D26/D12 -> 0 | E32: =E26/E12 -> 0 | F32: =F26/F12 -> 0 | G32: =G26/G12 -> 0 | H32: =H26/H12 -> 0 | I32: =I26/I12 -> 0 | ... EC32: =EC26/EC12 -> 0.077537289 | ED32: x
ED33: x
A34: #RTO | BJ34: 2808 | BK34: 2199 | BL34: 1827 | BM34: 1972 | BN34: 2125 | BO34: 1865 | BP34: 2217 | BQ34: 1759 | BR34: 1747 | BS34: 1552 | BT34: 1601 | BU34: 1548 | BV34: 1590 | BW34: 1999 | BX34: 2365 | BY34: 2005 | BZ34: 2244 | CA34: 2492 | CB34: 1813 | CC34: 2113 | CD34: 2171 | CE34: 1344 | CF34: 912 | CG34: 1088 | CH34: 1054 | CI34: 1054 | CJ34: 1012 | CK34: 1342 | CL34: 1336 | CM34: 1834 | CN34: 1779 | CO34: 1744 | CP34: 2046 | CQ34: 1301 | CR34: 1320 | CS34: 1363 | CT34: =CS34/CS26*CT26 -> 1334.2972 | CU34: =CT34/CT26*CU26 -> 1388.07 | CV34: =CU34/CU26*CV26 -> 1486.6766 | CW34: =CV34/CV26*CW26 -> 1458.9012 | CX34: =CW34/CW26*CX26 -> 1392.4993 | CY34: =CX34/CX26*CY26 -> 1181.2787 | CZ34: =CY34/CY26*CZ26 -> 1422.3143 | DA34: =CZ34/CZ26*DA26 -> 1659.1332 | ... EC34: =EB34/EB26*EC26 -> 2623.3703 | ED34: x
A35: #Quality return | BJ35: =BJ26-BJ34 -> 6372 | BK35: =BK26-BK34 -> 5979 | BL35: =BL26-BL34 -> 4346 | BM35: =BM26-BM34 -> 4296 | BN35: =BN26-BN34 -> 4402 | BO35: =BO26-BO34 -> 3805 | BP35: =BP26-BP34 -> 2585 | BQ35: =BQ26-BQ34 -> 1676 | ... EC35: =EC26-EC34 -> 6597.8823 | ED35: x
ED36: x
A37: Revenue Pre Tax (after returns) | B37: =B7-B22 -> 127373162 | C37: =C7-C22 -> 119525214 | D37: =D7-D22 -> 1.3361892e+08 | E37: =E7-E22 -> 1.5572126e+08 | F37: =F7-F22 -> 1.8292117e+08 | G37: =G7-G22 -> 190468885 | H37: =H7-H22 -> 203496304 | I37: =I7-I22 -> 191306750 | ... AY37: =AY7-AY22 -> 353948479 | AZ37: =AZ38+AZ39 -> 2.5371895e+08 | BA37: =BA38+BA39 -> 2.9535237e+08 | BB37: =BB38+BB39 -> 3.1485956e+08 | BC37: =BC38+BC39 -> 3.2301777e+08 | BD37: =BD38+BD39 -> 3.7999148e+08 | BE37: =BE38+BE39 -> 4.1113798e+08 | BF37: =BF38+BF39 -> 5.2349925e+08 | BG37: =BG38+BG39 -> 4.7201029e+08 | ... EC37: =EC38+EC39 -> 1.0516969e+09 | ED37: x
A38: Offline | AZ38: =AZ8-AZ23 -> 57315452 | BA38: =BA8-BA23 -> 62354498 | BB38: =BB8-BB23 -> 63129962 | BC38: =BC8-BC23 -> 1.123392e+08 | BD38: =BD8-BD23 -> 1.0043798e+08 | BE38: =BE8-BE23 -> 1.2020981e+08 | BF38: =BF8-BF23 -> 1.4746099e+08 | BG38: =BG8-BG23 -> 1.1183517e+08 | ... EC38: =EC8-EC23 -> 45874397 | ED38: x
A39: Online | AZ39: =AZ9-AZ24 -> 1.964035e+08 | BA39: =BA9-BA24 -> 2.3299787e+08 | BB39: =BB9-BB24 -> 2.5172959e+08 | BC39: =BC9-BC24 -> 2.1067857e+08 | BD39: =BD9-BD24 -> 2.795535e+08 | BE39: =BE9-BE24 -> 2.9092817e+08 | BF39: =BF9-BF24 -> 3.7603826e+08 | BG39: =BG9-BG24 -> 3.6017512e+08 | ... EC39: =EC9-EC24 -> 1.0058225e+09 | ED39: x
ED40: x
ED41: x
A42: Tax | B42: 1571885 | C42: 1933225.9 | D42: 2144810.8 | E42: 2670744.5 | F42: 3520739.2 | G42: 3375803 | H42: 2640496 | I42: 3233060 | J42: 3701309 | K42: 2919247 | L42: 2007686 | M42: 2008229 | N42: 2074638.9 | O42: 2149447 | P42: 2794451.4 | Q42: 3291671.1 | R42: 3107953 | S42: 2375814.6 | T42: 2358981.6 | U42: 2789918.8 | V42: 2858485.1 | W42: 2908758.5 | X42: 3984937.7 | Y42: 2321371.6 | Z42: -1030.5643 | AA42: 3900614 | AB42: 3270039.7 | AC42: 2663850.8 | AD42: 4690032.1 | AE42: 4140394.6 | AF42: 3479215.8 | AG42: 4885138.6 | AH42: 5677808.9 | AI42: 4311081.9 | AJ42: 5245946.8 | AK42: 3879587.6 | AL42: 2963722 | AM42: 2025289 | AN42: 4833429.7 | AO42: 6484924.1 | AP42: 6968696.5 | AQ42: 6104232 | AR42: 5760470 | AS42: 4515277 | AT42: 5958902.2 | AU42: 5855167 | AV42: 5581986 | AW42: 5571264.4 | AX42: 4708314 | AY42: 6279353 | AZ42: =AZ43+AZ44 -> 4093538 | BA42: =BA43+BA44 -> 5519187.2 | BB42: =BB43+BB44 -> 5516764.6 | BC42: =BC43+BC44 -> 4791404.7 | BD42: =BD43+BD44 -> 6953816.6 | BE42: =BE43+BE44 -> 7179089.4 | BF42: =BF43+BF44 -> 10406552 | BG42: =BG43+BG44 -> 9057356 | ... EC42: =EC43+EC44 -> 37029906 | ED42: x
A43: Offline | AZ43: 960772.07 | BA43: 1180105.8 | BB43: 1161482.7 | BC43: 1878845 | BD43: 1629749.6 | BE43: 2117305.1 | BF43: 1382356.2 | BG43: 779964.99 | BH43: 596616.3 | BI43: 653500.05 | BJ43: 475368.76 | BK43: 198593.3 | BL43: 139299.02 | BM43: 137603.5 | BN43: 146922.95 | BO43: 179555.22 | BP43: 263183.63 | BQ43: 210872.93 | BR43: 198148.78 | BS43: 102098.82 | BT43: 125079.52 | BU43: 193607.99 | BV43: 256230.94 | BW43: 104389.34 | BX43: 83506.939 | BY43: 171907.84 | BZ43: 119979.73 | CA43: 117804.4 | CB43: 73628.41 | CC43: 115456.84 | CD43: 108032.84 | CE43: 267402.99 | CF43: 403646.39 | CG43: 411033.32 | CH43: 222232.41 | CI43: 339234.07 | CJ43: 218144.36 | CK43: 418634.84 | CL43: 236448.76 | CM43: 197511.29 | CN43: 279793.06 | CO43: 444109.4 | CP43: 618311.15 | CQ43: 522041.17 | CR43: 550125.01 | CS43: 352470.32 | CT43: =CS43/CS38*CT38 -> 360873.9 | CU43: =CT43/CT38*CU38 -> 374239.11 | CV43: =CU43/CU38*CV38 -> 358489.12 | CW43: =CV43/CV38*CW38 -> 357696.02 | CX43: =CW43/CW38*CX38 -> 333948.7 | CY43: =CX43/CX38*CY38 -> 289965.43 | CZ43: =CY43/CY38*CZ38 -> 340756.47 | DA43: =CZ43/CZ38*DA38 -> 418109.41 | ... EC43: =EB43/EB38*EC38 -> 620428.92 | ED43: x
A44: Online | AZ44: 3132765.9 | BA44: 4339081.4 | BB44: 4355281.9 | BC44: 2912559.7 | BD44: 5324067 | BE44: 5061784.3 | BF44: 9024195.8 | BG44: 8277391.1 | BH44: 6656547.8 | BI44: 7729670.7 | BJ44: 8363230.5 | BK44: 7156313.9 | BL44: 7022111.1 | BM44: 7815907.2 | BN44: 8136675.3 | BO44: 6020908 | BP44: 6350776.3 | BQ44: 7198305.9 | BR44: 5551900.4 | BS44: 5584592.1 | BT44: 7544686.7 | BU44: 7830571.5 | BV44: 8261600.7 | BW44: 8732766.7 | BX44: 8098787.9 | BY44: 7351110.3 | BZ44: 6390671.9 | CA44: 5169085 | CB44: 7376989.1 | CC44: 8396610 | CD44: 7479113.1 | CE44: 8702327.1 | CF44: 11041332 | CG44: 11266326 | CH44: 10768936 | CI44: 13780580 | CJ44: 16283897 | CK44: 12669575 | CL44: 11624734 | CM44: 11375144 | CN44: 13815388 | CO44: 15375280 | CP44: 17711509 | CQ44: 20663540 | CR44: 20888366 | CS44: 20955480 | CT44: =CS44/CS39*CT39 -> 21708161 | CU44: =CT44/CT39*CU39 -> 22500075 | CV44: =CU44/CU39*CV39 -> 21118363 | CW44: =CV44/CV39*CW39 -> 21139443 | CX44: =CW44/CW39*CX39 -> 19651677 | CY44: =CX44/CX39*CY39 -> 17140449 | CZ44: =CY44/CY39*CZ39 -> 20048336 | DA44: =CZ44/CZ39*DA39 -> 24837651 | ... EC44: =EB44/EB39*EC39 -> 36409477 | ED44: x
ED45: x
A46: Revenue Post Tax (after returns) | B46: =B37-B42 -> 125801277 | C46: =C37-C42 -> 1.1759199e+08 | D46: =D37-D42 -> 1.3147411e+08 | E46: =E37-E42 -> 1.5305052e+08 | F46: =F37-F42 -> 1.7940043e+08 | G46: =G37-G42 -> 187093082 | H46: =H37-H42 -> 200855808 | I46: =I37-I42 -> 188073690 | ... EC46: =EC37-EC42 -> 1.014667e+09 | ED46: x
A47: Offline | AZ47: =AZ38-AZ43 -> 56354680 | BA47: =BA38-BA43 -> 61174392 | BB47: =BB38-BB43 -> 61968479 | BC47: =BC38-BC43 -> 1.1046035e+08 | BD47: =BD38-BD43 -> 98808232 | BE47: =BE38-BE43 -> 1.1809251e+08 | BF47: =BF38-BF43 -> 1.4607863e+08 | BG47: =BG38-BG43 -> 1.1105521e+08 | ... EC47: =EC38-EC43 -> 45253968 | ED47: x
A48: Online | AZ48: =AZ39-AZ44 -> 1.9327073e+08 | BA48: =BA39-BA44 -> 2.2865879e+08 | BB48: =BB39-BB44 -> 2.4737431e+08 | BC48: =BC39-BC44 -> 2.0776601e+08 | BD48: =BD39-BD44 -> 2.7422944e+08 | BE48: =BE39-BE44 -> 2.8586639e+08 | BF48: =BF39-BF44 -> 3.6701407e+08 | BG48: =BG39-BG44 -> 3.5189773e+08 | ... EC48: =EC39-EC44 -> 9.6941299e+08 | ED48: x
ED49: x
A50: Net Devices Sold | B50: =B12-B26 -> 32077 | C50: =C12-C26 -> 28685 | D50: =D12-D26 -> 34758 | E50: =E12-E26 -> 39298 | F50: =F12-F26 -> 47222 | G50: =G12-G26 -> 49152 | H50: =H12-H26 -> 52716 | I50: =I12-I26 -> 52798 | ... EC50: =EC12-EC26 -> 109705.43 | ED50: x
A51: Offline | AZ51: =AZ13-AZ27 -> 9341 | BA51: =BA13-BA27 -> 10836 | BB51: =BB13-BB27 -> 10741 | BC51: =BC13-BC27 -> 21716 | BD51: =BD13-BD27 -> 13663 | BE51: =BE13-BE27 -> 17135 | BF51: =BF13-BF27 -> 20872 | BG51: =BG13-BG27 -> 15455 | ... EC51: =EC13-EC27 -> 4812.9271 | ED51: x
A52: Online | AZ52: =AZ14-AZ28 -> 33582 | BA52: =BA14-BA28 -> 41888 | BB52: =BB14-BB28 -> 45010 | BC52: =BC14-BC28 -> 39036 | BD52: =BD14-BD28 -> 42741 | BE52: =BE14-BE28 -> 44380 | BF52: =BF14-BF28 -> 56885 | BG52: =BG14-BG28 -> 53389 | ... EC52: =EC14-EC28 -> 104892.5 | ED52: x
ED53: x
A54: COGS | B54: =SUM(B55:B61) -> 121416986 | C54: =SUM(C55:C61) -> 1.1389136e+08 | D54: =SUM(D55:D61) -> 1.2786417e+08 | E54: =SUM(E55:E61) -> 1.4679653e+08 | F54: =SUM(F55:F61) -> 1.7600107e+08 | G54: =SUM(G55:G61) -> 1.7907035e+08 | H54: =SUM(H55:H61) -> 2.0651542e+08 | I54: =SUM(I55:I61) -> 1.8155977e+08 | ... EC54: =SUM(EC55:EC61) -> 9.294481e+08 | ED54: x
A55: Buying Cost | B55: 117992804 | C55: 1.1097537e+08 | D55: 1.2420018e+08 | E55: 1.4162867e+08 | F55: 1.6918118e+08 | G55: 1.7238326e+08 | H55: 1.9832001e+08 | I55: 1.7329524e+08 | J55: 2.2831392e+08 | K55: 2.2911915e+08 | L55: 2.2648714e+08 | M55: 1.950711e+08 | N55: 2.5413141e+08 | O55: 2.5279063e+08 | P55: 2.6851059e+08 | Q55: 2.6712898e+08 | R55: 2.2004165e+08 | S55: 1.984323e+08 | T55: 1.6527334e+08 | U55: 1.9919502e+08 | V55: 2.3205875e+08 | W55: 2.2998377e+08 | X55: 2.5815165e+08 | Y55: 1.6364927e+08 | Z55: -37759.9 | AA55: 1.2240413e+08 | AB55: 1.3442422e+08 | AC55: 1.0763378e+08 | AD55: 1.7450819e+08 | AE55: 1.8128952e+08 | AF55: 1.6758101e+08 | AG55: 1.8990463e+08 | AH55: 3.1999666e+08 | AI55: 2.8070324e+08 | AJ55: 3.4834616e+08 | AK55: 2.9106529e+08 | AL55: 2.0371931e+08 | AM55: 90688921 | AN55: 196353614 | AO55: 278939079 | AP55: 271579384 | AQ55: 2.57417e+08 | AR55: 219296725 | AS55: 269293459 | AT55: 363212766 | AU55: 341916143 | AV55: 3.5580742e+08 | AW55: 304684916 | AX55: 3.0753364e+08 | AY55: 3.505182e+08 | AZ55: 2.4584597e+08 | BA55: 2.7173758e+08 | BB55: 3.0009936e+08 | BC55: 3.1489762e+08 | BD55: 3.5779928e+08 | BE55: 3.8914169e+08 | BF55: 4.8264494e+08 | BG55: 4.4462016e+08 | BH55: 3.5853138e+08 | BI55: 3.8871302e+08 | BJ55: 3.5448142e+08 | BK55: 3.6332886e+08 | BL55: 2.6878692e+08 | BM55: 2.4552429e+08 | BN55: 2.5829869e+08 | BO55: 2.5938822e+08 | BP55: 2.4006205e+08 | BQ55: 2.9796389e+08 | BR55: 2.8335977e+08 | BS55: 2.6937837e+08 | BT55: 2.568076e+08 | BU55: 2.602369e+08 | BV55: 2.6264179e+08 | BW55: 2.7074647e+08 | BX55: 2.5795618e+08 | BY55: 2.5586104e+08 | BZ55: 2.4493187e+08 | CA55: 2.1750357e+08 | CB55: 2.5401384e+08 | CC55: 2.5644339e+08 | CD55: 2.9686334e+08 | CE55: 3.4210249e+08 | CF55: 3.8954706e+08 | CG55: 5.0243464e+08 | CH55: 4.1210844e+08 | CI55: 4.0412824e+08 | CJ55: 3.9590177e+08 | CK55: 3.9729224e+08 | CL55: 3.2977296e+08 | CM55: 2.9076737e+08 | CN55: 3.7064228e+08 | CO55: 4.5365234e+08 | CP55: 5.646534e+08 | CQ55: 5.9465429e+08 | CR55: 5.2066671e+08 | CS55: 4.9913931e+08 | CT55: =CT46*CT67 -> 5.3132534e+08 | CU55: =CU46*CU67 -> 5.5072097e+08 | CV55: =CV46*CV67 -> 5.173654e+08 | CW55: =CW46*CW67 -> 5.1780801e+08 | CX55: =CX46*CX67 -> 4.8145687e+08 | CY55: =CY46*CY67 -> 4.1984903e+08 | CZ55: =CZ46*CZ67 -> 4.9117915e+08 | DA55: =DA46*DA67 -> 6.0825642e+08 | ... EC55: =EC46*EC67 -> 8.7437139e+08 | ED55: x
A56: Spares & Consumables | B56: 1747 | C56: 1189 | D56: 1715 | E56: 17589 | F56: 105746 | G56: 60200 | H56: 43652 | I56: 8389 | J56: 18053 | K56: 8345 | L56: 491505 | M56: 385074 | N56: 408337 | O56: 657087 | P56: 564676 | Q56: 1203627 | R56: 614202 | S56: 118045 | T56: 867198 | U56: 811354 | V56: 876833 | W56: 917758 | X56: 1289927 | Y56: 372868 | Z56: 0 | AA56: 250682 | AB56: 380082 | AC56: 377444 | AD56: 813605 | AE56: 862469 | AF56: 1105888 | AG56: 396246 | AH56: 543353 | AI56: 276432 | AJ56: 72555 | AK56: 374651 | AL56: 331519 | AM56: 225597 | AN56: 383322 | AO56: 569787 | AP56: 735175 | AQ56: 343460 | AR56: 155241 | AS56: 206394 | AT56: 169838 | AU56: 363053 | AV56: 992001 | AW56: 2095405 | AX56: 1396030 | AY56: 2139424 | AZ56: 1684410 | BA56: 523143.56 | BB56: 182450.22 | BC56: 1887382 | BD56: 3093768.7 | BE56: 2641790.2 | BF56: 5310676.6 | BG56: 3624979.2 | BH56: 1366242.5 | BI56: 1103351.3 | BJ56: 3374696.7 | BK56: 3949270.1 | BL56: 3328352.8 | BM56: 2453706.9 | BN56: 6680645 | BO56: 5790162 | BP56: 4964739.7 | BQ56: 7486193.5 | BR56: 8281888.7 | BS56: 9161005.9 | BT56: 6860135.2 | BU56: 7888648.9 | BV56: 6751637 | BW56: 7349226.3 | BX56: 8470569.5 | BY56: 8829571.6 | BZ56: 7076330.8 | CA56: 6168901.4 | CB56: 7611028.5 | CC56: 7652256.9 | CD56: 7381059.2 | CE56: 7429940.3 | CF56: 6529129.6 | CG56: 11058911 | CH56: 8241204.4 | CI56: 9139198 | CJ56: 10252207 | CK56: 13070502 | CL56: 10685690 | CM56: 9725004.9 | CN56: 11388845 | CO56: 10276267 | CP56: 14919719 | CQ56: 17931013 | CR56: 20407170 | CS56: 23101571 | CT56: =CT46*CT71 -> 16319922 | CU56: =CU46*CU71 -> 16915668 | CV56: =CV46*CV71 -> 15891135 | CW56: =CW46*CW71 -> 15904731 | CX56: =CX46*CX71 -> 14788187 | CY56: =CY46*CY71 -> 12895872 | CZ56: =CZ46*CZ71 -> 15086812 | DA56: =DA46*DA71 -> 18682898 | ... EC56: =EC46*EC71 -> 27402053 | ED56: x
A57: Warranty Cost t/f to D2C | B57: 0 | C57: 0 | D57: 0 | E57: 0 | F57: 0 | G57: 0 | H57: 0 | I57: 0 | J57: 0 | K57: 0 | L57: 0 | M57: 0 | N57: 0 | O57: 0 | P57: 0 | Q57: 0 | R57: 0 | S57: 0 | T57: 0 | U57: 0 | V57: 0 | W57: 0 | X57: 0 | Y57: 0 | Z57: 0 | AA57: 0 | AB57: 0 | AC57: 0 | AD57: 0 | AE57: 0 | AF57: 0 | AG57: 0 | AH57: 0 | AI57: 0 | AJ57: 0 | AK57: 0 | AL57: 0 | AM57: 0 | AN57: 0 | AO57: 0 | AP57: 0 | AQ57: 0 | AR57: 0 | AS57: 0 | AT57: 0 | AU57: 0 | AV57: 0 | AW57: 0 | AX57: 0 | AY57: 0 | AZ57: 0 | BA57: 0 | BB57: 0 | BC57: 0 | BD57: 0 | BE57: 0 | BF57: 0 | BG57: 0 | BH57: 0 | BI57: 0 | BJ57: 0 | BK57: 0 | BL57: 0 | BM57: 0 | BN57: 0 | BO57: 0 | BP57: -2373549.1 | BQ57: -3431435.4 | BR57: -5125023.6 | BS57: -7083550 | BT57: -5449308.3 | BU57: -3157680.9 | BV57: -2305770.3 | BW57: -3240183 | BX57: -3725761.6 | BY57: -5584959 | BZ57: -4195543 | CA57: -4673576.7 | CB57: -4700421 | CC57: -3237513.6 | CD57: -3231083 | CE57: -2940546.2 | CF57: -2373473.3 | CG57: -4750933.4 | CH57: -3893397.5 | CI57: -3971325.8 | CJ57: -4222781.1 | CK57: -5264748 | CL57: -5169465 | CM57: -6401161 | CN57: -5508032 | CO57: -4777393 | CP57: -5456838 | CQ57: -5140813 | CR57: -5008114 | CS57: -6917477 | CT57: =CT46*CT74 -> -6330678.6 | CU57: =CU46*CU74 -> -6561775.3 | CV57: =CV46*CV74 -> -6164347.6 | CW57: =CW46*CW74 -> -6169621.3 | CX57: =CX46*CX74 -> -5736501.7 | CY57: =CY46*CY74 -> -5002451.5 | CZ57: =CZ46*CZ74 -> -5852341.5 | DA57: =DA46*DA74 -> -7247303.4 | ... EC57: =EC46*EC74 -> -10629560 | ED57: x
A58: Inventory Writeoff | B58: 0 | C58: 0 | D58: 0 | E58: 0 | F58: 0 | G58: 0 | H58: 0 | I58: 0 | J58: 0 | K58: 0 | L58: 0 | M58: 0 | N58: 0 | O58: 0 | P58: 0 | Q58: 0 | R58: 0 | S58: 0 | T58: 0 | U58: 0 | V58: 0 | W58: 0 | X58: 0 | Y58: 0 | Z58: 0 | AA58: 0 | AB58: 0 | AC58: 0 | AD58: 0 | AE58: 0 | AF58: 0 | AG58: 0 | AH58: 0 | AI58: 0 | AJ58: 0 | AK58: 0 | AL58: 0 | AM58: 0 | AN58: 0 | AO58: 0 | AP58: 0 | AQ58: 0 | AR58: 0 | AS58: 0 | AT58: 0 | AU58: 0 | AV58: 0 | AW58: 0 | AX58: 0 | AY58: 0 | AZ58: 0 | BA58: 0 | BB58: 0 | BC58: 3295281.9 | BD58: 2971501.1 | BE58: 2698666.8 | BF58: 2815227.8 | BG58: 1715273 | BH58: 3984273.8 | BI58: 2497809.4 | BJ58: 2566333.7 | BK58: 4075332.6 | BL58: 2305229.1 | BM58: 2993850.3 | BN58: 3757036.4 | BO58: 1891493.8 | BP58: 3332729.7 | BQ58: 3707777.4 | BR58: 2056831.1 | BS58: 1677305.3 | BT58: 3281099.1 | BU58: 3104364.8 | BV58: 2379589.3 | BW58: 1641649.6 | BX58: 2254110.4 | BY58: 892409.45 | BZ58: 939165.28 | CA58: 874632.77 | CB58: 1704781.7 | CC58: 1018567.9 | CD58: 974088.9 | CE58: 1241997.5 | CF58: 2170292.1 | CG58: 2035413.7 | CH58: 1995634.9 | CI58: 1742480.1 | CJ58: 1450440.1 | CK58: 2126192.6 | CL58: 1834047.9 | CM58: 1641282.2 | CN58: 883618.71 | CO58: 1387285.9 | CP58: 1422235.7 | CQ58: 2697871.9 | CR58: 2553219.3 | CS58: 2656530.3 | CT58: =CT76*CT46 -> 2325140 | CU58: =CU76*CU46 -> 2410017.5 | CV58: =CV76*CV46 -> 2264049.7 | CW58: =CW76*CW46 -> 2265986.7 | CX58: =CX76*CX46 -> 2106909.9 | CY58: =CY76*CY46 -> 1837307 | CZ58: =CZ76*CZ46 -> 2149455.7 | DA58: =DA76*DA46 -> 2661799.2 | ... EC58: =EC76*EC46 -> 3904038.9 | ED58: x
A59: Pick up Logistics Cost | B59: 3422435 | C59: 2914807 | D59: 3662274 | E59: 5150278 | F59: 6714146 | G59: 6626896 | H59: 8151760 | I59: 8256143 | J59: 7985592 | K59: 8407527 | L59: 8382902 | M59: 8633978 | N59: 8789815 | O59: 9263281 | P59: 9580238 | Q59: 9429281 | R59: 7766738 | S59: 8079197 | T59: 11529263 | U59: 10645700 | V59: 7937644.3 | W59: 8737671 | X59: 8376783 | Y59: 7136995.5 | Z59: 3937725.9 | AA59: 4795338 | AB59: 3971808 | AC59: 5918712 | AD59: 11934459 | AE59: 9664661 | AF59: 7410024 | AG59: 10041136 | AH59: 12631923 | AI59: 9949462 | AJ59: 11943458 | AK59: 8771651 | AL59: 7434368 | AM59: 5122339 | AN59: 7932703 | AO59: 11964479 | AP59: 11954590 | AQ59: 12054890 | AR59: 9408189.8 | AS59: 8448871 | AT59: 10202963 | AU59: 9291520 | AV59: 9422988 | AW59: 9292583 | AX59: 9130696 | AY59: 9501674 | AZ59: 8709700 | BA59: 7800901.2 | BB59: 10632737 | BC59: 18578311 | BD59: 22249422 | BE59: 15129867 | BF59: 15311503 | BG59: 11557838 | BH59: 11038809 | BI59: 11688790 | BJ59: 3845614.3 | BK59: 3323608.6 | BL59: 4780338.1 | BM59: 5505816.1 | BN59: 6243792.8 | BO59: 5078518.9 | BP59: 4612320.4 | BQ59: 5459439.3 | BR59: 3611800 | BS59: 3624572.5 | BT59: 4307758 | BU59: 3522927 | BV59: 4021821.9 | BW59: 4122464 | BX59: 4038503.1 | BY59: 4339648.4 | BZ59: 3948798.2 | CA59: 3338100.8 | CB59: 3879857.3 | CC59: 4236585.2 | CD59: 4315045.3 | CE59: 4595317.4 | CF59: 5473914.9 | CG59: 5554063 | CH59: 5366407.3 | CI59: 5955124.3 | CJ59: 5550706.2 | CK59: 5905972.6 | CL59: 6033888.6 | CM59: 5339485.1 | CN59: 6063398.9 | CO59: 7280267.9 | CP59: 10795380 | CQ59: 12007441 | CR59: 12389129 | CS59: 11761424 | CT59: =CT78*CT46 -> 16319922 | CU59: =CU78*CU46 -> 16915668 | CV59: =CV78*CV46 -> 15891135 | CW59: =CW78*CW46 -> 15904731 | CX59: =CX78*CX46 -> 14788187 | CY59: =CY78*CY46 -> 12895872 | CZ59: =CZ78*CZ46 -> 15086812 | DA59: =DA78*DA46 -> 18682898 | ... EC59: =EC78*EC46 -> 27402053 | ED59: x
A60: Engineers Cost | B60: 0 | C60: 0 | D60: 0 | E60: 0 | F60: 0 | G60: 0 | H60: 0 | I60: 0 | J60: 0 | K60: 0 | L60: 0 | M60: 0 | N60: 0 | O60: 0 | P60: 0 | Q60: 0 | R60: 0 | S60: 0 | T60: 0 | U60: 0 | V60: 0 | W60: 0 | X60: 0 | Y60: 0 | Z60: 0 | AA60: 0 | AB60: 0 | AC60: 0 | AD60: 0 | AE60: 0 | AF60: 0 | AG60: 0 | AH60: 0 | AI60: 0 | AJ60: 0 | AK60: 0 | AL60: 0 | AM60: 0 | AN60: 0 | AO60: 0 | AP60: 0 | AQ60: 0 | AR60: 0 | AS60: 0 | AT60: 0 | AU60: 0 | AV60: 0 | AW60: 0 | AX60: 0 | AY60: 0 | AZ60: 0 | BA60: 0 | BB60: 0 | BC60: 0 | BD60: 0 | BE60: 0 | BF60: 0 | BG60: 0 | BH60: 0 | BI60: 0 | BJ60: 0 | BK60: 0 | BL60: 0 | BM60: 0 | BN60: 0 | BO60: 0 | BP60: 0 | BQ60: 0 | BR60: 0 | BS60: 0 | BT60: 0 | BU60: 0 | BV60: 926511.78 | BW60: 985447.93 | BX60: 884594.43 | BY60: 769498.25 | BZ60: 578308.39 | CA60: 508720.84 | CB60: 1080733.9 | CC60: 1354401.5 | CD60: 1216185.5 | CE60: 1064303.6 | CF60: 1047213.9 | CG60: 1150390.8 | CH60: 1064764.6 | CI60: 2019403.1 | CJ60: 1546811.5 | CK60: 2127567.4 | CL60: 2010361.4 | CM60: 1539473.6 | CN60: 2297714.9 | CO60: 2522735.4 | CP60: 2281653.7 | CQ60: 2426025.3 | CR60: 2704206 | CS60: 2318846.5 | CT60: =CT46*CT81 -> 2549392 | CU60: =CU46*CU81 -> 2642455.6 | CV60: =CV46*CV81 -> 2482409.7 | CW60: =CW46*CW81 -> 2484533.5 | CX60: =CX46*CX81 -> 2310114.3 | CY60: =CY46*CY81 -> 2014509.1 | CZ60: =CZ46*CZ81 -> 2356763.5 | DA60: =DA46*DA81 -> 2918520.8 | ... EC60: =EC46*EC81 -> 4280570.3 | ED60: x
A61: Refurbishing Center Cost | B61: 0 | C61: 0 | D61: 0 | E61: 0 | F61: 0 | G61: 0 | H61: 0 | I61: 0 | J61: 0 | K61: 0 | L61: 0 | M61: 0 | N61: 0 | O61: 0 | P61: 0 | Q61: 0 | R61: 0 | S61: 0 | T61: 0 | U61: 0 | V61: 0 | W61: 0 | X61: 0 | Y61: 0 | Z61: 0 | AA61: 0 | AB61: 0 | AC61: 0 | AD61: 0 | AE61: 0 | AF61: 0 | AG61: 0 | AH61: 0 | AI61: 0 | AJ61: 0 | AK61: 0 | AL61: 0 | AM61: 0 | AN61: 0 | AO61: 0 | AP61: 0 | AQ61: 0 | AR61: 0 | AS61: 0 | AT61: 0 | AU61: 0 | AV61: 0 | AW61: 0 | AX61: 0 | AY61: 0 | AZ61: 0 | BA61: 0 | BB61: 0 | BC61: 0 | BD61: 0 | BE61: 0 | BF61: 0 | BG61: 0 | BH61: 0 | BI61: 0 | BJ61: 0 | BK61: 0 | BL61: 0 | BM61: 0 | BN61: 0 | BO61: 0 | BP61: 0 | BQ61: 0 | BR61: 0 | BS61: 0 | BT61: 0 | BU61: 0 | BV61: 640053.68 | BW61: 832117.4 | BX61: 798077.43 | BY61: 691332.1 | BZ61: 459535.56 | CA61: 389381.77 | CB61: 803818.75 | CC61: 925844.34 | CD61: 839067.33 | CE61: 695218.97 | CF61: 674051.71 | CG61: 740860.23 | CH61: 694381.59 | CI61: 1379137.5 | CJ61: 1597960.2 | CK61: 1364339 | CL61: 1238721.3 | CM61: 897074.83 | CN61: 1314486 | CO61: 1516024.2 | CP61: 1353092.9 | CQ61: 1424955.2 | CR61: 1619602.7 | CS61: 1382520.2 | CT61: =CT84*CT46 -> 1618502.2 | CU61: =CU84*CU46 -> 1677584.4 | CV61: =CV84*CV46 -> 1575978 | CW61: =CW84*CW46 -> 1577326.3 | CX61: =CX84*CX46 -> 1466594.8 | CY61: =CY84*CY46 -> 1278927.5 | CZ61: =CZ84*CZ46 -> 1496210.5 | DA61: =DA84*DA46 -> 1852846.6 | ... EC61: =EC84*EC46 -> 2717554.8 | ED61: x
ED62: x
A63: Offline COGS | AZ63: 59968517 | BA63: 65267957 | BB63: 63835875 | BC63: 1.2335484e+08 | BD63: 1.0635941e+08 | BE63: 1.2345471e+08 | BF63: 1.458111e+08 | BG63: 1.1439181e+08 | BH63: 56626670 | BI63: 58500693 | BJ63: 36169325 | BK63: 32858152 | BL63: 35284584 | BM63: 15534155 | BN63: 11801731 | BO63: 16599595 | BP63: 25730803 | BQ63: 49883983 | BR63: 41121430 | BS63: 29991438 | BT63: 17478259 | BU63: 34648197 | BV63: 29039792 | BW63: 24723779 | BX63: 9679846.1 | BY63: 25197158 | BZ63: 32392617 | CA63: 42532725 | CB63: 30108076 | CC63: 15488559 | CD63: 46034974 | CE63: 69436694 | CF63: 37207840 | CG63: 82008602 | CH63: 60717888 | CI63: 59194094 | CJ63: 32216699 | CK63: 32877791 | CL63: 22729120 | CM63: 21031999 | CN63: 26744237 | CO63: 48055142 | CP63: 89051342 | CQ63: 67800452 | CR63: 36890916 | CS63: 36614814 | CT63: =SUM(CH63:CS63)/SUM(CH54:CS54)*CT54 -> 54880982 | CU63: =CT63/CT54*CU54 -> 56884371 | CV63: =CU63/CU54*CV54 -> 53439050 | CW63: =CV63/CV54*CW54 -> 53484767 | CX63: =CW63/CW54*CX54 -> 49730031 | CY63: =CX63/CX54*CY54 -> 43366512 | CZ63: =CY63/CY54*CZ54 -> 50734253 | DA63: =CZ63/CZ54*DA54 -> 62827250 | DB63: =DA63/DA54*DB54 -> 70007290 | ... EC63: =EB63/EB54*EC54 -> 90421086 | ED63: x
A64: Online COGS | AZ64: 1.9627156e+08 | BA64: 2.1479367e+08 | BB64: 2.4707867e+08 | BC64: 2.1530376e+08 | BD64: 2.7975456e+08 | BE64: 2.8649755e+08 | BF64: 3.6027125e+08 | BG64: 3.4712644e+08 | BH64: 3.1829403e+08 | BI64: 3.4550228e+08 | BJ64: 3.2809874e+08 | BK64: 3.4181892e+08 | BL64: 2.4391626e+08 | BM64: 2.4094351e+08 | BN64: 2.6317843e+08 | BO64: 2.555488e+08 | BP64: 2.2486748e+08 | BQ64: 2.6130189e+08 | BR64: 2.5156384e+08 | BS64: 2.4676627e+08 | BT64: 2.4832902e+08 | BU64: 2.3694696e+08 | BV64: 2.4601584e+08 | BW64: 2.5771341e+08 | BX64: 2.6099642e+08 | BY64: 2.4060139e+08 | BZ64: 2.2234584e+08 | CA64: 1.8157701e+08 | CB64: 2.3428556e+08 | CC64: 2.5290497e+08 | CD64: 2.6232273e+08 | CE64: 2.8475203e+08 | CF64: 3.6586035e+08 | CG64: 4.3621475e+08 | CH64: 3.6485955e+08 | CI64: 3.6045377e+08 | CJ64: 3.8431328e+08 | CK64: 3.8374427e+08 | CL64: 3.2467569e+08 | CM64: 2.8390091e+08 | CN64: 3.6033807e+08 | CO64: 4.2305239e+08 | CP64: 5.1023062e+08 | CQ64: 5.5820033e+08 | CR64: 5.114789e+08 | CS64: 4.9682791e+08 | CT64: =SUM(CH64:CS64)/SUM(CH54:CS54)*CT54 -> 5.1004138e+08 | CU64: =CU54-CU63 -> 5.2783622e+08 | CV64: =CV54-CV63 -> 4.9586671e+08 | CW64: =CW54-CW63 -> 4.9629093e+08 | CX64: =CX54-CX63 -> 4.6145033e+08 | CY64: =CY54-CY63 -> 4.0240255e+08 | CZ64: =CZ54-CZ63 -> 4.7076861e+08 | DA64: =DA54-DA63 -> 5.8298083e+08 | DB64: =DB54-DB63 -> 6.496052e+08 | ... EC64: =EC54-EC63 -> 8.3902702e+08 | ED64: x
ED65: x
A66: COGS Assumptions | ED66: x
A67: Buying cost as a % of revenue | B67: =B55/B37 -> 0.9263553 | C67: =C55/C37 -> 0.92846827 | D67: =D55/D37 -> 0.92951044 | E67: =E55/E37 -> 0.90950116 | F67: =F55/F37 -> 0.92488569 | G67: =G55/G37 -> 0.90504681 | H67: =H55/H37 -> 0.97456321 | I67: =I55/I37 -> 0.90585011 | ... CS67: =CS55/CS37 -> 0.82507431 | CT67: =SUM(CH55:CS55)/SUM(CH46:CS46)*(1+CT68) -> 0.87922906 | CU67: =CT67*(1+CU68) -> 0.87922906 | CV67: =CU67*(1+CV68) -> 0.87922906 | CW67: =CV67*(1+CW68) -> 0.87922906 | CX67: =CW67*(1+CX68) -> 0.87922906 | CY67: =CX67*(1+CY68) -> 0.87922906 | CZ67: =CY67*(1+CZ68) -> 0.87922906 | DA67: =CZ67*(1+DA68) -> 0.87922906 | DB67: =DA67*(1+DB68) -> 0.87922906 | ... EC67: =EB67*(1+EC68) -> 0.8617324 | ED67: x
CT68: -0.01 | DF68: -0.01 | DR68: -0.01 | ED68: x
A69: Gross Margin % | B69: =(B46-B54)/B46 -> 0.034850926 | C69: =(C46-C54)/C46 -> 0.031470035 | D69: =(D46-D54)/D46 -> 0.027457414 | E69: =(E46-E54)/E46 -> 0.04086221 | F69: =(F46-F54)/F46 -> 0.018948484 | G69: =(G46-G54)/G46 -> 0.042880948 | H69: =(H46-H54)/H46 -> -0.028177506 | I69: =(I46-I54)/I46 -> 0.034634925 | ... EC69: =(EC46-EC54)/EC46 -> 0.08398702 | ED69: x
ED70: x
A71: Spares & Consumables as a % of sales | BA71: =BA56/BA46 -> 0.0018049816 | BB71: =BB56/BB46 -> 0.00058979949 | BC71: =BC56/BC46 -> 0.0059309416 | BD71: =BD56/BD46 -> 0.0082934484 | BE71: =BE56/BE46 -> 0.00653975 | BF71: =BF56/BF46 -> 0.010350326 | BG71: =BG56/BG46 -> 0.0078301246 | BH71: =BH56/BH46 -> 0.003665707 | ... CS71: =CS56/CS46 -> 0.039580873 | CT71: =SUM(CH56:CS56)/SUM(CH46:CS46) -> 0.027005958 | CU71: =CT71 -> 0.027005958 | CV71: =CU71 -> 0.027005958 | CW71: =CV71 -> 0.027005958 | CX71: =CW71 -> 0.027005958 | CY71: =CX71 -> 0.027005958 | CZ71: =CY71 -> 0.027005958 | DA71: =CZ71 -> 0.027005958 | DB71: =DA71 -> 0.027005958 | ... EC71: =EB71 -> 0.027005958 | ED71: x
DF72: 0.05 | DR72: 0.05 | ED72: x
ED73: x
A74: Warranty Cost t/f to D2C | B74: =B57/B46 -> 0 | C74: =C57/C46 -> 0 | D74: =D57/D46 -> 0 | E74: =E57/E46 -> 0 | F74: =F57/F46 -> 0 | G74: =G57/G46 -> 0 | H74: =H57/H46 -> 0 | I74: =I57/I46 -> 0 | ... CS74: =CS57/CS46 -> -0.011851998 | CT74: =SUM(CH57:CS57)/SUM(CH46:CS46) -> -0.01047591 | CU74: =CT74 -> -0.01047591 | CV74: =CU74 -> -0.01047591 | CW74: =CV74 -> -0.01047591 | CX74: =CW74 -> -0.01047591 | CY74: =CX74 -> -0.01047591 | CZ74: =CY74 -> -0.01047591 | DA74: =CZ74 -> -0.01047591 | DB74: =DA74 -> -0.01047591 | ... EC74: =EB74 -> -0.01047591 | ED74: x
ED75: x
A76: Inventory writeoff (as a % of revenue) | B76: =B58/B46 -> 0 | C76: =C58/C46 -> 0 | D76: =D58/D46 -> 0 | E76: =E58/E46 -> 0 | F76: =F58/F46 -> 0 | G76: =G58/G46 -> 0 | H76: =H58/H46 -> 0 | I76: =I58/I46 -> 0 | ... CS76: =CS58/CS46 -> 0.0045515429 | CT76: =AVERAGE(CH76:CS76) -> 0.0038476062 | CU76: =CT76 -> 0.0038476062 | CV76: =CU76 -> 0.0038476062 | CW76: =CV76 -> 0.0038476062 | CX76: =CW76 -> 0.0038476062 | CY76: =CX76 -> 0.0038476062 | CZ76: =CY76 -> 0.0038476062 | DA76: =CZ76 -> 0.0038476062 | DB76: =DA76 -> 0.0038476062 | ... EC76: =EB76 -> 0.0038476062 | ED76: x
ED77: x
A78: Pickup Logistics cost | B78: =B59/B50 -> 106.69436 | C78: =C59/C50 -> 101.61433 | D78: =D59/D50 -> 105.36492 | E78: =E59/E50 -> 131.057 | F78: =F59/F50 -> 142.18258 | G78: =G59/G50 -> 134.82454 | H78: =H59/H50 -> 154.6354 | I78: =I59/I50 -> 156.37227 | ... CS78: =CS59/CS50 -> 214.54084 | CT78: =SUM(CH56:CS56)/SUM(CH46:CS46) -> 0.027005958 | CU78: =CT78 -> 0.027005958 | CV78: =CU78 -> 0.027005958 | CW78: =CV78 -> 0.027005958 | CX78: =CW78 -> 0.027005958 | CY78: =CX78 -> 0.027005958 | CZ78: =CY78 -> 0.027005958 | DA78: =CZ78 -> 0.027005958 | DB78: =DA78 -> 0.027005958 | ... EC78: =EB78 -> 0.027005958 | ED78: x
A79: Pickup Logistics cost - Inflation | CT79: 0.05 | DF79: 0.05 | ED79: x
ED80: x
A81: Engineers cost (as a % of revenue) | B81: =B60/B46 -> 0 | C81: =C60/C46 -> 0 | D81: =D60/D46 -> 0 | E81: =E60/E46 -> 0 | F81: =F60/F46 -> 0 | G81: =G60/G46 -> 0 | H81: =H60/H46 -> 0 | I81: =I60/I46 -> 0 | ... CS81: =CS60/CS46 -> 0.0039729752 | CT81: =SUM(CH60:CS60)/SUM(CH46:CS46) -> 0.0042186949 | CU81: =CT81 -> 0.0042186949 | CV81: =CU81 -> 0.0042186949 | CW81: =CV81 -> 0.0042186949 | CX81: =CW81 -> 0.0042186949 | CY81: =CX81 -> 0.0042186949 | CZ81: =CY81 -> 0.0042186949 | DA81: =CZ81 -> 0.0042186949 | DB81: =DA81 -> 0.0042186949 | ... EC81: =EB81 -> 0.0042186949 | ED81: x
DF82: -0.05 | DR82: 0.05 | ED82: x
ED83: x
A84: Refurbishing center cost (as a % of revenue) | B84: =B61/B46 -> 0 | C84: =C61/C46 -> 0 | D84: =D61/D46 -> 0 | E84: =E61/E46 -> 0 | F84: =F61/F46 -> 0 | G84: =G61/G46 -> 0 | H84: =H61/H46 -> 0 | I84: =I61/I46 -> 0 | ... CS84: =CS61/CS46 -> 0.0023687288 | CT84: =SUM(CH61:CS61)/SUM(CH46:CS46) -> 0.0026782727 | CU84: =CT84 -> 0.0026782727 | CV84: =CU84 -> 0.0026782727 | CW84: =CV84 -> 0.0026782727 | CX84: =CW84 -> 0.0026782727 | CY84: =CX84 -> 0.0026782727 | CZ84: =CY84 -> 0.0026782727 | DA84: =CZ84 -> 0.0026782727 | DB84: =DA84 -> 0.0026782727 | ... EC84: =EB84 -> 0.0026782727 | ED84: x
DR85: 0.05 | ED85: x
ED86: x
A87: Operational Cost | B87: =SUM(B88:B91) -> 1980988 | C87: =SUM(C88:C91) -> 2116069 | D87: =SUM(D88:D91) -> 2396018 | E87: =SUM(E88:E91) -> 2631623 | F87: =SUM(F88:F91) -> 2869257 | G87: =SUM(G88:G91) -> 3128521 | H87: =SUM(H88:H91) -> 3073497 | I87: =SUM(I88:I91) -> 3352277 | ... EC87: =SUM(EC88:EC91) -> 14186993 | ED87: x
A88: Sales Logistics | B88: 100000 | C88: 100000 | D88: 100000 | E88: 100000 | F88: 100000 | G88: 100000 | H88: 100000 | I88: 100000 | J88: 1513276 | K88: 218659 | L88: 102777.25 | M88: 558721 | N88: 381848 | O88: 427406 | P88: 324778 | Q88: 531756 | R88: 254340 | S88: 338501 | T88: 145594 | U88: 290720 | V88: 265000 | W88: 250000 | X88: 343000 | Y88: 343804 | Z88: 0 | AA88: 180000 | AB88: 378429 | AC88: 362477 | AD88: 745165 | AE88: 1025348 | AF88: 1240275 | AG88: 1202000 | AH88: 1200000 | AI88: 955000 | AJ88: 1240099 | AK88: 1407488 | AL88: 1130000 | AM88: 1052202 | AN88: 1322631 | AO88: 2568354 | AP88: 2611158 | AQ88: 2695387 | AR88: 3676000 | AS88: 3223000 | AT88: 2124850 | AU88: 1730254 | AV88: 3606000 | AW88: 3725101 | AX88: 3643253 | AY88: 4094144 | AZ88: 3776004 | BA88: 5495656 | BB88: 5474300.3 | BC88: 5584250 | BD88: 4761209.8 | BE88: 5733746.8 | BF88: 6736133.1 | BG88: 6789185.9 | BH88: 5909991.9 | BI88: 5857433.1 | BJ88: 4188687.5 | BK88: 4192436.7 | BL88: 3940588.5 | BM88: 2862031 | BN88: 2262122.4 | BO88: 3270119.5 | BP88: 3057698.2 | BQ88: 3163409.7 | BR88: 3496031.5 | BS88: 3566447.9 | BT88: 2598749.3 | BU88: 1941818.2 | BV88: 1577676.6 | BW88: 224944.23 | BX88: 1006398.5 | BY88: 987651.04 | BZ88: 972251.1 | CA88: 861325.43 | CB88: 1401246.8 | CC88: 1605327.7 | CD88: 1468068.1 | CE88: 1905514.2 | CF88: 2006815.2 | CG88: 712163.73 | CH88: 981427.75 | CI88: 630831.57 | CJ88: 1083376.6 | CK88: 1828370.4 | CL88: 1045035.4 | CM88: 939178.36 | CN88: 789412.71 | CO88: 1173780.1 | CP88: 1239939.3 | CQ88: 1748579.9 | CR88: 1023512.8 | CS88: 2954482.8 | CT88: =CT95*CT50 -> 1718424 | CU88: =CU95*CU50 -> 1781340.6 | CV88: =CV95*CV50 -> 1680189.3 | CW88: =CW95*CW50 -> 1680555.1 | CX88: =CX95*CX50 -> 1563905.5 | CY88: =CY95*CY50 -> 1362567.4 | CZ88: =CZ95*CZ50 -> 1595548.7 | DA88: =DA95*DA50 -> 1972092.6 | ... EC88: =EC95*EC50 -> 3196653.5 | ED88: x
A89: Warehousing | B89: 1880988 | C89: 2016069 | D89: 2296018 | E89: 2531623 | F89: 2769257 | G89: 3028521 | H89: 2973497 | I89: 3252277 | J89: 2490212 | K89: 2583127 | L89: 3527031 | M89: 3658791 | N89: 4063527 | O89: 4598310 | P89: 4749582 | Q89: 4461145 | R89: 4515366 | S89: 4286936 | T89: 4520071 | U89: 5039990 | V89: 5101568 | W89: 5322872 | X89: 5585425 | Y89: 5506825.1 | Z89: 5194527.4 | AA89: 5256027 | AB89: 5257183 | AC89: 5109878 | AD89: 5709650 | AE89: 4596089 | AF89: 4583831 | AG89: 4977489 | AH89: 4195905 | AI89: 4988820 | AJ89: 4545877 | AK89: 4606685 | AL89: 5040054 | AM89: 4680313 | AN89: 4735590 | AO89: 4708142 | AP89: 5566490.9 | AQ89: 6070137 | AR89: 5878392.1 | AS89: 6480425 | AT89: 6568532.6 | AU89: 6452343.1 | AV89: 6030859 | AW89: 6512163 | AX89: 6305437.5 | AY89: 6310370 | AZ89: 6631614.4 | BA89: 6519843 | BB89: 7860316 | BC89: 7676372.3 | BD89: 7979123.5 | BE89: 7946870.2 | BF89: 7900601.5 | BG89: 7762008.1 | BH89: 7575778.4 | BI89: 6743096.8 | BJ89: 6616688.3 | BK89: 6117904 | BL89: 5710275.1 | BM89: 5713954.6 | BN89: 7105542 | BO89: 6307842.9 | BP89: 5309073.3 | BQ89: 5687567.1 | BR89: 5085156.5 | BS89: 4218337.9 | BT89: 4892500.1 | BU89: 5188690.3 | BV89: 4802134.7 | BW89: 6504049.4 | BX89: 5623825.2 | BY89: 6199033.5 | BZ89: 5484101.9 | CA89: 5808934.4 | CB89: 5410907.2 | CC89: 5790145.3 | CD89: 6206958.1 | CE89: 6402955 | CF89: 6622949.4 | CG89: 7177654.8 | CH89: 7030043.1 | CI89: 6890101.6 | CJ89: 7244690.6 | CK89: 7565410.7 | CL89: 7355532.4 | CM89: 7324360.9 | CN89: 8162593.9 | CO89: 9404240.4 | CP89: 8895400 | CQ89: 8079054.4 | CR89: 8536708.5 | CS89: 7717618 | CT89: =CS89*(1+CT99) -> 8103498.9 | CU89: =CT89*(1+CU99) -> 8103498.9 | CV89: =CU89*(1+CV99) -> 8103498.9 | CW89: =CV89*(1+CW99) -> 8103498.9 | CX89: =CW89*(1+CX99) -> 8103498.9 | CY89: =CX89*(1+CY99) -> 8103498.9 | CZ89: =CY89*(1+CZ99) -> 8103498.9 | DA89: =CZ89*(1+DA99) -> 8103498.9 | ... EC89: =EB89*(1+EC99) -> 8934107.6 | ED89: x
A90: Collection Cost | B90: 0 | C90: 0 | D90: 0 | E90: 0 | F90: 0 | G90: 0 | H90: 0 | I90: 0 | J90: 0 | K90: 0 | L90: 0 | M90: 0 | N90: 0 | O90: 0 | P90: 0 | Q90: 0 | R90: 0 | S90: 0 | T90: 0 | U90: 0 | V90: 0 | W90: 0 | X90: 0 | Y90: 0 | Z90: 0 | AA90: 0 | AB90: 0 | AC90: 0 | AD90: 0 | AE90: 0 | AF90: 0 | AG90: 0 | AH90: 0 | AI90: 809552 | AJ90: 816376 | AK90: 497982 | AL90: 466651 | AM90: 374698 | AN90: 720916.86 | AO90: 1357513.8 | AP90: 1297784.2 | AQ90: 1334624 | AR90: 1052798 | AS90: 1341651 | AT90: 1806139 | AU90: 1517439 | AV90: 1642441.3 | AW90: 1101807 | AX90: 1065755.4 | AY90: 1092267 | AZ90: 889922 | BA90: 1043874.8 | BB90: 961400 | BC90: 539452 | BD90: 494035 | BE90: 580184 | BF90: 316241.54 | BG90: 324508 | BH90: 401301.78 | BI90: 279410 | BJ90: 186000 | BK90: 195946 | BL90: 80607 | BM90: 88994.79 | BN90: 365 | BO90: 102418 | BP90: 0 | BQ90: 0 | BR90: 0 | BS90: 0 | BT90: 0 | BU90: 0 | BV90: 0 | BW90: 0 | BX90: 0 | BY90: 0 | BZ90: 0 | CA90: 0 | CB90: 0 | CC90: 0 | CD90: 0 | CE90: 0 | CF90: 0 | CG90: 0 | CH90: 0 | CI90: 0 | CJ90: 0 | CK90: 0 | CL90: 0 | CM90: 0 | CN90: 0 | CO90: 0 | CP90: 0 | CQ90: 0 | CR90: 0 | CS90: 0 | CT90: 0 | CU90: 0 | CV90: 0 | CW90: 0 | CX90: 0 | CY90: 0 | CZ90: 0 | DA90: 0 | DB90: 0 | DC90: 0 | DD90: 0 | DE90: 0 | DF90: 0 | DG90: 0 | DH90: 0 | DI90: 0 | DJ90: 0 | DK90: 0 | DL90: 0 | DM90: 0 | DN90: 0 | DO90: 0 | DP90: 0 | DQ90: 0 | DR90: 0 | DS90: 0 | DT90: 0 | DU90: 0 | DV90: 0 | DW90: 0 | DX90: 0 | DY90: 0 | DZ90: 0 | EA90: 0 | EB90: 0 | EC90: 0 | ED90: x
A91: Packaging | P91: 132236 | Q91: 246328 | R91: 100000 | S91: 0 | T91: 22200 | V91: 3664 | W91: 0 | X91: 15400 | Y91: 10780 | Z91: 0 | AA91: 0 | AB91: 0 | AC91: 0 | AD91: 0 | AE91: 0 | AF91: 991235 | AG91: 27047 | AH91: 636741 | AI91: 525417 | AJ91: 994895 | AK91: 524193 | AL91: 526382 | AM91: 183628 | AN91: 486306 | AO91: 629079 | AP91: 893154 | AQ91: 1037449 | AR91: 1358157 | AS91: 1180268 | AT91: 1431850 | AU91: 1283728 | AV91: 1284172 | AW91: 1091070 | AX91: 757143 | AY91: 835450 | AZ91: 611523 | BA91: 688281 | BB91: 785268 | BC91: 833268 | BD91: 773124 | BE91: 973784 | BF91: 1210258 | BG91: 1070468 | BH91: 860902 | BI91: 996898 | BJ91: 857850 | BK91: 885705 | BL91: 651765 | BM91: 661890 | BN91: 717165 | BO91: 707160 | BP91: 594480 | BQ91: 700800 | BR91: 523785 | BS91: 486195 | BT91: 501645 | BU91: 495225 | BV91: 522030 | BW91: 587160 | BX91: 567930 | BY91: 596655 | BZ91: 529095 | CA91: 477675 | CB91: 502500 | CC91: 538455 | CD91: 687360 | CE91: 762930 | CF91: 703875 | CG91: 888150 | CH91: 786195 | CI91: 815175 | CJ91: 775920 | CK91: 774975 | CL91: 722565 | CM91: 628275 | CN91: 737250 | CO91: 907320 | CP91: 1010580 | CQ91: 950055 | CR91: 927878.46 | CS91: 894185.59 | CT91: =CT50*CT98 -> 1105368.1 | CU91: =CU50*CU98 -> 1145839 | CV91: =CV50*CV98 -> 1080773.8 | CW91: =CW50*CW98 -> 1081009.1 | CX91: =CX50*CX98 -> 1005974.8 | CY91: =CY50*CY98 -> 876465.06 | CZ91: =CZ50*CZ98 -> 1026329.2 | DA91: =DA50*DA98 -> 1268539.3 | ... EC91: =EC50*EC98 -> 2056232.2 | ED91: x
A92: Operational Cost% | B92: =B87/B46 -> 0.015746963 | C92: =C87/C46 -> 0.01799501 | D92: =D87/D46 -> 0.018224258 | E92: =E87/E46 -> 0.017194473 | F92: =F87/F46 -> 0.01599359 | G92: =G87/G46 -> 0.016721735 | H92: =H87/H46 -> 0.015302007 | I92: =I87/I46 -> 0.017824274 | ... EC92: =EC87/EC46 -> 0.013981921 | ED92: x
ED93: x
A94: Operational Cost Assumptions | ED94: x
A95: Sales logistic cost per device | B95: =B88/B50 -> 3.1174985 | C95: =C88/C50 -> 3.4861426 | D95: =D88/D50 -> 2.8770355 | E95: =E88/E50 -> 2.5446588 | F95: =F88/F50 -> 2.117657 | G95: =G88/G50 -> 2.0345052 | H95: =H88/H50 -> 1.8969573 | I95: =I88/I50 -> 1.8940111 | ... CS95: =CS88/CS50 -> 53.892901 | CT95: =SUM(CH88:CS88)/SUM($CH$50:$CS$50)*(1+CT96) -> 26.429493 | CU95: =CT95*(1+CU96) -> 26.429493 | CV95: =CU95*(1+CV96) -> 26.429493 | CW95: =CV95*(1+CW96) -> 26.429493 | CX95: =CW95*(1+CX96) -> 26.429493 | CY95: =CX95*(1+CY96) -> 26.429493 | CZ95: =CY95*(1+CZ96) -> 26.429493 | DA95: =CZ95*(1+DA96) -> 26.429493 | DB95: =DA95*(1+DB96) -> 26.429493 | ... EC95: =EB95*(1+EC96) -> 29.138516 | ED95: x
A96: Sales logistic - Inflation | CT96: 0.05 | DF96: 0.05 | DR96: 0.05 | ED96: x
ED97: x
A98: Packaging cost per device | B98: =B91/B50 -> 0 | C98: =C91/C50 -> 0 | D98: =D91/D50 -> 0 | E98: =E91/E50 -> 0 | F98: =F91/F50 -> 0 | G98: =G91/G50 -> 0 | H98: =H91/H50 -> 0 | I98: =I91/I50 -> 0 | ... CS98: =CS91/CS50 -> 16.310894 | CT98: =SUM(CH91:CS91)/SUM($CH$50:$CS$50)*(1+CT99) -> 17.000647 | CU98: =CT98*(1+CU99) -> 17.000647 | CV98: =CU98*(1+CV99) -> 17.000647 | CW98: =CV98*(1+CW99) -> 17.000647 | CX98: =CW98*(1+CX99) -> 17.000647 | CY98: =CX98*(1+CY99) -> 17.000647 | CZ98: =CY98*(1+CZ99) -> 17.000647 | DA98: =CZ98*(1+DA99) -> 17.000647 | DB98: =DA98*(1+DB99) -> 17.000647 | ... EC98: =EB98*(1+EC99) -> 18.743213 | ED98: x
A99: Warehousing cost growth | C99: =C89/B89-1 -> 0.071813855 | D99: =D89/C89-1 -> 0.13885884 | E99: =E89/D89-1 -> 0.10261461 | F99: =F89/E89-1 -> 0.093866267 | G99: =G89/F89-1 -> 0.093622224 | H99: =H89/G89-1 -> -0.018168604 | I99: =I89/H89-1 -> 0.093754929 | J99: =J89/I89-1 -> -0.23431737 | ... CS99: =CS89/CR89-1 -> -0.095949219 | CT99: 0.05 | DF99: 0.05 | DR99: 0.05 | ED99: x
ED100: x
...

Sheet P&L Summary
B2: Cashify | J2: Common Size across the years
B3: Amounts in ₹ Crores | J3: Particulars | K3: FY24A | L3: FY25A | M3: FY26A | N3: FY27E | O3: FY28E | P3: FY29E
B4: Particulars | C4: FY24A | D4: FY25A | E4: FY26A | F4: FY27E | G4: FY28E | H4: FY29E | J4: Revenue Post Tax (Rs. Cr) | K4: 1001.3779 | L4: 1158.3452 | M4: 1719.155 | N4: 2186.6364 | O4: 2658.0117 | P4: 3109.1173
B5: GMV (after returns) | C5: =('Consolidated - P&L'!FE34)/10000000 -> 1482.0928 | D5: =('Consolidated - P&L'!FF34)/10000000 -> 1744.9847 | E5: =('Consolidated - P&L'!FG34)/10000000 -> 2441.5956 | F5: =('Consolidated - P&L'!FH34)/10000000 -> 3117.7265 | G5: =('Consolidated - P&L'!FI34)/10000000 -> 3776.2949 | H5: =('Consolidated - P&L'!FJ34)/10000000 -> 4397.3352 | J5: GMV (after returns) | K5: =('Consolidated - P&L'!FM34)/10000000 -> 0 | L5: =('Consolidated - P&L'!FN34)/10000000 -> 0 | M5: =('Consolidated - P&L'!FO34)/10000000 -> 0 | N5: =('Consolidated - P&L'!FP34)/10000000 -> 0 | O5: =('Consolidated - P&L'!FQ34)/10000000 -> 0 | P5: =('Consolidated - P&L'!FR34)/10000000 -> 0
B6: Non- Repair | C6: =('Consolidated - P&L'!FE35)/10000000 -> 371.80841 | D6: =('Consolidated - P&L'!FF35)/10000000 -> 403.94291 | E6: =('Consolidated - P&L'!FG35)/10000000 -> 608.30257 | F6: =('Consolidated - P&L'!FH35)/10000000 -> 783.16183 | G6: =('Consolidated - P&L'!FI35)/10000000 -> 978.95228 | H6: =('Consolidated - P&L'!FJ35)/10000000 -> 1174.7427 | J6: Non- Repair | K6: =('Consolidated - P&L'!FM35)/10000000 -> 0 | L6: =('Consolidated - P&L'!FN35)/10000000 -> 0 | M6: =('Consolidated - P&L'!FO35)/10000000 -> 0 | N6: =('Consolidated - P&L'!FP35)/10000000 -> 0 | O6: =('Consolidated - P&L'!FQ35)/10000000 -> 0 | P6: =('Consolidated - P&L'!FR35)/10000000 -> 0
B7: Refurbished | C7: =('Consolidated - P&L'!FE36)/10000000 -> 584.05711 | D7: =('Consolidated - P&L'!FF36)/10000000 -> 700.4068 | E7: =('Consolidated - P&L'!FG36)/10000000 -> 1051.848 | F7: =('Consolidated - P&L'!FH36)/10000000 -> 1333.9691 | G7: =('Consolidated - P&L'!FI36)/10000000 -> 1603.0075 | H7: =('Consolidated - P&L'!FJ36)/10000000 -> 1854.3997 | J7: Refurbished | K7: =('Consolidated - P&L'!FM36)/10000000 -> 0 | L7: =('Consolidated - P&L'!FN36)/10000000 -> 0 | M7: =('Consolidated - P&L'!FO36)/10000000 -> 0 | N7: =('Consolidated - P&L'!FP36)/10000000 -> 0 | O7: =('Consolidated - P&L'!FQ36)/10000000 -> 0 | P7: =('Consolidated - P&L'!FR36)/10000000 -> 0
B8: Market Place | C8: =('Consolidated - P&L'!FE37)/10000000 -> 493.51541 | D8: =('Consolidated - P&L'!FF37)/10000000 -> 599.40465 | E8: =('Consolidated - P&L'!FG37)/10000000 -> 717.03825 | F8: =('Consolidated - P&L'!FH37)/10000000 -> 923.18675 | G8: =('Consolidated - P&L'!FI37)/10000000 -> 1107.8241 | H8: =('Consolidated - P&L'!FJ37)/10000000 -> 1273.9977 | J8: Market Place | K8: =('Consolidated - P&L'!FM37)/10000000 -> 0 | L8: =('Consolidated - P&L'!FN37)/10000000 -> 0 | M8: =('Consolidated - P&L'!FO37)/10000000 -> 0 | N8: =('Consolidated - P&L'!FP37)/10000000 -> 0 | O8: =('Consolidated - P&L'!FQ37)/10000000 -> 0 | P8: =('Consolidated - P&L'!FR37)/10000000 -> 0
B9: Screen Pro + Accessories | C9: =('Consolidated - P&L'!FE38)/10000000 -> 30.984226 | D9: =('Consolidated - P&L'!FF38)/10000000 -> 38.001386 | E9: =('Consolidated - P&L'!FG38)/10000000 -> 59.804978 | F9: =('Consolidated - P&L'!FH38)/10000000 -> 72.807056 | G9: =('Consolidated - P&L'!FI38)/10000000 -> 81.90918 | H9: =('Consolidated - P&L'!FJ38)/10000000 -> 89.593241 | J9: Screen Pro + Accessories | K9: =('Consolidated - P&L'!FM38)/10000000 -> 0 | L9: =('Consolidated - P&L'!FN38)/10000000 -> 0 | M9: =('Consolidated - P&L'!FO38)/10000000 -> 0 | N9: =('Consolidated - P&L'!FP38)/10000000 -> 0 | O9: =('Consolidated - P&L'!FQ38)/10000000 -> 0 | P9: =('Consolidated - P&L'!FR38)/10000000 -> 0
B10: Enterprise Sales | C10: =('Consolidated - P&L'!FE39)/10000000 -> 1.7276083 | D10: =('Consolidated - P&L'!FF39)/10000000 -> 3.2290095 | E10: =('Consolidated - P&L'!FG39)/10000000 -> 4.6017858 | F10: =('Consolidated - P&L'!FH39)/10000000 -> 4.6017858 | G10: =('Consolidated - P&L'!FI39)/10000000 -> 4.6017858 | H10: =('Consolidated - P&L'!FJ39)/10000000 -> 4.6017858 | J10: Enterprise Sales | K10: =('Consolidated - P&L'!FM39)/10000000 -> 0 | L10: =('Consolidated - P&L'!FN39)/10000000 -> 0 | M10: =('Consolidated - P&L'!FO39)/10000000 -> 0 | N10: =('Consolidated - P&L'!FP39)/10000000 -> 0 | O10: =('Consolidated - P&L'!FQ39)/10000000 -> 0 | P10: =('Consolidated - P&L'!FR39)/10000000 -> 0
B12: Revenue Post Tax (after returns) | C12: =('Consolidated - P&L'!FE63)/10000000 -> 1001.3779 | D12: =('Consolidated - P&L'!FF63)/10000000 -> 1158.3452 | E12: =('Consolidated - P&L'!FG63)/10000000 -> 1719.155 | F12: =('Consolidated - P&L'!FH63)/10000000 -> 2186.6364 | G12: =('Consolidated - P&L'!FI63)/10000000 -> 2658.0117 | H12: =('Consolidated - P&L'!FJ63)/10000000 -> 3109.1173 | J12: Revenue Post Tax | K12: =C12/C$12 -> 1 | L12: =D12/D$12 -> 1 | M12: =E12/E$12 -> 1 | N12: =F12/F$12 -> 1 | O12: =G12/G$12 -> 1 | P12: =H12/H$12 -> 1
B13: Non- Repair | C13: =('Consolidated - P&L'!FE64)/10000000 -> 363.11378 | D13: =('Consolidated - P&L'!FF64)/10000000 -> 393.89294 | E13: =('Consolidated - P&L'!FG64)/10000000 -> 589.27142 | F13: =('Consolidated - P&L'!FH64)/10000000 -> 755.58035 | G13: =('Consolidated - P&L'!FI64)/10000000 -> 944.47544 | H13: =('Consolidated - P&L'!FJ64)/10000000 -> 1133.3705 | J13: Non- Repair | K13: =('Consolidated - P&L'!FM64)/10000000 -> 0 | L13: =('Consolidated - P&L'!FN64)/10000000 -> 0 | M13: =('Consolidated - P&L'!FO64)/10000000 -> 0 | N13: =('Consolidated - P&L'!FP64)/10000000 -> 0 | O13: =('Consolidated - P&L'!FQ64)/10000000 -> 0 | P13: =('Consolidated - P&L'!FR64)/10000000 -> 0
B14: Refurbished | C14: =('Consolidated - P&L'!FE65)/10000000 -> 558.41442 | D14: =('Consolidated - P&L'!FF65)/10000000 -> 665.69803 | E14: =('Consolidated - P&L'!FG65)/10000000 -> 997.76044 | F14: =('Consolidated - P&L'!FH65)/10000000 -> 1267.2722 | G14: =('Consolidated - P&L'!FI65)/10000000 -> 1523.2108 | H14: =('Consolidated - P&L'!FJ65)/10000000 -> 1762.0933 | J14: Refurbished | K14: =('Consolidated - P&L'!FM65)/10000000 -> 0 | L14: =('Consolidated - P&L'!FN65)/10000000 -> 0 | M14: =('Consolidated - P&L'!FO65)/10000000 -> 0 | N14: =('Consolidated - P&L'!FP65)/10000000 -> 0 | O14: =('Consolidated - P&L'!FQ65)/10000000 -> 0 | P14: =('Consolidated - P&L'!FR65)/10000000 -> 0
B15: Market Place | C15: =('Consolidated - P&L'!FE66)/10000000 -> 52.097639 | D15: =('Consolidated - P&L'!FF66)/10000000 -> 63.813216 | E15: =('Consolidated - P&L'!FG66)/10000000 -> 81.954121 | F15: =('Consolidated - P&L'!FH66)/10000000 -> 105.51593 | G15: =('Consolidated - P&L'!FI66)/10000000 -> 126.61912 | H15: =('Consolidated - P&L'!FJ66)/10000000 -> 145.61199 | J15: Market Place | K15: =('Consolidated - P&L'!FM66)/10000000 -> 0 | L15: =('Consolidated - P&L'!FN66)/10000000 -> 0 | M15: =('Consolidated - P&L'!FO66)/10000000 -> 0 | N15: =('Consolidated - P&L'!FP66)/10000000 -> 0 | O15: =('Consolidated - P&L'!FQ66)/10000000 -> 0 | P15: =('Consolidated - P&L'!FR66)/10000000 -> 0
B16: Screen Pro + Accessories | C16: =('Consolidated - P&L'!FE67)/10000000 -> 26.257819 | D16: =('Consolidated - P&L'!FF67)/10000000 -> 32.204564 | E16: =('Consolidated - P&L'!FG67)/10000000 -> 46.269226 | F16: =('Consolidated - P&L'!FH67)/10000000 -> 54.368071 | G16: =('Consolidated - P&L'!FI67)/10000000 -> 59.80646 | H16: =('Consolidated - P&L'!FJ67)/10000000 -> 64.141757 | J16: Screen Pro + Accessories | K16: =('Consolidated - P&L'!FM67)/10000000 -> 0 | L16: =('Consolidated - P&L'!FN67)/10000000 -> 0 | M16: =('Consolidated - P&L'!FO67)/10000000 -> 0 | N16: =('Consolidated - P&L'!FP67)/10000000 -> 0 | O16: =('Consolidated - P&L'!FQ67)/10000000 -> 0 | P16: =('Consolidated - P&L'!FR67)/10000000 -> 0
B17: Enterprise Sales | C17: =('Consolidated - P&L'!FE68)/10000000 -> 1.4942548 | D17: =('Consolidated - P&L'!FF68)/10000000 -> 2.7364487 | E17: =('Consolidated - P&L'!FG68)/10000000 -> 3.8998185 | F17: =('Consolidated - P&L'!FH68)/10000000 -> 3.8998185 | G17: =('Consolidated - P&L'!FI68)/10000000 -> 3.8998185 | H17: =('Consolidated - P&L'!FJ68)/10000000 -> 3.8998185 | J17: Enterprise Sales | K17: =('Consolidated - P&L'!FM68)/10000000 -> 0 | L17: =('Consolidated - P&L'!FN68)/10000000 -> 0 | M17: =('Consolidated - P&L'!FO68)/10000000 -> 0 | N17: =('Consolidated - P&L'!FP68)/10000000 -> 0 | O17: =('Consolidated - P&L'!FQ68)/10000000 -> 0 | P17: =('Consolidated - P&L'!FR68)/10000000 -> 0
B18: Revenue Growth % | D18: =D12/C12-1 -> 0.1567513 | E18: =E12/D12-1 -> 0.48414742 | F18: =F12/E12-1 -> 0.27192507 | G18: =G12/F12-1 -> 0.21557096 | H18: =H12/G12-1 -> 0.16971545 | J18: Revenue Growth % | L18: =L12/K12-1 -> 0 | M18: =M12/L12-1 -> 0 | N18: =N12/M12-1 -> 0 | O18: =O12/N12-1 -> 0 | P18: =P12/O12-1 -> 0
B20: #Transactions | C20: ='Consolidated - P&L'!FE78 -> 1400717 | D20: ='Consolidated - P&L'!FF78 -> 1422394 | E20: ='Consolidated - P&L'!FG78 -> 1830710.6 | F20: ='Consolidated - P&L'!FH78 -> 2330266.5 | G20: ='Consolidated - P&L'!FI78 -> 2821043.9 | H20: ='Consolidated - P&L'!FJ78 -> 3291993.7 | J20: #Transactions | K20: ='Consolidated - P&L'!FM78 -> 0 | L20: ='Consolidated - P&L'!FN78 -> 0 | M20: ='Consolidated - P&L'!FO78 -> 0 | N20: ='Consolidated - P&L'!FP78 -> 0 | O20: ='Consolidated - P&L'!FQ78 -> 0 | P20: ='Consolidated - P&L'!FR78 -> 0
B21: Non- Repair | C21: ='Consolidated - P&L'!FE79 -> 459194 | D21: ='Consolidated - P&L'!FF79 -> 447334 | E21: ='Consolidated - P&L'!FG79 -> 613323.31 | F21: ='Consolidated - P&L'!FH79 -> 815479.92 | G21: ='Consolidated - P&L'!FI79 -> 1019349.9 | H21: ='Consolidated - P&L'!FJ79 -> 1223219.9 | J21: Non- Repair | K21: ='Consolidated - P&L'!FM79 -> 0 | L21: ='Consolidated - P&L'!FN79 -> 0 | M21: ='Consolidated - P&L'!FO79 -> 0 | N21: ='Consolidated - P&L'!FP79 -> 0 | O21: ='Consolidated - P&L'!FQ79 -> 0 | P21: ='Consolidated - P&L'!FR79 -> 0
B22: Refurbished | C22: ='Consolidated - P&L'!FE80 -> 243372 | D22: ='Consolidated - P&L'!FF80 -> 253977 | E22: ='Consolidated - P&L'!FG80 -> 359093.29 | F22: ='Consolidated - P&L'!FH80 -> 441919.04 | G22: ='Consolidated - P&L'!FI80 -> 514252.95 | H22: ='Consolidated - P&L'!FJ80 -> 588216.62 | J22: Refurbished | K22: ='Consolidated - P&L'!FM80 -> 0 | L22: ='Consolidated - P&L'!FN80 -> 0 | M22: ='Consolidated - P&L'!FO80 -> 0 | N22: ='Consolidated - P&L'!FP80 -> 0 | O22: ='Consolidated - P&L'!FQ80 -> 0 | P22: ='Consolidated - P&L'!FR80 -> 0
B23: Market Place | C23: ='Consolidated - P&L'!FE81 -> 698151 | D23: ='Consolidated - P&L'!FF81 -> 721083 | E23: ='Consolidated - P&L'!FG81 -> 858294 | F23: ='Consolidated - P&L'!FH81 -> 1072867.5 | G23: ='Consolidated - P&L'!FI81 -> 1287441 | H23: ='Consolidated - P&L'!FJ81 -> 1480557.1 | J23: Market Place | K23: ='Consolidated - P&L'!FM81 -> 0 | L23: ='Consolidated - P&L'!FN81 -> 0 | M23: ='Consolidated - P&L'!FO81 -> 0 | N23: ='Consolidated - P&L'!FP81 -> 0 | O23: ='Consolidated - P&L'!FQ81 -> 0 | P23: ='Consolidated - P&L'!FR81 -> 0
B25: Gross Margin 1 | C25: =('Consolidated - P&L'!FE101)/10000000 -> 174.53873 | D25: =('Consolidated - P&L'!FF101)/10000000 -> 242.71886 | E25: =('Consolidated - P&L'!FG101)/10000000 -> 345.32878 | F25: =('Consolidated - P&L'!FH101)/10000000 -> 431.70878 | G25: =('Consolidated - P&L'!FI101)/10000000 -> 524.96996 | H25: =('Consolidated - P&L'!FJ101)/10000000 -> 612.95692 | J25: Gross Margin 1 | K25: =C25/C$12 -> 0.17429857 | L25: =D25/D$12 -> 0.20953932 | M25: =E25/E$12 -> 0.20087123 | N25: =F25/F$12 -> 0.19743053 | O25: =G25/G$12 -> 0.19750476 | P25: =H25/H$12 -> 0.19714821
B26: Non- Repair | C26: =('Consolidated - P&L'!FE102)/10000000 -> 14.125598 | D26: =('Consolidated - P&L'!FF102)/10000000 -> 27.054408 | E26: =('Consolidated - P&L'!FG102)/10000000 -> 44.508853 | F26: =('Consolidated - P&L'!FH102)/10000000 -> 55.450024 | G26: =('Consolidated - P&L'!FI102)/10000000 -> 77.616632 | H26: =('Consolidated - P&L'!FJ102)/10000000 -> 103.00523 | J26: Non- Repair | K26: =('Consolidated - P&L'!FM102)/10000000 -> 0 | L26: =('Consolidated - P&L'!FN102)/10000000 -> 0 | M26: =('Consolidated - P&L'!FO102)/10000000 -> 0 | N26: =('Consolidated - P&L'!FP102)/10000000 -> 0 | O26: =('Consolidated - P&L'!FQ102)/10000000 -> 0 | P26: =('Consolidated - P&L'!FR102)/10000000 -> 0
B27: Refurbished | C27: =('Consolidated - P&L'!FE103)/10000000 -> 99.369447 | D27: =('Consolidated - P&L'!FF103)/10000000 -> 139.47381 | E27: =('Consolidated - P&L'!FG103)/10000000 -> 201.88745 | F27: =('Consolidated - P&L'!FH103)/10000000 -> 253.4483 | G27: =('Consolidated - P&L'!FI103)/10000000 -> 302.87904 | H27: =('Consolidated - P&L'!FJ103)/10000000 -> 346.03004 | J27: Refurbished | K27: =('Consolidated - P&L'!FM103)/10000000 -> 0 | L27: =('Consolidated - P&L'!FN103)/10000000 -> 0 | M27: =('Consolidated - P&L'!FO103)/10000000 -> 0 | N27: =('Consolidated - P&L'!FP103)/10000000 -> 0 | O27: =('Consolidated - P&L'!FQ103)/10000000 -> 0 | P27: =('Consolidated - P&L'!FR103)/10000000 -> 0
B28: Market Place | C28: =('Consolidated - P&L'!FE104)/10000000 -> 52.097639 | D28: =('Consolidated - P&L'!FF104)/10000000 -> 63.813216 | E28: =('Consolidated - P&L'!FG104)/10000000 -> 81.954121 | F28: =('Consolidated - P&L'!FH104)/10000000 -> 105.51593 | G28: =('Consolidated - P&L'!FI104)/10000000 -> 126.61912 | H28: =('Consolidated - P&L'!FJ104)/10000000 -> 145.61199 | J28: Market Place | K28: =('Consolidated - P&L'!FM104)/10000000 -> 0 | L28: =('Consolidated - P&L'!FN104)/10000000 -> 0 | M28: =('Consolidated - P&L'!FO104)/10000000 -> 0 | N28: =('Consolidated - P&L'!FP104)/10000000 -> 0 | O28: =('Consolidated - P&L'!FQ104)/10000000 -> 0 | P28: =('Consolidated - P&L'!FR104)/10000000 -> 0
B29: Screen Pro + Accessories | C29: =('Consolidated - P&L'!FE105)/10000000 -> 7.4517943 | D29: =('Consolidated - P&L'!FF105)/10000000 -> 9.6409796 | E29: =('Consolidated - P&L'!FG105)/10000000 -> 13.078534 | F29: =('Consolidated - P&L'!FH105)/10000000 -> 13.394705 | G29: =('Consolidated - P&L'!FI105)/10000000 -> 13.955344 | H29: =('Consolidated - P&L'!FJ105)/10000000 -> 14.409844 | J29: Screen Pro + Accessories | K29: =('Consolidated - P&L'!FM105)/10000000 -> 0 | L29: =('Consolidated - P&L'!FN105)/10000000 -> 0 | M29: =('Consolidated - P&L'!FO105)/10000000 -> 0 | N29: =('Consolidated - P&L'!FP105)/10000000 -> 0 | O29: =('Consolidated - P&L'!FQ105)/10000000 -> 0 | P29: =('Consolidated - P&L'!FR105)/10000000 -> 0
B30: Enterprise Sales | C30: =('Consolidated - P&L'!FE106)/10000000 -> 1.4942548 | D30: =('Consolidated - P&L'!FF106)/10000000 -> 2.7364487 | E30: =('Consolidated - P&L'!FG106)/10000000 -> 3.8998185 | F30: =('Consolidated - P&L'!FH106)/10000000 -> 3.8998185 | G30: =('Consolidated - P&L'!FI106)/10000000 -> 3.8998185 | H30: =('Consolidated - P&L'!FJ106)/10000000 -> 3.8998185 | J30: Enterprise Sales | K30: =('Consolidated - P&L'!FM106)/10000000 -> 0 | L30: =('Consolidated - P&L'!FN106)/10000000 -> 0 | M30: =('Consolidated - P&L'!FO106)/10000000 -> 0 | N30: =('Consolidated - P&L'!FP106)/10000000 -> 0 | O30: =('Consolidated - P&L'!FQ106)/10000000 -> 0 | P30: =('Consolidated - P&L'!FR106)/10000000 -> 0
B31: Gross Margin 1% | C31: ='Consolidated - P&L'!FE107 -> 0.17429857 | D31: ='Consolidated - P&L'!FF107 -> 0.20953932 | E31: ='Consolidated - P&L'!FG107 -> 0.20087123 | F31: ='Consolidated - P&L'!FH107 -> 0.19743053 | G31: ='Consolidated - P&L'!FI107 -> 0.19750476 | H31: ='Consolidated - P&L'!FJ107 -> 0.19714821 | J31: Gross Margin 1% | K31: ='Consolidated - P&L'!FM107 -> 0 | L31: ='Consolidated - P&L'!FN107 -> 0 | M31: ='Consolidated - P&L'!FO107 -> 0 | N31: ='Consolidated - P&L'!FP107 -> 0 | O31: ='Consolidated - P&L'!FQ107 -> 0 | P31: ='Consolidated - P&L'!FR107 -> 0
B32: Gross Margin 1% w/o MP | C32: ='Consolidated - P&L'!FE108 -> 0.12898308 | D32: ='Consolidated - P&L'!FF108 -> 0.16345402 | E32: ='Consolidated - P&L'!FG108 -> 0.16086887 | F32: ='Consolidated - P&L'!FH108 -> 0.15673905 | G32: ='Consolidated - P&L'!FI108 -> 0.15736431 | H32: ='Consolidated - P&L'!FJ108 -> 0.15770005 | J32: Gross Margin 1% w/o MP | K32: ='Consolidated - P&L'!FM108 -> 0 | L32: ='Consolidated - P&L'!FN108 -> 0 | M32: ='Consolidated - P&L'!FO108 -> 0 | N32: ='Consolidated - P&L'!FP108 -> 0 | O32: ='Consolidated - P&L'!FQ108 -> 0 | P32: ='Consolidated - P&L'!FR108 -> 0
B34: Gross Margin 2 | C34: =('Consolidated - P&L'!FE110)/10000000 -> 161.61025 | D34: =('Consolidated - P&L'!FF110)/10000000 -> 226.93981 | E34: =('Consolidated - P&L'!FG110)/10000000 -> 319.86178 | F34: =('Consolidated - P&L'!FH110)/10000000 -> 403.55687 | G34: =('Consolidated - P&L'!FI110)/10000000 -> 491.07039 | H34: =('Consolidated - P&L'!FJ110)/10000000 -> 573.29335 | J34: Gross Margin 2 | K34: =C34/C$12 -> 0.16138788 | L34: =D34/D$12 -> 0.19591726 | M34: =E34/E$12 -> 0.18605755 | N34: =F34/F$12 -> 0.184556 | O34: =G34/G$12 -> 0.18475103 | P34: =H34/H$12 -> 0.18439103
B35: Non- Repair | C35: =('Consolidated - P&L'!FE111)/10000000 -> 14.125598 | D35: =('Consolidated - P&L'!FF111)/10000000 -> 25.048841 | E35: =('Consolidated - P&L'!FG111)/10000000 -> 40.444667 | F35: =('Consolidated - P&L'!FH111)/10000000 -> 50.238811 | G35: =('Consolidated - P&L'!FI111)/10000000 -> 71.102616 | H35: =('Consolidated - P&L'!FJ111)/10000000 -> 95.188413 | J35: Non- Repair | K35: =('Consolidated - P&L'!FM111)/10000000 -> 0 | L35: =('Consolidated - P&L'!FN111)/10000000 -> 0 | M35: =('Consolidated - P&L'!FO111)/10000000 -> 0 | N35: =('Consolidated - P&L'!FP111)/10000000 -> 0 | O35: =('Consolidated - P&L'!FQ111)/10000000 -> 0 | P35: =('Consolidated - P&L'!FR111)/10000000 -> 0
B36: Refurbished | C36: =('Consolidated - P&L'!FE112)/10000000 -> 86.440968 | D36: =('Consolidated - P&L'!FF112)/10000000 -> 125.70032 | E36: =('Consolidated - P&L'!FG112)/10000000 -> 180.48463 | F36: =('Consolidated - P&L'!FH112)/10000000 -> 230.5076 | G36: =('Consolidated - P&L'!FI112)/10000000 -> 275.49349 | H36: =('Consolidated - P&L'!FJ112)/10000000 -> 314.18329 | J36: Refurbished | K36: =('Consolidated - P&L'!FM112)/10000000 -> 0 | L36: =('Consolidated - P&L'!FN112)/10000000 -> 0 | M36: =('Consolidated - P&L'!FO112)/10000000 -> 0 | N36: =('Consolidated - P&L'!FP112)/10000000 -> 0 | O36: =('Consolidated - P&L'!FQ112)/10000000 -> 0 | P36: =('Consolidated - P&L'!FR112)/10000000 -> 0
B37: Market Place | C37: =('Consolidated - P&L'!FE113)/10000000 -> 52.097639 | D37: =('Consolidated - P&L'!FF113)/10000000 -> 63.813216 | E37: =('Consolidated - P&L'!FG113)/10000000 -> 81.954121 | F37: =('Consolidated - P&L'!FH113)/10000000 -> 105.51593 | G37: =('Consolidated - P&L'!FI113)/10000000 -> 126.61912 | H37: =('Consolidated - P&L'!FJ113)/10000000 -> 145.61199 | J37: Market Place | K37: =('Consolidated - P&L'!FM113)/10000000 -> 0 | L37: =('Consolidated - P&L'!FN113)/10000000 -> 0 | M37: =('Consolidated - P&L'!FO113)/10000000 -> 0 | N37: =('Consolidated - P&L'!FP113)/10000000 -> 0 | O37: =('Consolidated - P&L'!FQ113)/10000000 -> 0 | P37: =('Consolidated - P&L'!FR113)/10000000 -> 0
B38: Screen Pro + Accessories | C38: =('Consolidated - P&L'!FE114)/10000000 -> 7.4517943 | D38: =('Consolidated - P&L'!FF114)/10000000 -> 9.6409796 | E38: =('Consolidated - P&L'!FG114)/10000000 -> 13.078534 | F38: =('Consolidated - P&L'!FH114)/10000000 -> 13.394705 | G38: =('Consolidated - P&L'!FI114)/10000000 -> 13.955344 | H38: =('Consolidated - P&L'!FJ114)/10000000 -> 14.409844 | J38: Screen Pro + Accessories | K38: =('Consolidated - P&L'!FM114)/10000000 -> 0 | L38: =('Consolidated - P&L'!FN114)/10000000 -> 0 | M38: =('Consolidated - P&L'!FO114)/10000000 -> 0 | N38: =('Consolidated - P&L'!FP114)/10000000 -> 0 | O38: =('Consolidated - P&L'!FQ114)/10000000 -> 0 | P38: =('Consolidated - P&L'!FR114)/10000000 -> 0
B39: Enterprise Sales | C39: =('Consolidated - P&L'!FE115)/10000000 -> 1.4942548 | D39: =('Consolidated - P&L'!FF115)/10000000 -> 2.7364487 | E39: =('Consolidated - P&L'!FG115)/10000000 -> 3.8998185 | F39: =('Consolidated - P&L'!FH115)/10000000 -> 3.8998185 | G39: =('Consolidated - P&L'!FI115)/10000000 -> 3.8998185 | H39: =('Consolidated - P&L'!FJ115)/10000000 -> 3.8998185 | J39: Enterprise Sales | K39: =('Consolidated - P&L'!FM115)/10000000 -> 0 | L39: =('Consolidated - P&L'!FN115)/10000000 -> 0 | M39: =('Consolidated - P&L'!FO115)/10000000 -> 0 | N39: =('Consolidated - P&L'!FP115)/10000000 -> 0 | O39: =('Consolidated - P&L'!FQ115)/10000000 -> 0 | P39: =('Consolidated - P&L'!FR115)/10000000 -> 0
B40: Gross Margin 2% | C40: ='Consolidated - P&L'!FE116 -> 0.16138788 | D40: ='Consolidated - P&L'!FF116 -> 0.19591726 | E40: ='Consolidated - P&L'!FG116 -> 0.18605755 | F40: ='Consolidated - P&L'!FH116 -> 0.184556 | G40: ='Consolidated - P&L'!FI116 -> 0.18475103 | H40: ='Consolidated - P&L'!FJ116 -> 0.18439103 | J40: Gross Margin 2% | K40: ='Consolidated - P&L'!FM116 -> 0 | L40: ='Consolidated - P&L'!FN116 -> 0 | M40: ='Consolidated - P&L'!FO116 -> 0 | N40: ='Consolidated - P&L'!FP116 -> 0 | O40: ='Consolidated - P&L'!FQ116 -> 0 | P40: ='Consolidated - P&L'!FR116 -> 0
B41: Gross Margin 2% w/o MP | C41: ='Consolidated - P&L'!FE117 -> 0.11536384 | D41: ='Consolidated - P&L'!FF117 -> 0.14903776 | E41: ='Consolidated - P&L'!FG117 -> 0.14531366 | F41: ='Consolidated - P&L'!FH117 -> 0.14321177 | G41: ='Consolidated - P&L'!FI117 -> 0.14397264 | H41: ='Consolidated - P&L'!FJ117 -> 0.14431604 | J41: Gross Margin 2% w/o MP | K41: ='Consolidated - P&L'!FM117 -> 0 | L41: ='Consolidated - P&L'!FN117 -> 0 | M41: ='Consolidated - P&L'!FO117 -> 0 | N41: ='Consolidated - P&L'!FP117 -> 0 | O41: ='Consolidated - P&L'!FQ117 -> 0 | P41: ='Consolidated - P&L'!FR117 -> 0
B43: Contribution Margin 1 | C43: =('Consolidated - P&L'!FE136)/10000000 -> 120.45747 | D43: =('Consolidated - P&L'!FF136)/10000000 -> 182.61407 | E43: =('Consolidated - P&L'!FG136)/10000000 -> 257.09541 | F43: =('Consolidated - P&L'!FH136)/10000000 -> 333.52046 | G43: =('Consolidated - P&L'!FI136)/10000000 -> 408.4684 | H43: =('Consolidated - P&L'!FJ136)/10000000 -> 478.93205 | J43: Contribution Margin 1 | K43: =C43/C$12 -> 0.12029172 | L43: =D43/D$12 -> 0.15765082 | M43: =E43/E$12 -> 0.14954754 | N43: =F43/F$12 -> 0.15252671 | O43: =G43/G$12 -> 0.15367442 | P43: =H43/H$12 -> 0.15404116
B44: Non- Repair | C44: =('Consolidated - P&L'!FE137)/10000000 -> 2.6324315 | D44: =('Consolidated - P&L'!FF137)/10000000 -> 15.636157 | E44: =('Consolidated - P&L'!FG137)/10000000 -> 28.487262 | F44: =('Consolidated - P&L'!FH137)/10000000 -> 36.972971 | G44: =('Consolidated - P&L'!FI137)/10000000 -> 56.243804 | H44: =('Consolidated - P&L'!FJ137)/10000000 -> 78.610496 | J44: Non- Repair | K44: =('Consolidated - P&L'!FM137)/10000000 -> 0 | L44: =('Consolidated - P&L'!FN137)/10000000 -> 0 | M44: =('Consolidated - P&L'!FO137)/10000000 -> 0 | N44: =('Consolidated - P&L'!FP137)/10000000 -> 0 | O44: =('Consolidated - P&L'!FQ137)/10000000 -> 0 | P44: =('Consolidated - P&L'!FR137)/10000000 -> 0
B45: Refurbished | C45: =('Consolidated - P&L'!FE138)/10000000 -> 56.781349 | D45: =('Consolidated - P&L'!FF138)/10000000 -> 90.78727 | E45: =('Consolidated - P&L'!FG138)/10000000 -> 129.67567 | F45: =('Consolidated - P&L'!FH138)/10000000 -> 173.73704 | G45: =('Consolidated - P&L'!FI138)/10000000 -> 207.75032 | H45: =('Consolidated - P&L'!FJ138)/10000000 -> 236.39991 | J45: Refurbished | K45: =('Consolidated - P&L'!FM138)/10000000 -> 0 | L45: =('Consolidated - P&L'!FN138)/10000000 -> 0 | M45: =('Consolidated - P&L'!FO138)/10000000 -> 0 | N45: =('Consolidated - P&L'!FP138)/10000000 -> 0 | O45: =('Consolidated - P&L'!FQ138)/10000000 -> 0 | P45: =('Consolidated - P&L'!FR138)/10000000 -> 0
B46: Market Place | C46: =('Consolidated - P&L'!FE139)/10000000 -> 52.097639 | D46: =('Consolidated - P&L'!FF139)/10000000 -> 63.813216 | E46: =('Consolidated - P&L'!FG139)/10000000 -> 81.954121 | F46: =('Consolidated - P&L'!FH139)/10000000 -> 105.51593 | G46: =('Consolidated - P&L'!FI139)/10000000 -> 126.61912 | H46: =('Consolidated - P&L'!FJ139)/10000000 -> 145.61199 | J46: Market Place | K46: =('Consolidated - P&L'!FM139)/10000000 -> 0 | L46: =('Consolidated - P&L'!FN139)/10000000 -> 0 | M46: =('Consolidated - P&L'!FO139)/10000000 -> 0 | N46: =('Consolidated - P&L'!FP139)/10000000 -> 0 | O46: =('Consolidated - P&L'!FQ139)/10000000 -> 0 | P46: =('Consolidated - P&L'!FR139)/10000000 -> 0
B47: Screen Pro + Accessories | C47: =('Consolidated - P&L'!FE140)/10000000 -> 7.4517943 | D47: =('Consolidated - P&L'!FF140)/10000000 -> 9.6409796 | E47: =('Consolidated - P&L'!FG140)/10000000 -> 13.078534 | F47: =('Consolidated - P&L'!FH140)/10000000 -> 13.394705 | G47: =('Consolidated - P&L'!FI140)/10000000 -> 13.955344 | H47: =('Consolidated - P&L'!FJ140)/10000000 -> 14.409844 | J47: Screen Pro + Accessories | K47: =('Consolidated - P&L'!FM140)/10000000 -> 0 | L47: =('Consolidated - P&L'!FN140)/10000000 -> 0 | M47: =('Consolidated - P&L'!FO140)/10000000 -> 0 | N47: =('Consolidated - P&L'!FP140)/10000000 -> 0 | O47: =('Consolidated - P&L'!FQ140)/10000000 -> 0 | P47: =('Consolidated - P&L'!FR140)/10000000 -> 0
B48: Enterprise Sales | C48: =('Consolidated - P&L'!FE141)/10000000 -> 1.4942548 | D48: =('Consolidated - P&L'!FF141)/10000000 -> 2.7364487 | E48: =('Consolidated - P&L'!FG141)/10000000 -> 3.8998185 | F48: =('Consolidated - P&L'!FH141)/10000000 -> 3.8998185 | G48: =('Consolidated - P&L'!FI141)/10000000 -> 3.8998185 | H48: =('Consolidated - P&L'!FJ141)/10000000 -> 3.8998185 | J48: Enterprise Sales | K48: =('Consolidated - P&L'!FM141)/10000000 -> 0 | L48: =('Consolidated - P&L'!FN141)/10000000 -> 0 | M48: =('Consolidated - P&L'!FO141)/10000000 -> 0 | N48: =('Consolidated - P&L'!FP141)/10000000 -> 0 | O48: =('Consolidated - P&L'!FQ141)/10000000 -> 0 | P48: =('Consolidated - P&L'!FR141)/10000000 -> 0
B49: CM1% | C49: ='Consolidated - P&L'!FE143 -> 0.12029172 | D49: ='Consolidated - P&L'!FF143 -> 0.15765082 | E49: ='Consolidated - P&L'!FG143 -> 0.14954754 | F49: ='Consolidated - P&L'!FH143 -> 0.15252671 | G49: ='Consolidated - P&L'!FI143 -> 0.15367442 | H49: ='Consolidated - P&L'!FJ143 -> 0.15404116 | J49: CM1% | K49: ='Consolidated - P&L'!FM143 -> 0 | L49: ='Consolidated - P&L'!FN143 -> 0 | M49: ='Consolidated - P&L'!FO143 -> 0 | N49: ='Consolidated - P&L'!FP143 -> 0 | O49: ='Consolidated - P&L'!FQ143 -> 0 | P49: ='Consolidated - P&L'!FR143 -> 0
B51: Contribution Margin 2 | C51: =('Consolidated - P&L'!FE166)/10000000 -> 54.043868 | D51: =('Consolidated - P&L'!FF166)/10000000 -> 114.27211 | E51: =('Consolidated - P&L'!FG166)/10000000 -> 156.44506 | F51: =('Consolidated - P&L'!FH166)/10000000 -> 205.7087 | G51: =('Consolidated - P&L'!FI166)/10000000 -> 266.78988 | H51: =('Consolidated - P&L'!FJ166)/10000000 -> 322.2607 | J51: Contribution Margin 2 | K51: =C51/C$12 -> 0.053969503 | L51: =D51/D$12 -> 0.098651167 | M51: =E51/E$12 -> 0.091001137 | N51: =F51/F$12 -> 0.094075405 | O51: =G51/G$12 -> 0.10037197 | P51: =H51/H$12 -> 0.10365022
B52: Non- Repair | C52: =('Consolidated - P&L'!FE167)/10000000 -> -5.0254699 | D52: =('Consolidated - P&L'!FF167)/10000000 -> 9.0064734 | E52: =('Consolidated - P&L'!FG167)/10000000 -> 19.222227 | F52: =('Consolidated - P&L'!FH167)/10000000 -> 25.641459 | G52: =('Consolidated - P&L'!FI167)/10000000 -> 43.542987 | H52: =('Consolidated - P&L'!FJ167)/10000000 -> 64.364343 | J52: Non- Repair | K52: =('Consolidated - P&L'!FM167)/10000000 -> 0 | L52: =('Consolidated - P&L'!FN167)/10000000 -> 0 | M52: =('Consolidated - P&L'!FO167)/10000000 -> 0 | N52: =('Consolidated - P&L'!FP167)/10000000 -> 0 | O52: =('Consolidated - P&L'!FQ167)/10000000 -> 0 | P52: =('Consolidated - P&L'!FR167)/10000000 -> 0
B53: Refurbished | C53: =('Consolidated - P&L'!FE168)/10000000 -> 8.1714722 | D53: =('Consolidated - P&L'!FF168)/10000000 -> 40.663493 | E53: =('Consolidated - P&L'!FG168)/10000000 -> 53.692823 | F53: =('Consolidated - P&L'!FH168)/10000000 -> 74.899675 | G53: =('Consolidated - P&L'!FI168)/10000000 -> 97.526098 | H53: =('Consolidated - P&L'!FJ168)/10000000 -> 114.0501 | J53: Refurbished | K53: =('Consolidated - P&L'!FM168)/10000000 -> 0 | L53: =('Consolidated - P&L'!FN168)/10000000 -> 0 | M53: =('Consolidated - P&L'!FO168)/10000000 -> 0 | N53: =('Consolidated - P&L'!FP168)/10000000 -> 0 | O53: =('Consolidated - P&L'!FQ168)/10000000 -> 0 | P53: =('Consolidated - P&L'!FR168)/10000000 -> 0
B54: Market Place | C54: =('Consolidated - P&L'!FE169)/10000000 -> 43.520944 | D54: =('Consolidated - P&L'!FF169)/10000000 -> 54.162759 | E54: =('Consolidated - P&L'!FG169)/10000000 -> 69.546278 | F54: =('Consolidated - P&L'!FH169)/10000000 -> 91.110584 | G54: =('Consolidated - P&L'!FI169)/10000000 -> 111.07682 | H54: =('Consolidated - P&L'!FJ169)/10000000 -> 128.84255 | J54: Market Place | K54: =('Consolidated - P&L'!FM169)/10000000 -> 0 | L54: =('Consolidated - P&L'!FN169)/10000000 -> 0 | M54: =('Consolidated - P&L'!FO169)/10000000 -> 0 | N54: =('Consolidated - P&L'!FP169)/10000000 -> 0 | O54: =('Consolidated - P&L'!FQ169)/10000000 -> 0 | P54: =('Consolidated - P&L'!FR169)/10000000 -> 0
B55: Screen Pro + Accessories | C55: =('Consolidated - P&L'!FE170)/10000000 -> 5.8826666 | D55: =('Consolidated - P&L'!FF170)/10000000 -> 7.7029321 | E55: =('Consolidated - P&L'!FG170)/10000000 -> 10.083916 | F55: =('Consolidated - P&L'!FH170)/10000000 -> 10.157167 | G55: =('Consolidated - P&L'!FI170)/10000000 -> 10.744153 | H55: =('Consolidated - P&L'!FJ170)/10000000 -> 11.103885 | J55: Screen Pro + Accessories | K55: =('Consolidated - P&L'!FM170)/10000000 -> 0 | L55: =('Consolidated - P&L'!FN170)/10000000 -> 0 | M55: =('Consolidated - P&L'!FO170)/10000000 -> 0 | N55: =('Consolidated - P&L'!FP170)/10000000 -> 0 | O55: =('Consolidated - P&L'!FQ170)/10000000 -> 0 | P55: =('Consolidated - P&L'!FR170)/10000000 -> 0
B56: Enterprise Sales | C56: =('Consolidated - P&L'!FE171)/10000000 -> 1.4942548 | D56: =('Consolidated - P&L'!FF171)/10000000 -> 2.7364487 | E56: =('Consolidated - P&L'!FG171)/10000000 -> 3.8998185 | F56: =('Consolidated - P&L'!FH171)/10000000 -> 3.8998185 | G56: =('Consolidated - P&L'!FI171)/10000000 -> 3.8998185 | H56: =('Consolidated - P&L'!FJ171)/10000000 -> 3.8998185 | J56: Enterprise Sales | K56: =('Consolidated - P&L'!FM171)/10000000 -> 0 | L56: =('Consolidated - P&L'!FN171)/10000000 -> 0 | M56: =('Consolidated - P&L'!FO171)/10000000 -> 0 | N56: =('Consolidated - P&L'!FP171)/10000000 -> 0 | O56: =('Consolidated - P&L'!FQ171)/10000000 -> 0 | P56: =('Consolidated - P&L'!FR171)/10000000 -> 0
B57: CM2% | C57: ='Consolidated - P&L'!FE173 -> 0.053969503 | D57: ='Consolidated - P&L'!FF173 -> 0.098651167 | E57: ='Consolidated - P&L'!FG173 -> 0.091001137 | F57: ='Consolidated - P&L'!FH173 -> 0.094075405 | G57: ='Consolidated - P&L'!FI173 -> 0.10037197 | H57: ='Consolidated - P&L'!FJ173 -> 0.10365022 | J57: CM2% | K57: ='Consolidated - P&L'!FM173 -> 0 | L57: ='Consolidated - P&L'!FN173 -> 0 | M57: ='Consolidated - P&L'!FO173 -> 0 | N57: ='Consolidated - P&L'!FP173 -> 0 | O57: ='Consolidated - P&L'!FQ173 -> 0 | P57: ='Consolidated - P&L'!FR173 -> 0
B59: CM2 - Marketing | C59: =('Consolidated - P&L'!FE197)/10000000 -> 20.617033 | D59: =('Consolidated - P&L'!FF197)/10000000 -> 80.939667 | E59: =('Consolidated - P&L'!FG197)/10000000 -> 120.79894 | F59: =('Consolidated - P&L'!FH197)/10000000 -> 157.74759 | G59: =('Consolidated - P&L'!FI197)/10000000 -> 226.47241 | H59: =('Consolidated - P&L'!FJ197)/10000000 -> 277.10791 | J59: CM2 - Marketing | K59: =C59/C$12 -> 0.020588663 | L59: =D59/D$12 -> 0.069875256 | M59: =E59/E$12 -> 0.070266462 | N59: =F59/F$12 -> 0.072141664 | O59: =G59/G$12 -> 0.085203694 | P59: =H59/H$12 -> 0.089127518
B60: CM3% | C60: ='Consolidated - P&L'!FE198 -> 0.020588663 | D60: ='Consolidated - P&L'!FF198 -> 0.069875256 | E60: ='Consolidated - P&L'!FG198 -> 0.070266462 | F60: ='Consolidated - P&L'!FH198 -> 0.072141664 | G60: ='Consolidated - P&L'!FI198 -> 0.085203694 | H60: ='Consolidated - P&L'!FJ198 -> 0.089127518 | J60: CM3% | K60: ='Consolidated - P&L'!FM198 -> 0 | L60: ='Consolidated - P&L'!FN198 -> 0 | M60: ='Consolidated - P&L'!FO198 -> 0 | N60: ='Consolidated - P&L'!FP198 -> 0 | O60: ='Consolidated - P&L'!FQ198 -> 0 | P60: ='Consolidated - P&L'!FR198 -> 0
B62: EBITDA | C62: =('Consolidated - P&L'!FE211)/10000000 -> -50.043695 | D62: =('Consolidated - P&L'!FF211)/10000000 -> 3.1725511 | E62: =('Consolidated - P&L'!FG211)/10000000 -> 26.108637 | F62: =('Consolidated - P&L'!FH211)/10000000 -> 48.228462 | G62: =('Consolidated - P&L'!FI211)/10000000 -> 111.47733 | H62: =('Consolidated - P&L'!FJ211)/10000000 -> 156.36308 | J62: EBITDA | K62: =C62/C$12 -> -0.049974834 | L62: =D62/D$12 -> 0.002738865 | M62: =E62/E$12 -> 0.015186901 | N62: =F62/F$12 -> 0.022056005 | O62: =G62/G$12 -> 0.041940122 | P62: =H62/H$12 -> 0.05029179
B63: EBITDA% | C63: ='Consolidated - P&L'!FE212 -> -0.049974834 | D63: ='Consolidated - P&L'!FF212 -> 0.002738865 | E63: ='Consolidated - P&L'!FG212 -> 0.015186901 | F63: ='Consolidated - P&L'!FH212 -> 0.022056005 | G63: ='Consolidated - P&L'!FI212 -> 0.041940122 | H63: ='Consolidated - P&L'!FJ212 -> 0.05029179 | J63: EBITDA% | K63: ='Consolidated - P&L'!FM212 -> 0 | L63: ='Consolidated - P&L'!FN212 -> 0 | M63: ='Consolidated - P&L'!FO212 -> 0 | N63: ='Consolidated - P&L'!FP212 -> 0 | O63: ='Consolidated - P&L'!FQ212 -> 0 | P63: ='Consolidated - P&L'!FR212 -> 0

Sheet Consolidated - P&L
B2: Consolidated P&L | C2: 43208 | D2: 43238 | E2: 43269 | F2: 43282 | G2: 43313 | H2: 43344 | I2: 43374 | J2: 43405 | K2: 43435 | L2: 43466 | M2: 43497 | N2: 43525 | O2: 43556 | P2: 43586 | Q2: 43617 | R2: 43647 | S2: 43678 | T2: 43709 | U2: 43740 | V2: 43771 | W2: 43802 | X2: 43833 | Y2: 43864 | Z2: 43895 | AA2: 43926 | AB2: 43957 | AC2: 43988 | AD2: 44019 | AE2: 44050 | AF2: 44081 | AG2: 44112 | AH2: 44143 | AI2: 44174 | AJ2: 44205 | AK2: 44236 | AL2: 44267 | AM2: 44298 | AN2: 44329 | AO2: 44360 | AP2: 44391 | AQ2: 44422 | AR2: 44453 | AS2: 44484 | AT2: 44515 | AU2: 44546 | AV2: 44577 | AW2: 44608 | AX2: 44639 | AY2: 44670 | AZ2: 44701 | BA2: 44732 | BB2: 44763 | BC2: 44794 | BD2: 44825 | BE2: 44856 | BF2: 44887 | BG2: 44918 | BH2: 44949 | BI2: 44980 | BJ2: 45011 | BK2: 45042 | BL2: 45073 | BM2: 45104 | BN2: 45135 | BO2: 45166 | BP2: 45197 | BQ2: 45228 | BR2: 45259 | BS2: 45290 | BT2: 45321 | BU2: 45351 | BV2: 45381 | BW2: 45411 | BX2: 45441 | BY2: 45471 | BZ2: 45501 | CA2: 45531 | CB2: 45561 | CC2: 45591 | CD2: 45621 | CE2: 45651 | CF2: 45681 | CG2: 45711 | CH2: 45741 | CI2: 45771 | CJ2: 45801 | CK2: 45831 | CL2: 45861 | CM2: 45891 | CN2: 45921 | CO2: 45951 | CP2: 45981 | CQ2: 46011 | CR2: 46041 | CS2: 46071 | CT2: 46101 | CU2: 46131 | CV2: 46161 | CW2: 46191 | CX2: 46221 | CY2: 46251 | CZ2: 46281 | DA2: 46311 | DB2: 46341 | DC2: 46371 | DD2: 46401 | DE2: 46431 | DF2: 46461 | DG2: 46491 | DH2: 46521 | DI2: 46551 | DJ2: 46581 | DK2: 46611 | DL2: 46641 | DM2: 46671 | DN2: 46701 | DO2: 46731 | DP2: 46761 | DQ2: 46791 | DR2: 46820 | DS2: 46850 | DT2: 46880 | DU2: 46910 | DV2: 46940 | DW2: 46970 | DX2: 47000 | DY2: 47030 | DZ2: 47060 | EA2: 47090 | EB2: 47120 | EC2: 47150 | ED2: 47180 | EF2: AMJ FY'24 | EG2: JAS FY'24 | EH2: OND FY'24 | EI2: JFM FY'24 | EJ2: AMJ FY'25 | EK2: JAS FY'25 | EL2: OND FY'25 | EM2: JFM FY'25 | EN2: AMJ FY'26 | EO2: JAS FY'26 | EP2: OND FY'26 | EQ2: JFM FY'26 | ER2: AMJ FY'27 | ES2: JAS FY'27 | ET2: OND FY'27 | EU2: JFM FY'27 | EV2: AMJ FY'28 | EW2: JAS FY'28 | EX2: OND FY'28 | EY2: JFM FY'28 | EZ2: AMJ FY'29 | FA2: JAS FY'29 | FB2: OND FY'29 | FC2: JFM FY'29 | FE2: FY24 | FF2: FY25 | FG2: FY26 | FH2: FY27 | FI2: FY28 | FJ2: FY29 | FK2: x
B3: Gross GMV (inc. tax) | C3: =SUM(C4:C9) -> 2.0625874e+08 | D3: =SUM(D4:D9) -> 2.2021778e+08 | E3: =SUM(E4:E9) -> 2.2237028e+08 | F3: =SUM(F4:F9) -> 2.342284e+08 | G3: =SUM(G4:G9) -> 2.3427191e+08 | H3: =SUM(H4:H9) -> 2.2878563e+08 | I3: =SUM(I4:I9) -> 2.4871762e+08 | J3: =SUM(J4:J9) -> 2.3864068e+08 | ... ED3: =SUM(ED4:ED9) -> 4.5898209e+09 | EF3: =SUM(BK3:BM3) -> 4.202441e+09 | EG3: =SUM(BN3:BP3) -> 3.8734387e+09 | EH3: =SUM(BQ3:BS3) -> 4.5157231e+09 | EI3: =SUM(BT3:BV3) -> 4.0192773e+09 | EJ3: =SUM(BW3:BY3) -> 4.3041726e+09 | EK3: =SUM(BZ3:CB3) -> 4.2496062e+09 | EL3: =SUM(CC3:CE3) -> 4.7966889e+09 | EM3: =SUM(CF3:CH3) -> 5.851463e+09 | EN3: =SUM(CI3:CK3) -> 6.045668e+09 | EO3: =SUM(CL3:CN3) -> 5.7937619e+09 | EP3: =SUM(CO3:CQ3) -> 7.0511732e+09 | EQ3: =SUM(CR3:CT3) -> 8.0772257e+09 | ER3: =SUM(CU3:CW3) -> 7.8956376e+09 | ES3: =SUM(CX3:CZ3) -> 7.8881837e+09 | ET3: =SUM(DA3:DC3) -> 9.0657965e+09 | EU3: =SUM(DD3:DF3) -> 9.5312974e+09 | EV3: =SUM(DG3:DI3) -> 9.5976489e+09 | EW3: =SUM(DJ3:DL3) -> 9.5613119e+09 | EX3: =SUM(DM3:DO3) -> 1.0969893e+10 | EY3: =SUM(DP3:DR3) -> 1.1479926e+10 | EZ3: =SUM(DS3:DU3) -> 1.1201536e+10 | FA3: =SUM(DV3:DX3) -> 1.1139467e+10 | FB3: =SUM(DY3:EA3) -> 1.278477e+10 | FC3: =SUM(EB3:ED3) -> 1.3379655e+10 | FE3: =SUM(EF3:EI3) -> 1.661088e+10 | FF3: =SUM(EJ3:EM3) -> 1.9201931e+10 | FG3: =SUM(EN3:EQ3) -> 2.6967829e+10 | FH3: =SUM(ER3:EU3) -> 3.4380915e+10 | FI3: =SUM(EV3:EY3) -> 4.160878e+10 | FJ3: =SUM(EZ3:FC3) -> 4.8505428e+10 | FK3: x
B4: Non- Repair | C4: ='B2B- Non Repair'!C3 -> 127373162 | D4: ='B2B- Non Repair'!D3 -> 119525214 | E4: ='B2B- Non Repair'!E3 -> 1.3361892e+08 | F4: ='B2B- Non Repair'!F3 -> 1.5572126e+08 | G4: ='B2B- Non Repair'!G3 -> 1.8292117e+08 | H4: ='B2B- Non Repair'!H3 -> 190468885 | I4: ='B2B- Non Repair'!I3 -> 203496304 | J4: ='B2B- Non Repair'!J3 -> 191306750 | ... ED4: ='B2B- Non Repair'!ED3 -> 1.179033e+09 | EF4: =SUM(BK4:BM4) -> 1.2890757e+09 | EG4: =SUM(BN4:BP4) -> 1.0415865e+09 | EH4: =SUM(BQ4:BS4) -> 1.0252914e+09 | EI4: =SUM(BT4:BV4) -> 9.6793688e+08 | EJ4: =SUM(BW4:BY4) -> 1.0451431e+09 | EK4: =SUM(BZ4:CB4) -> 9.227319e+08 | EL4: =SUM(CC4:CE4) -> 1.0353764e+09 | EM4: =SUM(CF4:CH4) -> 1.4890117e+09 | EN4: =SUM(CI4:CK4) -> 1.5407526e+09 | EO4: =SUM(CL4:CN4) -> 1.3237275e+09 | EP4: =SUM(CO4:CQ4) -> 1.7371697e+09 | EQ4: =SUM(CR4:CT4) -> 2.0955757e+09 | ER4: =SUM(CU4:CW4) -> 2.0897253e+09 | ES4: =SUM(CX4:CZ4) -> 1.8686695e+09 | ET4: =SUM(DA4:DC4) -> 2.3339744e+09 | EU4: =SUM(DD4:DF4) -> 2.4367945e+09 | EV4: =SUM(DG4:DI4) -> 2.6121566e+09 | EW4: =SUM(DJ4:DL4) -> 2.3358369e+09 | EX4: =SUM(DM4:DO4) -> 2.917468e+09 | EY4: =SUM(DP4:DR4) -> 3.0459931e+09 | EZ4: =SUM(DS4:DU4) -> 3.1345879e+09 | FA4: =SUM(DV4:DX4) -> 2.8030043e+09 | FB4: =SUM(DY4:EA4) -> 3.5009616e+09 | FC4: =SUM(EB4:ED4) -> 3.6551918e+09 | FE4: =SUM(EF4:EI4) -> 4.3238904e+09 | FF4: =SUM(EJ4:EM4) -> 4.4922631e+09 | FG4: =SUM(EN4:EQ4) -> 6.6972255e+09 | FH4: =SUM(ER4:EU4) -> 8.7291637e+09 | FI4: =SUM(EV4:EY4) -> 1.0911455e+10 | FJ4: =SUM(EZ4:FC4) -> 1.3093746e+10 | FK4: x
B5: Refurbished | C5: =Refurbished!C3 -> 6493223.7 | D5: =Refurbished!D3 -> 6995016 | E5: =Refurbished!E3 -> 6266783 | F5: =Refurbished!F3 -> 9975111.8 | G5: =Refurbished!G3 -> 8792729.1 | H5: =Refurbished!H3 -> 7349297.7 | I5: =Refurbished!I3 -> 8404052.8 | J5: =Refurbished!J3 -> 10228739 | ... ED5: =Refurbished!ED3 -> 2.1542574e+09 | EF5: =SUM(BK5:BM5) -> 1.7621507e+09 | EG5: =SUM(BN5:BP5) -> 1.5922534e+09 | EH5: =SUM(BQ5:BS5) -> 2.0350976e+09 | EI5: =SUM(BT5:BV5) -> 1.6352156e+09 | EJ5: =SUM(BW5:BY5) -> 1.8783475e+09 | EK5: =SUM(BZ5:CB5) -> 1.8101626e+09 | EL5: =SUM(CC5:CE5) -> 2.0350473e+09 | EM5: =SUM(CF5:CH5) -> 2.5797599e+09 | EN5: =SUM(CI5:CK5) -> 2.802627e+09 | EO5: =SUM(CL5:CN5) -> 2.6976702e+09 | EP5: =SUM(CO5:CQ5) -> 3.1920014e+09 | EQ5: =SUM(CR5:CT5) -> 3.7638547e+09 | ER5: =SUM(CU5:CW5) -> 3.5884436e+09 | ES5: =SUM(CX5:CZ5) -> 3.5409821e+09 | ET5: =SUM(DA5:DC5) -> 3.990973e+09 | EU5: =SUM(DD5:DF5) -> 4.5253968e+09 | EV5: =SUM(DG5:DI5) -> 4.3364377e+09 | EW5: =SUM(DJ5:DL5) -> 4.2658392e+09 | EX5: =SUM(DM5:DO5) -> 4.7800495e+09 | EY5: =SUM(DP5:DR5) -> 5.3716486e+09 | EZ5: =SUM(DS5:DU5) -> 5.0320902e+09 | FA5: =SUM(DV5:DX5) -> 4.9462534e+09 | FB5: =SUM(DY5:EA5) -> 5.5342234e+09 | FC5: =SUM(EB5:ED5) -> 6.2171883e+09 | FE5: =SUM(EF5:EI5) -> 7.0247173e+09 | FF5: =SUM(EJ5:EM5) -> 8.3033172e+09 | FG5: =SUM(EN5:EQ5) -> 1.2456153e+10 | FH5: =SUM(ER5:EU5) -> 1.5645796e+10 | FI5: =SUM(EV5:EY5) -> 1.8753975e+10 | FJ5: =SUM(EZ5:FC5) -> 2.1729755e+10 | FK5: x
B6: Market Place | C6: =Marketplace!C3 -> 71270132 | D6: =Marketplace!D3 -> 92247410 | E6: =Marketplace!E3 -> 80512562 | F6: =Marketplace!F3 -> 66231280 | G6: =Marketplace!G3 -> 40103506 | H6: =Marketplace!H3 -> 27837941 | I6: =Marketplace!I3 -> 33141999 | J6: =Marketplace!J3 -> 31956623 | ... ED6: =Marketplace!ED3 -> 1.1714241e+09 | EF6: =SUM(BK6:BM6) -> 1072114128 | EG6: =SUM(BN6:BP6) -> 1148662191 | EH6: =SUM(BQ6:BS6) -> 1371300053 | EI6: =SUM(BT6:BV6) -> 1343077704 | EJ6: =SUM(BW6:BY6) -> 1290092206 | EK6: =SUM(BZ6:CB6) -> 1414314262 | EL6: =SUM(CC6:CE6) -> 1617078865 | EM6: =SUM(CF6:CH6) -> 1672561133 | EN6: =SUM(CI6:CK6) -> 1580509516 | EO6: =SUM(CL6:CN6) -> 1627577564 | EP6: =SUM(CO6:CQ6) -> 1954180574 | EQ6: =SUM(CR6:CT6) -> 2008114870 | ER6: =SUM(CU6:CW6) -> 2.0381886e+09 | ES6: =SUM(CX6:CZ6) -> 2.2867613e+09 | ET6: =SUM(DA6:DC6) -> 2.5442938e+09 | EU6: =SUM(DD6:DF6) -> 2.3626238e+09 | EV6: =SUM(DG6:DI6) -> 2.4458263e+09 | EW6: =SUM(DJ6:DL6) -> 2.7441135e+09 | EX6: =SUM(DM6:DO6) -> 3.0531526e+09 | EY6: =SUM(DP6:DR6) -> 2.8351486e+09 | EZ6: =SUM(DS6:DU6) -> 2.8127003e+09 | FA6: =SUM(DV6:DX6) -> 3.1557306e+09 | FB6: =SUM(DY6:EA6) -> 3.5111254e+09 | FC6: =SUM(EB6:ED6) -> 3.2604209e+09 | FE6: =SUM(EF6:EI6) -> 4935154076 | FF6: =SUM(EJ6:EM6) -> 5994046466 | FG6: =SUM(EN6:EQ6) -> 7170382524 | FH6: =SUM(ER6:EU6) -> 9.2318675e+09 | FI6: =SUM(EV6:EY6) -> 1.1078241e+10 | FJ6: =SUM(EZ6:FC6) -> 1.2739977e+10 | FK6: x
B7: Screen Pro + Accessories | C7: =C38 -> 0 | D7: =D38 -> 0 | E7: =E38 -> 0 | F7: =F38 -> 0 | G7: =G38 -> 0 | H7: =H38 -> 0 | I7: =I38 -> 0 | J7: =J38 -> 0 | ... ED7: =ED38 -> 77805406 | EF7: =SUM(BK7:BM7) -> 75240991 | EG7: =SUM(BN7:BP7) -> 86629413 | EH7: =SUM(BQ7:BS7) -> 78698620 | EI7: =SUM(BT7:BV7) -> 69273240 | EJ7: =SUM(BW7:BY7) -> 86679585 | EK7: =SUM(BZ7:CB7) -> 92809367 | EL7: =SUM(CC7:CE7) -> 97839727 | EM7: =SUM(CF7:CH7) -> 1.0268518e+08 | EN7: =SUM(CI7:CK7) -> 1.1525647e+08 | EO7: =SUM(CL7:CN7) -> 1.3117917e+08 | EP7: =SUM(CO7:CQ7) -> 1.5621076e+08 | EQ7: =SUM(CR7:CT7) -> 1.9540338e+08 | ER7: =SUM(CU7:CW7) -> 1.7275758e+08 | ES7: =SUM(CX7:CZ7) -> 1.7816339e+08 | ET7: =SUM(DA7:DC7) -> 1.8494447e+08 | EU7: =SUM(DD7:DF7) -> 1.9220512e+08 | EV7: =SUM(DG7:DI7) -> 1.9670584e+08 | EW7: =SUM(DJ7:DL7) -> 2.0191485e+08 | EX7: =SUM(DM7:DO7) -> 2.0761225e+08 | EY7: =SUM(DP7:DR7) -> 2.1285887e+08 | EZ7: =SUM(DS7:DU7) -> 2.1563518e+08 | FA7: =SUM(DV7:DX7) -> 2.2087167e+08 | FB7: =SUM(DY7:EA7) -> 2.2684901e+08 | FC7: =SUM(EB7:ED7) -> 2.3257655e+08 | FE7: =SUM(EF7:EI7) -> 3.0984226e+08 | FF7: =SUM(EJ7:EM7) -> 3.8001386e+08 | FG7: =SUM(EN7:EQ7) -> 5.9804978e+08 | FH7: =SUM(ER7:EU7) -> 7.2807056e+08 | FI7: =SUM(EV7:EY7) -> 8.190918e+08 | FJ7: =SUM(EZ7:FC7) -> 8.9593241e+08 | FK7: x
B8: Enterprise Sales | C8: =C39 -> 0 | D8: =D39 -> 0 | E8: =E39 -> 0 | F8: =F39 -> 0 | G8: =G39 -> 0 | H8: =H39 -> 0 | I8: =I39 -> 0 | J8: =J39 -> 0 | ... ED8: =ED39 -> 7301025.8 | EF8: =SUM(BK8:BM8) -> 3859521.2 | EG8: =SUM(BN8:BP8) -> 4307213.7 | EH8: =SUM(BQ8:BS8) -> 5335443.4 | EI8: =SUM(BT8:BV8) -> 3773904.9 | EJ8: =SUM(BW8:BY8) -> 3910177 | EK8: =SUM(BZ8:CB8) -> 9588135.2 | EL8: =SUM(CC8:CE8) -> 11346653 | EM8: =SUM(CF8:CH8) -> 7445129.8 | EN8: =SUM(CI8:CK8) -> 6522521 | EO8: =SUM(CL8:CN8) -> 13607431 | EP8: =SUM(CO8:CQ8) -> 11610803 | EQ8: =SUM(CR8:CT8) -> 14277103 | ER8: =SUM(CU8:CW8) -> 6522521 | ES8: =SUM(CX8:CZ8) -> 13607431 | ET8: =SUM(DA8:DC8) -> 11610803 | EU8: =SUM(DD8:DF8) -> 14277103 | EV8: =SUM(DG8:DI8) -> 6522521 | EW8: =SUM(DJ8:DL8) -> 13607431 | EX8: =SUM(DM8:DO8) -> 11610803 | EY8: =SUM(DP8:DR8) -> 14277103 | EZ8: =SUM(DS8:DU8) -> 6522521 | FA8: =SUM(DV8:DX8) -> 13607431 | FB8: =SUM(DY8:EA8) -> 11610803 | FC8: =SUM(EB8:ED8) -> 14277103 | FE8: =SUM(EF8:EI8) -> 17276083 | FF8: =SUM(EJ8:EM8) -> 32290095 | FG8: =SUM(EN8:EQ8) -> 46017858 | FH8: =SUM(ER8:EU8) -> 46017858 | FI8: =SUM(EV8:EY8) -> 46017858 | FJ8: =SUM(EZ8:FC8) -> 46017858 | FK8: x
B9: Screen Pro | C9: =C40 -> 1122221.3 | D9: =D40 -> 1450136.2 | E9: =E40 -> 1972016 | F9: =F40 -> 2300746.3 | G9: =G40 -> 2454507.4 | H9: =H40 -> 3129509.9 | I9: =I40 -> 3675259.9 | J9: =J40 -> 5148563 | ... ED9: =ED40 -> 0 | EF9: =SUM(BK9:BM9) -> 0 | EG9: =SUM(BN9:BP9) -> 0 | EH9: =SUM(BQ9:BS9) -> 0 | EI9: =SUM(BT9:BV9) -> 0 | EJ9: =SUM(BW9:BY9) -> 0 | EK9: =SUM(BZ9:CB9) -> 0 | EL9: =SUM(CC9:CE9) -> 0 | EM9: =SUM(CF9:CH9) -> 0 | EN9: =SUM(CI9:CK9) -> 0 | EO9: =SUM(CL9:CN9) -> 0 | EP9: =SUM(CO9:CQ9) -> 0 | EQ9: =SUM(CR9:CT9) -> 0 | ER9: =SUM(CU9:CW9) -> 0 | ES9: =SUM(CX9:CZ9) -> 0 | ET9: =SUM(DA9:DC9) -> 0 | EU9: =SUM(DD9:DF9) -> 0 | EV9: =SUM(DG9:DI9) -> 0 | EW9: =SUM(DJ9:DL9) -> 0 | EX9: =SUM(DM9:DO9) -> 0 | EY9: =SUM(DP9:DR9) -> 0 | EZ9: =SUM(DS9:DU9) -> 0 | FA9: =SUM(DV9:DX9) -> 0 | FB9: =SUM(DY9:EA9) -> 0 | FC9: =SUM(EB9:ED9) -> 0 | FE9: =SUM(EF9:EI9) -> 0 | FF9: =SUM(EJ9:EM9) -> 0 | FG9: =SUM(EN9:EQ9) -> 0 | FH9: =SUM(ER9:EU9) -> 0 | FI9: =SUM(EV9:EY9) -> 0 | FJ9: =SUM(EZ9:FC9) -> 0 | FK9: x
B11: Non- Repair | C11: ='B2B- Non Repair'!C7 -> 32077 | D11: ='B2B- Non Repair'!D7 -> 28685 | E11: ='B2B- Non Repair'!E7 -> 34758 | F11: ='B2B- Non Repair'!F7 -> 39298 | G11: ='B2B- Non Repair'!G7 -> 47222 | H11: ='B2B- Non Repair'!H7 -> 49152 | I11: ='B2B- Non Repair'!I7 -> 52716 | J11: ='B2B- Non Repair'!J7 -> 52798 | ... ED11: ='B2B- Non Repair'!ED7 -> 118926.68 | EF11: =SUM(BK11:BM11) -> 163773 | EG11: =SUM(BN11:BP11) -> 139081 | EH11: =SUM(BQ11:BS11) -> 121271 | EI11: =SUM(BT11:BV11) -> 98871 | EJ11: =SUM(BW11:BY11) -> 111808 | EK11: =SUM(BZ11:CB11) -> 106895 | EL11: =SUM(CC11:CE11) -> 115221 | EM11: =SUM(CF11:CH11) -> 156997 | EN11: =SUM(CI11:CK11) -> 158486 | EO11: =SUM(CL11:CN11) -> 141721 | EP11: =SUM(CO11:CQ11) -> 177010 | EQ11: =SUM(CR11:CT11) -> 184807.94 | ER11: =SUM(CU11:CW11) -> 210786.38 | ES11: =SUM(CX11:CZ11) -> 188488.93 | ET11: =SUM(DA11:DC11) -> 235423.3 | EU11: =SUM(DD11:DF11) -> 245794.56 | EV11: =SUM(DG11:DI11) -> 263482.98 | EW11: =SUM(DJ11:DL11) -> 235611.16 | EX11: =SUM(DM11:DO11) -> 294279.12 | EY11: =SUM(DP11:DR11) -> 307243.19 | EZ11: =SUM(DS11:DU11) -> 316179.57 | FA11: =SUM(DV11:DX11) -> 282733.4 | FB11: =SUM(DY11:EA11) -> 353134.95 | FC11: =SUM(EB11:ED11) -> 368691.83 | FE11: =SUM(EF11:EI11) -> 522996 | FF11: =SUM(EJ11:EM11) -> 490921 | FG11: =SUM(EN11:EQ11) -> 662024.94 | FH11: =SUM(ER11:EU11) -> 880493.17 | FI11: =SUM(EV11:EY11) -> 1100616.5 | FJ11: =SUM(EZ11:FC11) -> 1320739.7 | FK11: x
B12: Refurbished | C12: =SUM(Refurbished!C8:C10) -> 957 | D12: =SUM(Refurbished!D8:D10) -> 1008 | E12: =SUM(Refurbished!E8:E10) -> 894 | F12: =SUM(Refurbished!F8:F10) -> 1508 | G12: =SUM(Refurbished!G8:G10) -> 1514 | H12: =SUM(Refurbished!H8:H10) -> 1391 | I12: =SUM(Refurbished!I8:I10) -> 1527 | J12: =SUM(Refurbished!J8:J10) -> 1783 | ... ED12: =SUM(Refurbished!ED8:ED10) -> 68315.284 | EF12: =SUM(BK12:BM12) -> 77266 | EG12: =SUM(BN12:BP12) -> 72535 | EH12: =SUM(BQ12:BS12) -> 80861 | EI12: =SUM(BT12:BV12) -> 65935 | EJ12: =SUM(BW12:BY12) -> 75041 | EK12: =SUM(BZ12:CB12) -> 70493 | EL12: =SUM(CC12:CE12) -> 71084 | EM12: =SUM(CF12:CH12) -> 89414 | EN12: =SUM(CI12:CK12) -> 96052 | EO12: =SUM(CL12:CN12) -> 95989 | EP12: =SUM(CO12:CQ12) -> 108289 | EQ12: =SUM(CR12:CT12) -> 127912 | ER12: =SUM(CU12:CW12) -> 119083.81 | ES12: =SUM(CX12:CZ12) -> 117731.02 | ET12: =SUM(DA12:DC12) -> 132315.08 | EU12: =SUM(DD12:DF12) -> 150120.36 | EV12: =SUM(DG12:DI12) -> 139481.67 | EW12: =SUM(DJ12:DL12) -> 137501.95 | EX12: =SUM(DM12:DO12) -> 153719.25 | EY12: =SUM(DP12:DR12) -> 172973.84 | EZ12: =SUM(DS12:DU12) -> 159850.34 | FA12: =SUM(DV12:DX12) -> 157419.85 | FB12: =SUM(DY12:EA12) -> 175799.3 | FC12: =SUM(EB12:ED12) -> 197725.7 | FE12: =SUM(EF12:EI12) -> 296597 | FF12: =SUM(EJ12:EM12) -> 306032 | FG12: =SUM(EN12:EQ12) -> 428242 | FH12: =SUM(ER12:EU12) -> 519250.26 | FI12: =SUM(EV12:EY12) -> 603676.72 | FJ12: =SUM(EZ12:FC12) -> 690795.19 | FK12: x
B13: Market Place | C13: =Marketplace!C10 -> 12462 | D13: =Marketplace!D10 -> 16130 | E13: =Marketplace!E10 -> 15564 | F13: =Marketplace!F10 -> 13358 | G13: =Marketplace!G10 -> 7745 | H13: =Marketplace!H10 -> 5065 | I13: =Marketplace!I10 -> 6044 | J13: =Marketplace!J10 -> 5387 | ... ED13: =Marketplace!ED10 -> 136135.27 | EF13: =SUM(BK13:BM13) -> 167535 | EG13: =SUM(BN13:BP13) -> 168742 | EH13: =SUM(BQ13:BS13) -> 194108 | EI13: =SUM(BT13:BV13) -> 167766 | EJ13: =SUM(BW13:BY13) -> 166377 | EK13: =SUM(BZ13:CB13) -> 179298 | EL13: =SUM(CC13:CE13) -> 194617 | EM13: =SUM(CF13:CH13) -> 180791 | EN13: =SUM(CI13:CK13) -> 189492 | EO13: =SUM(CL13:CN13) -> 212602 | EP13: =SUM(CO13:CQ13) -> 236545 | EQ13: =SUM(CR13:CT13) -> 219655 | ER13: =SUM(CU13:CW13) -> 236865 | ES13: =SUM(CX13:CZ13) -> 265752.5 | ET13: =SUM(DA13:DC13) -> 295681.25 | EU13: =SUM(DD13:DF13) -> 274568.75 | EV13: =SUM(DG13:DI13) -> 284238 | EW13: =SUM(DJ13:DL13) -> 318903 | EX13: =SUM(DM13:DO13) -> 354817.5 | EY13: =SUM(DP13:DR13) -> 329482.5 | EZ13: =SUM(DS13:DU13) -> 326873.7 | FA13: =SUM(DV13:DX13) -> 366738.45 | FB13: =SUM(DY13:EA13) -> 408040.12 | FC13: =SUM(EB13:ED13) -> 378904.88 | FE13: =SUM(EF13:EI13) -> 698151 | FF13: =SUM(EJ13:EM13) -> 721083 | FG13: =SUM(EN13:EQ13) -> 858294 | FH13: =SUM(ER13:EU13) -> 1072867.5 | FI13: =SUM(EV13:EY13) -> 1287441 | FJ13: =SUM(EZ13:FC13) -> 1480557.1 | FK13: x
B15: Returns + RTO (inc. tax) | C15: =SUM(C16:C21) -> 300576.72 | D15: =SUM(D16:D21) -> 227209 | E15: =SUM(E16:E21) -> 519222.2 | F15: =SUM(F16:F21) -> 643912.92 | G15: =SUM(G16:G21) -> 1657311.2 | H15: =SUM(H16:H21) -> 1519172.1 | I15: =SUM(I16:I21) -> 1077853.8 | J15: =SUM(J16:J21) -> 692513.06 | ... ED15: =SUM(ED16:ED21) -> 4.385372e+08 | EF15: =SUM(BK15:BM15) -> 4.7799796e+08 | EG15: =SUM(BN15:BP15) -> 4.7065565e+08 | EH15: =SUM(BQ15:BS15) -> 4.5452122e+08 | EI15: =SUM(BT15:BV15) -> 3.8677771e+08 | EJ15: =SUM(BW15:BY15) -> 3.986735e+08 | EK15: =SUM(BZ15:CB15) -> 4.3463802e+08 | EL15: =SUM(CC15:CE15) -> 4.0472821e+08 | EM15: =SUM(CF15:CH15) -> 5.1404352e+08 | EN15: =SUM(CI15:CK15) -> 6.5415066e+08 | EO15: =SUM(CL15:CN15) -> 5.5536801e+08 | EP15: =SUM(CO15:CQ15) -> 6.314101e+08 | EQ15: =SUM(CR15:CT15) -> 7.1094382e+08 | ER15: =SUM(CU15:CW15) -> 7.32935e+08 | ES15: =SUM(CX15:CZ15) -> 7.2227659e+08 | ET15: =SUM(DA15:DC15) -> 8.2415611e+08 | EU15: =SUM(DD15:DF15) -> 9.2428261e+08 | EV15: =SUM(DG15:DI15) -> 8.8272314e+08 | EW15: =SUM(DJ15:DL15) -> 8.6851717e+08 | EX15: =SUM(DM15:DO15) -> 9.8951911e+08 | EY15: =SUM(DP15:DR15) -> 1.1050721e+09 | EZ15: =SUM(DS15:DU15) -> 1.0407672e+09 | FA15: =SUM(DV15:DX15) -> 1.02359e+09 | FB15: =SUM(DY15:EA15) -> 1.165978e+09 | FC15: =SUM(EB15:ED15) -> 1.3017409e+09 | FE15: =SUM(EF15:EI15) -> 1.7899525e+09 | FF15: =SUM(EJ15:EM15) -> 1.7520832e+09 | FG15: =SUM(EN15:EQ15) -> 2.5518726e+09 | FH15: =SUM(ER15:EU15) -> 3.2036503e+09 | FI15: =SUM(EV15:EY15) -> 3.8458315e+09 | FJ15: =SUM(EZ15:FC15) -> 4.5320761e+09 | FK15: x
B16: Non- Repair | C16: ='B2B- Non Repair'!C11 -> 0 | D16: ='B2B- Non Repair'!D11 -> 0 | E16: ='B2B- Non Repair'!E11 -> 0 | F16: ='B2B- Non Repair'!F11 -> 0 | G16: ='B2B- Non Repair'!G11 -> 0 | H16: ='B2B- Non Repair'!H11 -> 0 | I16: ='B2B- Non Repair'!I11 -> 0 | J16: ='B2B- Non Repair'!J11 -> 0 | ... ED16: ='B2B- Non Repair'!ED11 -> 1.2733613e+08 | EF16: =SUM(BK16:BM16) -> 2.0492693e+08 | EG16: =SUM(BN16:BP16) -> 1.6763593e+08 | EH16: =SUM(BQ16:BS16) -> 1.1748016e+08 | EI16: =SUM(BT16:BV16) -> 1.1576334e+08 | EJ16: =SUM(BW16:BY16) -> 1.1802846e+08 | EK16: =SUM(BZ16:CB16) -> 1.1824167e+08 | EL16: =SUM(CC16:CE16) -> 1.1246787e+08 | EM16: =SUM(CF16:CH16) -> 1.04096e+08 | EN16: =SUM(CI16:CK16) -> 1.4391606e+08 | EO16: =SUM(CL16:CN16) -> 1.3783239e+08 | EP16: =SUM(CO16:CQ16) -> 1.4540632e+08 | EQ16: =SUM(CR16:CT16) -> 1.8704505e+08 | ER16: =SUM(CU16:CW16) -> 2.041981e+08 | ES16: =SUM(CX16:CZ16) -> 1.9571287e+08 | ET16: =SUM(DA16:DC16) -> 2.3886515e+08 | EU16: =SUM(DD16:DF16) -> 2.5876931e+08 | EV16: =SUM(DG16:DI16) -> 2.5524762e+08 | EW16: =SUM(DJ16:DL16) -> 2.4464108e+08 | EX16: =SUM(DM16:DO16) -> 2.9858144e+08 | EY16: =SUM(DP16:DR16) -> 3.2346164e+08 | EZ16: =SUM(DS16:DU16) -> 3.0629714e+08 | FA16: =SUM(DV16:DX16) -> 2.935693e+08 | FB16: =SUM(DY16:EA16) -> 3.5829773e+08 | FC16: =SUM(EB16:ED16) -> 3.8815397e+08 | FE16: =SUM(EF16:EI16) -> 6.0580637e+08 | FF16: =SUM(EJ16:EM16) -> 4.5283401e+08 | FG16: =SUM(EN16:EQ16) -> 6.1419981e+08 | FH16: =SUM(ER16:EU16) -> 8.9754543e+08 | FI16: =SUM(EV16:EY16) -> 1.1219318e+09 | FJ16: =SUM(EZ16:FC16) -> 1.3463181e+09 | FK16: x
B17: Refurbished | C17: =Refurbished!C12 -> 300576.72 | D17: =Refurbished!D12 -> 227209 | E17: =Refurbished!E12 -> 519222.2 | F17: =Refurbished!F12 -> 643912.92 | G17: =Refurbished!G12 -> 1657311.2 | H17: =Refurbished!H12 -> 1519172.1 | I17: =Refurbished!I12 -> 1077853.8 | J17: =Refurbished!J12 -> 692513.06 | ... ED17: =Refurbished!ED12 -> 3.1120107e+08 | EF17: =SUM(BK17:BM17) -> 2.7307103e+08 | EG17: =SUM(BN17:BP17) -> 3.0301973e+08 | EH17: =SUM(BQ17:BS17) -> 3.3704106e+08 | EI17: =SUM(BT17:BV17) -> 2.7101436e+08 | EJ17: =SUM(BW17:BY17) -> 2.8064504e+08 | EK17: =SUM(BZ17:CB17) -> 3.1639635e+08 | EL17: =SUM(CC17:CE17) -> 2.9226033e+08 | EM17: =SUM(CF17:CH17) -> 4.0994752e+08 | EN17: =SUM(CI17:CK17) -> 5.102346e+08 | EO17: =SUM(CL17:CN17) -> 4.1753562e+08 | EP17: =SUM(CO17:CQ17) -> 4.8600378e+08 | EQ17: =SUM(CR17:CT17) -> 5.2389877e+08 | ER17: =SUM(CU17:CW17) -> 5.2873691e+08 | ES17: =SUM(CX17:CZ17) -> 5.2656372e+08 | ET17: =SUM(DA17:DC17) -> 5.8529096e+08 | EU17: =SUM(DD17:DF17) -> 6.655133e+08 | EV17: =SUM(DG17:DI17) -> 6.2747552e+08 | EW17: =SUM(DJ17:DL17) -> 6.2387608e+08 | EX17: =SUM(DM17:DO17) -> 6.9093767e+08 | EY17: =SUM(DP17:DR17) -> 7.8161048e+08 | EZ17: =SUM(DS17:DU17) -> 7.3447006e+08 | FA17: =SUM(DV17:DX17) -> 7.3002075e+08 | FB17: =SUM(DY17:EA17) -> 8.0768023e+08 | FC17: =SUM(EB17:ED17) -> 9.1358693e+08 | FE17: =SUM(EF17:EI17) -> 1.1841462e+09 | FF17: =SUM(EJ17:EM17) -> 1.2992492e+09 | FG17: =SUM(EN17:EQ17) -> 1.9376728e+09 | FH17: =SUM(ER17:EU17) -> 2.3061049e+09 | FI17: =SUM(EV17:EY17) -> 2.7238998e+09 | FJ17: =SUM(EZ17:FC17) -> 3.185758e+09 | FK17: x
B18: Market Place | C18: 0 | D18: 0 | E18: 0 | F18: 0 | G18: 0 | H18: 0 | I18: 0 | J18: 0 | K18: 0 | L18: 0 | M18: 0 | N18: 0 | O18: 0 | P18: 0 | Q18: 0 | R18: 0 | S18: 0 | T18: 0 | U18: 0 | V18: 0 | W18: 0 | X18: 0 | Y18: 0 | Z18: 0 | AA18: 0 | AB18: 0 | AC18: 0 | AD18: 0 | AE18: 0 | AF18: 0 | AG18: 0 | AH18: 0 | AI18: 0 | AJ18: 0 | AK18: 0 | AL18: 0 | AM18: 0 | AN18: 0 | AO18: 0 | AP18: 0 | AQ18: 0 | AR18: 0 | AS18: 0 | AT18: 0 | AU18: 0 | AV18: 0 | AW18: 0 | AX18: 0 | AY18: 0 | AZ18: 0 | BA18: 0 | BB18: 0 | BC18: 0 | BD18: 0 | BE18: 0 | BF18: 0 | BG18: 0 | BH18: 0 | BI18: 0 | BJ18: 0 | BK18: 0 | BL18: 0 | BM18: 0 | BN18: 0 | BO18: 0 | BP18: 0 | BQ18: 0 | BR18: 0 | BS18: 0 | BT18: 0 | BU18: 0 | BV18: 0 | BW18: 0 | BX18: 0 | BY18: 0 | BZ18: 0 | CA18: 0 | CB18: 0 | CC18: 0 | CD18: 0 | CE18: 0 | CF18: 0 | CG18: 0 | CH18: 0 | CI18: 0 | CJ18: 0 | CK18: 0 | CL18: 0 | CM18: 0 | CN18: 0 | CO18: 0 | CP18: 0 | CQ18: 0 | CR18: 0 | CS18: 0 | CT18: 0 | CU18: 0 | CV18: 0 | CW18: 0 | CX18: 0 | CY18: 0 | CZ18: 0 | DA18: 0 | DB18: 0 | DC18: 0 | DD18: 0 | DE18: 0 | DF18: 0 | DG18: 0 | DH18: 0 | DI18: 0 | DJ18: 0 | DK18: 0 | DL18: 0 | DM18: 0 | DN18: 0 | DO18: 0 | DP18: 0 | DQ18: 0 | DR18: 0 | DS18: 0 | DT18: 0 | DU18: 0 | DV18: 0 | DW18: 0 | DX18: 0 | DY18: 0 | DZ18: 0 | EA18: 0 | EB18: 0 | EC18: 0 | ED18: 0 | EF18: =SUM(BK18:BM18) -> 0 | EG18: =SUM(BN18:BP18) -> 0 | EH18: =SUM(BQ18:BS18) -> 0 | EI18: =SUM(BT18:BV18) -> 0 | EJ18: =SUM(BW18:BY18) -> 0 | EK18: =SUM(BZ18:CB18) -> 0 | EL18: =SUM(CC18:CE18) -> 0 | EM18: =SUM(CF18:CH18) -> 0 | EN18: =SUM(CI18:CK18) -> 0 | EO18: =SUM(CL18:CN18) -> 0 | EP18: =SUM(CO18:CQ18) -> 0 | EQ18: =SUM(CR18:CT18) -> 0 | ER18: =SUM(CU18:CW18) -> 0 | ES18: =SUM(CX18:CZ18) -> 0 | ET18: =SUM(DA18:DC18) -> 0 | EU18: =SUM(DD18:DF18) -> 0 | EV18: =SUM(DG18:DI18) -> 0 | EW18: =SUM(DJ18:DL18) -> 0 | EX18: =SUM(DM18:DO18) -> 0 | EY18: =SUM(DP18:DR18) -> 0 | EZ18: =SUM(DS18:DU18) -> 0 | FA18: =SUM(DV18:DX18) -> 0 | FB18: =SUM(DY18:EA18) -> 0 | FC18: =SUM(EB18:ED18) -> 0 | FE18: =SUM(EF18:EI18) -> 0 | FF18: =SUM(EJ18:EM18) -> 0 | FG18: =SUM(EN18:EQ18) -> 0 | FH18: =SUM(ER18:EU18) -> 0 | FI18: =SUM(EV18:EY18) -> 0 | FJ18: =SUM(EZ18:FC18) -> 0 | FK18: x
B19: Screen Pro + Accessories | C19: 0 | D19: 0 | E19: 0 | F19: 0 | G19: 0 | H19: 0 | I19: 0 | J19: 0 | K19: 0 | L19: 0 | M19: 0 | N19: 0 | O19: 0 | P19: 0 | Q19: 0 | R19: 0 | S19: 0 | T19: 0 | U19: 0 | V19: 0 | W19: 0 | X19: 0 | Y19: 0 | Z19: 0 | AA19: 0 | AB19: 0 | AC19: 0 | AD19: 0 | AE19: 0 | AF19: 0 | AG19: 0 | AH19: 0 | AI19: 0 | AJ19: 0 | AK19: 0 | AL19: 0 | AM19: 0 | AN19: 0 | AO19: 0 | AP19: 0 | AQ19: 0 | AR19: 0 | AS19: 0 | AT19: 0 | AU19: 0 | AV19: 0 | AW19: 0 | AX19: 0 | AY19: 0 | AZ19: 0 | BA19: 0 | BB19: 0 | BC19: 0 | BD19: 0 | BE19: 0 | BF19: 0 | BG19: 0 | BH19: 0 | BI19: 0 | BJ19: 0 | BK19: 0 | BL19: 0 | BM19: 0 | BN19: 0 | BO19: 0 | BP19: 0 | BQ19: 0 | BR19: 0 | BS19: 0 | BT19: 0 | BU19: 0 | BV19: 0 | BW19: 0 | BX19: 0 | BY19: 0 | BZ19: 0 | CA19: 0 | CB19: 0 | CC19: 0 | CD19: 0 | CE19: 0 | CF19: 0 | CG19: 0 | CH19: 0 | CI19: 0 | CJ19: 0 | CK19: 0 | CL19: 0 | CM19: 0 | CN19: 0 | CO19: 0 | CP19: 0 | CQ19: 0 | CR19: 0 | CS19: 0 | CT19: 0 | CU19: 0 | CV19: 0 | CW19: 0 | CX19: 0 | CY19: 0 | CZ19: 0 | DA19: 0 | DB19: 0 | DC19: 0 | DD19: 0 | DE19: 0 | DF19: 0 | DG19: 0 | DH19: 0 | DI19: 0 | DJ19: 0 | DK19: 0 | DL19: 0 | DM19: 0 | DN19: 0 | DO19: 0 | DP19: 0 | DQ19: 0 | DR19: 0 | DS19: 0 | DT19: 0 | DU19: 0 | DV19: 0 | DW19: 0 | DX19: 0 | DY19: 0 | DZ19: 0 | EA19: 0 | EB19: 0 | EC19: 0 | ED19: 0 | EF19: =SUM(BK19:BM19) -> 0 | EG19: =SUM(BN19:BP19) -> 0 | EH19: =SUM(BQ19:BS19) -> 0 | EI19: =SUM(BT19:BV19) -> 0 | EJ19: =SUM(BW19:BY19) -> 0 | EK19: =SUM(BZ19:CB19) -> 0 | EL19: =SUM(CC19:CE19) -> 0 | EM19: =SUM(CF19:CH19) -> 0 | EN19: =SUM(CI19:CK19) -> 0 | EO19: =SUM(CL19:CN19) -> 0 | EP19: =SUM(CO19:CQ19) -> 0 | EQ19: =SUM(CR19:CT19) -> 0 | ER19: =SUM(CU19:CW19) -> 0 | ES19: =SUM(CX19:CZ19) -> 0 | ET19: =SUM(DA19:DC19) -> 0 | EU19: =SUM(DD19:DF19) -> 0 | EV19: =SUM(DG19:DI19) -> 0 | EW19: =SUM(DJ19:DL19) -> 0 | EX19: =SUM(DM19:DO19) -> 0 | EY19: =SUM(DP19:DR19) -> 0 | EZ19: =SUM(DS19:DU19) -> 0 | FA19: =SUM(DV19:DX19) -> 0 | FB19: =SUM(DY19:EA19) -> 0 | FC19: =SUM(EB19:ED19) -> 0 | FE19: =SUM(EF19:EI19) -> 0 | FF19: =SUM(EJ19:EM19) -> 0 | FG19: =SUM(EN19:EQ19) -> 0 | FH19: =SUM(ER19:EU19) -> 0 | FI19: =SUM(EV19:EY19) -> 0 | FJ19: =SUM(EZ19:FC19) -> 0 | FK19: x
B20: Enterprise Sales | C20: 0 | D20: 0 | E20: 0 | F20: 0 | G20: 0 | H20: 0 | I20: 0 | J20: 0 | K20: 0 | L20: 0 | M20: 0 | N20: 0 | O20: 0 | P20: 0 | Q20: 0 | R20: 0 | S20: 0 | T20: 0 | U20: 0 | V20: 0 | W20: 0 | X20: 0 | Y20: 0 | Z20: 0 | AA20: 0 | AB20: 0 | AC20: 0 | AD20: 0 | AE20: 0 | AF20: 0 | AG20: 0 | AH20: 0 | AI20: 0 | AJ20: 0 | AK20: 0 | AL20: 0 | AM20: 0 | AN20: 0 | AO20: 0 | AP20: 0 | AQ20: 0 | AR20: 0 | AS20: 0 | AT20: 0 | AU20: 0 | AV20: 0 | AW20: 0 | AX20: 0 | AY20: 0 | AZ20: 0 | BA20: 0 | BB20: 0 | BC20: 0 | BD20: 0 | BE20: 0 | BF20: 0 | BG20: 0 | BH20: 0 | BI20: 0 | BJ20: 0 | BK20: 0 | BL20: 0 | BM20: 0 | BN20: 0 | BO20: 0 | BP20: 0 | BQ20: 0 | BR20: 0 | BS20: 0 | BT20: 0 | BU20: 0 | BV20: 0 | BW20: 0 | BX20: 0 | BY20: 0 | BZ20: 0 | CA20: 0 | CB20: 0 | CC20: 0 | CD20: 0 | CE20: 0 | CF20: 0 | CG20: 0 | CH20: 0 | CI20: 0 | CJ20: 0 | CK20: 0 | CL20: 0 | CM20: 0 | CN20: 0 | CO20: 0 | CP20: 0 | CQ20: 0 | CR20: 0 | CS20: 0 | CT20: 0 | CU20: 0 | CV20: 0 | CW20: 0 | CX20: 0 | CY20: 0 | CZ20: 0 | DA20: 0 | DB20: 0 | DC20: 0 | DD20: 0 | DE20: 0 | DF20: 0 | DG20: 0 | DH20: 0 | DI20: 0 | DJ20: 0 | DK20: 0 | DL20: 0 | DM20: 0 | DN20: 0 | DO20: 0 | DP20: 0 | DQ20: 0 | DR20: 0 | DS20: 0 | DT20: 0 | DU20: 0 | DV20: 0 | DW20: 0 | DX20: 0 | DY20: 0 | DZ20: 0 | EA20: 0 | EB20: 0 | EC20: 0 | ED20: 0 | EF20: =SUM(BK20:BM20) -> 0 | EG20: =SUM(BN20:BP20) -> 0 | EH20: =SUM(BQ20:BS20) -> 0 | EI20: =SUM(BT20:BV20) -> 0 | EJ20: =SUM(BW20:BY20) -> 0 | EK20: =SUM(BZ20:CB20) -> 0 | EL20: =SUM(CC20:CE20) -> 0 | EM20: =SUM(CF20:CH20) -> 0 | EN20: =SUM(CI20:CK20) -> 0 | EO20: =SUM(CL20:CN20) -> 0 | EP20: =SUM(CO20:CQ20) -> 0 | EQ20: =SUM(CR20:CT20) -> 0 | ER20: =SUM(CU20:CW20) -> 0 | ES20: =SUM(CX20:CZ20) -> 0 | ET20: =SUM(DA20:DC20) -> 0 | EU20: =SUM(DD20:DF20) -> 0 | EV20: =SUM(DG20:DI20) -> 0 | EW20: =SUM(DJ20:DL20) -> 0 | EX20: =SUM(DM20:DO20) -> 0 | EY20: =SUM(DP20:DR20) -> 0 | EZ20: =SUM(DS20:DU20) -> 0 | FA20: =SUM(DV20:DX20) -> 0 | FB20: =SUM(DY20:EA20) -> 0 | FC20: =SUM(EB20:ED20) -> 0 | FE20: =SUM(EF20:EI20) -> 0 | FF20: =SUM(EJ20:EM20) -> 0 | FG20: =SUM(EN20:EQ20) -> 0 | FH20: =SUM(ER20:EU20) -> 0 | FI20: =SUM(EV20:EY20) -> 0 | FJ20: =SUM(EZ20:FC20) -> 0 | FK20: x
B21: Screen Pro | C21: 0 | D21: 0 | E21: 0 | F21: 0 | G21: 0 | H21: 0 | I21: 0 | J21: 0 | K21: 0 | L21: 0 | M21: 0 | N21: 0 | O21: 0 | P21: 0 | Q21: 0 | R21: 0 | S21: 0 | T21: 0 | U21: 0 | V21: 0 | W21: 0 | X21: 0 | Y21: 0 | Z21: 0 | AA21: 0 | AB21: 0 | AC21: 0 | AD21: 0 | AE21: 0 | AF21: 0 | AG21: 0 | AH21: 0 | AI21: 0 | AJ21: 0 | AK21: 0 | AL21: 0 | AM21: 0 | AN21: 0 | AO21: 0 | AP21: 0 | AQ21: 0 | AR21: 0 | AS21: 0 | AT21: 0 | AU21: 0 | AV21: 0 | AW21: 0 | AX21: 0 | AY21: 0 | AZ21: 0 | BA21: 0 | BB21: 0 | BC21: 0 | BD21: 0 | BE21: 0 | BF21: 0 | BG21: 0 | BH21: 0 | BI21: 0 | BJ21: 0 | BK21: 0 | BL21: 0 | BM21: 0 | BN21: 0 | BO21: 0 | BP21: 0 | BQ21: 0 | BR21: 0 | BS21: 0 | BT21: 0 | BU21: 0 | BV21: 0 | BW21: 0 | BX21: 0 | BY21: 0 | BZ21: 0 | CA21: 0 | CB21: 0 | CC21: 0 | CD21: 0 | CE21: 0 | CF21: 0 | CG21: 0 | CH21: 0 | CI21: 0 | CJ21: 0 | CK21: 0 | CL21: 0 | CM21: 0 | CN21: 0 | CO21: 0 | CP21: 0 | CQ21: 0 | CR21: 0 | CS21: 0 | CT21: 0 | CU21: 0 | CV21: 0 | CW21: 0 | CX21: 0 | CY21: 0 | CZ21: 0 | DA21: 0 | DB21: 0 | DC21: 0 | DD21: 0 | DE21: 0 | DF21: 0 | DG21: 0 | DH21: 0 | DI21: 0 | DJ21: 0 | DK21: 0 | DL21: 0 | DM21: 0 | DN21: 0 | DO21: 0 | DP21: 0 | DQ21: 0 | DR21: 0 | DS21: 0 | DT21: 0 | DU21: 0 | DV21: 0 | DW21: 0 | DX21: 0 | DY21: 0 | DZ21: 0 | EA21: 0 | EB21: 0 | EC21: 0 | ED21: 0 | EF21: =SUM(BK21:BM21) -> 0 | EG21: =SUM(BN21:BP21) -> 0 | EH21: =SUM(BQ21:BS21) -> 0 | EI21: =SUM(BT21:BV21) -> 0 | EJ21: =SUM(BW21:BY21) -> 0 | EK21: =SUM(BZ21:CB21) -> 0 | EL21: =SUM(CC21:CE21) -> 0 | EM21: =SUM(CF21:CH21) -> 0 | EN21: =SUM(CI21:CK21) -> 0 | EO21: =SUM(CL21:CN21) -> 0 | EP21: =SUM(CO21:CQ21) -> 0 | EQ21: =SUM(CR21:CT21) -> 0 | ER21: =SUM(CU21:CW21) -> 0 | ES21: =SUM(CX21:CZ21) -> 0 | ET21: =SUM(DA21:DC21) -> 0 | EU21: =SUM(DD21:DF21) -> 0 | EV21: =SUM(DG21:DI21) -> 0 | EW21: =SUM(DJ21:DL21) -> 0 | EX21: =SUM(DM21:DO21) -> 0 | EY21: =SUM(DP21:DR21) -> 0 | EZ21: =SUM(DS21:DU21) -> 0 | FA21: =SUM(DV21:DX21) -> 0 | FB21: =SUM(DY21:EA21) -> 0 | FC21: =SUM(EB21:ED21) -> 0 | FE21: =SUM(EF21:EI21) -> 0 | FF21: =SUM(EJ21:EM21) -> 0 | FG21: =SUM(EN21:EQ21) -> 0 | FH21: =SUM(ER21:EU21) -> 0 | FI21: =SUM(EV21:EY21) -> 0 | FJ21: =SUM(EZ21:FC21) -> 0 | FK21: x
B23: Non- Repair | C23: ='B2B- Non Repair'!C15 -> 0 | D23: ='B2B- Non Repair'!D15 -> 0 | E23: ='B2B- Non Repair'!E15 -> 0 | F23: ='B2B- Non Repair'!F15 -> 0 | G23: ='B2B- Non Repair'!G15 -> 0 | H23: ='B2B- Non Repair'!H15 -> 0 | I23: ='B2B- Non Repair'!I15 -> 0 | J23: ='B2B- Non Repair'!J15 -> 0 | ... ED23: ='B2B- Non Repair'!ED15 -> 9221.2526 | EF23: =SUM(BK23:BM23) -> 23531 | EG23: =SUM(BN23:BP23) -> 18465 | EH23: =SUM(BQ23:BS23) -> 11934 | EI23: =SUM(BT23:BV23) -> 9872 | EJ23: =SUM(BW23:BY23) -> 11249 | EK23: =SUM(BZ23:CB23) -> 12204 | EL23: =SUM(CC23:CE23) -> 11421 | EM23: =SUM(CF23:CH23) -> 8713 | EN23: =SUM(CI23:CK23) -> 11448.632 | EO23: =SUM(CL23:CN23) -> 11130 | EP23: =SUM(CO23:CQ23) -> 12639 | EQ23: =SUM(CR23:CT23) -> 13484 | ER23: =SUM(CU23:CW23) -> 14794.959 | ES23: =SUM(CX23:CZ23) -> 14175.03 | ET23: =SUM(DA23:DC23) -> 17302.491 | EU23: =SUM(DD23:DF23) -> 18740.763 | EV23: =SUM(DG23:DI23) -> 18493.698 | EW23: =SUM(DJ23:DL23) -> 17718.788 | EX23: =SUM(DM23:DO23) -> 21628.114 | EY23: =SUM(DP23:DR23) -> 23425.954 | EZ23: =SUM(DS23:DU23) -> 22192.438 | FA23: =SUM(DV23:DX23) -> 21262.545 | FB23: =SUM(DY23:EA23) -> 25953.737 | FC23: =SUM(EB23:ED23) -> 28111.144 | FE23: =SUM(EF23:EI23) -> 63802 | FF23: =SUM(EJ23:EM23) -> 43587 | FG23: =SUM(EN23:EQ23) -> 48701.632 | FH23: =SUM(ER23:EU23) -> 65013.243 | FI23: =SUM(EV23:EY23) -> 81266.554 | FJ23: =SUM(EZ23:FC23) -> 97519.864 | FK23: x
B24: #RTO | C24: ='B2B- Non Repair'!C20 -> 0 | D24: ='B2B- Non Repair'!D20 -> 0 | E24: ='B2B- Non Repair'!E20 -> 0 | F24: ='B2B- Non Repair'!F20 -> 0 | G24: ='B2B- Non Repair'!G20 -> 0 | H24: ='B2B- Non Repair'!H20 -> 0 | I24: ='B2B- Non Repair'!I20 -> 0 | J24: ='B2B- Non Repair'!J20 -> 0 | ... ED24: ='B2B- Non Repair'!ED20 -> 2623.3703 | EF24: =SUM(BK24:BM24) -> 6834 | EG24: =SUM(BN24:BP24) -> 5962 | EH24: =SUM(BQ24:BS24) -> 5723 | EI24: =SUM(BT24:BV24) -> 4701 | EJ24: =SUM(BW24:BY24) -> 5954 | EK24: =SUM(BZ24:CB24) -> 6741 | EL24: =SUM(CC24:CE24) -> 6097 | EM24: =SUM(CF24:CH24) -> 3344 | EN24: =SUM(CI24:CK24) -> 3120 | EO24: =SUM(CL24:CN24) -> 4512 | EP24: =SUM(CO24:CQ24) -> 5569 | EQ24: =SUM(CR24:CT24) -> 3984 | ER24: =SUM(CU24:CW24) -> 4209.0438 | ES24: =SUM(CX24:CZ24) -> 4032.6792 | ET24: =SUM(DA24:DC24) -> 4922.416 | EU24: =SUM(DD24:DF24) -> 5331.5925 | EV24: =SUM(DG24:DI24) -> 5261.3047 | EW24: =SUM(DJ24:DL24) -> 5040.849 | EX24: =SUM(DM24:DO24) -> 6153.0201 | EY24: =SUM(DP24:DR24) -> 6664.4907 | EZ24: =SUM(DS24:DU24) -> 6313.5657 | FA24: =SUM(DV24:DX24) -> 6049.0188 | FB24: =SUM(DY24:EA24) -> 7383.6241 | FC24: =SUM(EB24:ED24) -> 7997.3888 | FE24: =SUM(EF24:EI24) -> 23220 | FF24: =SUM(EJ24:EM24) -> 22136 | FG24: =SUM(EN24:EQ24) -> 17185 | FH24: =SUM(ER24:EU24) -> 18495.732 | FI24: =SUM(EV24:EY24) -> 23119.664 | FJ24: =SUM(EZ24:FC24) -> 27743.597 | FK24: x
B25: #Quality return | C25: =C23-C24 -> 0 | D25: =D23-D24 -> 0 | E25: =E23-E24 -> 0 | F25: =F23-F24 -> 0 | G25: =G23-G24 -> 0 | H25: =H23-H24 -> 0 | I25: =I23-I24 -> 0 | J25: =J23-J24 -> 0 | ... ED25: =ED23-ED24 -> 6597.8823 | EF25: =SUM(BK25:BM25) -> 16697 | EG25: =SUM(BN25:BP25) -> 12503 | EH25: =SUM(BQ25:BS25) -> 6211 | EI25: =SUM(BT25:BV25) -> 5171 | EJ25: =SUM(BW25:BY25) -> 5295 | EK25: =SUM(BZ25:CB25) -> 5463 | EL25: =SUM(CC25:CE25) -> 5324 | EM25: =SUM(CF25:CH25) -> 5369 | EN25: =SUM(CI25:CK25) -> 8328.6316 | EO25: =SUM(CL25:CN25) -> 6618 | EP25: =SUM(CO25:CQ25) -> 7070 | EQ25: =SUM(CR25:CT25) -> 9500 | ER25: =SUM(CU25:CW25) -> 10585.915 | ES25: =SUM(CX25:CZ25) -> 10142.351 | ET25: =SUM(DA25:DC25) -> 12380.075 | EU25: =SUM(DD25:DF25) -> 13409.17 | EV25: =SUM(DG25:DI25) -> 13232.394 | EW25: =SUM(DJ25:DL25) -> 12677.939 | EX25: =SUM(DM25:DO25) -> 15475.094 | EY25: =SUM(DP25:DR25) -> 16761.463 | EZ25: =SUM(DS25:DU25) -> 15878.872 | FA25: =SUM(DV25:DX25) -> 15213.526 | FB25: =SUM(DY25:EA25) -> 18570.112 | FC25: =SUM(EB25:ED25) -> 20113.756 | FE25: =SUM(EF25:EI25) -> 40582 | FF25: =SUM(EJ25:EM25) -> 21451 | FG25: =SUM(EN25:EQ25) -> 31516.632 | FH25: =SUM(ER25:EU25) -> 46517.511 | FI25: =SUM(EV25:EY25) -> 58146.889 | FJ25: =SUM(EZ25:FC25) -> 69776.267 | FK25: x
B26: Non- Repair% | EF26: =SUM(BK26:BM26) -> 0 | EG26: =SUM(BN26:BP26) -> 0 | EH26: =SUM(BQ26:BS26) -> 0 | EI26: =SUM(BT26:BV26) -> 0 | EJ26: =SUM(BW26:BY26) -> 0 | EK26: =SUM(BZ26:CB26) -> 0 | EL26: =SUM(CC26:CE26) -> 0 | EM26: =SUM(CF26:CH26) -> 0 | EN26: =SUM(CI26:CK26) -> 0 | EO26: =SUM(CL26:CN26) -> 0 | EP26: =SUM(CO26:CQ26) -> 0 | EQ26: =SUM(CR26:CT26) -> 0 | ER26: =SUM(CU26:CW26) -> 0 | ES26: =SUM(CX26:CZ26) -> 0 | ET26: =SUM(DA26:DC26) -> 0 | EU26: =SUM(DD26:DF26) -> 0 | EV26: =SUM(DG26:DI26) -> 0 | EW26: =SUM(DJ26:DL26) -> 0 | EX26: =SUM(DM26:DO26) -> 0 | EY26: =SUM(DP26:DR26) -> 0 | EZ26: =SUM(DS26:DU26) -> 0 | FA26: =SUM(DV26:DX26) -> 0 | FB26: =SUM(DY26:EA26) -> 0 | FC26: =SUM(EB26:ED26) -> 0 | FE26: =SUM(EF26:EI26) -> 0 | FF26: =SUM(EJ26:EM26) -> 0 | FG26: =SUM(EN26:EQ26) -> 0 | FH26: =SUM(ER26:EU26) -> 0 | FI26: =SUM(EV26:EY26) -> 0 | FJ26: =SUM(EZ26:FC26) -> 0 | FK26: x
B27: Refurbished | C27: =SUM(Refurbished!C17:C19) -> 41 | D27: =SUM(Refurbished!D17:D19) -> 39 | E27: =SUM(Refurbished!E17:E19) -> 77 | F27: =SUM(Refurbished!F17:F19) -> 89 | G27: =SUM(Refurbished!G17:G19) -> 176 | H27: =SUM(Refurbished!H17:H19) -> 214 | I27: =SUM(Refurbished!I17:I19) -> 161 | J27: =SUM(Refurbished!J17:J19) -> 94 | ... ED27: =SUM(Refurbished!ED17:ED19) -> 9984.4941 | EF27: =SUM(BK27:BM27) -> 12380 | EG27: =SUM(BN27:BP27) -> 14571 | EH27: =SUM(BQ27:BS27) -> 14633 | EI27: =SUM(BT27:BV27) -> 11641 | EJ27: =SUM(BW27:BY27) -> 12163 | EK27: =SUM(BZ27:CB27) -> 13242 | EL27: =SUM(CC27:CE27) -> 11495 | EM27: =SUM(CF27:CH27) -> 15155 | EN27: =SUM(CI27:CK27) -> 18269.714 | EO27: =SUM(CL27:CN27) -> 14849 | EP27: =SUM(CO27:CQ27) -> 17469 | EQ27: =SUM(CR27:CT27) -> 18561 | ER27: =SUM(CU27:CW27) -> 17728.486 | ES27: =SUM(CX27:CZ27) -> 17704.376 | ET27: =SUM(DA27:DC27) -> 19596.839 | EU27: =SUM(DD27:DF27) -> 22301.518 | EV27: =SUM(DG27:DI27) -> 20578.854 | EW27: =SUM(DJ27:DL27) -> 20519.168 | EX27: =SUM(DM27:DO27) -> 22653.716 | EY27: =SUM(DP27:DR27) -> 25672.028 | EZ27: =SUM(DS27:DU27) -> 23623.957 | FA27: =SUM(DV27:DX27) -> 23543.724 | FB27: =SUM(DY27:EA27) -> 25978.07 | FC27: =SUM(EB27:ED27) -> 29432.819 | FE27: =SUM(EF27:EI27) -> 53225 | FF27: =SUM(EJ27:EM27) -> 52055 | FG27: =SUM(EN27:EQ27) -> 69148.714 | FH27: =SUM(ER27:EU27) -> 77331.219 | FI27: =SUM(EV27:EY27) -> 89423.765 | FJ27: =SUM(EZ27:FC27) -> 102578.57 | FK27: x
B28: #RTO | L28: ='D2C Online'!C24+'D2C Online'!C29 -> 0 | M28: ='D2C Online'!D24+'D2C Online'!D29 -> 0 | N28: ='D2C Online'!E24+'D2C Online'!E29 -> 0 | O28: ='D2C Online'!F24+'D2C Online'!F29 -> 0 | P28: ='D2C Online'!G24+'D2C Online'!G29 -> 0 | Q28: ='D2C Online'!H24+'D2C Online'!H29 -> 0 | R28: ='D2C Online'!I24+'D2C Online'!I29 -> 0 | S28: ='D2C Online'!J24+'D2C Online'!J29 -> 0 | ... ED28: ='D2C Online'!DU24+'D2C Online'!DU29 -> 3186.2331 | EF28: =SUM(BK28:BM28) -> 5837 | EG28: =SUM(BN28:BP28) -> 6798 | EH28: =SUM(BQ28:BS28) -> 6560 | EI28: =SUM(BT28:BV28) -> 5265 | EJ28: =SUM(BW28:BY28) -> 4659 | EK28: =SUM(BZ28:CB28) -> 4575 | EL28: =SUM(CC28:CE28) -> 4249 | EM28: =SUM(CF28:CH28) -> 5731 | EN28: =SUM(CI28:CK28) -> 7486.7143 | EO28: =SUM(CL28:CN28) -> 3320 | EP28: =SUM(CO28:CQ28) -> 6068 | EQ28: =SUM(CR28:CT28) -> 6233 | ER28: =SUM(CU28:CW28) -> 5767.5915 | ES28: =SUM(CX28:CZ28) -> 5818.8938 | ET28: =SUM(DA28:DC28) -> 6341.5785 | EU28: =SUM(DD28:DF28) -> 7239.4828 | EV28: =SUM(DG28:DI28) -> 6632.7302 | EW28: =SUM(DJ28:DL28) -> 6691.7278 | EX28: =SUM(DM28:DO28) -> 7292.8153 | EY28: =SUM(DP28:DR28) -> 8325.4052 | EZ28: =SUM(DS28:DU28) -> 7627.6398 | FA28: =SUM(DV28:DX28) -> 7695.487 | FB28: =SUM(DY28:EA28) -> 8386.7376 | FC28: =SUM(EB28:ED28) -> 9574.216 | FE28: =SUM(EF28:EI28) -> 24460 | FF28: =SUM(EJ28:EM28) -> 19214 | FG28: =SUM(EN28:EQ28) -> 23107.714 | FH28: =SUM(ER28:EU28) -> 25167.547 | FI28: =SUM(EV28:EY28) -> 28942.679 | FJ28: =SUM(EZ28:FC28) -> 33284.08 | FK28: x
B29: #Cancelled (CBD) | L29: ='D2C Online'!C25 -> 0 | M29: ='D2C Online'!D25 -> 0 | N29: ='D2C Online'!E25 -> 0 | O29: ='D2C Online'!F25 -> 0 | P29: ='D2C Online'!G25 -> 0 | Q29: ='D2C Online'!H25 -> 0 | R29: ='D2C Online'!I25 -> 0 | S29: ='D2C Online'!J25 -> 0 | ... ED29: ='D2C Online'!DU25 -> 868.41962 | EF29: =SUM(BK29:BM29) -> 44 | EG29: =SUM(BN29:BP29) -> 1291 | EH29: =SUM(BQ29:BS29) -> 1332 | EI29: =SUM(BT29:BV29) -> 858 | EJ29: =SUM(BW29:BY29) -> 1136 | EK29: =SUM(BZ29:CB29) -> 1317 | EL29: =SUM(CC29:CE29) -> 1225 | EM29: =SUM(CF29:CH29) -> 1521 | EN29: =SUM(CI29:CK29) -> 1481 | EO29: =SUM(CL29:CN29) -> 1740 | EP29: =SUM(CO29:CQ29) -> 1691 | EQ29: =SUM(CR29:CT29) -> 1664 | ER29: =SUM(CU29:CW29) -> 1571.9784 | ES29: =SUM(CX29:CZ29) -> 1585.961 | ET29: =SUM(DA29:DC29) -> 1728.4207 | EU29: =SUM(DD29:DF29) -> 1973.1478 | EV29: =SUM(DG29:DI29) -> 1807.7752 | EW29: =SUM(DJ29:DL29) -> 1823.8552 | EX29: =SUM(DM29:DO29) -> 1987.6838 | EY29: =SUM(DP29:DR29) -> 2269.12 | EZ29: =SUM(DS29:DU29) -> 2078.9414 | FA29: =SUM(DV29:DX29) -> 2097.4334 | FB29: =SUM(DY29:EA29) -> 2285.8363 | FC29: =SUM(EB29:ED29) -> 2609.488 | FE29: =SUM(EF29:EI29) -> 3525 | FF29: =SUM(EJ29:EM29) -> 5199 | FG29: =SUM(EN29:EQ29) -> 6576 | FH29: =SUM(ER29:EU29) -> 6859.5079 | FI29: =SUM(EV29:EY29) -> 7888.4341 | FJ29: =SUM(EZ29:FC29) -> 9071.6992 | FK29: x
B30: #Within 7 days | L30: ='D2C Online'!C26 -> 0 | M30: ='D2C Online'!D26 -> 0 | N30: ='D2C Online'!E26 -> 0 | O30: ='D2C Online'!F26 -> 0 | P30: ='D2C Online'!G26 -> 0 | Q30: ='D2C Online'!H26 -> 0 | R30: ='D2C Online'!I26 -> 0 | S30: ='D2C Online'!J26 -> 0 | ... ED30: ='D2C Online'!DU26 -> 635.72575 | EF30: =SUM(BK30:BM30) -> 1586 | EG30: =SUM(BN30:BP30) -> 619 | EH30: =SUM(BQ30:BS30) -> 585 | EI30: =SUM(BT30:BV30) -> 476 | EJ30: =SUM(BW30:BY30) -> 384 | EK30: =SUM(BZ30:CB30) -> 568 | EL30: =SUM(CC30:CE30) -> 713 | EM30: =SUM(CF30:CH30) -> 1280 | EN30: =SUM(CI30:CK30) -> 1822 | EO30: =SUM(CL30:CN30) -> 1771 | EP30: =SUM(CO30:CQ30) -> 1953 | EQ30: =SUM(CR30:CT30) -> 1797 | ER30: =SUM(CU30:CW30) -> 1150.7653 | ES30: =SUM(CX30:CZ30) -> 1161.0012 | ET30: =SUM(DA30:DC30) -> 1265.2887 | EU30: =SUM(DD30:DF30) -> 1444.441 | EV30: =SUM(DG30:DI30) -> 1323.3801 | EW30: =SUM(DJ30:DL30) -> 1335.1514 | EX30: =SUM(DM30:DO30) -> 1455.082 | EY30: =SUM(DP30:DR30) -> 1661.1071 | EZ30: =SUM(DS30:DU30) -> 1521.8871 | FA30: =SUM(DV30:DX30) -> 1535.4241 | FB30: =SUM(DY30:EA30) -> 1673.3443 | FC30: =SUM(EB30:ED30) -> 1910.2732 | FE30: =SUM(EF30:EI30) -> 3266 | FF30: =SUM(EJ30:EM30) -> 2945 | FG30: =SUM(EN30:EQ30) -> 7343 | FH30: =SUM(ER30:EU30) -> 5021.4962 | FI30: =SUM(EV30:EY30) -> 5774.7206 | FJ30: =SUM(EZ30:FC30) -> 6640.9287 | FK30: x
B31: #After 7 days | L31: ='D2C Online'!C27+'D2C Online'!C30 -> 0 | M31: ='D2C Online'!D27+'D2C Online'!D30 -> 0 | N31: ='D2C Online'!E27+'D2C Online'!E30 -> 0 | O31: ='D2C Online'!F27+'D2C Online'!F30 -> 0 | P31: ='D2C Online'!G27+'D2C Online'!G30 -> 0 | Q31: ='D2C Online'!H27+'D2C Online'!H30 -> 0 | R31: ='D2C Online'!I27+'D2C Online'!I30 -> 0 | S31: ='D2C Online'!J27+'D2C Online'!J30 -> 0 | ... AB31: ='D2C Online'!S27+'D2C Online'!S30 -> 0 | AC31: ='D2C Online'!T27+'D2C Online'!T30+'D2C - Retail'!C25 -> 4 | AD31: ='D2C Online'!U27+'D2C Online'!U30+'D2C - Retail'!D25 -> 4 | AE31: ='D2C Online'!V27+'D2C Online'!V30+'D2C - Retail'!E25 -> 73 | AF31: ='D2C Online'!W27+'D2C Online'!W30+'D2C - Retail'!F25 -> 156 | AG31: ='D2C Online'!X27+'D2C Online'!X30+'D2C - Retail'!G25 -> 97 | AH31: ='D2C Online'!Y27+'D2C Online'!Y30+'D2C - Retail'!H25 -> 99 | AI31: ='D2C Online'!Z27+'D2C Online'!Z30+'D2C - Retail'!I25 -> 116 | AJ31: ='D2C Online'!AA27+'D2C Online'!AA30+'D2C - Retail'!J25 -> 131 | ... ED31: ='D2C Online'!DU27+'D2C Online'!DU30+'D2C - Retail'!DD25 -> 5294.1156 | EF31: =SUM(BK31:BM31) -> 4913 | EG31: =SUM(BN31:BP31) -> 5863 | EH31: =SUM(BQ31:BS31) -> 6156 | EI31: =SUM(BT31:BV31) -> 5042 | EJ31: =SUM(BW31:BY31) -> 5984 | EK31: =SUM(BZ31:CB31) -> 6782 | EL31: =SUM(CC31:CE31) -> 5308 | EM31: =SUM(CF31:CH31) -> 6623 | EN31: =SUM(CI31:CK31) -> 7480 | EO31: =SUM(CL31:CN31) -> 8018 | EP31: =SUM(CO31:CQ31) -> 7757 | EQ31: =SUM(CR31:CT31) -> 8867 | ER31: =SUM(CU31:CW31) -> 9238.1511 | ES31: =SUM(CX31:CZ31) -> 9138.5199 | ET31: =SUM(DA31:DC31) -> 10261.551 | EU31: =SUM(DD31:DF31) -> 11644.446 | EV31: =SUM(DG31:DI31) -> 10814.969 | EW31: =SUM(DJ31:DL31) -> 10668.433 | EX31: =SUM(DM31:DO31) -> 11918.135 | EY31: =SUM(DP31:DR31) -> 13416.395 | EZ31: =SUM(DS31:DU31) -> 12395.488 | FA31: =SUM(DV31:DX31) -> 12215.379 | FB31: =SUM(DY31:EA31) -> 13632.151 | FC31: =SUM(EB31:ED31) -> 15338.842 | FE31: =SUM(EF31:EI31) -> 21974 | FF31: =SUM(EJ31:EM31) -> 24697 | FG31: =SUM(EN31:EQ31) -> 32122 | FH31: =SUM(ER31:EU31) -> 40282.669 | FI31: =SUM(EV31:EY31) -> 46817.932 | FJ31: =SUM(EZ31:FC31) -> 53581.861 | FK31: x
B32: Refurbished% | L32: =L27/L12 -> 0.058354324 | M32: =M27/M12 -> 0.056494046 | N32: =N27/N12 -> 0.040835708 | O32: =O27/O12 -> 0.036794171 | P32: =P27/P12 -> 0.028752353 | Q32: =Q27/Q12 -> 0.032318105 | R32: =R27/R12 -> 0.031564708 | S32: =S27/S12 -> 0.024300156 | ... ED32: =ED27/ED12 -> 0.14615315 | EZ32: =SUM(DS32:DU32) -> 0.44337292 | FA32: =SUM(DV32:DX32) -> 0.44904127 | FB32: =SUM(DY32:EA32) -> 0.44308951 | FC32: =SUM(EB32:ED32) -> 0.44656472 | FJ32: =SUM(EZ32:FC32) -> 1.7820684 | FK32: x
B34: GMV (after returns) | C34: =SUM(C35:C40) -> 2.0595816e+08 | D34: =SUM(D35:D40) -> 2.1999057e+08 | E34: =SUM(E35:E40) -> 2.2185105e+08 | F34: =SUM(F35:F40) -> 2.3358449e+08 | G34: =SUM(G35:G40) -> 2.326146e+08 | H34: =SUM(H35:H40) -> 2.2726646e+08 | I34: =SUM(I35:I40) -> 2.4763976e+08 | J34: =SUM(J35:J40) -> 2.3794816e+08 | ... ED34: =SUM(ED35:ED40) -> 4.1512837e+09 | EF34: =SUM(BK34:BM34) -> 3.724443e+09 | EG34: =SUM(BN34:BP34) -> 3.4027831e+09 | EH34: =SUM(BQ34:BS34) -> 4.0612019e+09 | EI34: =SUM(BT34:BV34) -> 3.6324996e+09 | EJ34: =SUM(BW34:BY34) -> 3.9054991e+09 | EK34: =SUM(BZ34:CB34) -> 3.8149682e+09 | EL34: =SUM(CC34:CE34) -> 4.3919607e+09 | EM34: =SUM(CF34:CH34) -> 5.3374195e+09 | EN34: =SUM(CI34:CK34) -> 5.3915174e+09 | EO34: =SUM(CL34:CN34) -> 5.2383939e+09 | EP34: =SUM(CO34:CQ34) -> 6.4197631e+09 | EQ34: =SUM(CR34:CT34) -> 7.3662819e+09 | ER34: =SUM(CU34:CW34) -> 7.1627026e+09 | ES34: =SUM(CX34:CZ34) -> 7.1659071e+09 | ET34: =SUM(DA34:DC34) -> 8.2416403e+09 | EU34: =SUM(DD34:DF34) -> 8.6070148e+09 | EV34: =SUM(DG34:DI34) -> 8.7149258e+09 | EW34: =SUM(DJ34:DL34) -> 8.6927948e+09 | EX34: =SUM(DM34:DO34) -> 9.980374e+09 | EY34: =SUM(DP34:DR34) -> 1.0374854e+10 | EZ34: =SUM(DS34:DU34) -> 1.0160769e+10 | FA34: =SUM(DV34:DX34) -> 1.0115877e+10 | FB34: =SUM(DY34:EA34) -> 1.1618792e+10 | FC34: =SUM(EB34:ED34) -> 1.2077914e+10 | FE34: =SUM(EF34:EI34) -> 1.4820928e+10 | FF34: =SUM(EJ34:EM34) -> 1.7449847e+10 | FG34: =SUM(EN34:EQ34) -> 2.4415956e+10 | FH34: =SUM(ER34:EU34) -> 3.1177265e+10 | FI34: =SUM(EV34:EY34) -> 3.7762949e+10 | FJ34: =SUM(EZ34:FC34) -> 4.3973352e+10 | FK34: x
B35: Non- Repair | C35: ='B2B- Non Repair'!C23 -> 127373162 | D35: ='B2B- Non Repair'!D23 -> 119525214 | E35: ='B2B- Non Repair'!E23 -> 1.3361892e+08 | F35: ='B2B- Non Repair'!F23 -> 1.5572126e+08 | G35: ='B2B- Non Repair'!G23 -> 1.8292117e+08 | H35: ='B2B- Non Repair'!H23 -> 190468885 | I35: ='B2B- Non Repair'!I23 -> 203496304 | J35: ='B2B- Non Repair'!J23 -> 191306750 | ... ED35: ='B2B- Non Repair'!ED23 -> 1.0516969e+09 | EF35: =SUM(BK35:BM35) -> 1.0841488e+09 | EG35: =SUM(BN35:BP35) -> 8.7395053e+08 | EH35: =SUM(BQ35:BS35) -> 9.0781123e+08 | EI35: =SUM(BT35:BV35) -> 8.5217354e+08 | EJ35: =SUM(BW35:BY35) -> 9.2711467e+08 | EK35: =SUM(BZ35:CB35) -> 8.0449024e+08 | EL35: =SUM(CC35:CE35) -> 9.2290855e+08 | EM35: =SUM(CF35:CH35) -> 1.3849157e+09 | EN35: =SUM(CI35:CK35) -> 1.3968365e+09 | EO35: =SUM(CL35:CN35) -> 1.1858951e+09 | EP35: =SUM(CO35:CQ35) -> 1.5917634e+09 | EQ35: =SUM(CR35:CT35) -> 1.9085306e+09 | ER35: =SUM(CU35:CW35) -> 1.8855272e+09 | ES35: =SUM(CX35:CZ35) -> 1.6729566e+09 | ET35: =SUM(DA35:DC35) -> 2.0951093e+09 | EU35: =SUM(DD35:DF35) -> 2.1780252e+09 | EV35: =SUM(DG35:DI35) -> 2.356909e+09 | EW35: =SUM(DJ35:DL35) -> 2.0911958e+09 | EX35: =SUM(DM35:DO35) -> 2.6188866e+09 | EY35: =SUM(DP35:DR35) -> 2.7225315e+09 | EZ35: =SUM(DS35:DU35) -> 2.8282908e+09 | FA35: =SUM(DV35:DX35) -> 2.509435e+09 | FB35: =SUM(DY35:EA35) -> 3.1426639e+09 | FC35: =SUM(EB35:ED35) -> 3.2670378e+09 | FE35: =SUM(EF35:EI35) -> 3.7180841e+09 | FF35: =SUM(EJ35:EM35) -> 4.0394291e+09 | FG35: =SUM(EN35:EQ35) -> 6.0830257e+09 | FH35: =SUM(ER35:EU35) -> 7.8316183e+09 | FI35: =SUM(EV35:EY35) -> 9.7895228e+09 | FJ35: =SUM(EZ35:FC35) -> 1.1747427e+10 | FK35: x
B36: Refurbished | C36: =Refurbished!C21 -> 6192647 | D36: =Refurbished!D21 -> 6767807 | E36: =Refurbished!E21 -> 5747560.8 | F36: =Refurbished!F21 -> 9331198.9 | G36: =Refurbished!G21 -> 7135417.9 | H36: =Refurbished!H21 -> 5830125.6 | I36: =Refurbished!I21 -> 7326199 | J36: =Refurbished!J21 -> 9536226 | ... ED36: =Refurbished!ED21 -> 1.8430563e+09 | EF36: =SUM(BK36:BM36) -> 1.4890796e+09 | EG36: =SUM(BN36:BP36) -> 1.2892337e+09 | EH36: =SUM(BQ36:BS36) -> 1.6980566e+09 | EI36: =SUM(BT36:BV36) -> 1.3642012e+09 | EJ36: =SUM(BW36:BY36) -> 1.5977024e+09 | EK36: =SUM(BZ36:CB36) -> 1.4937662e+09 | EL36: =SUM(CC36:CE36) -> 1.7427869e+09 | EM36: =SUM(CF36:CH36) -> 2.1698124e+09 | EN36: =SUM(CI36:CK36) -> 2.2923924e+09 | EO36: =SUM(CL36:CN36) -> 2.2801346e+09 | EP36: =SUM(CO36:CQ36) -> 2.7059976e+09 | EQ36: =SUM(CR36:CT36) -> 3.2399559e+09 | ER36: =SUM(CU36:CW36) -> 3.0597067e+09 | ES36: =SUM(CX36:CZ36) -> 3.0144184e+09 | ET36: =SUM(DA36:DC36) -> 3.405682e+09 | EU36: =SUM(DD36:DF36) -> 3.8598835e+09 | EV36: =SUM(DG36:DI36) -> 3.7089622e+09 | EW36: =SUM(DJ36:DL36) -> 3.6419632e+09 | EX36: =SUM(DM36:DO36) -> 4.0891118e+09 | EY36: =SUM(DP36:DR36) -> 4.5900381e+09 | EZ36: =SUM(DS36:DU36) -> 4.2976201e+09 | FA36: =SUM(DV36:DX36) -> 4.2162326e+09 | FB36: =SUM(DY36:EA36) -> 4.7265432e+09 | FC36: =SUM(EB36:ED36) -> 5.3036013e+09 | FE36: =SUM(EF36:EI36) -> 5.8405711e+09 | FF36: =SUM(EJ36:EM36) -> 7.004068e+09 | FG36: =SUM(EN36:EQ36) -> 1.051848e+10 | FH36: =SUM(ER36:EU36) -> 1.3339691e+10 | FI36: =SUM(EV36:EY36) -> 1.6030075e+10 | FJ36: =SUM(EZ36:FC36) -> 1.8543997e+10 | FK36: x
B37: Market Place | C37: =Marketplace!C3 -> 71270132 | D37: =Marketplace!D3 -> 92247410 | E37: =Marketplace!E3 -> 80512562 | F37: =Marketplace!F3 -> 66231280 | G37: =Marketplace!G3 -> 40103506 | H37: =Marketplace!H3 -> 27837941 | I37: =Marketplace!I3 -> 33141999 | J37: =Marketplace!J3 -> 31956623 | ... ED37: =Marketplace!ED3 -> 1.1714241e+09 | EF37: =SUM(BK37:BM37) -> 1072114128 | EG37: =SUM(BN37:BP37) -> 1148662191 | EH37: =SUM(BQ37:BS37) -> 1371300053 | EI37: =SUM(BT37:BV37) -> 1343077704 | EJ37: =SUM(BW37:BY37) -> 1290092206 | EK37: =SUM(BZ37:CB37) -> 1414314262 | EL37: =SUM(CC37:CE37) -> 1617078865 | EM37: =SUM(CF37:CH37) -> 1672561133 | EN37: =SUM(CI37:CK37) -> 1580509516 | EO37: =SUM(CL37:CN37) -> 1627577564 | EP37: =SUM(CO37:CQ37) -> 1954180574 | EQ37: =SUM(CR37:CT37) -> 2008114870 | ER37: =SUM(CU37:CW37) -> 2.0381886e+09 | ES37: =SUM(CX37:CZ37) -> 2.2867613e+09 | ET37: =SUM(DA37:DC37) -> 2.5442938e+09 | EU37: =SUM(DD37:DF37) -> 2.3626238e+09 | EV37: =SUM(DG37:DI37) -> 2.4458263e+09 | EW37: =SUM(DJ37:DL37) -> 2.7441135e+09 | EX37: =SUM(DM37:DO37) -> 3.0531526e+09 | EY37: =SUM(DP37:DR37) -> 2.8351486e+09 | EZ37: =SUM(DS37:DU37) -> 2.8127003e+09 | FA37: =SUM(DV37:DX37) -> 3.1557306e+09 | FB37: =SUM(DY37:EA37) -> 3.5111254e+09 | FC37: =SUM(EB37:ED37) -> 3.2604209e+09 | FE37: =SUM(EF37:EI37) -> 4935154076 | FF37: =SUM(EJ37:EM37) -> 5994046466 | FG37: =SUM(EN37:EQ37) -> 7170382524 | FH37: =SUM(ER37:EU37) -> 9.2318675e+09 | FI37: =SUM(EV37:EY37) -> 1.1078241e+10 | FJ37: =SUM(EZ37:FC37) -> 1.2739977e+10 | FK37: x
B38: Screen Pro + Accessories | L38: ='D2C Online'!C40 -> 0 | M38: ='D2C Online'!D40 -> 0 | N38: ='D2C Online'!E40 -> 0 | O38: ='D2C Online'!F40 -> 0 | P38: ='D2C Online'!G40 -> 0 | Q38: ='D2C Online'!H40 -> 0 | R38: ='D2C Online'!I40 -> 0 | S38: ='D2C Online'!J40 -> 0 | ... AB38: ='D2C Online'!S40 -> 0 | AC38: ='D2C Online'!T40+'D2C - Retail'!C34+'D2C - Retail'!C35 -> 3855584 | AD38: ='D2C Online'!U40+'D2C - Retail'!D34+'D2C - Retail'!D35 -> 4106966 | AE38: ='D2C Online'!V40+'D2C - Retail'!E34+'D2C - Retail'!E35 -> 4333550.5 | AF38: ='D2C Online'!W40+'D2C - Retail'!F34+'D2C - Retail'!F35 -> 3785324.8 | AG38: ='D2C Online'!X40+'D2C - Retail'!G34+'D2C - Retail'!G35 -> 3549308.3 | AH38: ='D2C Online'!Y40+'D2C - Retail'!H34+'D2C - Retail'!H35 -> 3452754 | AI38: ='D2C Online'!Z40+'D2C - Retail'!I34+'D2C - Retail'!I35 -> 3507793.4 | AJ38: ='D2C Online'!AA40+'D2C - Retail'!J34+'D2C - Retail'!J35 -> 3548218.7 | ... ED38: ='D2C Online'!DU40+'D2C - Retail'!DD34+'D2C - Retail'!DD35 -> 77805406 | EF38: =SUM(BK38:BM38) -> 75240991 | EG38: =SUM(BN38:BP38) -> 86629413 | EH38: =SUM(BQ38:BS38) -> 78698620 | EI38: =SUM(BT38:BV38) -> 69273240 | EJ38: =SUM(BW38:BY38) -> 86679585 | EK38: =SUM(BZ38:CB38) -> 92809367 | EL38: =SUM(CC38:CE38) -> 97839727 | EM38: =SUM(CF38:CH38) -> 1.0268518e+08 | EN38: =SUM(CI38:CK38) -> 1.1525647e+08 | EO38: =SUM(CL38:CN38) -> 1.3117917e+08 | EP38: =SUM(CO38:CQ38) -> 1.5621076e+08 | EQ38: =SUM(CR38:CT38) -> 1.9540338e+08 | ER38: =SUM(CU38:CW38) -> 1.7275758e+08 | ES38: =SUM(CX38:CZ38) -> 1.7816339e+08 | ET38: =SUM(DA38:DC38) -> 1.8494447e+08 | EU38: =SUM(DD38:DF38) -> 1.9220512e+08 | EV38: =SUM(DG38:DI38) -> 1.9670584e+08 | EW38: =SUM(DJ38:DL38) -> 2.0191485e+08 | EX38: =SUM(DM38:DO38) -> 2.0761225e+08 | EY38: =SUM(DP38:DR38) -> 2.1285887e+08 | EZ38: =SUM(DS38:DU38) -> 2.1563518e+08 | FA38: =SUM(DV38:DX38) -> 2.2087167e+08 | FB38: =SUM(DY38:EA38) -> 2.2684901e+08 | FC38: =SUM(EB38:ED38) -> 2.3257655e+08 | FE38: =SUM(EF38:EI38) -> 3.0984226e+08 | FF38: =SUM(EJ38:EM38) -> 3.8001386e+08 | FG38: =SUM(EN38:EQ38) -> 5.9804978e+08 | FH38: =SUM(ER38:EU38) -> 7.2807056e+08 | FI38: =SUM(EV38:EY38) -> 8.190918e+08 | FJ38: =SUM(EZ38:FC38) -> 8.9593241e+08 | FK38: x
B39: Enterprise Sales | C39: =C51 -> 0 | D39: =D51 -> 0 | E39: =E51 -> 0 | F39: =F51 -> 0 | G39: =G51 -> 0 | H39: =H51 -> 0 | I39: =I51 -> 0 | J39: =J51 -> 0 | ... ED39: =ED51 -> 7301025.8 | EF39: =SUM(BK39:BM39) -> 3859521.2 | EG39: =SUM(BN39:BP39) -> 4307213.7 | EH39: =SUM(BQ39:BS39) -> 5335443.4 | EI39: =SUM(BT39:BV39) -> 3773904.9 | EJ39: =SUM(BW39:BY39) -> 3910177 | EK39: =SUM(BZ39:CB39) -> 9588135.2 | EL39: =SUM(CC39:CE39) -> 11346653 | EM39: =SUM(CF39:CH39) -> 7445129.8 | EN39: =SUM(CI39:CK39) -> 6522521 | EO39: =SUM(CL39:CN39) -> 13607431 | EP39: =SUM(CO39:CQ39) -> 11610803 | EQ39: =SUM(CR39:CT39) -> 14277103 | ER39: =SUM(CU39:CW39) -> 6522521 | ES39: =SUM(CX39:CZ39) -> 13607431 | ET39: =SUM(DA39:DC39) -> 11610803 | EU39: =SUM(DD39:DF39) -> 14277103 | EV39: =SUM(DG39:DI39) -> 6522521 | EW39: =SUM(DJ39:DL39) -> 13607431 | EX39: =SUM(DM39:DO39) -> 11610803 | EY39: =SUM(DP39:DR39) -> 14277103 | EZ39: =SUM(DS39:DU39) -> 6522521 | FA39: =SUM(DV39:DX39) -> 13607431 | FB39: =SUM(DY39:EA39) -> 11610803 | FC39: =SUM(EB39:ED39) -> 14277103 | FE39: =SUM(EF39:EI39) -> 17276083 | FF39: =SUM(EJ39:EM39) -> 32290095 | FG39: =SUM(EN39:EQ39) -> 46017858 | FH39: =SUM(ER39:EU39) -> 46017858 | FI39: =SUM(EV39:EY39) -> 46017858 | FJ39: =SUM(EZ39:FC39) -> 46017858 | FK39: x
B40: Screen Pro | C40: ='Screen Pro'!B2 -> 1122221.3 | D40: ='Screen Pro'!C2 -> 1450136.2 | E40: ='Screen Pro'!D2 -> 1972016 | F40: ='Screen Pro'!E2 -> 2300746.3 | G40: ='Screen Pro'!F2 -> 2454507.4 | H40: ='Screen Pro'!G2 -> 3129509.9 | I40: ='Screen Pro'!H2 -> 3675259.9 | J40: ='Screen Pro'!I2 -> 5148563 | ... ED40: ='Screen Pro'!EC2 -> 0 | EF40: =SUM(BK40:BM40) -> 0 | EG40: =SUM(BN40:BP40) -> 0 | EH40: =SUM(BQ40:BS40) -> 0 | EI40: =SUM(BT40:BV40) -> 0 | EJ40: =SUM(BW40:BY40) -> 0 | EK40: =SUM(BZ40:CB40) -> 0 | EL40: =SUM(CC40:CE40) -> 0 | EM40: =SUM(CF40:CH40) -> 0 | EN40: =SUM(CI40:CK40) -> 0 | EO40: =SUM(CL40:CN40) -> 0 | EP40: =SUM(CO40:CQ40) -> 0 | EQ40: =SUM(CR40:CT40) -> 0 | ER40: =SUM(CU40:CW40) -> 0 | ES40: =SUM(CX40:CZ40) -> 0 | ET40: =SUM(DA40:DC40) -> 0 | EU40: =SUM(DD40:DF40) -> 0 | EV40: =SUM(DG40:DI40) -> 0 | EW40: =SUM(DJ40:DL40) -> 0 | EX40: =SUM(DM40:DO40) -> 0 | EY40: =SUM(DP40:DR40) -> 0 | EZ40: =SUM(DS40:DU40) -> 0 | FA40: =SUM(DV40:DX40) -> 0 | FB40: =SUM(DY40:EA40) -> 0 | FC40: =SUM(EB40:ED40) -> 0 | FE40: =SUM(EF40:EI40) -> 0 | FF40: =SUM(EJ40:EM40) -> 0 | FG40: =SUM(EN40:EQ40) -> 0 | FH40: =SUM(ER40:EU40) -> 0 | FI40: =SUM(EV40:EY40) -> 0 | FJ40: =SUM(EZ40:FC40) -> 0 | FK40: x
B42: Non- Repair | C42: =C11-C23 -> 32077 | D42: =D11-D23 -> 28685 | E42: =E11-E23 -> 34758 | F42: =F11-F23 -> 39298 | G42: =G11-G23 -> 47222 | H42: =H11-H23 -> 49152 | I42: =I11-I23 -> 52716 | J42: =J11-J23 -> 52798 | ... ED42: =ED11-ED23 -> 109705.43 | EF42: =SUM(BK42:BM42) -> 140242 | EG42: =SUM(BN42:BP42) -> 120616 | EH42: =SUM(BQ42:BS42) -> 109337 | EI42: =SUM(BT42:BV42) -> 88999 | EJ42: =SUM(BW42:BY42) -> 100559 | EK42: =SUM(BZ42:CB42) -> 94691 | EL42: =SUM(CC42:CE42) -> 103800 | EM42: =SUM(CF42:CH42) -> 148284 | EN42: =SUM(CI42:CK42) -> 147037.37 | EO42: =SUM(CL42:CN42) -> 130591 | EP42: =SUM(CO42:CQ42) -> 164371 | EQ42: =SUM(CR42:CT42) -> 171323.94 | ER42: =SUM(CU42:CW42) -> 195991.42 | ES42: =SUM(CX42:CZ42) -> 174313.9 | ET42: =SUM(DA42:DC42) -> 218120.81 | EU42: =SUM(DD42:DF42) -> 227053.79 | EV42: =SUM(DG42:DI42) -> 244989.28 | EW42: =SUM(DJ42:DL42) -> 217892.37 | EX42: =SUM(DM42:DO42) -> 272651.01 | EY42: =SUM(DP42:DR42) -> 283817.24 | EZ42: =SUM(DS42:DU42) -> 293987.13 | FA42: =SUM(DV42:DX42) -> 261470.85 | FB42: =SUM(DY42:EA42) -> 327181.21 | FC42: =SUM(EB42:ED42) -> 340580.69 | FE42: =SUM(EF42:EI42) -> 459194 | FF42: =SUM(EJ42:EM42) -> 447334 | FG42: =SUM(EN42:EQ42) -> 613323.31 | FH42: =SUM(ER42:EU42) -> 815479.92 | FI42: =SUM(EV42:EY42) -> 1019349.9 | FJ42: =SUM(EZ42:FC42) -> 1223219.9 | FK42: x
B43: Refurbished | C43: =C12-C27 -> 916 | D43: =D12-D27 -> 969 | E43: =E12-E27 -> 817 | F43: =F12-F27 -> 1419 | G43: =G12-G27 -> 1338 | H43: =H12-H27 -> 1177 | I43: =I12-I27 -> 1366 | J43: =J12-J27 -> 1689 | ... ED43: =ED12-ED27 -> 58330.79 | EF43: =SUM(BK43:BM43) -> 64886 | EG43: =SUM(BN43:BP43) -> 57964 | EH43: =SUM(BQ43:BS43) -> 66228 | EI43: =SUM(BT43:BV43) -> 54294 | EJ43: =SUM(BW43:BY43) -> 62878 | EK43: =SUM(BZ43:CB43) -> 57251 | EL43: =SUM(CC43:CE43) -> 59589 | EM43: =SUM(CF43:CH43) -> 74259 | EN43: =SUM(CI43:CK43) -> 77782.286 | EO43: =SUM(CL43:CN43) -> 81140 | EP43: =SUM(CO43:CQ43) -> 90820 | EQ43: =SUM(CR43:CT43) -> 109351 | ER43: =SUM(CU43:CW43) -> 101355.32 | ES43: =SUM(CX43:CZ43) -> 100026.64 | ET43: =SUM(DA43:DC43) -> 112718.24 | EU43: =SUM(DD43:DF43) -> 127818.84 | EV43: =SUM(DG43:DI43) -> 118902.82 | EW43: =SUM(DJ43:DL43) -> 116982.79 | EX43: =SUM(DM43:DO43) -> 131065.54 | EY43: =SUM(DP43:DR43) -> 147301.81 | EZ43: =SUM(DS43:DU43) -> 136226.39 | FA43: =SUM(DV43:DX43) -> 133876.13 | FB43: =SUM(DY43:EA43) -> 149821.23 | FC43: =SUM(EB43:ED43) -> 168292.88 | FE43: =SUM(EF43:EI43) -> 243372 | FF43: =SUM(EJ43:EM43) -> 253977 | FG43: =SUM(EN43:EQ43) -> 359093.29 | FH43: =SUM(ER43:EU43) -> 441919.04 | FI43: =SUM(EV43:EY43) -> 514252.95 | FJ43: =SUM(EZ43:FC43) -> 588216.62 | FK43: x
B44: Market Place | C44: =C13 -> 12462 | D44: =D13 -> 16130 | E44: =E13 -> 15564 | F44: =F13 -> 13358 | G44: =G13 -> 7745 | H44: =H13 -> 5065 | I44: =I13 -> 6044 | J44: =J13 -> 5387 | ... ED44: =ED13 -> 136135.27 | EF44: =SUM(BK44:BM44) -> 167535 | EG44: =SUM(BN44:BP44) -> 168742 | EH44: =SUM(BQ44:BS44) -> 194108 | EI44: =SUM(BT44:BV44) -> 167766 | EJ44: =SUM(BW44:BY44) -> 166377 | EK44: =SUM(BZ44:CB44) -> 179298 | EL44: =SUM(CC44:CE44) -> 194617 | EM44: =SUM(CF44:CH44) -> 180791 | EN44: =SUM(CI44:CK44) -> 189492 | EO44: =SUM(CL44:CN44) -> 212602 | EP44: =SUM(CO44:CQ44) -> 236545 | EQ44: =SUM(CR44:CT44) -> 219655 | ER44: =SUM(CU44:CW44) -> 236865 | ES44: =SUM(CX44:CZ44) -> 265752.5 | ET44: =SUM(DA44:DC44) -> 295681.25 | EU44: =SUM(DD44:DF44) -> 274568.75 | EV44: =SUM(DG44:DI44) -> 284238 | EW44: =SUM(DJ44:DL44) -> 318903 | EX44: =SUM(DM44:DO44) -> 354817.5 | EY44: =SUM(DP44:DR44) -> 329482.5 | EZ44: =SUM(DS44:DU44) -> 326873.7 | FA44: =SUM(DV44:DX44) -> 366738.45 | FB44: =SUM(DY44:EA44) -> 408040.12 | FC44: =SUM(EB44:ED44) -> 378904.88 | FE44: =SUM(EF44:EI44) -> 698151 | FF44: =SUM(EJ44:EM44) -> 721083 | FG44: =SUM(EN44:EQ44) -> 858294 | FH44: =SUM(ER44:EU44) -> 1072867.5 | FI44: =SUM(EV44:EY44) -> 1287441 | FJ44: =SUM(EZ44:FC44) -> 1480557.1 | FK44: x
B46: Revenue Pre Tax (after returns) | C46: =SUM(C47:C52) -> 1.3972517e+08 | D46: =SUM(D47:D52) -> 1.3522652e+08 | E46: =SUM(E47:E52) -> 1.4827906e+08 | F46: =SUM(F47:F52) -> 1.7334583e+08 | G46: =SUM(G47:G52) -> 1.9610351e+08 | H46: =SUM(H47:H52) -> 2.0209471e+08 | I46: =SUM(I47:I52) -> 2.1779249e+08 | J46: =SUM(J47:J52) -> 2.0893986e+08 | ... ED46: =SUM(ED47:ED52) -> 3.1378478e+09 | EF46: =SUM(BK46:BM46) -> 2.7855511e+09 | EG46: =SUM(BN46:BP46) -> 2.3985813e+09 | EH46: =SUM(BQ46:BS46) -> 2.8637562e+09 | EI46: =SUM(BT46:BV46) -> 2.452637e+09 | EJ46: =SUM(BW46:BY46) -> 2.7788511e+09 | EK46: =SUM(BZ46:CB46) -> 2.5815905e+09 | EL46: =SUM(CC46:CE46) -> 2.9803463e+09 | EM46: =SUM(CF46:CH46) -> 3.8680091e+09 | EN46: =SUM(CI46:CK46) -> 4.0196188e+09 | EO46: =SUM(CL46:CN46) -> 3.8362057e+09 | EP46: =SUM(CO46:CQ46) -> 4.7352659e+09 | EQ46: =SUM(CR46:CT46) -> 5.621542e+09 | ER46: =SUM(CU46:CW46) -> 5.3994014e+09 | ES46: =SUM(CX46:CZ46) -> 5.1875579e+09 | ET46: =SUM(DA46:DC46) -> 6.0404916e+09 | EU46: =SUM(DD46:DF46) -> 6.5630345e+09 | EV46: =SUM(DG46:DI46) -> 6.5989644e+09 | EW46: =SUM(DJ46:DL46) -> 6.3187757e+09 | EX46: =SUM(DM46:DO46) -> 7.3389955e+09 | EY46: =SUM(DP46:DR46) -> 7.9220778e+09 | EZ46: =SUM(DS46:DU46) -> 7.7274132e+09 | FA46: =SUM(DV46:DX46) -> 7.3857553e+09 | FB46: =SUM(DY46:EA46) -> 8.5812071e+09 | FC46: =SUM(EB46:ED46) -> 9.2572208e+09 | FE46: =SUM(EF46:EI46) -> 1.0500526e+10 | FF46: =SUM(EJ46:EM46) -> 1.2208797e+10 | FG46: =SUM(EN46:EQ46) -> 1.8212632e+10 | FH46: =SUM(ER46:EU46) -> 2.3190485e+10 | FI46: =SUM(EV46:EY46) -> 2.8178813e+10 | FJ46: =SUM(EZ46:FC46) -> 3.2951596e+10 | FK46: x
B47: Non- Repair | C47: ='B2B- Non Repair'!C23 -> 127373162 | D47: ='B2B- Non Repair'!D23 -> 119525214 | E47: ='B2B- Non Repair'!E23 -> 1.3361892e+08 | F47: ='B2B- Non Repair'!F23 -> 1.5572126e+08 | G47: ='B2B- Non Repair'!G23 -> 1.8292117e+08 | H47: ='B2B- Non Repair'!H23 -> 190468885 | I47: ='B2B- Non Repair'!I23 -> 203496304 | J47: ='B2B- Non Repair'!J23 -> 191306750 | ... ED47: ='B2B- Non Repair'!ED23 -> 1.0516969e+09 | EF47: =SUM(BK47:BM47) -> 1.0841488e+09 | EG47: =SUM(BN47:BP47) -> 8.7395053e+08 | EH47: =SUM(BQ47:BS47) -> 9.0781123e+08 | EI47: =SUM(BT47:BV47) -> 8.5217354e+08 | EJ47: =SUM(BW47:BY47) -> 9.2711467e+08 | EK47: =SUM(BZ47:CB47) -> 8.0449024e+08 | EL47: =SUM(CC47:CE47) -> 9.2290855e+08 | EM47: =SUM(CF47:CH47) -> 1.3849157e+09 | EN47: =SUM(CI47:CK47) -> 1.3968365e+09 | EO47: =SUM(CL47:CN47) -> 1.1858951e+09 | EP47: =SUM(CO47:CQ47) -> 1.5917634e+09 | EQ47: =SUM(CR47:CT47) -> 1.9085306e+09 | ER47: =SUM(CU47:CW47) -> 1.8855272e+09 | ES47: =SUM(CX47:CZ47) -> 1.6729566e+09 | ET47: =SUM(DA47:DC47) -> 2.0951093e+09 | EU47: =SUM(DD47:DF47) -> 2.1780252e+09 | EV47: =SUM(DG47:DI47) -> 2.356909e+09 | EW47: =SUM(DJ47:DL47) -> 2.0911958e+09 | EX47: =SUM(DM47:DO47) -> 2.6188866e+09 | EY47: =SUM(DP47:DR47) -> 2.7225315e+09 | EZ47: =SUM(DS47:DU47) -> 2.8282908e+09 | FA47: =SUM(DV47:DX47) -> 2.509435e+09 | FB47: =SUM(DY47:EA47) -> 3.1426639e+09 | FC47: =SUM(EB47:ED47) -> 3.2670378e+09 | FE47: =SUM(EF47:EI47) -> 3.7180841e+09 | FF47: =SUM(EJ47:EM47) -> 4.0394291e+09 | FG47: =SUM(EN47:EQ47) -> 6.0830257e+09 | FH47: =SUM(ER47:EU47) -> 7.8316183e+09 | FI47: =SUM(EV47:EY47) -> 9.7895228e+09 | FJ47: =SUM(EZ47:FC47) -> 1.1747427e+10 | FK47: x
B48: Refurbished | C48: =Refurbished!C21 -> 6192647 | D48: =Refurbished!D21 -> 6767807 | E48: =Refurbished!E21 -> 5747560.8 | F48: =Refurbished!F21 -> 9331198.9 | G48: =Refurbished!G21 -> 7135417.9 | H48: =Refurbished!H21 -> 5830125.6 | I48: =Refurbished!I21 -> 7326199 | J48: =Refurbished!J21 -> 9536226 | ... ED48: =Refurbished!ED21 -> 1.8430563e+09 | EF48: =SUM(BK48:BM48) -> 1.4890796e+09 | EG48: =SUM(BN48:BP48) -> 1.2892337e+09 | EH48: =SUM(BQ48:BS48) -> 1.6980566e+09 | EI48: =SUM(BT48:BV48) -> 1.3642012e+09 | EJ48: =SUM(BW48:BY48) -> 1.5977024e+09 | EK48: =SUM(BZ48:CB48) -> 1.4937662e+09 | EL48: =SUM(CC48:CE48) -> 1.7427869e+09 | EM48: =SUM(CF48:CH48) -> 2.1698124e+09 | EN48: =SUM(CI48:CK48) -> 2.2923924e+09 | EO48: =SUM(CL48:CN48) -> 2.2801346e+09 | EP48: =SUM(CO48:CQ48) -> 2.7059976e+09 | EQ48: =SUM(CR48:CT48) -> 3.2399559e+09 | ER48: =SUM(CU48:CW48) -> 3.0597067e+09 | ES48: =SUM(CX48:CZ48) -> 3.0144184e+09 | ET48: =SUM(DA48:DC48) -> 3.405682e+09 | EU48: =SUM(DD48:DF48) -> 3.8598835e+09 | EV48: =SUM(DG48:DI48) -> 3.7089622e+09 | EW48: =SUM(DJ48:DL48) -> 3.6419632e+09 | EX48: =SUM(DM48:DO48) -> 4.0891118e+09 | EY48: =SUM(DP48:DR48) -> 4.5900381e+09 | EZ48: =SUM(DS48:DU48) -> 4.2976201e+09 | FA48: =SUM(DV48:DX48) -> 4.2162326e+09 | FB48: =SUM(DY48:EA48) -> 4.7265432e+09 | FC48: =SUM(EB48:ED48) -> 5.3036013e+09 | FE48: =SUM(EF48:EI48) -> 5.8405711e+09 | FF48: =SUM(EJ48:EM48) -> 7.004068e+09 | FG48: =SUM(EN48:EQ48) -> 1.051848e+10 | FH48: =SUM(ER48:EU48) -> 1.3339691e+10 | FI48: =SUM(EV48:EY48) -> 1.6030075e+10 | FJ48: =SUM(EZ48:FC48) -> 1.8543997e+10 | FK48: x
B49: Market Place | C49: =Marketplace!C5 -> 5037141.5 | D49: =Marketplace!D5 -> 7483366.5 | E49: =Marketplace!E5 -> 6940571.2 | F49: =Marketplace!F5 -> 5992624.1 | G49: =Marketplace!G5 -> 3592413.2 | H49: =Marketplace!H5 -> 2666191.1 | I49: =Marketplace!I5 -> 3294731.1 | J49: =Marketplace!J5 -> 2948318.5 | ... ED49: =Marketplace!ED5 -> 1.5798819e+08 | EF49: =SUM(BK49:BM49) -> 1.3322221e+08 | EG49: =SUM(BN49:BP49) -> 1.4446043e+08 | EH49: =SUM(BQ49:BS49) -> 1.7385438e+08 | EI49: =SUM(BT49:BV49) -> 1.6321513e+08 | EJ49: =SUM(BW49:BY49) -> 1.6344421e+08 | EK49: =SUM(BZ49:CB49) -> 1.8093655e+08 | EL49: =SUM(CC49:CE49) -> 2.0546443e+08 | EM49: =SUM(CF49:CH49) -> 2.0315076e+08 | EN49: =SUM(CI49:CK49) -> 2.0861093e+08 | EO49: =SUM(CL49:CN49) -> 2.2538942e+08 | EP49: =SUM(CO49:CQ49) -> 2.6968335e+08 | EQ49: =SUM(CR49:CT49) -> 2.6337493e+08 | ER49: =SUM(CU49:CW49) -> 2.7488741e+08 | ES49: =SUM(CX49:CZ49) -> 3.0841203e+08 | ET49: =SUM(DA49:DC49) -> 3.4314505e+08 | EU49: =SUM(DD49:DF49) -> 3.186435e+08 | EV49: =SUM(DG49:DI49) -> 3.2986489e+08 | EW49: =SUM(DJ49:DL49) -> 3.7009444e+08 | EX49: =SUM(DM49:DO49) -> 4.1177406e+08 | EY49: =SUM(DP49:DR49) -> 3.823722e+08 | EZ49: =SUM(DS49:DU49) -> 3.7934462e+08 | FA49: =SUM(DV49:DX49) -> 4.256086e+08 | FB49: =SUM(DY49:EA49) -> 4.7354017e+08 | FC49: =SUM(EB49:ED49) -> 4.3972803e+08 | FE49: =SUM(EF49:EI49) -> 6.1475214e+08 | FF49: =SUM(EJ49:EM49) -> 7.5299595e+08 | FG49: =SUM(EN49:EQ49) -> 9.6705863e+08 | FH49: =SUM(ER49:EU49) -> 1.245088e+09 | FI49: =SUM(EV49:EY49) -> 1.4941056e+09 | FJ49: =SUM(EZ49:FC49) -> 1.7182214e+09 | FK49: x
B50: Screen Pro + Accessories | C50: 0 | D50: 0 | E50: 0 | F50: 0 | G50: 0 | H50: 0 | I50: 0 | J50: 0 | K50: 0 | L50: ='D2C Online'!C40 -> 0 | M50: ='D2C Online'!D40 -> 0 | N50: ='D2C Online'!E40 -> 0 | O50: ='D2C Online'!F40 -> 0 | P50: ='D2C Online'!G40 -> 0 | Q50: ='D2C Online'!H40 -> 0 | R50: ='D2C Online'!I40 -> 0 | S50: ='D2C Online'!J40 -> 0 | ... AB50: ='D2C Online'!S40 -> 0 | AC50: ='D2C Online'!T40+'D2C - Retail'!C34+'D2C - Retail'!C35 -> 3855584 | AD50: ='D2C Online'!U40+'D2C - Retail'!D34+'D2C - Retail'!D35 -> 4106966 | AE50: ='D2C Online'!V40+'D2C - Retail'!E34+'D2C - Retail'!E35 -> 4333550.5 | AF50: ='D2C Online'!W40+'D2C - Retail'!F34+'D2C - Retail'!F35 -> 3785324.8 | AG50: ='D2C Online'!X40+'D2C - Retail'!G34+'D2C - Retail'!G35 -> 3549308.3 | AH50: ='D2C Online'!Y40+'D2C - Retail'!H34+'D2C - Retail'!H35 -> 3452754 | AI50: ='D2C Online'!Z40+'D2C - Retail'!I34+'D2C - Retail'!I35 -> 3507793.4 | AJ50: ='D2C Online'!AA40+'D2C - Retail'!J34+'D2C - Retail'!J35 -> 3548218.7 | ... ED50: ='D2C Online'!DU40+'D2C - Retail'!DD34+'D2C - Retail'!DD35 -> 77805406 | EF50: =SUM(BK50:BM50) -> 75240991 | EG50: =SUM(BN50:BP50) -> 86629413 | EH50: =SUM(BQ50:BS50) -> 78698620 | EI50: =SUM(BT50:BV50) -> 69273240 | EJ50: =SUM(BW50:BY50) -> 86679585 | EK50: =SUM(BZ50:CB50) -> 92809367 | EL50: =SUM(CC50:CE50) -> 97839727 | EM50: =SUM(CF50:CH50) -> 1.0268518e+08 | EN50: =SUM(CI50:CK50) -> 1.1525647e+08 | EO50: =SUM(CL50:CN50) -> 1.3117917e+08 | EP50: =SUM(CO50:CQ50) -> 1.5621076e+08 | EQ50: =SUM(CR50:CT50) -> 1.9540338e+08 | ER50: =SUM(CU50:CW50) -> 1.7275758e+08 | ES50: =SUM(CX50:CZ50) -> 1.7816339e+08 | ET50: =SUM(DA50:DC50) -> 1.8494447e+08 | EU50: =SUM(DD50:DF50) -> 1.9220512e+08 | EV50: =SUM(DG50:DI50) -> 1.9670584e+08 | EW50: =SUM(DJ50:DL50) -> 2.0191485e+08 | EX50: =SUM(DM50:DO50) -> 2.0761225e+08 | EY50: =SUM(DP50:DR50) -> 2.1285887e+08 | EZ50: =SUM(DS50:DU50) -> 2.1563518e+08 | FA50: =SUM(DV50:DX50) -> 2.2087167e+08 | FB50: =SUM(DY50:EA50) -> 2.2684901e+08 | FC50: =SUM(EB50:ED50) -> 2.3257655e+08 | FE50: =SUM(EF50:EI50) -> 3.0984226e+08 | FF50: =SUM(EJ50:EM50) -> 3.8001386e+08 | FG50: =SUM(EN50:EQ50) -> 5.9804978e+08 | FH50: =SUM(ER50:EU50) -> 7.2807056e+08 | FI50: =SUM(EV50:EY50) -> 8.190918e+08 | FJ50: =SUM(EZ50:FC50) -> 8.9593241e+08 | FK50: x
B51: Enterprise Sales | C51: ='P&L - Inputs'!B745 -> 0 | D51: ='P&L - Inputs'!C745 -> 0 | E51: ='P&L - Inputs'!D745 -> 0 | F51: ='P&L - Inputs'!E745 -> 0 | G51: ='P&L - Inputs'!F745 -> 0 | H51: ='P&L - Inputs'!G745 -> 0 | I51: ='P&L - Inputs'!H745 -> 0 | J51: ='P&L - Inputs'!I745 -> 0 | ... ED51: ='P&L - Inputs'!EC745 -> 7301025.8 | EF51: =SUM(BK51:BM51) -> 3859521.2 | EG51: =SUM(BN51:BP51) -> 4307213.7 | EH51: =SUM(BQ51:BS51) -> 5335443.4 | EI51: =SUM(BT51:BV51) -> 3773904.9 | EJ51: =SUM(BW51:BY51) -> 3910177 | EK51: =SUM(BZ51:CB51) -> 9588135.2 | EL51: =SUM(CC51:CE51) -> 11346653 | EM51: =SUM(CF51:CH51) -> 7445129.8 | EN51: =SUM(CI51:CK51) -> 6522521 | EO51: =SUM(CL51:CN51) -> 13607431 | EP51: =SUM(CO51:CQ51) -> 11610803 | EQ51: =SUM(CR51:CT51) -> 14277103 | ER51: =SUM(CU51:CW51) -> 6522521 | ES51: =SUM(CX51:CZ51) -> 13607431 | ET51: =SUM(DA51:DC51) -> 11610803 | EU51: =SUM(DD51:DF51) -> 14277103 | EV51: =SUM(DG51:DI51) -> 6522521 | EW51: =SUM(DJ51:DL51) -> 13607431 | EX51: =SUM(DM51:DO51) -> 11610803 | EY51: =SUM(DP51:DR51) -> 14277103 | EZ51: =SUM(DS51:DU51) -> 6522521 | FA51: =SUM(DV51:DX51) -> 13607431 | FB51: =SUM(DY51:EA51) -> 11610803 | FC51: =SUM(EB51:ED51) -> 14277103 | FE51: =SUM(EF51:EI51) -> 17276083 | FF51: =SUM(EJ51:EM51) -> 32290095 | FG51: =SUM(EN51:EQ51) -> 46017858 | FH51: =SUM(ER51:EU51) -> 46017858 | FI51: =SUM(EV51:EY51) -> 46017858 | FJ51: =SUM(EZ51:FC51) -> 46017858 | FK51: x
B52: Screen Pro | C52: ='Screen Pro'!B2 -> 1122221.3 | D52: ='Screen Pro'!C2 -> 1450136.2 | E52: ='Screen Pro'!D2 -> 1972016 | F52: ='Screen Pro'!E2 -> 2300746.3 | G52: ='Screen Pro'!F2 -> 2454507.4 | H52: ='Screen Pro'!G2 -> 3129509.9 | I52: ='Screen Pro'!H2 -> 3675259.9 | J52: ='Screen Pro'!I2 -> 5148563 | ... ED52: ='Screen Pro'!EC2 -> 0 | EF52: =SUM(BK52:BM52) -> 0 | EG52: =SUM(BN52:BP52) -> 0 | EH52: =SUM(BQ52:BS52) -> 0 | EI52: =SUM(BT52:BV52) -> 0 | EJ52: =SUM(BW52:BY52) -> 0 | EK52: =SUM(BZ52:CB52) -> 0 | EL52: =SUM(CC52:CE52) -> 0 | EM52: =SUM(CF52:CH52) -> 0 | EN52: =SUM(CI52:CK52) -> 0 | EO52: =SUM(CL52:CN52) -> 0 | EP52: =SUM(CO52:CQ52) -> 0 | EQ52: =SUM(CR52:CT52) -> 0 | ER52: =SUM(CU52:CW52) -> 0 | ES52: =SUM(CX52:CZ52) -> 0 | ET52: =SUM(DA52:DC52) -> 0 | EU52: =SUM(DD52:DF52) -> 0 | EV52: =SUM(DG52:DI52) -> 0 | EW52: =SUM(DJ52:DL52) -> 0 | EX52: =SUM(DM52:DO52) -> 0 | EY52: =SUM(DP52:DR52) -> 0 | EZ52: =SUM(DS52:DU52) -> 0 | FA52: =SUM(DV52:DX52) -> 0 | FB52: =SUM(DY52:EA52) -> 0 | FC52: =SUM(EB52:ED52) -> 0 | FE52: =SUM(EF52:EI52) -> 0 | FF52: =SUM(EJ52:EM52) -> 0 | FG52: =SUM(EN52:EQ52) -> 0 | FH52: =SUM(ER52:EU52) -> 0 | FI52: =SUM(EV52:EY52) -> 0 | FJ52: =SUM(EZ52:FC52) -> 0 | FK52: x
B54: Tax | C54: =SUM(C55:C60) -> 2659885.9 | D54: =SUM(D55:D60) -> 3477826.5 | E54: =SUM(E55:E60) -> 3656603.4 | F54: =SUM(F55:F60) -> 4133990.3 | G54: =SUM(G55:G60) -> 4632250.1 | H54: =SUM(H55:H60) -> 4441054.4 | I54: =SUM(I55:I60) -> 3949934.8 | J54: =SUM(J55:J60) -> 4838900.8 | ... ED54: =SUM(ED55:ED60) -> 1.7140993e+08 | EF54: =SUM(BK54:BM54) -> 1.163055e+08 | EG54: =SUM(BN54:BP54) -> 1.1238009e+08 | EH54: =SUM(BQ54:BS54) -> 1.285729e+08 | EI54: =SUM(BT54:BV54) -> 1.2984426e+08 | EJ54: =SUM(BW54:BY54) -> 1.4406213e+08 | EK54: =SUM(BZ54:CB54) -> 1.3716254e+08 | EL54: =SUM(CC54:CE54) -> 1.5715362e+08 | EM54: =SUM(CF54:CH54) -> 1.8696679e+08 | EN54: =SUM(CI54:CK54) -> 2.1739484e+08 | EO54: =SUM(CL54:CN54) -> 2.1351355e+08 | EP54: =SUM(CO54:CQ54) -> 2.520917e+08 | EQ54: =SUM(CR54:CT54) -> 2.9395238e+08 | ER54: =SUM(CU54:CW54) -> 2.9302374e+08 | ES54: =SUM(CX54:CZ54) -> 2.8939752e+08 | ET54: =SUM(DA54:DC54) -> 3.319563e+08 | EU54: =SUM(DD54:DF54) -> 3.577245e+08 | EV54: =SUM(DG54:DI54) -> 3.5632162e+08 | EW54: =SUM(DJ54:DL54) -> 3.5057769e+08 | EX54: =SUM(DM54:DO54) -> 4.0102915e+08 | EY54: =SUM(DP54:DR54) -> 4.2928365e+08 | EZ54: =SUM(DS54:DU54) -> 4.1493041e+08 | FA54: =SUM(DV54:DX54) -> 4.0739987e+08 | FB54: =SUM(DY54:EA54) -> 4.661281e+08 | FC54: =SUM(EB54:ED54) -> 4.9876665e+08 | FE54: =SUM(EF54:EI54) -> 4.8710275e+08 | FF54: =SUM(EJ54:EM54) -> 6.2534507e+08 | FG54: =SUM(EN54:EQ54) -> 9.7695247e+08 | FH54: =SUM(ER54:EU54) -> 1.2721021e+09 | FI54: =SUM(EV54:EY54) -> 1.5372121e+09 | FJ54: =SUM(EZ54:FC54) -> 1.787225e+09 | FK54: x
B55: Non- Repair | C55: ='B2B- Non Repair'!C27 -> 1571885 | D55: ='B2B- Non Repair'!D27 -> 1933225.9 | E55: ='B2B- Non Repair'!E27 -> 2144810.8 | F55: ='B2B- Non Repair'!F27 -> 2670744.5 | G55: ='B2B- Non Repair'!G27 -> 3520739.2 | H55: ='B2B- Non Repair'!H27 -> 3375803 | I55: ='B2B- Non Repair'!I27 -> 2640496 | J55: ='B2B- Non Repair'!J27 -> 3233060 | ... ED55: ='B2B- Non Repair'!ED27 -> 37029906 | EF55: =SUM(BK55:BM55) -> 23354917 | EG55: =SUM(BN55:BP55) -> 22437572 | EH55: =SUM(BQ55:BS55) -> 19773188 | EI55: =SUM(BT55:BV55) -> 21380637 | EJ55: =SUM(BW55:BY55) -> 25537282 | EK55: =SUM(BZ55:CB55) -> 19320559 | EL55: =SUM(CC55:CE55) -> 23549830 | EM55: =SUM(CF55:CH55) -> 32092067 | EN55: =SUM(CI55:CK55) -> 41613023 | EO55: =SUM(CL55:CN55) -> 36522048 | EP55: =SUM(CO55:CQ55) -> 48244390 | EQ55: =SUM(CR55:CT55) -> 63932022 | ER55: =SUM(CU55:CW55) -> 66420201 | ES55: =SUM(CX55:CZ55) -> 58913179 | ET55: =SUM(DA55:DC55) -> 73787410 | EU55: =SUM(DD55:DF55) -> 76693998 | EV55: =SUM(DG55:DI55) -> 83025251 | EW55: =SUM(DJ55:DL55) -> 73641474 | EX55: =SUM(DM55:DO55) -> 92234263 | EY55: =SUM(DP55:DR55) -> 95867498 | EZ55: =SUM(DS55:DU55) -> 99630302 | FA55: =SUM(DV55:DX55) -> 88369769 | FB55: =SUM(DY55:EA55) -> 1.1068112e+08 | FC55: =SUM(EB55:ED55) -> 1.15041e+08 | FE55: =SUM(EF55:EI55) -> 86946313 | FF55: =SUM(EJ55:EM55) -> 1.0049974e+08 | FG55: =SUM(EN55:EQ55) -> 1.9031148e+08 | FH55: =SUM(ER55:EU55) -> 2.7581479e+08 | FI55: =SUM(EV55:EY55) -> 3.4476849e+08 | FJ55: =SUM(EZ55:FC55) -> 4.1372218e+08 | FK55: x
B56: Refurbished | C56: =Refurbished!C30 -> 148437.04 | D56: =Refurbished!D30 -> 181862.97 | E56: =Refurbished!E30 -> 152245.42 | F56: =Refurbished!F30 -> 198155.39 | G56: =Refurbished!G30 -> 189099.36 | H56: =Refurbished!H30 -> 181161.42 | I56: =Refurbished!I30 -> 246219.83 | J56: =Refurbished!J30 -> 370723.32 | ... ED56: =Refurbished!ED30 -> 90923005 | EF56: =SUM(BK56:BM56) -> 60526206 | EG56: =SUM(BN56:BP56) -> 54016332 | EH56: =SUM(BQ56:BS56) -> 69460799 | EI56: =SUM(BT56:BV56) -> 72423618 | EJ56: =SUM(BW56:BY56) -> 79773899 | EK56: =SUM(BZ56:CB56) -> 74621531 | EL56: =SUM(CC56:CE56) -> 85606205 | EM56: =SUM(CF56:CH56) -> 1.0708608e+08 | EN56: =SUM(CI56:CK56) -> 1.2538336e+08 | EO56: =SUM(CL56:CN56) -> 1.2052397e+08 | EP56: =SUM(CO56:CQ56) -> 1.3710927e+08 | EQ56: =SUM(CR56:CT56) -> 1.5785936e+08 | ER56: =SUM(CU56:CW56) -> 1.5321456e+08 | ES56: =SUM(CX56:CZ56) -> 1.5164507e+08 | ET56: =SUM(DA56:DC56) -> 1.7002047e+08 | EU56: =SUM(DD56:DF56) -> 1.9208847e+08 | EV56: =SUM(DG56:DI56) -> 1.8476441e+08 | EW56: =SUM(DJ56:DL56) -> 1.8228376e+08 | EX56: =SUM(DM56:DO56) -> 2.0325314e+08 | EY56: =SUM(DP56:DR56) -> 2.2766542e+08 | EZ56: =SUM(DS56:DU56) -> 2.1402533e+08 | FA56: =SUM(DV56:DX56) -> 2.1096051e+08 | FB56: =SUM(DY56:EA56) -> 2.3493966e+08 | FC56: =SUM(EB56:ED56) -> 2.6313927e+08 | FE56: =SUM(EF56:EI56) -> 2.5642696e+08 | FF56: =SUM(EJ56:EM56) -> 3.4708772e+08 | FG56: =SUM(EN56:EQ56) -> 5.4087596e+08 | FH56: =SUM(ER56:EU56) -> 6.6696858e+08 | FI56: =SUM(EV56:EY56) -> 7.9796672e+08 | FJ56: =SUM(EZ56:FC56) -> 9.2306478e+08 | FK56: x
B57: Market Place | C57: =Marketplace!C6 -> 768377.52 | D57: =Marketplace!D6 -> 1141530.5 | E57: =Marketplace!E6 -> 1058731.2 | F57: =Marketplace!F6 -> 914129.1 | G57: =Marketplace!G6 -> 547995.24 | H57: =Marketplace!H6 -> 406707.12 | I57: =Marketplace!I6 -> 502586.1 | J57: =Marketplace!J6 -> 449743.5 | ... ED57: =Marketplace!ED6 -> 24099894 | EF57: =SUM(BK57:BM57) -> 20322031 | EG57: =SUM(BN57:BP57) -> 22036336 | EH57: =SUM(BQ57:BS57) -> 26520159 | EI57: =SUM(BT57:BV57) -> 24897223 | EJ57: =SUM(BW57:BY57) -> 24932168 | EK57: =SUM(BZ57:CB57) -> 27600491 | EL57: =SUM(CC57:CE57) -> 31342032 | EM57: =SUM(CF57:CH57) -> 30989098 | EN57: =SUM(CI57:CK57) -> 31822006 | EO57: =SUM(CL57:CN57) -> 34381437 | EP57: =SUM(CO57:CQ57) -> 41138139 | EQ57: =SUM(CR57:CT57) -> 40175837 | ER57: =SUM(CU57:CW57) -> 41931978 | ES57: =SUM(CX57:CZ57) -> 47045903 | ET57: =SUM(DA57:DC57) -> 52344160 | EU57: =SUM(DD57:DF57) -> 48606635 | EV57: =SUM(DG57:DI57) -> 50318373 | EW57: =SUM(DJ57:DL57) -> 56455084 | EX57: =SUM(DM57:DO57) -> 62812992 | EY57: =SUM(DP57:DR57) -> 58327962 | EZ57: =SUM(DS57:DU57) -> 57866129 | FA57: =SUM(DV57:DX57) -> 64923346 | FB57: =SUM(DY57:EA57) -> 72234941 | FC57: =SUM(EB57:ED57) -> 67077157 | FE57: =SUM(EF57:EI57) -> 93775750 | FF57: =SUM(EJ57:EM57) -> 1.1486379e+08 | FG57: =SUM(EN57:EQ57) -> 1.4751742e+08 | FH57: =SUM(ER57:EU57) -> 1.8992868e+08 | FI57: =SUM(EV57:EY57) -> 2.2791441e+08 | FJ57: =SUM(EZ57:FC57) -> 2.6210157e+08 | FK57: x
B58: Screen Pro + Accessories | C58: 0 | D58: 0 | E58: 0 | F58: 0 | G58: 0 | H58: 0 | I58: 0 | J58: 0 | K58: 0 | L58: ='D2C Online'!C55 -> 0 | M58: ='D2C Online'!D55 -> 0 | N58: ='D2C Online'!E55 -> 0 | O58: ='D2C Online'!F55 -> 0 | P58: ='D2C Online'!G55 -> 0 | Q58: ='D2C Online'!H55 -> 0 | R58: ='D2C Online'!I55 -> 0 | S58: ='D2C Online'!J55 -> 0 | ... AB58: ='D2C Online'!S55 -> 0 | AC58: ='D2C - Retail'!C58+'D2C - Retail'!C59+'D2C Online'!T55 -> 588118.55 | AD58: ='D2C - Retail'!D58+'D2C - Retail'!D59+'D2C Online'!U55 -> 626075.08 | AE58: ='D2C - Retail'!E58+'D2C - Retail'!E59+'D2C Online'!V55 -> 661050.08 | AF58: ='D2C - Retail'!F58+'D2C - Retail'!F59+'D2C Online'!W55 -> 577422.43 | AG58: ='D2C - Retail'!G58+'D2C - Retail'!G59+'D2C Online'!X55 -> 541419.92 | AH58: ='D2C - Retail'!H58+'D2C - Retail'!H59+'D2C Online'!Y55 -> 526691.29 | AI58: ='D2C - Retail'!I58+'D2C - Retail'!I59+'D2C Online'!Z55 -> 535087.13 | AJ58: ='D2C - Retail'!J58+'D2C - Retail'!J59+'D2C Online'!AA55 -> 541253.69 | ... CT58: ='D2C - Retail'!BT58+'D2C - Retail'!BT59+'D2C Online'!CK55 -> 12448370 | CU58: ='D2C Online'!CL55+'D2C - Retail'!BU58+'D2C - Retail'!BU59 -> 10297627 | CV58: ='D2C Online'!CM55+'D2C - Retail'!BV58+'D2C - Retail'!BV59 -> 10092545 | CW58: ='D2C Online'!CN55+'D2C - Retail'!BW58+'D2C - Retail'!BW59 -> 10071868 | CX58: ='D2C Online'!CO55+'D2C - Retail'!BX58+'D2C - Retail'!BX59 -> 10888627 | CY58: ='D2C Online'!CP55+'D2C - Retail'!BY58+'D2C - Retail'!BY59 -> 9741495.2 | CZ58: ='D2C Online'!CQ55+'D2C - Retail'!BZ58+'D2C - Retail'!BZ59 -> 9087529.1 | DA58: ='D2C Online'!CR55+'D2C - Retail'!CA58+'D2C - Retail'!CA59 -> 11263127 | DB58: ='D2C Online'!CS55+'D2C - Retail'!CB58+'D2C - Retail'!CB59 -> 10394397 | ... ED58: ='D2C Online'!DU55+'D2C - Retail'!DD58+'D2C - Retail'!DD59 -> 18243415 | EF58: =SUM(BK58:BM58) -> 11477439 | EG58: =SUM(BN58:BP58) -> 13214656 | EH58: =SUM(BQ58:BS58) -> 12004874 | EI58: =SUM(BT58:BV58) -> 10567104 | EJ58: =SUM(BW58:BY58) -> 13222310 | EK58: =SUM(BZ58:CB58) -> 14157361 | EL58: =SUM(CC58:CE58) -> 14924704 | EM58: =SUM(CF58:CH58) -> 15663841 | EN58: =SUM(CI58:CK58) -> 17581495 | EO58: =SUM(CL58:CN58) -> 20010382 | EP58: =SUM(CO58:CQ58) -> 23828759 | EQ58: =SUM(CR58:CT58) -> 29807295 | ER58: =SUM(CU58:CW58) -> 30462041 | ES58: =SUM(CX58:CZ58) -> 29717652 | ET58: =SUM(DA58:DC58) -> 34033111 | EU58: =SUM(DD58:DF58) -> 38157535 | EV58: =SUM(DG58:DI58) -> 37218630 | EW58: =SUM(DJ58:DL58) -> 36121669 | EX58: =SUM(DM58:DO58) -> 40957612 | EY58: =SUM(DP58:DR58) -> 45244909 | EZ58: =SUM(DS58:DU58) -> 42413685 | FA58: =SUM(DV58:DX58) -> 41070536 | FB58: =SUM(DY58:EA58) -> 46501241 | FC58: =SUM(EB58:ED58) -> 51331367 | FE58: =SUM(EF58:EI58) -> 47264074 | FF58: =SUM(EJ58:EM58) -> 57968216 | FG58: =SUM(EN58:EQ58) -> 91227932 | FH58: =SUM(ER58:EU58) -> 1.3237034e+08 | FI58: =SUM(EV58:EY58) -> 1.5954282e+08 | FJ58: =SUM(EZ58:FC58) -> 1.8131683e+08 | FK58: x
B59: Enterprise Sales | C59: =C68*18% -> 0 | D59: =D68*18% -> 0 | E59: =E68*18% -> 0 | F59: =F68*18% -> 0 | G59: =G68*18% -> 0 | H59: =H68*18% -> 0 | I59: =I68*18% -> 0 | J59: =J68*18% -> 0 | ... ED59: =ED68*18% -> 1113715.8 | FJ59: =SUM(EZ59:FC59) -> 0 | FK59: x
B60: Screen Pro | C60: ='Screen Pro'!B3 -> 171186.3 | D60: ='Screen Pro'!C3 -> 221207.22 | E60: ='Screen Pro'!D3 -> 300816 | F60: ='Screen Pro'!E3 -> 350961.3 | G60: ='Screen Pro'!F3 -> 374416.38 | H60: ='Screen Pro'!G3 -> 477382.86 | I60: ='Screen Pro'!H3 -> 560632.86 | J60: ='Screen Pro'!I3 -> 785374.02 | ... ED60: ='Screen Pro'!EC3 -> 0 | FJ60: =SUM(EZ60:FC60) -> 0 | FK60: x
B61: Tax% | C61: =C54/C34 -> 0.01291469 | D61: =D54/D34 -> 0.01580898 | E61: =E54/E34 -> 0.016482245 | F61: =F54/F34 -> 0.017698052 | G61: =G54/G34 -> 0.019913841 | H61: =H54/H34 -> 0.019541178 | I61: =I54/I34 -> 0.015950325 | J61: =J54/J34 -> 0.020335945 | ... ED61: =ED54/ED34 -> 0.041290827 | EF61: =EF54/EF34 -> 0.031227622 | EG61: =EG54/EG34 -> 0.033025933 | EH61: =EH54/EH34 -> 0.03165883 | EI61: =EI54/EI34 -> 0.035745155 | EJ61: =EJ54/EJ34 -> 0.036886995 | EK61: =EK54/EK34 -> 0.035953783 | EL61: =EL54/EL34 -> 0.035782109 | EM61: =EM54/EM34 -> 0.035029434 | ... FC61: =FC54/FC34 -> 0.041295762 | FE61: =FE54/FE34 -> 0.032865875 | FF61: =FF54/FF34 -> 0.035836707 | FG61: =FG54/FG34 -> 0.040012869 | FH61: =FH54/FH34 -> 0.040802234 | FI61: =FI54/FI34 -> 0.040706888 | FJ61: =FJ54/FJ34 -> 0.040643366 | FK61: x
B63: Revenue Post Tax (after returns) | C63: =SUM(C64:C68) -> 1.3611425e+08 | D63: =SUM(D64:D68) -> 1.3051977e+08 | E63: =SUM(E64:E68) -> 1.4295126e+08 | F63: =SUM(F64:F68) -> 1.6726205e+08 | G63: =SUM(G64:G68) -> 1.8939117e+08 | H63: =SUM(H64:H68) -> 1.9500153e+08 | I63: =SUM(I64:I68) -> 2.1072793e+08 | J63: =SUM(J64:J68) -> 1.9973777e+08 | ... ED63: =SUM(ED64:ED68) -> 2.9594735e+09 | EF63: =SUM(BK63:BM63) -> 2.6694827e+09 | EG63: =SUM(BN63:BP63) -> 2.2863202e+09 | EH63: =SUM(BQ63:BS63) -> 2.7351833e+09 | EI63: =SUM(BT63:BV63) -> 2.3227928e+09 | EJ63: =SUM(BW63:BY63) -> 2.634789e+09 | EK63: =SUM(BZ63:CB63) -> 2.444428e+09 | EL63: =SUM(CC63:CE63) -> 2.8231927e+09 | EM63: =SUM(CF63:CH63) -> 3.6810423e+09 | EN63: =SUM(CI63:CK63) -> 3.7949056e+09 | EO63: =SUM(CL63:CN63) -> 3.6133269e+09 | EP63: =SUM(CO63:CQ63) -> 4.4728274e+09 | EQ63: =SUM(CR63:CT63) -> 5.3104904e+09 | ER63: =SUM(CU63:CW63) -> 5.0944626e+09 | ES63: =SUM(CX63:CZ63) -> 4.8860903e+09 | ET63: =SUM(DA63:DC63) -> 5.6954605e+09 | EU63: =SUM(DD63:DF63) -> 6.1903504e+09 | EV63: =SUM(DG63:DI63) -> 6.2285842e+09 | EW63: =SUM(DJ63:DL63) -> 5.9539454e+09 | EX63: =SUM(DM63:DO63) -> 6.9225104e+09 | EY63: =SUM(DP63:DR63) -> 7.4750768e+09 | EZ63: =SUM(DS63:DU63) -> 7.2957497e+09 | FA63: =SUM(DV63:DX63) -> 6.9613905e+09 | FB63: =SUM(DY63:EA63) -> 8.0966742e+09 | FC63: =SUM(EB63:ED63) -> 8.7373589e+09 | FE63: =SUM(EF63:EI63) -> 1.0013779e+10 | FF63: =SUM(EJ63:EM63) -> 1.1583452e+10 | FG63: =SUM(EN63:EQ63) -> 1.719155e+10 | FH63: =SUM(ER63:EU63) -> 2.1866364e+10 | FI63: =SUM(EV63:EY63) -> 2.6580117e+10 | FJ63: =SUM(EZ63:FC63) -> 3.1091173e+10 | FK63: x
B64: Non- Repair | C64: ='B2B- Non Repair'!C32 -> 125801277 | D64: ='B2B- Non Repair'!D32 -> 1.1759199e+08 | E64: ='B2B- Non Repair'!E32 -> 1.3147411e+08 | F64: ='B2B- Non Repair'!F32 -> 1.5305052e+08 | G64: ='B2B- Non Repair'!G32 -> 1.7940043e+08 | H64: ='B2B- Non Repair'!H32 -> 187093082 | I64: ='B2B- Non Repair'!I32 -> 200855808 | J64: ='B2B- Non Repair'!J32 -> 188073690 | ... ED64: ='B2B- Non Repair'!ED32 -> 1.014667e+09 | EF64: =SUM(BK64:BM64) -> 1.0607939e+09 | EG64: =SUM(BN64:BP64) -> 8.5151296e+08 | EH64: =SUM(BQ64:BS64) -> 8.8803804e+08 | EI64: =SUM(BT64:BV64) -> 8.307929e+08 | EJ64: =SUM(BW64:BY64) -> 9.0157739e+08 | EK64: =SUM(BZ64:CB64) -> 7.8516968e+08 | EL64: =SUM(CC64:CE64) -> 8.9935872e+08 | EM64: =SUM(CF64:CH64) -> 1.3528236e+09 | EN64: =SUM(CI64:CK64) -> 1.3552235e+09 | EO64: =SUM(CL64:CN64) -> 1.1493731e+09 | EP64: =SUM(CO64:CQ64) -> 1.543519e+09 | EQ64: =SUM(CR64:CT64) -> 1.8445986e+09 | ER64: =SUM(CU64:CW64) -> 1.819107e+09 | ES64: =SUM(CX64:CZ64) -> 1.6140435e+09 | ET64: =SUM(DA64:DC64) -> 2.0213219e+09 | EU64: =SUM(DD64:DF64) -> 2.1013312e+09 | EV64: =SUM(DG64:DI64) -> 2.2738837e+09 | EW64: =SUM(DJ64:DL64) -> 2.0175543e+09 | EX64: =SUM(DM64:DO64) -> 2.5266523e+09 | EY64: =SUM(DP64:DR64) -> 2.626664e+09 | EZ64: =SUM(DS64:DU64) -> 2.7286605e+09 | FA64: =SUM(DV64:DX64) -> 2.4210652e+09 | FB64: =SUM(DY64:EA64) -> 3.0319828e+09 | FC64: =SUM(EB64:ED64) -> 3.1519968e+09 | FE64: =SUM(EF64:EI64) -> 3.6311378e+09 | FF64: =SUM(EJ64:EM64) -> 3.9389294e+09 | FG64: =SUM(EN64:EQ64) -> 5.8927142e+09 | FH64: =SUM(ER64:EU64) -> 7.5558035e+09 | FI64: =SUM(EV64:EY64) -> 9.4447544e+09 | FJ64: =SUM(EZ64:FC64) -> 1.1333705e+10 | FK64: x
B65: Refurbished | C65: =Refurbished!C36 -> 6044210 | D65: =Refurbished!D36 -> 6585944 | E65: =Refurbished!E36 -> 5595315.3 | F65: =Refurbished!F36 -> 9133043.5 | G65: =Refurbished!G36 -> 6946318.6 | H65: =Refurbished!H36 -> 5648964.1 | I65: =Refurbished!I36 -> 7079979.2 | J65: =Refurbished!J36 -> 9165502.7 | ... ED65: =Refurbished!ED36 -> 1.7521333e+09 | EF65: =SUM(BK65:BM65) -> 1.4285534e+09 | EG65: =SUM(BN65:BP65) -> 1.2352174e+09 | EH65: =SUM(BQ65:BS65) -> 1.6285958e+09 | EI65: =SUM(BT65:BV65) -> 1.2917776e+09 | EJ65: =SUM(BW65:BY65) -> 1.5179285e+09 | EK65: =SUM(BZ65:CB65) -> 1.4191447e+09 | EL65: =SUM(CC65:CE65) -> 1.6571807e+09 | EM65: =SUM(CF65:CH65) -> 2.0627263e+09 | EN65: =SUM(CI65:CK65) -> 2.167009e+09 | EO65: =SUM(CL65:CN65) -> 2.1596106e+09 | EP65: =SUM(CO65:CQ65) -> 2.5688883e+09 | EQ65: =SUM(CR65:CT65) -> 3.0820966e+09 | ER65: =SUM(CU65:CW65) -> 2.9064922e+09 | ES65: =SUM(CX65:CZ65) -> 2.8627733e+09 | ET65: =SUM(DA65:DC65) -> 3.2356615e+09 | EU65: =SUM(DD65:DF65) -> 3.6677951e+09 | EV65: =SUM(DG65:DI65) -> 3.5241978e+09 | EW65: =SUM(DJ65:DL65) -> 3.4596794e+09 | EX65: =SUM(DM65:DO65) -> 3.8858587e+09 | EY65: =SUM(DP65:DR65) -> 4.3623727e+09 | EZ65: =SUM(DS65:DU65) -> 4.0835948e+09 | FA65: =SUM(DV65:DX65) -> 4.0052721e+09 | FB65: =SUM(DY65:EA65) -> 4.4916035e+09 | FC65: =SUM(EB65:ED65) -> 5.0404621e+09 | FE65: =SUM(EF65:EI65) -> 5.5841442e+09 | FF65: =SUM(EJ65:EM65) -> 6.6569803e+09 | FG65: =SUM(EN65:EQ65) -> 9.9776044e+09 | FH65: =SUM(ER65:EU65) -> 1.2672722e+10 | FI65: =SUM(EV65:EY65) -> 1.5232108e+10 | FJ65: =SUM(EZ65:FC65) -> 1.7620933e+10 | FK65: x
B66: Market Place | C66: =Marketplace!C9 -> 4268764 | D66: =Marketplace!D9 -> 6341836 | E66: =Marketplace!E9 -> 5881840 | F66: =Marketplace!F9 -> 5078495 | G66: =Marketplace!G9 -> 3044418 | H66: =Marketplace!H9 -> 2259484 | I66: =Marketplace!I9 -> 2792145 | J66: =Marketplace!J9 -> 2498575 | ... ED66: =Marketplace!ED9 -> 1.338883e+08 | EF66: =SUM(BK66:BM66) -> 1.1290017e+08 | EG66: =SUM(BN66:BP66) -> 1.2242409e+08 | EH66: =SUM(BQ66:BS66) -> 1.4733422e+08 | EI66: =SUM(BT66:BV66) -> 1.3831791e+08 | EJ66: =SUM(BW66:BY66) -> 1.3851204e+08 | EK66: =SUM(BZ66:CB66) -> 1.5333606e+08 | EL66: =SUM(CC66:CE66) -> 1.741224e+08 | EM66: =SUM(CF66:CH66) -> 1.7216166e+08 | EN66: =SUM(CI66:CK66) -> 1.7678892e+08 | EO66: =SUM(CL66:CN66) -> 1.9100798e+08 | EP66: =SUM(CO66:CQ66) -> 2.2854521e+08 | EQ66: =SUM(CR66:CT66) -> 2.2319909e+08 | ER66: =SUM(CU66:CW66) -> 2.3295543e+08 | ES66: =SUM(CX66:CZ66) -> 2.6136613e+08 | ET66: =SUM(DA66:DC66) -> 2.9080089e+08 | EU66: =SUM(DD66:DF66) -> 2.7003686e+08 | EV66: =SUM(DG66:DI66) -> 2.7954652e+08 | EW66: =SUM(DJ66:DL66) -> 3.1363935e+08 | EX66: =SUM(DM66:DO66) -> 3.4896107e+08 | EY66: =SUM(DP66:DR66) -> 3.2404423e+08 | EZ66: =SUM(DS66:DU66) -> 3.2147849e+08 | FA66: =SUM(DV66:DX66) -> 3.6068526e+08 | FB66: =SUM(DY66:EA66) -> 4.0130523e+08 | FC66: =SUM(EB66:ED66) -> 3.7265087e+08 | FE66: =SUM(EF66:EI66) -> 5.2097639e+08 | FF66: =SUM(EJ66:EM66) -> 6.3813216e+08 | FG66: =SUM(EN66:EQ66) -> 8.1954121e+08 | FH66: =SUM(ER66:EU66) -> 1.0551593e+09 | FI66: =SUM(EV66:EY66) -> 1.2661912e+09 | FJ66: =SUM(EZ66:FC66) -> 1.4561199e+09 | FK66: x
B67: Screen Pro + Accessories | C67: 0 | D67: 0 | E67: 0 | F67: 0 | G67: 0 | H67: 0 | I67: 0 | J67: 0 | K67: 0 | L67: ='D2C Online'!C62 -> 0 | M67: ='D2C Online'!D62 -> 0 | N67: ='D2C Online'!E62 -> 0 | O67: ='D2C Online'!F62 -> 0 | P67: ='D2C Online'!G62 -> 0 | Q67: ='D2C Online'!H62 -> 0 | R67: ='D2C Online'!I62 -> 0 | S67: ='D2C Online'!J62 -> 0 | ... AB67: ='D2C Online'!S62 -> 0 | AC67: ='D2C Online'!T62+'D2C - Retail'!C76+'D2C - Retail'!C77 -> 3267465.5 | AD67: ='D2C Online'!U62+'D2C - Retail'!D76+'D2C - Retail'!D77 -> 3480890.9 | AE67: ='D2C Online'!V62+'D2C - Retail'!E76+'D2C - Retail'!E77 -> 3672500.4 | AF67: ='D2C Online'!W62+'D2C - Retail'!F76+'D2C - Retail'!F77 -> 3207902.4 | AG67: ='D2C Online'!X62+'D2C - Retail'!G76+'D2C - Retail'!G77 -> 3007888.4 | AH67: ='D2C Online'!Y62+'D2C - Retail'!H76+'D2C - Retail'!H77 -> 2926062.7 | AI67: ='D2C Online'!Z62+'D2C - Retail'!I76+'D2C - Retail'!I77 -> 2972706.3 | AJ67: ='D2C Online'!AA62+'D2C - Retail'!J76+'D2C - Retail'!J77 -> 3006965 | ... CF67: ='D2C Online'!BW62+'D2C - Retail'!BF76+'D2C - Retail'!BF77 -> 28929718 | CG67: ='D2C - Retail'!BG76+'D2C - Retail'!BG77 -> 25672337 | CH67: ='D2C - Retail'!BH76+'D2C - Retail'!BH77 -> 32419282 | CI67: ='D2C - Retail'!BI76+'D2C - Retail'!BI77 -> 30049958 | CJ67: ='D2C - Retail'!BJ76+'D2C - Retail'!BJ77 -> 31398343 | CK67: ='D2C - Retail'!BK76+'D2C - Retail'!BK77 -> 28908302 | CL67: ='D2C - Retail'!BL76+'D2C - Retail'!BL77 -> 33392533 | CM67: ='D2C - Retail'!BM76+'D2C - Retail'!BM77 -> 35163087 | CN67: ='D2C - Retail'!BN76+'D2C - Retail'!BN77 -> 33247917 | ... ED67: ='D2C - Retail'!DD76+'D2C - Retail'!DD77 -> 52597631 | EF67: =SUM(BK67:BM67) -> 63763552 | EG67: =SUM(BN67:BP67) -> 73414757 | EH67: =SUM(BQ67:BS67) -> 66693746 | EI67: =SUM(BT67:BV67) -> 58706136 | EJ67: =SUM(BW67:BY67) -> 73457276 | EK67: =SUM(BZ67:CB67) -> 78652006 | EL67: =SUM(CC67:CE67) -> 82915023 | EM67: =SUM(CF67:CH67) -> 87021338 | EN67: =SUM(CI67:CK67) -> 90356603 | EO67: =SUM(CL67:CN67) -> 1.0180354e+08 | EP67: =SUM(CO67:CQ67) -> 1.2203519e+08 | EQ67: =SUM(CR67:CT67) -> 1.4849693e+08 | ER67: =SUM(CU67:CW67) -> 1.3038047e+08 | ES67: =SUM(CX67:CZ67) -> 1.3637569e+08 | ET67: =SUM(DA67:DC67) -> 1.3783655e+08 | EU67: =SUM(DD67:DF67) -> 1.39088e+08 | EV67: =SUM(DG67:DI67) -> 1.4542866e+08 | EW67: =SUM(DJ67:DL67) -> 1.5154066e+08 | EX67: =SUM(DM67:DO67) -> 1.5119867e+08 | EY67: =SUM(DP67:DR67) -> 1.4989662e+08 | EZ67: =SUM(DS67:DU67) -> 1.5648846e+08 | FA67: =SUM(DV67:DX67) -> 1.6283622e+08 | FB67: =SUM(DY67:EA67) -> 1.6194303e+08 | FC67: =SUM(EB67:ED67) -> 1.6014986e+08 | FE67: =SUM(EF67:EI67) -> 2.6257819e+08 | FF67: =SUM(EJ67:EM67) -> 3.2204564e+08 | FG67: =SUM(EN67:EQ67) -> 4.6269226e+08 | FH67: =SUM(ER67:EU67) -> 5.4368071e+08 | FI67: =SUM(EV67:EY67) -> 5.980646e+08 | FJ67: =SUM(EZ67:FC67) -> 6.4141757e+08 | FK67: x
B68: Enterprise Sales | C68: ='P&L - Inputs'!B748 -> 0 | D68: ='P&L - Inputs'!C748 -> 0 | E68: ='P&L - Inputs'!D748 -> 0 | F68: ='P&L - Inputs'!E748 -> 0 | G68: ='P&L - Inputs'!F748 -> 0 | H68: ='P&L - Inputs'!G748 -> 0 | I68: ='P&L - Inputs'!H748 -> 0 | J68: ='P&L - Inputs'!I748 -> 0 | ... ED68: ='P&L - Inputs'!EC748 -> 6187310 | EF68: =SUM(BK68:BM68) -> 3471706.3 | EG68: =SUM(BN68:BP68) -> 3751054.9 | EH68: =SUM(BQ68:BS68) -> 4521562.2 | EI68: =SUM(BT68:BV68) -> 3198224.5 | EJ68: =SUM(BW68:BY68) -> 3313709.3 | EK68: =SUM(BZ68:CB68) -> 8125538.3 | EL68: =SUM(CC68:CE68) -> 9615807.9 | EM68: =SUM(CF68:CH68) -> 6309432 | EN68: =SUM(CI68:CK68) -> 5527560.2 | EO68: =SUM(CL68:CN68) -> 11531721 | EP68: =SUM(CO68:CQ68) -> 9839663.9 | EQ68: =SUM(CR68:CT68) -> 12099240 | ER68: =SUM(CU68:CW68) -> 5527560.2 | ES68: =SUM(CX68:CZ68) -> 11531721 | ET68: =SUM(DA68:DC68) -> 9839663.9 | EU68: =SUM(DD68:DF68) -> 12099240 | EV68: =SUM(DG68:DI68) -> 5527560.2 | EW68: =SUM(DJ68:DL68) -> 11531721 | EX68: =SUM(DM68:DO68) -> 9839663.9 | EY68: =SUM(DP68:DR68) -> 12099240 | EZ68: =SUM(DS68:DU68) -> 5527560.2 | FA68: =SUM(DV68:DX68) -> 11531721 | FB68: =SUM(DY68:EA68) -> 9839663.9 | FC68: =SUM(EB68:ED68) -> 12099240 | FE68: =SUM(EF68:EI68) -> 14942548 | FF68: =SUM(EJ68:EM68) -> 27364487 | FG68: =SUM(EN68:EQ68) -> 38998185 | FH68: =SUM(ER68:EU68) -> 38998185 | FI68: =SUM(EV68:EY68) -> 38998185 | FJ68: =SUM(EZ68:FC68) -> 38998185 | FK68: x
B70: Growth% | D70: =D63/C63-1 -> -0.041101374 | E70: =E63/D63-1 -> 0.095246049 | F70: =F63/E63-1 -> 0.17006352 | G70: =G63/F63-1 -> 0.13230207 | H70: =H63/G63-1 -> 0.029623135 | I70: =I63/H63-1 -> 0.080647583 | J70: =J63/I63-1 -> -0.052153335 | K70: =K63/J63-1 -> 0.26274324 | ... ED70: =ED63/EC63-1 -> 0.066303754 | EG70: =EG63/EF63-1 -> -0.14353435 | EH70: =EH63/EG63-1 -> 0.19632555 | EI70: =EI63/EH63-1 -> -0.15077255 | EJ70: =EJ63/EI63-1 -> 0.13431942 | EK70: =EK63/EJ63-1 -> -0.072249049 | EL70: =EL63/EK63-1 -> 0.15495025 | EM70: =EM63/EL63-1 -> 0.30385799 | EN70: =EN63/EM63-1 -> 0.030932338 | ... FC70: =FC63/FB63-1 -> 0.079129354 | FF70: =FF63/FE63-1 -> 0.1567513 | FG70: =FG63/FF63-1 -> 0.48414742 | FH70: =FH63/FG63-1 -> 0.27192507 | FI70: =FI63/FH63-1 -> 0.21557096 | FJ70: =FJ63/FI63-1 -> 0.16971545 | FK70: x
